Workbook

Sheet Indirect Active (2)
A1: Company code | B1: Pers.no. | C1: Name_C | D1: Name_E | E1: Subgroup | F1: Area | G1: Subarea | H1: Dept. | I1: Cost ctr | J1: Join date | K1: Job | L1: Position | M1: Band Level | N1: Workplan type | O1: 2025 Performance Level | P1: Basic salary | Q1: ① Merit increase % | R1: Merit Increase amount | S1: ② Equity Increase% | T1: Equity Increase amount | U1: Total recommended Increase % (①+②) | V1: Total Recommended Increase amount | W1: Recommended new basic salary | X1: Adjutsed basic salary (input by DH) | Y1: Adjutsed increased/decreased basic salary by DH | Z1: Adjusted basic increase/decreased % by DH | AA1: Adjustment range reference | AB1: Promotion or demotion | AC1: New position title | AD1: New band | AE1: ③ Promotion increase/Demotion decrease % (±5%-±20%) | AF1: Promotion increase/Demotion decrease amount | AG1: Final new basic salary | AH1: Final increase/decrease amount | AI1: Final increase/decrease rate | AJ1: Pay months | AK1: Monthly allowance/bonus | AL1: Monthly Car Allowance | AM1: Other income(e.g.:festival bonus) | AN1: Annual target cash | AO1: 2024 Performance Level | AP1: Disciplinary Records | AQ1: Justifications by DH | AR1: HR Remark | AS1: Responsible ASR Manager | AT1: Responsible ASR HRBP | AU1: PY | AV1: 85% of LMW (for Technician/Counsellor) | AW1: Editable column 1 | AX1: Editable column 2 | AY1: -
A2: CN15 | B2: 15000447 | C2: 柏 正曹 | D2: Bo Zhengcao | E2: Indirect Active | F2: OP | G2: SNa | H2: FCGNa-VVP | I2: 330404 | J2: 38808 | K2: Workshop Leader | L2: Head of FCGNa-VVP | M2: BAND A6 | N2: 2 | O2: 5 | P2: 15840 | Q2: 0.05 | R2: =ROUND(P2*Q2,0) -> 792 | S2: 0 | T2: =ROUND(P2*S2,0) -> 0 | U2: =V2/P2 -> 0.05 | V2: =R2+T2 -> 792 | W2: =P2+V2 -> 16632 | X2: 16780 | Y2: =X2-P2 -> 940 | Z2: =ROUND(X2/P2-1,4) -> 0.0593 | AA2: =IF(OR(N2=1,N2=2,N2=4), TEXT(U2*0.8,"0.00%") & "-" & TEXT(U2*1.2,"0.00%"), IF(OR(N2=3,N2=6), TEXT(0,"0.00%") & "-" & TEXT(7%*1.2,"0.00%"), IF(OR(N2=5,N2=7), TEXT((T2/P2),"0.00%") & "-" & TEXT((T2/P2)+7%,"0.00%"), "" ) ) ) -> 4.00%-6.00% | AF2: =ROUND(P2*AE2,0) -> 0 | AG2: =X2+AF2 -> 16780 | AH2: =AG2-P2 -> 940 | AI2: =AG2/P2-1 -> 0.059343434 | AJ2: 14 | AK2: 450 | AM2: 688 | AN2: =AG2*AJ2+AK2*12+AM2+IF(AD2="",AL2,IF(AD2="D",5000,IF(AD2="C",1000,0)))*12 -> 241008 | AO2: 4 | AS2: Miao Siyuan（15005811） | AT2: Zhu Qianqian（11016705） | AU2: Zhao Chujun | AY2: =_xlfn.LET(_xlpm.actual,Z2,_xlpm.low,VALUE(_xlfn.TEXTBEFORE(AA2,"-")),_xlpm.high,VALUE(_xlfn.TEXTAFTER(AA2,"-")),IF(AND(_xlpm.actual=0,OR(_xlpm.low<>0,_xlpm.high<>0)),"0 increase",IF(_xlpm.actual>_xlpm.high*1.2,">20",IF(_xlpm.actual<_xlpm.low*0.8,"<20","OK")))) -> OK
A3: CN15 | B3: 15014416 | C3: 蔡 凯健 | D3: Cai Kaijian | E3: Indirect Active | F3: OP | G3: SNa | H3: FCGNa-VVE | I3: 330404 | J3: 45063 | K3: Supervisor | L3: Head of Engineering Ventilation | M3: BAND A6 | N3: 2 | O3: 4 | P3: 16456 | Q3: 0.045 | R3: =ROUND(P3*Q3,0) -> 741 | S3: 0.0155 | T3: =ROUND(P3*S3,0) -> 255 | U3: =V3/P3 -> 0.060525036 | V3: =R3+T3 -> 996 | W3: =P3+V3 -> 17452 | X3: 17456 | Y3: =X3-P3 -> 1000 | Z3: =ROUND(X3/P3-1,4) -> 0.0608 | AA3: =IF(OR(N3=1,N3=2,N3=4), TEXT(U3*0.8,"0.00%") & "-" & TEXT(U3*1.2,"0.00%"), IF(OR(N3=3,N3=6), TEXT(0,"0.00%") & "-" & TEXT(7%*1.2,"0.00%"), IF(OR(N3=5,N3=7), TEXT((T3/P3),"0.00%") & "-" & TEXT((T3/P3)+7%,"0.00%"), "" ) ) ) -> 4.84%-7.26% | AF3: =ROUND(P3*AE3,0) -> 0 | AG3: =X3+AF3 -> 17456 | AH3: =AG3-P3 -> 1000 | AI3: =AG3/P3-1 -> 0.060768109 | AJ3: 14 | AK3: 450 | AM3: 688 | AN3: =AG3*AJ3+AK3*12+AM3+IF(AD3="",AL3,IF(AD3="D",5000,IF(AD3="C",1000,0)))*12 -> 250472 | AO3: 5 | AS3: Miao Siyuan（15005811） | AT3: Zhu Qianqian（11016705） | AU3: Zhao Chujun | AY3: =_xlfn.LET(_xlpm.actual,Z3,_xlpm.low,VALUE(_xlfn.TEXTBEFORE(AA3,"-")),_xlpm.high,VALUE(_xlfn.TEXTAFTER(AA3,"-")),IF(AND(_xlpm.actual=0,OR(_xlpm.low<>0,_xlpm.high<>0)),"0 increase",IF(_xlpm.actual>_xlpm.high*1.2,">20",IF(_xlpm.actual<_xlpm.low*0.8,"<20","OK")))) -> OK
A4: CN15 | B4: 15014868 | C4: 符 卫卫 | D4: Fu Weiwei | E4: Indirect Active | F4: OP | G4: SNa | H4: FCGNa-VVE | I4: 330404 | J4: 42291 | K4: Project Manager | L4: Project Manager | M4: BAND A6 | N4: 2 | O4: 3 | P4: 13630 | Q4: 0.03 | R4: =ROUND(P4*Q4,0) -> 409 | S4: 0 | T4: =ROUND(P4*S4,0) -> 0 | U4: =V4/P4 -> 0.030007337 | V4: =R4+T4 -> 409 | W4: =P4+V4 -> 14039 | X4: 14038 | Y4: =X4-P4 -> 408 | Z4: =ROUND(X4/P4-1,4) -> 0.0299 | AA4: =IF(OR(N4=1,N4=2,N4=4), TEXT(U4*0.8,"0.00%") & "-" & TEXT(U4*1.2,"0.00%"), IF(OR(N4=3,N4=6), TEXT(0,"0.00%") & "-" & TEXT(7%*1.2,"0.00%"), IF(OR(N4=5,N4=7), TEXT((T4/P4),"0.00%") & "-" & TEXT((T4/P4)+7%,"0.00%"), "" ) ) ) -> 2.40%-3.60% | AF4: =ROUND(P4*AE4,0) -> 0 | AG4: =X4+AF4 -> 14038 | AH4: =AG4-P4 -> 408 | AI4: =AG4/P4-1 -> 0.029933969 | AJ4: 14 | AK4: 450 | AM4: 688 | AN4: =AG4*AJ4+AK4*12+AM4+IF(AD4="",AL4,IF(AD4="D",5000,IF(AD4="C",1000,0)))*12 -> 202620 | AO4: 4 | AS4: Miao Siyuan（15005811） | AT4: Zhu Qianqian（11016705） | AU4: Zhao Chujun | AY4: =_xlfn.LET(_xlpm.actual,Z4,_xlpm.low,VALUE(_xlfn.TEXTBEFORE(AA4,"-")),_xlpm.high,VALUE(_xlfn.TEXTAFTER(AA4,"-")),IF(AND(_xlpm.actual=0,OR(_xlpm.low<>0,_xlpm.high<>0)),"0 increase",IF(_xlpm.actual>_xlpm.high*1.2,">20",IF(_xlpm.actual<_xlpm.low*0.8,"<20","OK")))) -> OK
A5: CN15 | B5: 15022166 | C5: 李 超 | D5: Li Chao | E5: Indirect Active | F5: OP | G5: SNa | H5: FCGNa-VVE | I5: 330404 | J5: 44664 | K5: Senior Engineer | L5: Senior Electrical Engineer | M5: BAND A5 | N5: 2 | O5: 4 | P5: 14440 | Q5: 0.0375 | R5: =ROUND(P5*Q5,0) -> 542 | S5: 0 | T5: =ROUND(P5*S5,0) -> 0 | U5: =V5/P5 -> 0.037534626 | V5: =R5+T5 -> 542 | W5: =P5+V5 -> 14982 | X5: 15000 | Y5: =X5-P5 -> 560 | Z5: =ROUND(X5/P5-1,4) -> 0.0388 | AA5: =IF(OR(N5=1,N5=2,N5=4), TEXT(U5*0.8,"0.00%") & "-" & TEXT(U5*1.2,"0.00%"), IF(OR(N5=3,N5=6), TEXT(0,"0.00%") & "-" & TEXT(7%*1.2,"0.00%"), IF(OR(N5=5,N5=7), TEXT((T5/P5),"0.00%") & "-" & TEXT((T5/P5)+7%,"0.00%"), "" ) ) ) -> 3.00%-4.50% | AF5: =ROUND(P5*AE5,0) -> 0 | AG5: =X5+AF5 -> 15000 | AH5: =AG5-P5 -> 560 | AI5: =AG5/P5-1 -> 0.038781163 | AJ5: 14 | AK5: 450 | AM5: 688 | AN5: =AG5*AJ5+AK5*12+AM5+IF(AD5="",AL5,IF(AD5="D",5000,IF(AD5="C",1000,0)))*12 -> 216088 | AO5: 2 | AS5: Miao Siyuan（15005811） | AT5: Zhu Qianqian（11016705） | AU5: Zhao Chujun | AY5: =_xlfn.LET(_xlpm.actual,Z5,_xlpm.low,VALUE(_xlfn.TEXTBEFORE(AA5,"-")),_xlpm.high,VALUE(_xlfn.TEXTAFTER(AA5,"-")),IF(AND(_xlpm.actual=0,OR(_xlpm.low<>0,_xlpm.high<>0)),"0 increase",IF(_xlpm.actual>_xlpm.high*1.2,">20",IF(_xlpm.actual<_xlpm.low*0.8,"<20","OK")))) -> OK
A6: CN15 | B6: 15016337 | C6: 刘 文涛 | D6: Liu Wentao | E6: Indirect Active | F6: OP | G6: SNa | H6: FCGNa-VVE | I6: 330404 | J6: 42795 | K6: Functional Specialist | L6: Functional Specialist | M6: BAND A6 | N6: 2 | O6: 3 | P6: 14284 | Q6: 0.03 | R6: =ROUND(P6*Q6,0) -> 429 | S6: 0 | T6: =ROUND(P6*S6,0) -> 0 | U6: =V6/P6 -> 0.030033604 | V6: =R6+T6 -> 429 | W6: =P6+V6 -> 14713 | X6: 14688 | Y6: =X6-P6 -> 404 | Z6: =ROUND(X6/P6-1,4) -> 0.0283 | AA6: =IF(OR(N6=1,N6=2,N6=4), TEXT(U6*0.8,"0.00%") & "-" & TEXT(U6*1.2,"0.00%"), IF(OR(N6=3,N6=6), TEXT(0,"0.00%") & "-" & TEXT(7%*1.2,"0.00%"), IF(OR(N6=5,N6=7), TEXT((T6/P6),"0.00%") & "-" & TEXT((T6/P6)+7%,"0.00%"), "" ) ) ) -> 2.40%-3.60% | AF6: =ROUND(P6*AE6,0) -> 0 | AG6: =X6+AF6 -> 14688 | AH6: =AG6-P6 -> 404 | AI6: =AG6/P6-1 -> 0.028283394 | AJ6: 14 | AK6: 450 | AM6: 688 | AN6: =AG6*AJ6+AK6*12+AM6+IF(AD6="",AL6,IF(AD6="D",5000,IF(AD6="C",1000,0)))*12 -> 211720 | AO6: 2 | AS6: Miao Siyuan（15005811） | AT6: Zhu Qianqian（11016705） | AU6: Zhao Chujun | AY6: =_xlfn.LET(_xlpm.actual,Z6,_xlpm.low,VALUE(_xlfn.TEXTBEFORE(AA6,"-")),_xlpm.high,VALUE(_xlfn.TEXTAFTER(AA6,"-")),IF(AND(_xlpm.actual=0,OR(_xlpm.low<>0,_xlpm.high<>0)),"0 increase",IF(_xlpm.actual>_xlpm.high*1.2,">20",IF(_xlpm.actual<_xlpm.low*0.8,"<20","OK")))) -> OK
A7: CN15 | B7: 15022630 | C7: 王 长德 | D7: Wang Changde | E7: Indirect Active | F7: OP | G7: SNa | H7: FCGNa-VVE | I7: 330408 | J7: 45854 | K7: Functional Specialist | L7: Painting Functional Specialist | M7: BAND A6 | N7: 2 | O7: 3 | P7: 23000 | Q7: 0 | R7: =ROUND(P7*Q7,0) -> 0 | S7: 0 | T7: =ROUND(P7*S7,0) -> 0 | U7: =V7/P7 -> 0 | V7: =R7+T7 -> 0 | W7: =P7+V7 -> 23000 | X7: 23000 | Y7: =X7-P7 -> 0 | Z7: =ROUND(X7/P7-1,4) -> 0 | AA7: =IF(OR(N7=1,N7=2,N7=4), TEXT(U7*0.8,"0.00%") & "-" & TEXT(U7*1.2,"0.00%"), IF(OR(N7=3,N7=6), TEXT(0,"0.00%") & "-" & TEXT(7%*1.2,"0.00%"), IF(OR(N7=5,N7=7), TEXT((T7/P7),"0.00%") & "-" & TEXT((T7/P7)+7%,"0.00%"), "" ) ) ) -> 0.00%-0.00% | AF7: =ROUND(P7*AE7,0) -> 0 | AG7: =X7+AF7 -> 23000 | AH7: =AG7-P7 -> 0 | AI7: =AG7/P7-1 -> 0 | AJ7: 14 | AK7: 450 | AM7: 688 | AN7: =AG7*AJ7+AK7*12+AM7+IF(AD7="",AL7,IF(AD7="D",5000,IF(AD7="C",1000,0)))*12 -> 328088 | AO7: #N/A | AS7: Miao Siyuan（15005811） | AT7: Zhu Qianqian（11016705） | AU7: Zhao Chujun | AY7: =_xlfn.LET(_xlpm.actual,Z7,_xlpm.low,VALUE(_xlfn.TEXTBEFORE(AA7,"-")),_xlpm.high,VALUE(_xlfn.TEXTAFTER(AA7,"-")),IF(AND(_xlpm.actual=0,OR(_xlpm.low<>0,_xlpm.high<>0)),"0 increase",IF(_xlpm.actual>_xlpm.high*1.2,">20",IF(_xlpm.actual<_xlpm.low*0.8,"<20","OK")))) -> OK
A8: CN15 | B8: 15007556 | C8: 武 松 | D8: Wu Song | E8: Indirect Active | F8: OP | G8: SNa | H8: FCGNa-VVM | I8: 330204 | J8: 40962 | K8: Supervisor | L8: Head of FCGNa-VVM | M8: BAND A6 | N8: 2 | O8: 3 | P8: 16100 | Q8: 0.025 | R8: =ROUND(P8*Q8,0) -> 403 | S8: 0 | T8: =ROUND(P8*S8,0) -> 0 | U8: =V8/P8 -> 0.025031056 | V8: =R8+T8 -> 403 | W8: =P8+V8 -> 16503 | X8: 16518 | Y8: =X8-P8 -> 418 | Z8: =ROUND(X8/P8-1,4) -> 0.026 | AA8: =IF(OR(N8=1,N8=2,N8=4), TEXT(U8*0.8,"0.00%") & "-" & TEXT(U8*1.2,"0.00%"), IF(OR(N8=3,N8=6), TEXT(0,"0.00%") & "-" & TEXT(7%*1.2,"0.00%"), IF(OR(N8=5,N8=7), TEXT((T8/P8),"0.00%") & "-" & TEXT((T8/P8)+7%,"0.00%"), "" ) ) ) -> 2.00%-3.00% | AF8: =ROUND(P8*AE8,0) -> 0 | AG8: =X8+AF8 -> 16518 | AH8: =AG8-P8 -> 418 | AI8: =AG8/P8-1 -> 0.025962733 | AJ8: 14 | AK8: 450 | AM8: 688 | AN8: =AG8*AJ8+AK8*12+AM8+IF(AD8="",AL8,IF(AD8="D",5000,IF(AD8="C",1000,0)))*12 -> 237340 | AO8: 3 | AS8: Miao Siyuan（15005811） | AT8: Zhu Qianqian（11016705） | AU8: Zhao Chujun | AY8: =_xlfn.LET(_xlpm.actual,Z8,_xlpm.low,VALUE(_xlfn.TEXTBEFORE(AA8,"-")),_xlpm.high,VALUE(_xlfn.TEXTAFTER(AA8,"-")),IF(AND(_xlpm.actual=0,OR(_xlpm.low<>0,_xlpm.high<>0)),"0 increase",IF(_xlpm.actual>_xlpm.high*1.2,">20",IF(_xlpm.actual<_xlpm.low*0.8,"<20","OK")))) -> OK
A9: CN15 | B9: 1120246 | C9: 张 民强 | D9: Zhang Minqiang | E9: Indirect Active | F9: OP | G9: SNa | H9: FCGNa-VVE | I9: 330404 | J9: 43864 | K9: Functional Specialist | L9: Functional Specialist | M9: BAND A6 | N9: 2 | O9: 4 | P9: 13111 | Q9: 0.045 | R9: =ROUND(P9*Q9,0) -> 590 | S9: 0.0421 | T9: =ROUND(P9*S9,0) -> 552 | U9: =V9/P9 -> 0.087102433 | V9: =R9+T9 -> 1142 | W9: =P9+V9 -> 14253 | X9: 14066 | Y9: =X9-P9 -> 955 | Z9: =ROUND(X9/P9-1,4) -> 0.0728 | AA9: =IF(OR(N9=1,N9=2,N9=4), TEXT(U9*0.8,"0.00%") & "-" & TEXT(U9*1.2,"0.00%"), IF(OR(N9=3,N9=6), TEXT(0,"0.00%") & "-" & TEXT(7%*1.2,"0.00%"), IF(OR(N9=5,N9=7), TEXT((T9/P9),"0.00%") & "-" & TEXT((T9/P9)+7%,"0.00%"), "" ) ) ) -> 6.97%-10.45% | AF9: =ROUND(P9*AE9,0) -> 0 | AG9: =X9+AF9 -> 14066 | AH9: =AG9-P9 -> 955 | AI9: =AG9/P9-1 -> 0.0728396 | AJ9: 14 | AK9: 850 | AM9: 688 | AN9: =AG9*AJ9+AK9*12+AM9+IF(AD9="",AL9,IF(AD9="D",5000,IF(AD9="C",1000,0)))*12 -> 207812 | AO9: 3 | AS9: Miao Siyuan（15005811） | AT9: Zhu Qianqian（11016705） | AU9: Zhao Chujun | AY9: =_xlfn.LET(_xlpm.actual,Z9,_xlpm.low,VALUE(_xlfn.TEXTBEFORE(AA9,"-")),_xlpm.high,VALUE(_xlfn.TEXTAFTER(AA9,"-")),IF(AND(_xlpm.actual=0,OR(_xlpm.low<>0,_xlpm.high<>0)),"0 increase",IF(_xlpm.actual>_xlpm.high*1.2,">20",IF(_xlpm.actual<_xlpm.low*0.8,"<20","OK")))) -> OK
A10: CN15 | B10: 15000219 | C10: 周 金贵 | D10: Zhou Jingui | E10: Indirect Active | F10: OP | G10: SNa | H10: FCGNa-VVE | I10: 330404 | J10: 38608 | K10: Engineer | L10: Project Engineer | M10: BAND A4 | N10: 2 | O10: 2 | P10: 12256 | Q10: 0 | R10: =ROUND(P10*Q10,0) -> 0 | S10: 0 | T10: =ROUND(P10*S10,0) -> 0 | U10: =V10/P10 -> 0 | V10: =R10+T10 -> 0 | W10: =P10+V10 -> 12256 | X10: 12256 | Y10: =X10-P10 -> 0 | Z10: =ROUND(X10/P10-1,4) -> 0 | AA10: =IF(OR(N10=1,N10=2,N10=4), TEXT(U10*0.8,"0.00%") & "-" & TEXT(U10*1.2,"0.00%"), IF(OR(N10=3,N10=6), TEXT(0,"0.00%") & "-" & TEXT(7%*1.2,"0.00%"), IF(OR(N10=5,N10=7), TEXT((T10/P10),"0.00%") & "-" & TEXT((T10/P10)+7%,"0.00%"), "" ) ) ) -> 0.00%-0.00% | AF10: =ROUND(P10*AE10,0) -> 0 | AG10: =X10+AF10 -> 12256 | AH10: =AG10-P10 -> 0 | AI10: =AG10/P10-1 -> 0 | AJ10: 14 | AK10: 450 | AM10: 688 | AN10: =AG10*AJ10+AK10*12+AM10+IF(AD10="",AL10,IF(AD10="D",5000,IF(AD10="C",1000,0)))*12 -> 177672 | AO10: 3 | AS10: Miao Siyuan（15005811） | AT10: Zhu Qianqian（11016705） | AU10: Zhao Chujun | AY10: =_xlfn.LET(_xlpm.actual,Z10,_xlpm.low,VALUE(_xlfn.TEXTBEFORE(AA10,"-")),_xlpm.high,VALUE(_xlfn.TEXTAFTER(AA10,"-")),IF(AND(_xlpm.actual=0,OR(_xlpm.low<>0,_xlpm.high<>0)),"0 increase",IF(_xlpm.actual>_xlpm.high*1.2,">20",IF(_xlpm.actual<_xlpm.low*0.8,"<20","OK")))) -> OK
A11: CN15 | B11: 15014810 | C11: 朱 菊香 | D11: Zhu Juxiang | E11: Indirect Active | F11: OP | G11: SNa | H11: FCGNa-VVE | I11: 330404 | J11: 42248 | K11: Senior Specialist | L11: Senior IE Specialist | M11: BAND A5 | N11: 2 | O11: 4 | P11: 11666 | Q11: 0.0375 | R11: =ROUND(P11*Q11,0) -> 437 | S11: 0.0155 | T11: =ROUND(P11*S11,0) -> 181 | U11: =V11/P11 -> 0.052974456 | V11: =R11+T11 -> 618 | W11: =P11+V11 -> 12284 | X11: 12312 | Y11: =X11-P11 -> 646 | Z11: =ROUND(X11/P11-1,4) -> 0.0554 | AA11: =IF(OR(N11=1,N11=2,N11=4), TEXT(U11*0.8,"0.00%") & "-" & TEXT(U11*1.2,"0.00%"), IF(OR(N11=3,N11=6), TEXT(0,"0.00%") & "-" & TEXT(7%*1.2,"0.00%"), IF(OR(N11=5,N11=7), TEXT((T11/P11),"0.00%") & "-" & TEXT((T11/P11)+7%,"0.00%"), "" ) ) ) -> 4.24%-6.36% | AB11: Promotion | AC11: Function specialist | AD11: A6 | AE11: 0.0646 | AF11: =ROUND(P11*AE11,0) -> 754 | AG11: =X11+AF11 -> 13066 | AH11: =AG11-P11 -> 1400 | AI11: =AG11/P11-1 -> 0.12000686 | AJ11: 14 | AK11: 550 | AM11: 688 | AN11: =AG11*AJ11+AK11*12+AM11+IF(AD11="",AL11,IF(AD11="D",5000,IF(AD11="C",1000,0)))*12 -> 190212 | AO11: 4 | AQ11: Good performance and high competence | AR11: Good performance and high competence | AS11: Miao Siyuan（15005811） | AT11: Zhu Qianqian（11016705） | AU11: Zhao Chujun | AY11: =_xlfn.LET(_xlpm.actual,Z11,_xlpm.low,VALUE(_xlfn.TEXTBEFORE(AA11,"-")),_xlpm.high,VALUE(_xlfn.TEXTAFTER(AA11,"-")),IF(AND(_xlpm.actual=0,OR(_xlpm.low<>0,_xlpm.high<>0)),"0 increase",IF(_xlpm.actual>_xlpm.high*1.2,">20",IF(_xlpm.actual<_xlpm.low*0.8,"<20","OK")))) -> OK
A12: CN15 | B12: 15000226 | C12: 江 兵 | D12: Jiang Bing | E12: Indirect Active | F12: OP | G12: SNa | H12: FCGNa-VCP | I12: 330405 | J12: 38614 | K12: Workshop Leader | L12: Head of FCGNa-VCP | M12: BAND A6 | N12: 2 | O12: 3 | P12: 15800 | Q12: 0.025 | R12: =ROUND(P12*Q12,0) -> 395 | S12: 0 | T12: =ROUND(P12*S12,0) -> 0 | U12: =V12/P12 -> 0.025 | V12: =R12+T12 -> 395 | W12: =P12+V12 -> 16195 | X12: 16272 | Y12: =X12-P12 -> 472 | Z12: =ROUND(X12/P12-1,4) -> 0.0299 | AA12: =IF(OR(N12=1,N12=2,N12=4), TEXT(U12*0.8,"0.00%") & "-" & TEXT(U12*1.2,"0.00%"), IF(OR(N12=3,N12=6), TEXT(0,"0.00%") & "-" & TEXT(7%*1.2,"0.00%"), IF(OR(N12=5,N12=7), TEXT((T12/P12),"0.00%") & "-" & TEXT((T12/P12)+7%,"0.00%"), "" ) ) ) -> 2.00%-3.00% | AF12: =ROUND(P12*AE12,0) -> 0 | AG12: =X12+AF12 -> 16272 | AH12: =AG12-P12 -> 472 | AI12: =AG12/P12-1 -> 0.029873418 | AJ12: 14 | AK12: 450 | AM12: 688 | AN12: =AG12*AJ12+AK12*12+AM12+IF(AD12="",AL12,IF(AD12="D",5000,IF(AD12="C",1000,0)))*12 -> 233896 | AO12: 5 | AS12: Liu Haigang（15013255） | AT12: Zhu Qianqian（11016705） | AU12: Zhao Chujun | AY12: =_xlfn.LET(_xlpm.actual,Z12,_xlpm.low,VALUE(_xlfn.TEXTBEFORE(AA12,"-")),_xlpm.high,VALUE(_xlfn.TEXTAFTER(AA12,"-")),IF(AND(_xlpm.actual=0,OR(_xlpm.low<>0,_xlpm.high<>0)),"0 increase",IF(_xlpm.actual>_xlpm.high*1.2,">20",IF(_xlpm.actual<_xlpm.low*0.8,"<20","OK")))) -> OK
A13: CN15 | B13: 15000166 | C13: 蒋 莹 | D13: Jiang Ying | E13: Indirect Active | F13: OP | G13: SNa | H13: FCGNa-VCE | I13: 330405 | J13: 38600 | K13: Senior Engineer | L13: Senior Engineer | M13: BAND A5 | N13: 2 | O13: 3 | P13: 14610 | Q13: 0.025 | R13: =ROUND(P13*Q13,0) -> 365 | S13: 0 | T13: =ROUND(P13*S13,0) -> 0 | U13: =V13/P13 -> 0.024982888 | V13: =R13+T13 -> 365 | W13: =P13+V13 -> 14975 | X13: 14610 | Y13: =X13-P13 -> 0 | Z13: =ROUND(X13/P13-1,4) -> 0 | AA13: =IF(OR(N13=1,N13=2,N13=4), TEXT(U13*0.8,"0.00%") & "-" & TEXT(U13*1.2,"0.00%"), IF(OR(N13=3,N13=6), TEXT(0,"0.00%") & "-" & TEXT(7%*1.2,"0.00%"), IF(OR(N13=5,N13=7), TEXT((T13/P13),"0.00%") & "-" & TEXT((T13/P13)+7%,"0.00%"), "" ) ) ) -> 2.00%-3.00% | AF13: =ROUND(P13*AE13,0) -> 0 | AG13: =X13+AF13 -> 14610 | AH13: =AG13-P13 -> 0 | AI13: =AG13/P13-1 -> 0 | AJ13: 14 | AK13: 450 | AM13: 688 | AN13: =AG13*AJ13+AK13*12+AM13+IF(AD13="",AL13,IF(AD13="D",5000,IF(AD13="C",1000,0)))*12 -> 210628 | AO13: 3 | AQ13: Only focus on route tasks, lack of innovation and new product maturity improvement | AR13: Less responsibility compare with job level | AS13: Liu Haigang（15013255） | AT13: Zhu Qianqian（11016705） | AU13: Zhao Chujun | AW13: recommend increasing but propose zero increase | AY13: =_xlfn.LET(_xlpm.actual,Z13,_xlpm.low,VALUE(_xlfn.TEXTBEFORE(AA13,"-")),_xlpm.high,VALUE(_xlfn.TEXTAFTER(AA13,"-")),IF(AND(_xlpm.actual=0,OR(_xlpm.low<>0,_xlpm.high<>0)),"0 increase",IF(_xlpm.actual>_xlpm.high*1.2,">20",IF(_xlpm.actual<_xlpm.low*0.8,"<20","OK")))) -> 0 increase
A14: CN15 | B14: 15007522 | C14: 刘 栋 | D14: Liu Dong | E14: Indirect Active | F14: OP | G14: SNa | H14: FCGNa-VCE | I14: 330405 | J14: 41091 | K14: Supervisor | L14: Head of FCGNa-VCE | M14: BAND A6 | N14: 2 | O14: 3 | P14: 13100 | Q14: 0.03 | R14: =ROUND(P14*Q14,0) -> 393 | S14: 0 | T14: =ROUND(P14*S14,0) -> 0 | U14: =V14/P14 -> 0.03 | V14: =R14+T14 -> 393 | W14: =P14+V14 -> 13493 | X14: 14312 | Y14: =X14-P14 -> 1212 | Z14: =ROUND(X14/P14-1,4) -> 0.0925 | AA14: =IF(OR(N14=1,N14=2,N14=4), TEXT(U14*0.8,"0.00%") & "-" & TEXT(U14*1.2,"0.00%"), IF(OR(N14=3,N14=6), TEXT(0,"0.00%") & "-" & TEXT(7%*1.2,"0.00%"), IF(OR(N14=5,N14=7), TEXT((T14/P14),"0.00%") & "-" & TEXT((T14/P14)+7%,"0.00%"), "" ) ) ) -> 2.40%-3.60% | AF14: =ROUND(P14*AE14,0) -> 0 | AG14: =X14+AF14 -> 14312 | AH14: =AG14-P14 -> 1212 | AI14: =AG14/P14-1 -> 0.092519084 | AJ14: 14 | AK14: 450 | AM14: 688 | AN14: =AG14*AJ14+AK14*12+AM14+IF(AD14="",AL14,IF(AD14="D",5000,IF(AD14="C",1000,0)))*12 -> 206456 | AO14: 2 | AQ14: 1. In 2025, he achieved an 11% reduction in cooker SPC and cut silicone usage by 50%. 2. As a supervisor, his salary is the lowest in the team, so I need to catch up appropriately. | AR14: Good performers with relatively lower salary | AS14: Liu Haigang（15013255） | AT14: Zhu Qianqian（11016705） | AU14: Zhao Chujun | AW14: exceed +/-20% adjustment | AX14: >20 | AY14: =_xlfn.LET(_xlpm.actual,Z14,_xlpm.low,VALUE(_xlfn.TEXTBEFORE(AA14,"-")),_xlpm.high,VALUE(_xlfn.TEXTAFTER(AA14,"-")),IF(AND(_xlpm.actual=0,OR(_xlpm.low<>0,_xlpm.high<>0)),"0 increase",IF(_xlpm.actual>_xlpm.high*1.2,">20",IF(_xlpm.actual<_xlpm.low*0.8,"<20","OK")))) -> >20
A15: CN15 | B15: 15001471 | C15: 马 爱军 | D15: Ma Aijun | E15: Indirect Active | F15: OP | G15: SNa | H15: FCGNa-VCM | I15: 330405 | J15: 39546 | K15: Supervisor | L15: Head of FCGNa-VCM | M15: BAND A6 | N15: 2 | O15: 3 | P15: 15326 | Q15: 0.03 | R15: =ROUND(P15*Q15,0) -> 460 | S15: 0 | T15: =ROUND(P15*S15,0) -> 0 | U15: =V15/P15 -> 0.030014355 | V15: =R15+T15 -> 460 | W15: =P15+V15 -> 15786 | X15: 15326 | Y15: =X15-P15 -> 0 | Z15: =ROUND(X15/P15-1,4) -> 0 | AA15: =IF(OR(N15=1,N15=2,N15=4), TEXT(U15*0.8,"0.00%") & "-" & TEXT(U15*1.2,"0.00%"), IF(OR(N15=3,N15=6), TEXT(0,"0.00%") & "-" & TEXT(7%*1.2,"0.00%"), IF(OR(N15=5,N15=7), TEXT((T15/P15),"0.00%") & "-" & TEXT((T15/P15)+7%,"0.00%"), "" ) ) ) -> 2.40%-3.60% | AF15: =ROUND(P15*AE15,0) -> 0 | AG15: =X15+AF15 -> 15326 | AH15: =AG15-P15 -> 0 | AI15: =AG15/P15-1 -> 0 | AJ15: 14 | AK15: 450 | AM15: 688 | AN15: =AG15*AJ15+AK15*12+AM15+IF(AD15="",AL15,IF(AD15="D",5000,IF(AD15="C",1000,0)))*12 -> 220652 | AO15: 4 | AQ15: Low performance as supervisor | AR15: Low performer | AS15: Liu Haigang（15013255） | AT15: Zhu Qianqian（11016705） | AU15: Zhao Chujun | AW15: recommend increasing but propose zero increase | AY15: =_xlfn.LET(_xlpm.actual,Z15,_xlpm.low,VALUE(_xlfn.TEXTBEFORE(AA15,"-")),_xlpm.high,VALUE(_xlfn.TEXTAFTER(AA15,"-")),IF(AND(_xlpm.actual=0,OR(_xlpm.low<>0,_xlpm.high<>0)),"0 increase",IF(_xlpm.actual>_xlpm.high*1.2,">20",IF(_xlpm.actual<_xlpm.low*0.8,"<20","OK")))) -> 0 increase
A16: CN15 | B16: 15022189 | C16: 张 林波 | D16: Zhang Linbo | E16: Indirect Active | F16: OP | G16: SNa | H16: FCGNa-VCE | I16: 330401 | J16: 44713 | K16: Senior Engineer | L16: Press Senior Engineer | M16: BAND A5 | N16: 2 | O16: 3 | P16: 14850 | Q16: 0.025 | R16: =ROUND(P16*Q16,0) -> 371 | S16: 0 | T16: =ROUND(P16*S16,0) -> 0 | U16: =V16/P16 -> 0.024983165 | V16: =R16+T16 -> 371 | W16: =P16+V16 -> 15221 | X16: 15150 | Y16: =X16-P16 -> 300 | Z16: =ROUND(X16/P16-1,4) -> 0.0202 | AA16: =IF(OR(N16=1,N16=2,N16=4), TEXT(U16*0.8,"0.00%") & "-" & TEXT(U16*1.2,"0.00%"), IF(OR(N16=3,N16=6), TEXT(0,"0.00%") & "-" & TEXT(7%*1.2,"0.00%"), IF(OR(N16=5,N16=7), TEXT((T16/P16),"0.00%") & "-" & TEXT((T16/P16)+7%,"0.00%"), "" ) ) ) -> 2.00%-3.00% | AF16: =ROUND(P16*AE16,0) -> 0 | AG16: =X16+AF16 -> 15150 | AH16: =AG16-P16 -> 300 | AI16: =AG16/P16-1 -> 0.02020202 | AJ16: 14 | AK16: 450 | AM16: 688 | AN16: =AG16*AJ16+AK16*12+AM16+IF(AD16="",AL16,IF(AD16="D",5000,IF(AD16="C",1000,0)))*12 -> 218188 | AO16: 3 | AS16: Liu Haigang（15013255） | AT16: Zhu Qianqian（11016705） | AU16: Zhao Chujun | AY16: =_xlfn.LET(_xlpm.actual,Z16,_xlpm.low,VALUE(_xlfn.TEXTBEFORE(AA16,"-")),_xlpm.high,VALUE(_xlfn.TEXTAFTER(AA16,"-")),IF(AND(_xlpm.actual=0,OR(_xlpm.low<>0,_xlpm.high<>0)),"0 increase",IF(_xlpm.actual>_xlpm.high*1.2,">20",IF(_xlpm.actual<_xlpm.low*0.8,"<20","OK")))) -> OK
A17: CN15 | B17: 15017481 | C17: 赵 磊 | D17: Zhao Lei | E17: Indirect Active | F17: OP | G17: SNa | H17: FCGNa-VCE | I17: 330405 | J17: 42893 | K17: Senior Engineer | L17: Senior Engineer | M17: BAND A5 | N17: 2 | O17: 2 | P17: 13610 | Q17: 0 | R17: =ROUND(P17*Q17,0) -> 0 | S17: 0 | T17: =ROUND(P17*S17,0) -> 0 | U17: =V17/P17 -> 0 | V17: =R17+T17 -> 0 | W17: =P17+V17 -> 13610 | X17: 13610 | Y17: =X17-P17 -> 0 | Z17: =ROUND(X17/P17-1,4) -> 0 | AA17: =IF(OR(N17=1,N17=2,N17=4), TEXT(U17*0.8,"0.00%") & "-" & TEXT(U17*1.2,"0.00%"), IF(OR(N17=3,N17=6), TEXT(0,"0.00%") & "-" & TEXT(7%*1.2,"0.00%"), IF(OR(N17=5,N17=7), TEXT((T17/P17),"0.00%") & "-" & TEXT((T17/P17)+7%,"0.00%"), "" ) ) ) -> 0.00%-0.00% | AF17: =ROUND(P17*AE17,0) -> 0 | AG17: =X17+AF17 -> 13610 | AH17: =AG17-P17 -> 0 | AI17: =AG17/P17-1 -> 0 | AJ17: 14 | AK17: 550 | AM17: 688 | AN17: =AG17*AJ17+AK17*12+AM17+IF(AD17="",AL17,IF(AD17="D",5000,IF(AD17="C",1000,0)))*12 -> 197828 | AO17: 3 | AS17: Liu Haigang（15013255） | AT17: Zhu Qianqian（11016705） | AU17: Zhao Chujun | AY17: =_xlfn.LET(_xlpm.actual,Z17,_xlpm.low,VALUE(_xlfn.TEXTBEFORE(AA17,"-")),_xlpm.high,VALUE(_xlfn.TEXTAFTER(AA17,"-")),IF(AND(_xlpm.actual=0,OR(_xlpm.low<>0,_xlpm.high<>0)),"0 increase",IF(_xlpm.actual>_xlpm.high*1.2,">20",IF(_xlpm.actual<_xlpm.low*0.8,"<20","OK")))) -> OK
A18: CN15 | B18: 15014900 | C18: 李 辉祥 | D18: Li Huixiang | E18: Indirect Active | F18: OP | G18: SNa | H18: FCGNa | I18: 330100 | J18: 42298 | K18: Manager | L18: Manager | M18: BAND B | N18: 2 | O18: 2 | P18: 20200 | Q18: 0 | R18: =ROUND(P18*Q18,0) -> 0 | S18: 0 | T18: =ROUND(P18*S18,0) -> 0 | U18: =V18/P18 -> 0 | V18: =R18+T18 -> 0 | W18: =P18+V18 -> 20200 | X18: =W18 -> 20200 | Y18: =X18-P18 -> 0 | Z18: =ROUND(X18/P18-1,4) -> 0 | AA18: =IF(OR(N18=1,N18=2,N18=4), TEXT(U18*0.8,"0.00%") & "-" & TEXT(U18*1.2,"0.00%"), IF(OR(N18=3,N18=6), TEXT(0,"0.00%") & "-" & TEXT(7%*1.2,"0.00%"), IF(OR(N18=5,N18=7), TEXT((T18/P18),"0.00%") & "-" & TEXT((T18/P18)+7%,"0.00%"), "" ) ) ) -> 0.00%-0.00% | AF18: =ROUND(P18*AE18,0) -> 0 | AG18: =X18+AF18 -> 20200 | AH18: =AG18-P18 -> 0 | AI18: =AG18/P18-1 -> 0 | AJ18: 14 | AK18: 450 | AM18: 688 | AN18: =AG18*AJ18+AK18*12+AM18+IF(AD18="",AL18,IF(AD18="D",5000,IF(AD18="C",1000,0)))*12 -> 288888 | AO18: 3 | AS18: Chen Chao（15005032） | AT18: Zhu Qianqian（11016705） | AU18: Zhao Chujun | AY18: =_xlfn.LET(_xlpm.actual,Z18,_xlpm.low,VALUE(_xlfn.TEXTBEFORE(AA18,"-")),_xlpm.high,VALUE(_xlfn.TEXTAFTER(AA18,"-")),IF(AND(_xlpm.actual=0,OR(_xlpm.low<>0,_xlpm.high<>0)),"0 increase",IF(_xlpm.actual>_xlpm.high*1.2,">20",IF(_xlpm.actual<_xlpm.low*0.8,"<20","OK")))) -> OK
A19: CN15 | B19: 15013255 | C19: 刘 海刚 | D19: Liu Haigang | E19: Indirect Active | F19: OP | G19: SNa | H19: FCGNa-VC | I19: 330405 | J19: 41801 | K19: Manager | L19: Head of Value Stream Cooktop | M19: BAND B | N19: 2 | O19: 4 | P19: 23800 | Q19: 0.03 | R19: =ROUND(P19*Q19,0) -> 714 | S19: 0 | T19: =ROUND(P19*S19,0) -> 0 | U19: =V19/P19 -> 0.03 | V19: =R19+T19 -> 714 | W19: =P19+V19 -> 24514 | X19: =W19 -> 24514 | Y19: =X19-P19 -> 714 | Z19: =ROUND(X19/P19-1,4) -> 0.03 | AA19: =IF(OR(N19=1,N19=2,N19=4), TEXT(U19*0.8,"0.00%") & "-" & TEXT(U19*1.2,"0.00%"), IF(OR(N19=3,N19=6), TEXT(0,"0.00%") & "-" & TEXT(7%*1.2,"0.00%"), IF(OR(N19=5,N19=7), TEXT((T19/P19),"0.00%") & "-" & TEXT((T19/P19)+7%,"0.00%"), "" ) ) ) -> 2.40%-3.60% | AB19: Promotion | AC19: Head of Value Stream Cooktop | AD19: C | AE19: 0.09 | AF19: =ROUND(P19*AE19,0) -> 2142 | AG19: =X19+AF19 -> 26656 | AH19: =AG19-P19 -> 2856 | AI19: =AG19/P19-1 -> 0.12 | AJ19: 14 | AK19: 450 | AM19: 688 | AN19: =AG19*AJ19+AK19*12+AM19+IF(AD19="",AL19,IF(AD19="D",5000,IF(AD19="C",1000,0)))*12 -> 391272 | AO19: 5 | AQ19: Good performance and high competence | AR19: Good performance and high competence | AS19: Chen Chao（15005032） | AT19: Zhu Qianqian（11016705） | AU19: Zhao Chujun | AY19: =_xlfn.LET(_xlpm.actual,Z19,_xlpm.low,VALUE(_xlfn.TEXTBEFORE(AA19,"-")),_xlpm.high,VALUE(_xlfn.TEXTAFTER(AA19,"-")),IF(AND(_xlpm.actual=0,OR(_xlpm.low<>0,_xlpm.high<>0)),"0 increase",IF(_xlpm.actual>_xlpm.high*1.2,">20",IF(_xlpm.actual<_xlpm.low*0.8,"<20","OK")))) -> OK
A20: CN15 | B20: 15005811 | C20: 缪 思远 | D20: Miao Siyuan | E20: Indirect Active | F20: OP | G20: SNa | H20: FCGNa-VV | I20: 330404 | J20: 40646 | K20: Manager | L20: Head of Value Stream Ventilation | M20: BAND B | N20: 2 | O20: 5 | P20: 24500 | Q20: 0.04 | R20: =ROUND(P20*Q20,0) -> 980 | S20: 0 | T20: =ROUND(P20*S20,0) -> 0 | U20: =V20/P20 -> 0.04 | V20: =R20+T20 -> 980 | W20: =P20+V20 -> 25480 | X20: =W20 -> 25480 | Y20: =X20-P20 -> 980 | Z20: =ROUND(X20/P20-1,4) -> 0.04 | AA20: =IF(OR(N20=1,N20=2,N20=4), TEXT(U20*0.8,"0.00%") & "-" & TEXT(U20*1.2,"0.00%"), IF(OR(N20=3,N20=6), TEXT(0,"0.00%") & "-" & TEXT(7%*1.2,"0.00%"), IF(OR(N20=5,N20=7), TEXT((T20/P20),"0.00%") & "-" & TEXT((T20/P20)+7%,"0.00%"), "" ) ) ) -> 3.20%-4.80% | AB20: Promotion | AC20: Head of Value Stream Ventilation | AD20: C | AE20: 0.08 | AF20: =ROUND(P20*AE20,0) -> 1960 | AG20: =X20+AF20 -> 27440 | AH20: =AG20-P20 -> 2940 | AI20: =AG20/P20-1 -> 0.12 | AJ20: 14 | AK20: 450 | AM20: 688 | AN20: =AG20*AJ20+AK20*12+AM20+IF(AD20="",AL20,IF(AD20="D",5000,IF(AD20="C",1000,0)))*12 -> 402248 | AO20: 3 | AQ20: Good performance and high competence | AR20: Good performance and high competence | AS20: Chen Chao（15005032） | AT20: Zhu Qianqian（11016705） | AU20: Zhao Chujun | AY20: =_xlfn.LET(_xlpm.actual,Z20,_xlpm.low,VALUE(_xlfn.TEXTBEFORE(AA20,"-")),_xlpm.high,VALUE(_xlfn.TEXTAFTER(AA20,"-")),IF(AND(_xlpm.actual=0,OR(_xlpm.low<>0,_xlpm.high<>0)),"0 increase",IF(_xlpm.actual>_xlpm.high*1.2,">20",IF(_xlpm.actual<_xlpm.low*0.8,"<20","OK")))) -> OK
A21: CN15 | B21: 15022316 | C21: 孙 超 | D21: Sun Chao | E21: Indirect Active | F21: OP | G21: SNa | H21: FCGNa | I21: 330100 | J21: 44930 | K21: Senior Engineer | L21: Senior Testing and Programming Engineer | M21: BAND A5 | N21: 2 | O21: 3 | P21: 14375 | Q21: 0.025 | R21: =ROUND(P21*Q21,0) -> 359 | S21: 0 | T21: =ROUND(P21*S21,0) -> 0 | U21: =V21/P21 -> 0.024973913 | V21: =R21+T21 -> 359 | W21: =P21+V21 -> 14734 | X21: =W21 -> 14734 | Y21: =X21-P21 -> 359 | Z21: =ROUND(X21/P21-1,4) -> 0.025 | AA21: =IF(OR(N21=1,N21=2,N21=4), TEXT(U21*0.8,"0.00%") & "-" & TEXT(U21*1.2,"0.00%"), IF(OR(N21=3,N21=6), TEXT(0,"0.00%") & "-" & TEXT(7%*1.2,"0.00%"), IF(OR(N21=5,N21=7), TEXT((T21/P21),"0.00%") & "-" & TEXT((T21/P21)+7%,"0.00%"), "" ) ) ) -> 2.00%-3.00% | AF21: =ROUND(P21*AE21,0) -> 0 | AG21: =X21+AF21 -> 14734 | AH21: =AG21-P21 -> 359 | AI21: =AG21/P21-1 -> 0.024973913 | AJ21: 14 | AK21: 450 | AM21: 688 | AN21: =AG21*AJ21+AK21*12+AM21+IF(AD21="",AL21,IF(AD21="D",5000,IF(AD21="C",1000,0)))*12 -> 212364 | AO21: 4 | AS21: Chen Chao（15005032） | AT21: Zhu Qianqian（11016705） | AU21: Zhao Chujun | AY21: =_xlfn.LET(_xlpm.actual,Z21,_xlpm.low,VALUE(_xlfn.TEXTBEFORE(AA21,"-")),_xlpm.high,VALUE(_xlfn.TEXTAFTER(AA21,"-")),IF(AND(_xlpm.actual=0,OR(_xlpm.low<>0,_xlpm.high<>0)),"0 increase",IF(_xlpm.actual>_xlpm.high*1.2,">20",IF(_xlpm.actual<_xlpm.low*0.8,"<20","OK")))) -> OK
A22: CN15 | B22: 15001764 | C22: 张 利利 | D22: Zhang Lili | E22: Indirect Active | F22: OP | G22: SNa | H22: FCGNa | I22: 330100 | J22: 40360 | K22: Senior Engineer | L22: Senior Engineer | M22: BAND A5 | N22: 2 | O22: 4 | P22: 9891 | Q22: 0.045 | R22: =ROUND(P22*Q22,0) -> 445 | S22: 0.0421 | T22: =ROUND(P22*S22,0) -> 416 | U22: =V22/P22 -> 0.087048832 | V22: =R22+T22 -> 861 | W22: =P22+V22 -> 10752 | X22: =W22 -> 10752 | Y22: =X22-P22 -> 861 | Z22: =ROUND(X22/P22-1,4) -> 0.087 | AA22: =IF(OR(N22=1,N22=2,N22=4), TEXT(U22*0.8,"0.00%") & "-" & TEXT(U22*1.2,"0.00%"), IF(OR(N22=3,N22=6), TEXT(0,"0.00%") & "-" & TEXT(7%*1.2,"0.00%"), IF(OR(N22=5,N22=7), TEXT((T22/P22),"0.00%") & "-" & TEXT((T22/P22)+7%,"0.00%"), "" ) ) ) -> 6.96%-10.45% | AF22: =ROUND(P22*AE22,0) -> 0 | AG22: =X22+AF22 -> 10752 | AH22: =AG22-P22 -> 861 | AI22: =AG22/P22-1 -> 0.087048832 | AJ22: 14 | AK22: 450 | AM22: 688 | AN22: =AG22*AJ22+AK22*12+AM22+IF(AD22="",AL22,IF(AD22="D",5000,IF(AD22="C",1000,0)))*12 -> 156616 | AO22: 3 | AS22: Chen Chao（15005032） | AT22: Zhu Qianqian（11016705） | AU22: Zhao Chujun | AY22: =_xlfn.LET(_xlpm.actual,Z22,_xlpm.low,VALUE(_xlfn.TEXTBEFORE(AA22,"-")),_xlpm.high,VALUE(_xlfn.TEXTAFTER(AA22,"-")),IF(AND(_xlpm.actual=0,OR(_xlpm.low<>0,_xlpm.high<>0)),"0 increase",IF(_xlpm.actual>_xlpm.high*1.2,">20",IF(_xlpm.actual<_xlpm.low*0.8,"<20","OK")))) -> OK
A23: CN15 | B23: 15022180 | C23: 陈 邢逸 | D23: Chen Xingyi | E23: Indirect Active | F23: OP | G23: SNa | H23: FEDNa-MEP | I23: 370200 | J23: 44686 | K23: Engineer | L23: Process Engineer | M23: BAND A4 | N23: 2 | O23: 3 | P23: 8200 | Q23: 0.025 | R23: =ROUND(P23*Q23,0) -> 205 | S23: 0 | T23: =ROUND(P23*S23,0) -> 0 | U23: =V23/P23 -> 0.025 | V23: =R23+T23 -> 205 | W23: =P23+V23 -> 8405 | X23: 8415 | Y23: =X23-P23 -> 215 | Z23: =ROUND(X23/P23-1,4) -> 0.0262 | AA23: =IF(OR(N23=1,N23=2,N23=4),TEXT(U23*0.8,"0.00%")&"-"&TEXT(U23*1.2,"0.00%"),IF(OR(N23=3,N23=6),TEXT(0,"0.00%")&"-"&TEXT(7%*1.2,"0.00%"),IF(OR(N23=5,N23=7),TEXT((T23/P23),"0.00%")&"-"&TEXT((T23/P23)+7%,"0.00%"),""))) -> 2.00%-3.00% | AF23: =ROUND(P23*AE23,0) -> 0 | AG23: =X23+AF23 -> 8415 | AH23: =AG23-P23 -> 215 | AI23: =AG23/P23-1 -> 0.026219512 | AJ23: 14 | AK23: 550 | AM23: 688 | AN23: =AG23*AJ23+AK23*12+AM23+IF(AD23="",AL23,IF(AD23="D",5000,IF(AD23="C",1000,0)))*12 -> 125098 | AO23: 3 | AS23: Ding Xudong（15000307） | AT23: Xu Lan（11013544） | AU23: Zhao Chujun | AY23: =_xlfn.LET(_xlpm.actual,Z23,_xlpm.low,VALUE(_xlfn.TEXTBEFORE(AA23,"-")),_xlpm.high,VALUE(_xlfn.TEXTAFTER(AA23,"-")),IF(AND(_xlpm.actual=0,OR(_xlpm.low<>0,_xlpm.high<>0)),"0 increase",IF(_xlpm.actual>_xlpm.high*1.2,">20",IF(_xlpm.actual<_xlpm.low*0.8,"<20","OK")))) -> OK
A24: CN15 | B24: 15003790 | C24: 方 红祥 | D24: Fang Hongxiang | E24: Indirect Active | F24: OP | G24: SNa | H24: FEDNa-MEM | I24: 370201 | J24: 40310 | K24: Supervisor | L24: Head of Mechanical Support | M24: BAND A6 | N24: 2 | O24: 3 | P24: 15324 | Q24: 0.03 | R24: =ROUND(P24*Q24,0) -> 460 | S24: 0 | T24: =ROUND(P24*S24,0) -> 0 | U24: =V24/P24 -> 0.030018272 | V24: =R24+T24 -> 460 | W24: =P24+V24 -> 15784 | X24: 15600 | Y24: =X24-P24 -> 276 | Z24: =ROUND(X24/P24-1,4) -> 0.018 | AA24: =IF(OR(N24=1,N24=2,N24=4),TEXT(U24*0.8,"0.00%")&"-"&TEXT(U24*1.2,"0.00%"),IF(OR(N24=3,N24=6),TEXT(0,"0.00%")&"-"&TEXT(7%*1.2,"0.00%"),IF(OR(N24=5,N24=7),TEXT((T24/P24),"0.00%")&"-"&TEXT((T24/P24)+7%,"0.00%"),""))) -> 2.40%-3.60% | AF24: =ROUND(P24*AE24,0) -> 0 | AG24: =X24+AF24 -> 15600 | AH24: =AG24-P24 -> 276 | AI24: =AG24/P24-1 -> 0.018010963 | AJ24: 14 | AK24: 450 | AM24: 688 | AN24: =AG24*AJ24+AK24*12+AM24+IF(AD24="",AL24,IF(AD24="D",5000,IF(AD24="C",1000,0)))*12 -> 224488 | AO24: 3 | AR24: Internal balance | AS24: Ding Xudong（15000307） | AT24: Xu Lan（11013544） | AU24: Zhao Chujun | AW24: exceed +/-20% adjustment | AX24: <20 | AY24: =_xlfn.LET(_xlpm.actual,Z24,_xlpm.low,VALUE(_xlfn.TEXTBEFORE(AA24,"-")),_xlpm.high,VALUE(_xlfn.TEXTAFTER(AA24,"-")),IF(AND(_xlpm.actual=0,OR(_xlpm.low<>0,_xlpm.high<>0)),"0 increase",IF(_xlpm.actual>_xlpm.high*1.2,">20",IF(_xlpm.actual<_xlpm.low*0.8,"<20","OK")))) -> <20
A25: CN15 | B25: 15016330 | C25: 何 磊 | D25: He Lei | E25: Indirect Active | F25: OP | G25: SNa | H25: FEDNa-V2 | I25: 370400 | J25: 42781 | K25: Manager | L25: Head of FEDNa-V2 | M25: BAND B | N25: 2 | O25: 4 | P25: 20300 | Q25: 0.0375 | R25: =ROUND(P25*Q25,0) -> 761 | S25: 0.0155 | T25: =ROUND(P25*S25,0) -> 315 | U25: =V25/P25 -> 0.053004926 | V25: =R25+T25 -> 1076 | W25: =P25+V25 -> 21376 | X25: 21500 | Y25: =X25-P25 -> 1200 | Z25: =ROUND(X25/P25-1,4) -> 0.0591 | AA25: =IF(OR(N25=1,N25=2,N25=4),TEXT(U25*0.8,"0.00%")&"-"&TEXT(U25*1.2,"0.00%"),IF(OR(N25=3,N25=6),TEXT(0,"0.00%")&"-"&TEXT(7%*1.2,"0.00%"),IF(OR(N25=5,N25=7),TEXT((T25/P25),"0.00%")&"-"&TEXT((T25/P25)+7%,"0.00%"),""))) -> 4.24%-6.36% | AF25: =ROUND(P25*AE25,0) -> 0 | AG25: =X25+AF25 -> 21500 | AH25: =AG25-P25 -> 1200 | AI25: =AG25/P25-1 -> 0.0591133 | AJ25: 14 | AK25: 450 | AM25: 688 | AN25: =AG25*AJ25+AK25*12+AM25+IF(AD25="",AL25,IF(AD25="D",5000,IF(AD25="C",1000,0)))*12 -> 307088 | AO25: 3 | AS25: Ding Xudong（15000307） | AT25: Xu Lan（11013544） | AU25: Zhao Chujun | AY25: =_xlfn.LET(_xlpm.actual,Z25,_xlpm.low,VALUE(_xlfn.TEXTBEFORE(AA25,"-")),_xlpm.high,VALUE(_xlfn.TEXTAFTER(AA25,"-")),IF(AND(_xlpm.actual=0,OR(_xlpm.low<>0,_xlpm.high<>0)),"0 increase",IF(_xlpm.actual>_xlpm.high*1.2,">20",IF(_xlpm.actual<_xlpm.low*0.8,"<20","OK")))) -> OK
A26: CN15 | B26: 15001485 | C26: 李 新华 | D26: Li Xinhua | E26: Indirect Active | F26: OP | G26: SNa | H26: FEDNa-ME | I26: 370200 | J26: 39547 | K26: Manager | L26: Head of Manufacturing Engineering | M26: BAND B | N26: 2 | O26: 3 | P26: 27011 | Q26: 0.025 | R26: =ROUND(P26*Q26,0) -> 675 | S26: 0 | T26: =ROUND(P26*S26,0) -> 0 | U26: =V26/P26 -> 0.024989819 | V26: =R26+T26 -> 675 | W26: =P26+V26 -> 27686 | X26: 27700 | Y26: =X26-P26 -> 689 | Z26: =ROUND(X26/P26-1,4) -> 0.0255 | AA26: =IF(OR(N26=1,N26=2,N26=4),TEXT(U26*0.8,"0.00%")&"-"&TEXT(U26*1.2,"0.00%"),IF(OR(N26=3,N26=6),TEXT(0,"0.00%")&"-"&TEXT(7%*1.2,"0.00%"),IF(OR(N26=5,N26=7),TEXT((T26/P26),"0.00%")&"-"&TEXT((T26/P26)+7%,"0.00%"),""))) -> 2.00%-3.00% | AF26: =ROUND(P26*AE26,0) -> 0 | AG26: =X26+AF26 -> 27700 | AH26: =AG26-P26 -> 689 | AI26: =AG26/P26-1 -> 0.025508126 | AJ26: 14 | AK26: 450 | AM26: 688 | AN26: =AG26*AJ26+AK26*12+AM26+IF(AD26="",AL26,IF(AD26="D",5000,IF(AD26="C",1000,0)))*12 -> 393888 | AO26: 4 | AS26: Ding Xudong（15000307） | AT26: Xu Lan（11013544） | AU26: Zhao Chujun | AY26: =_xlfn.LET(_xlpm.actual,Z26,_xlpm.low,VALUE(_xlfn.TEXTBEFORE(AA26,"-")),_xlpm.high,VALUE(_xlfn.TEXTAFTER(AA26,"-")),IF(AND(_xlpm.actual=0,OR(_xlpm.low<>0,_xlpm.high<>0)),"0 increase",IF(_xlpm.actual>_xlpm.high*1.2,">20",IF(_xlpm.actual<_xlpm.low*0.8,"<20","OK")))) -> OK
A27: CN15 | B27: 1020358 | C27: 刘 继萍 | D27: Liu Jiping | E27: Indirect Active | F27: OP | G27: SNa | H27: FEDNa-MEP | I27: 370200 | J27: 45000 | K27: Senior Engineer | L27: Senior Process Engineer | M27: BAND A5 | N27: 2 | O27: 5 | P27: 13610 | Q27: 0.05 | R27: =ROUND(P27*Q27,0) -> 681 | S27: 0.027 | T27: =ROUND(P27*S27,0) -> 367 | U27: =V27/P27 -> 0.077002204 | V27: =R27+T27 -> 1048 | W27: =P27+V27 -> 14658 | X27: 15000 | Y27: =X27-P27 -> 1390 | Z27: =ROUND(X27/P27-1,4) -> 0.1021 | AA27: =IF(OR(N27=1,N27=2,N27=4),TEXT(U27*0.8,"0.00%")&"-"&TEXT(U27*1.2,"0.00%"),IF(OR(N27=3,N27=6),TEXT(0,"0.00%")&"-"&TEXT(7%*1.2,"0.00%"),IF(OR(N27=5,N27=7),TEXT((T27/P27),"0.00%")&"-"&TEXT((T27/P27)+7%,"0.00%"),""))) -> 6.16%-9.24% | AF27: =ROUND(P27*AE27,0) -> 0 | AG27: =X27+AF27 -> 15000 | AH27: =AG27-P27 -> 1390 | AI27: =AG27/P27-1 -> 0.10213079 | AJ27: 14 | AK27: 450 | AM27: 688 | AN27: =AG27*AJ27+AK27*12+AM27+IF(AD27="",AL27,IF(AD27="D",5000,IF(AD27="C",1000,0)))*12 -> 216088 | AO27: 3 | AR27: Rounding | AS27: Ding Xudong（15000307） | AT27: Xu Lan（11013544） | AU27: Zhao Chujun | AW27: exceed +/-20% adjustment | AX27: >20 | AY27: =_xlfn.LET(_xlpm.actual,Z27,_xlpm.low,VALUE(_xlfn.TEXTBEFORE(AA27,"-")),_xlpm.high,VALUE(_xlfn.TEXTAFTER(AA27,"-")),IF(AND(_xlpm.actual=0,OR(_xlpm.low<>0,_xlpm.high<>0)),"0 increase",IF(_xlpm.actual>_xlpm.high*1.2,">20",IF(_xlpm.actual<_xlpm.low*0.8,"<20","OK")))) -> OK
A28: CN15 | B28: 15021547 | C28: 刘 彦达 | D28: Liu Yanda | E28: Indirect Active | F28: OP | G28: SNa | H28: FEDNa-MEP | I28: 370200 | J28: 44391 | K28: Engineer | L28: Electrical Engineer | M28: BAND A4 | N28: 2 | O28: 4 | P28: 10500 | Q28: 0.0375 | R28: =ROUND(P28*Q28,0) -> 394 | S28: 0 | T28: =ROUND(P28*S28,0) -> 0 | U28: =V28/P28 -> 0.03752381 | V28: =R28+T28 -> 394 | W28: =P28+V28 -> 10894 | X28: 10827 | Y28: =X28-P28 -> 327 | Z28: =ROUND(X28/P28-1,4) -> 0.0311 | AA28: =IF(OR(N28=1,N28=2,N28=4),TEXT(U28*0.8,"0.00%")&"-"&TEXT(U28*1.2,"0.00%"),IF(OR(N28=3,N28=6),TEXT(0,"0.00%")&"-"&TEXT(7%*1.2,"0.00%"),IF(OR(N28=5,N28=7),TEXT((T28/P28),"0.00%")&"-"&TEXT((T28/P28)+7%,"0.00%"),""))) -> 3.00%-4.50% | AB28: Promotion | AC28: senior engineer | AD28: A5 | AE28: 0.1117 | AF28: =ROUND(P28*AE28,0) -> 1173 | AG28: =X28+AF28 -> 12000 | AH28: =AG28-P28 -> 1500 | AI28: =AG28/P28-1 -> 0.14285714 | AJ28: 14 | AK28: 500 | AM28: 688 | AN28: =AG28*AJ28+AK28*12+AM28+IF(AD28="",AL28,IF(AD28="D",5000,IF(AD28="C",1000,0)))*12 -> 174688 | AO28: 3 | AR28: Good performance and high competence | AS28: Ding Xudong（15000307） | AT28: Xu Lan（11013544） | AU28: Zhao Chujun | AY28: =_xlfn.LET(_xlpm.actual,Z28,_xlpm.low,VALUE(_xlfn.TEXTBEFORE(AA28,"-")),_xlpm.high,VALUE(_xlfn.TEXTAFTER(AA28,"-")),IF(AND(_xlpm.actual=0,OR(_xlpm.low<>0,_xlpm.high<>0)),"0 increase",IF(_xlpm.actual>_xlpm.high*1.2,">20",IF(_xlpm.actual<_xlpm.low*0.8,"<20","OK")))) -> OK
A29: CN15 | B29: 15012913 | C29: 陆 彬 | D29: Lu Bin | E29: Indirect Active | F29: OP | G29: SNa | H29: FEDNa-ME | I29: 370200 | J29: 41738 | K29: Associate Expert (CN) | L29: Associate Expert (C) | M29: BAND A6 | N29: 2 | O29: 5 | P29: 16000 | Q29: 0.06 | R29: =ROUND(P29*Q29,0) -> 960 | S29: 0.0778 | T29: =ROUND(P29*S29,0) -> 1245 | U29: =V29/P29 -> 0.1378125 | V29: =R29+T29 -> 2205 | W29: =P29+V29 -> 18205 | X29: 18000 | Y29: =X29-P29 -> 2000 | Z29: =ROUND(X29/P29-1,4) -> 0.125 | AA29: =IF(OR(N29=1,N29=2,N29=4),TEXT(U29*0.8,"0.00%")&"-"&TEXT(U29*1.2,"0.00%"),IF(OR(N29=3,N29=6),TEXT(0,"0.00%")&"-"&TEXT(7%*1.2,"0.00%"),IF(OR(N29=5,N29=7),TEXT((T29/P29),"0.00%")&"-"&TEXT((T29/P29)+7%,"0.00%"),""))) -> 11.03%-16.54% | AF29: =ROUND(P29*AE29,0) -> 0 | AG29: =X29+AF29 -> 18000 | AH29: =AG29-P29 -> 2000 | AI29: =AG29/P29-1 -> 0.125 | AJ29: 14 | AK29: 500 | AM29: 688 | AN29: =AG29*AJ29+AK29*12+AM29+IF(AD29="",AL29,IF(AD29="D",5000,IF(AD29="C",1000,0)))*12 -> 258688 | AO29: 4 | AS29: Ding Xudong（15000307） | AT29: Xu Lan（11013544） | AU29: Zhao Chujun | AY29: =_xlfn.LET(_xlpm.actual,Z29,_xlpm.low,VALUE(_xlfn.TEXTBEFORE(AA29,"-")),_xlpm.high,VALUE(_xlfn.TEXTAFTER(AA29,"-")),IF(AND(_xlpm.actual=0,OR(_xlpm.low<>0,_xlpm.high<>0)),"0 increase",IF(_xlpm.actual>_xlpm.high*1.2,">20",IF(_xlpm.actual<_xlpm.low*0.8,"<20","OK")))) -> OK
A30: CN15 | B30: 15001306 | C30: 钱 山杰 | D30: Qian Shanjie | E30: Indirect Active | F30: OP | G30: SNa | H30: FEDNa-ME | I30: 370200 | J30: 39420 | K30: Functional Specialist | L30: Functional Specialist | M30: BAND A6 | N30: 2 | O30: 3 | P30: 20306 | Q30: 0 | R30: =ROUND(P30*Q30,0) -> 0 | S30: 0 | T30: =ROUND(P30*S30,0) -> 0 | U30: =V30/P30 -> 0 | V30: =R30+T30 -> 0 | W30: =P30+V30 -> 20306 | X30: 20500 | Y30: =X30-P30 -> 194 | Z30: =ROUND(X30/P30-1,4) -> 0.0096 | AA30: =IF(OR(N30=1,N30=2,N30=4),TEXT(U30*0.8,"0.00%")&"-"&TEXT(U30*1.2,"0.00%"),IF(OR(N30=3,N30=6),TEXT(0,"0.00%")&"-"&TEXT(7%*1.2,"0.00%"),IF(OR(N30=5,N30=7),TEXT((T30/P30),"0.00%")&"-"&TEXT((T30/P30)+7%,"0.00%"),""))) -> 0.00%-0.00% | AF30: =ROUND(P30*AE30,0) -> 0 | AG30: =X30+AF30 -> 20500 | AH30: =AG30-P30 -> 194 | AI30: =AG30/P30-1 -> 0.0095538265 | AJ30: 14 | AK30: 600 | AM30: 688 | AN30: =AG30*AJ30+AK30*12+AM30+IF(AD30="",AL30,IF(AD30="D",5000,IF(AD30="C",1000,0)))*12 -> 294888 | AO30: 4 | AR30: Good performance and high competence | AS30: Ding Xudong（15000307） | AT30: Xu Lan（11013544） | AU30: Zhao Chujun | AW30: exceed +/-20% adjustment | AX30: >20 | AY30: =_xlfn.LET(_xlpm.actual,Z30,_xlpm.low,VALUE(_xlfn.TEXTBEFORE(AA30,"-")),_xlpm.high,VALUE(_xlfn.TEXTAFTER(AA30,"-")),IF(AND(_xlpm.actual=0,OR(_xlpm.low<>0,_xlpm.high<>0)),"0 increase",IF(_xlpm.actual>_xlpm.high*1.2,">20",IF(_xlpm.actual<_xlpm.low*0.8,"<20","OK")))) -> >20
A31: CN15 | B31: 15021548 | C31: 沈 燕达 | D31: Shen Yanda | E31: Indirect Active | F31: OP | G31: SNa | H31: FEDNa-ME | I31: 370200 | J31: 44391 | K31: Senior Engineer | L31: Senior Equipment Engineer | M31: BAND A5 | N31: 2 | O31: 3 | P31: 13330 | Q31: 0.025 | R31: =ROUND(P31*Q31,0) -> 333 | S31: 0 | T31: =ROUND(P31*S31,0) -> 0 | U31: =V31/P31 -> 0.024981245 | V31: =R31+T31 -> 333 | W31: =P31+V31 -> 13663 | X31: 13600 | Y31: =X31-P31 -> 270 | Z31: =ROUND(X31/P31-1,4) -> 0.0203 | AA31: =IF(OR(N31=1,N31=2,N31=4),TEXT(U31*0.8,"0.00%")&"-"&TEXT(U31*1.2,"0.00%"),IF(OR(N31=3,N31=6),TEXT(0,"0.00%")&"-"&TEXT(7%*1.2,"0.00%"),IF(OR(N31=5,N31=7),TEXT((T31/P31),"0.00%")&"-"&TEXT((T31/P31)+7%,"0.00%"),""))) -> 2.00%-3.00% | AF31: =ROUND(P31*AE31,0) -> 0 | AG31: =X31+AF31 -> 13600 | AH31: =AG31-P31 -> 270 | AI31: =AG31/P31-1 -> 0.020255064 | AJ31: 14 | AK31: 450 | AM31: 688 | AN31: =AG31*AJ31+AK31*12+AM31+IF(AD31="",AL31,IF(AD31="D",5000,IF(AD31="C",1000,0)))*12 -> 196488 | AO31: 3 | AS31: Ding Xudong（15000307） | AT31: Xu Lan（11013544） | AU31: Zhao Chujun | AY31: =_xlfn.LET(_xlpm.actual,Z31,_xlpm.low,VALUE(_xlfn.TEXTBEFORE(AA31,"-")),_xlpm.high,VALUE(_xlfn.TEXTAFTER(AA31,"-")),IF(AND(_xlpm.actual=0,OR(_xlpm.low<>0,_xlpm.high<>0)),"0 increase",IF(_xlpm.actual>_xlpm.high*1.2,">20",IF(_xlpm.actual<_xlpm.low*0.8,"<20","OK")))) -> OK
A32: CN15 | B32: 15021979 | C32: 孙 毅 | D32: Sun Yi | E32: Indirect Active | F32: OP | G32: SNa | H32: FEDNa-V2 | I32: 370404 | J32: 44503 | K32: Engineer | L32: Production Engineer | M32: BAND A4 | N32: 2 | O32: 3 | P32: 9450 | Q32: 0.025 | R32: =ROUND(P32*Q32,0) -> 236 | S32: 0 | T32: =ROUND(P32*S32,0) -> 0 | U32: =V32/P32 -> 0.024973545 | V32: =R32+T32 -> 236 | W32: =P32+V32 -> 9686 | X32: 9700 | Y32: =X32-P32 -> 250 | Z32: =ROUND(X32/P32-1,4) -> 0.0265 | AA32: =IF(OR(N32=1,N32=2,N32=4),TEXT(U32*0.8,"0.00%")&"-"&TEXT(U32*1.2,"0.00%"),IF(OR(N32=3,N32=6),TEXT(0,"0.00%")&"-"&TEXT(7%*1.2,"0.00%"),IF(OR(N32=5,N32=7),TEXT((T32/P32),"0.00%")&"-"&TEXT((T32/P32)+7%,"0.00%"),""))) -> 2.00%-3.00% | AF32: =ROUND(P32*AE32,0) -> 0 | AG32: =X32+AF32 -> 9700 | AH32: =AG32-P32 -> 250 | AI32: =AG32/P32-1 -> 0.026455026 | AJ32: 14 | AK32: 450 | AM32: 688 | AN32: =AG32*AJ32+AK32*12+AM32+IF(AD32="",AL32,IF(AD32="D",5000,IF(AD32="C",1000,0)))*12 -> 141888 | AO32: 2 | AS32: Ding Xudong（15000307） | AT32: Xu Lan（11013544） | AU32: Zhao Chujun | AY32: =_xlfn.LET(_xlpm.actual,Z32,_xlpm.low,VALUE(_xlfn.TEXTBEFORE(AA32,"-")),_xlpm.high,VALUE(_xlfn.TEXTAFTER(AA32,"-")),IF(AND(_xlpm.actual=0,OR(_xlpm.low<>0,_xlpm.high<>0)),"0 increase",IF(_xlpm.actual>_xlpm.high*1.2,">20",IF(_xlpm.actual<_xlpm.low*0.8,"<20","OK")))) -> OK
A33: CN15 | B33: 15000525 | C33: 王 飞 | D33: Wang Fei | E33: Indirect Active | F33: OP | G33: SNa | H33: FEDNa-FS | I33: 370100 | J33: 38869 | K33: Coordinator | L33: TPM Coordinator | M33: BAND A4 | N33: 2 | O33: 3 | P33: 7900 | Q33: 0 | R33: =ROUND(P33*Q33,0) -> 0 | S33: 0 | T33: =ROUND(P33*S33,0) -> 0 | U33: =V33/P33 -> 0 | V33: =R33+T33 -> 0 | W33: =P33+V33 -> 7900 | X33: 8000 | Y33: =X33-P33 -> 100 | Z33: =ROUND(X33/P33-1,4) -> 0.0127 | AA33: =IF(OR(N33=1,N33=2,N33=4),TEXT(U33*0.8,"0.00%")&"-"&TEXT(U33*1.2,"0.00%"),IF(OR(N33=3,N33=6),TEXT(0,"0.00%")&"-"&TEXT(7%*1.2,"0.00%"),IF(OR(N33=5,N33=7),TEXT((T33/P33),"0.00%")&"-"&TEXT((T33/P33)+7%,"0.00%"),""))) -> 0.00%-0.00% | AF33: =ROUND(P33*AE33,0) -> 0 | AG33: =X33+AF33 -> 8000 | AH33: =AG33-P33 -> 100 | AI33: =AG33/P33-1 -> 0.012658228 | AJ33: 14 | AK33: 650 | AM33: 688 | AN33: =AG33*AJ33+AK33*12+AM33+IF(AD33="",AL33,IF(AD33="D",5000,IF(AD33="C",1000,0)))*12 -> 120488 | AO33: 3 | AR33: Internal balance | AS33: Ding Xudong（15000307） | AT33: Xu Lan（11013544） | AU33: Zhao Chujun | AW33: exceed +/-20% adjustment | AX33: >20 | AY33: =_xlfn.LET(_xlpm.actual,Z33,_xlpm.low,VALUE(_xlfn.TEXTBEFORE(AA33,"-")),_xlpm.high,VALUE(_xlfn.TEXTAFTER(AA33,"-")),IF(AND(_xlpm.actual=0,OR(_xlpm.low<>0,_xlpm.high<>0)),"0 increase",IF(_xlpm.actual>_xlpm.high*1.2,">20",IF(_xlpm.actual<_xlpm.low*0.8,"<20","OK")))) -> >20
A34: CN15 | B34: 15020089 | C34: 王 鲜 | D34: Wang Xian | E34: Indirect Active | F34: OP | G34: SNa | H34: FEDNa-MEP | I34: 370200 | J34: 43908 | K34: Engineer | L34: Process Engineer | M34: BAND A4 | N34: 2 | O34: 3 | P34: 10100 | Q34: 0.025 | R34: =ROUND(P34*Q34,0) -> 253 | S34: 0 | T34: =ROUND(P34*S34,0) -> 0 | U34: =V34/P34 -> 0.025049505 | V34: =R34+T34 -> 253 | W34: =P34+V34 -> 10353 | X34: 10300 | Y34: =X34-P34 -> 200 | Z34: =ROUND(X34/P34-1,4) -> 0.0198 | AA34: =IF(OR(N34=1,N34=2,N34=4),TEXT(U34*0.8,"0.00%")&"-"&TEXT(U34*1.2,"0.00%"),IF(OR(N34=3,N34=6),TEXT(0,"0.00%")&"-"&TEXT(7%*1.2,"0.00%"),IF(OR(N34=5,N34=7),TEXT((T34/P34),"0.00%")&"-"&TEXT((T34/P34)+7%,"0.00%"),""))) -> 2.00%-3.01% | AF34: =ROUND(P34*AE34,0) -> 0 | AG34: =X34+AF34 -> 10300 | AH34: =AG34-P34 -> 200 | AI34: =AG34/P34-1 -> 0.01980198 | AJ34: 14 | AK34: 450 | AM34: 688 | AN34: =AG34*AJ34+AK34*12+AM34+IF(AD34="",AL34,IF(AD34="D",5000,IF(AD34="C",1000,0)))*12 -> 150288 | AO34: 3 | AR34: Rounding | AS34: Ding Xudong（15000307） | AT34: Xu Lan（11013544） | AU34: Zhao Chujun | AW34: exceed +/-20% adjustment | AX34: <20 | AY34: =_xlfn.LET(_xlpm.actual,Z34,_xlpm.low,VALUE(_xlfn.TEXTBEFORE(AA34,"-")),_xlpm.high,VALUE(_xlfn.TEXTAFTER(AA34,"-")),IF(AND(_xlpm.actual=0,OR(_xlpm.low<>0,_xlpm.high<>0)),"0 increase",IF(_xlpm.actual>_xlpm.high*1.2,">20",IF(_xlpm.actual<_xlpm.low*0.8,"<20","OK")))) -> OK
A35: CN15 | B35: 15000550 | C35: 夏 邦猛 | D35: Xia Bangmeng | E35: Indirect Active | F35: OP | G35: SNa | H35: FEDNa-V2 | I35: 370404 | J35: 38881 | K35: Engineer | L35: Engineer | M35: BAND A4 | N35: 2 | O35: 4 | P35: 9800 | Q35: 0.0375 | R35: =ROUND(P35*Q35,0) -> 368 | S35: 0.0155 | T35: =ROUND(P35*S35,0) -> 152 | U35: =V35/P35 -> 0.053061224 | V35: =R35+T35 -> 520 | W35: =P35+V35 -> 10320 | X35: 10300 | Y35: =X35-P35 -> 500 | Z35: =ROUND(X35/P35-1,4) -> 0.051 | AA35: =IF(OR(N35=1,N35=2,N35=4),TEXT(U35*0.8,"0.00%")&"-"&TEXT(U35*1.2,"0.00%"),IF(OR(N35=3,N35=6),TEXT(0,"0.00%")&"-"&TEXT(7%*1.2,"0.00%"),IF(OR(N35=5,N35=7),TEXT((T35/P35),"0.00%")&"-"&TEXT((T35/P35)+7%,"0.00%"),""))) -> 4.24%-6.37% | AF35: =ROUND(P35*AE35,0) -> 0 | AG35: =X35+AF35 -> 10300 | AH35: =AG35-P35 -> 500 | AI35: =AG35/P35-1 -> 0.051020408 | AJ35: 14 | AK35: 550 | AM35: 688 | AN35: =AG35*AJ35+AK35*12+AM35+IF(AD35="",AL35,IF(AD35="D",5000,IF(AD35="C",1000,0)))*12 -> 151488 | AO35: 3 | AS35: Ding Xudong（15000307） | AT35: Xu Lan（11013544） | AU35: Zhao Chujun | AY35: =_xlfn.LET(_xlpm.actual,Z35,_xlpm.low,VALUE(_xlfn.TEXTBEFORE(AA35,"-")),_xlpm.high,VALUE(_xlfn.TEXTAFTER(AA35,"-")),IF(AND(_xlpm.actual=0,OR(_xlpm.low<>0,_xlpm.high<>0)),"0 increase",IF(_xlpm.actual>_xlpm.high*1.2,">20",IF(_xlpm.actual<_xlpm.low*0.8,"<20","OK")))) -> OK
A36: CN15 | B36: 15015967 | C36: 徐 擎月 | D36: Xu Qingyue | E36: Indirect Active | F36: OP | G36: SNa | H36: FEDNa-FS | I36: 370100 | J36: 42683 | K36: Associate Expert (CN) | L36: Associate Expert (C) | M36: BAND A6 | N36: 2 | O36: 4 | P36: 12360 | Q36: 0.045 | R36: =ROUND(P36*Q36,0) -> 556 | S36: 0.0421 | T36: =ROUND(P36*S36,0) -> 520 | U36: =V36/P36 -> 0.087055016 | V36: =R36+T36 -> 1076 | W36: =P36+V36 -> 13436 | X36: 13300 | Y36: =X36-P36 -> 940 | Z36: =ROUND(X36/P36-1,4) -> 0.0761 | AA36: =IF(OR(N36=1,N36=2,N36=4),TEXT(U36*0.8,"0.00%")&"-"&TEXT(U36*1.2,"0.00%"),IF(OR(N36=3,N36=6),TEXT(0,"0.00%")&"-"&TEXT(7%*1.2,"0.00%"),IF(OR(N36=5,N36=7),TEXT((T36/P36),"0.00%")&"-"&TEXT((T36/P36)+7%,"0.00%"),""))) -> 6.96%-10.45% | AF36: =ROUND(P36*AE36,0) -> 0 | AG36: =X36+AF36 -> 13300 | AH36: =AG36-P36 -> 940 | AI36: =AG36/P36-1 -> 0.07605178 | AJ36: 14 | AK36: 450 | AM36: 688 | AN36: =AG36*AJ36+AK36*12+AM36+IF(AD36="",AL36,IF(AD36="D",5000,IF(AD36="C",1000,0)))*12 -> 192288 | AO36: 3 | AS36: Ding Xudong（15000307） | AT36: Xu Lan（11013544） | AU36: Zhao Chujun | AY36: =_xlfn.LET(_xlpm.actual,Z36,_xlpm.low,VALUE(_xlfn.TEXTBEFORE(AA36,"-")),_xlpm.high,VALUE(_xlfn.TEXTAFTER(AA36,"-")),IF(AND(_xlpm.actual=0,OR(_xlpm.low<>0,_xlpm.high<>0)),"0 increase",IF(_xlpm.actual>_xlpm.high*1.2,">20",IF(_xlpm.actual<_xlpm.low*0.8,"<20","OK")))) -> OK
A37: CN15 | B37: 15001287 | C37: 原 丰霞 | D37: Yuan Fengxia | E37: Indirect Active | F37: OP | G37: SNa | H37: FEDNa-MEP | I37: 370200 | J37: 39392 | K37: Senior Engineer | L37: Senior Electrical Engineer | M37: BAND A5 | N37: 2 | O37: 3 | P37: 12500 | Q37: 0.025 | R37: =ROUND(P37*Q37,0) -> 313 | S37: 0 | T37: =ROUND(P37*S37,0) -> 0 | U37: =V37/P37 -> 0.02504 | V37: =R37+T37 -> 313 | W37: =P37+V37 -> 12813 | X37: 12600 | Y37: =X37-P37 -> 100 | Z37: =ROUND(X37/P37-1,4) -> 0.008 | AA37: =IF(OR(N37=1,N37=2,N37=4),TEXT(U37*0.8,"0.00%")&"-"&TEXT(U37*1.2,"0.00%"),IF(OR(N37=3,N37=6),TEXT(0,"0.00%")&"-"&TEXT(7%*1.2,"0.00%"),IF(OR(N37=5,N37=7),TEXT((T37/P37),"0.00%")&"-"&TEXT((T37/P37)+7%,"0.00%"),""))) -> 2.00%-3.00% | AF37: =ROUND(P37*AE37,0) -> 0 | AG37: =X37+AF37 -> 12600 | AH37: =AG37-P37 -> 100 | AI37: =AG37/P37-1 -> 0.008 | AJ37: 14 | AK37: 450 | AM37: 688 | AN37: =AG37*AJ37+AK37*12+AM37+IF(AD37="",AL37,IF(AD37="D",5000,IF(AD37="C",1000,0)))*12 -> 182488 | AO37: 3 | AR37: Left/will leave/retire soon | AS37: Ding Xudong（15000307） | AT37: Xu Lan（11013544） | AU37: Zhao Chujun | AW37: exceed +/-20% adjustment | AX37: <20 | AY37: =_xlfn.LET(_xlpm.actual,Z37,_xlpm.low,VALUE(_xlfn.TEXTBEFORE(AA37,"-")),_xlpm.high,VALUE(_xlfn.TEXTAFTER(AA37,"-")),IF(AND(_xlpm.actual=0,OR(_xlpm.low<>0,_xlpm.high<>0)),"0 increase",IF(_xlpm.actual>_xlpm.high*1.2,">20",IF(_xlpm.actual<_xlpm.low*0.8,"<20","OK")))) -> <20
A38: CN15 | B38: 15016938 | C38: 张 来翔 | D38: Zhang Laixiang | E38: Indirect Active | F38: OP | G38: SNa | H38: FEDNa-MEP | I38: 370200 | J38: 42830 | K38: Supervisor | L38: Head of FEDNa-MEP | M38: BAND A6 | N38: 2 | O38: 5 | P38: 18000 | Q38: 0.05 | R38: =ROUND(P38*Q38,0) -> 900 | S38: 0.027 | T38: =ROUND(P38*S38,0) -> 486 | U38: =V38/P38 -> 0.077 | V38: =R38+T38 -> 1386 | W38: =P38+V38 -> 19386 | X38: 19700 | Y38: =X38-P38 -> 1700 | Z38: =ROUND(X38/P38-1,4) -> 0.0944 | AA38: =IF(OR(N38=1,N38=2,N38=4),TEXT(U38*0.8,"0.00%")&"-"&TEXT(U38*1.2,"0.00%"),IF(OR(N38=3,N38=6),TEXT(0,"0.00%")&"-"&TEXT(7%*1.2,"0.00%"),IF(OR(N38=5,N38=7),TEXT((T38/P38),"0.00%")&"-"&TEXT((T38/P38)+7%,"0.00%"),""))) -> 6.16%-9.24% | AF38: =ROUND(P38*AE38,0) -> 0 | AG38: =X38+AF38 -> 19700 | AH38: =AG38-P38 -> 1700 | AI38: =AG38/P38-1 -> 0.094444444 | AJ38: 14 | AK38: 450 | AM38: 688 | AN38: =AG38*AJ38+AK38*12+AM38+IF(AD38="",AL38,IF(AD38="D",5000,IF(AD38="C",1000,0)))*12 -> 281888 | AO38: 5 | AR38: Good performance/talent | AS38: Ding Xudong（15000307） | AT38: Xu Lan（11013544） | AU38: Zhao Chujun | AW38: exceed +/-20% adjustment | AX38: >20 | AY38: =_xlfn.LET(_xlpm.actual,Z38,_xlpm.low,VALUE(_xlfn.TEXTBEFORE(AA38,"-")),_xlpm.high,VALUE(_xlfn.TEXTAFTER(AA38,"-")),IF(AND(_xlpm.actual=0,OR(_xlpm.low<>0,_xlpm.high<>0)),"0 increase",IF(_xlpm.actual>_xlpm.high*1.2,">20",IF(_xlpm.actual<_xlpm.low*0.8,"<20","OK")))) -> OK
A39: CN15 | B39: 15000503 | C39: 赵 斌 | D39: Zhao Bin | E39: Indirect Active | F39: OP | G39: SNa | H39: FEDNa-V1 | I39: 370402 | J39: 38852 | K39: Senior Engineer | L39: Senior Process Engineer | M39: BAND A5 | N39: 2 | O39: 4 | P39: 10000 | Q39: 0.045 | R39: =ROUND(P39*Q39,0) -> 450 | S39: 0.0421 | T39: =ROUND(P39*S39,0) -> 421 | U39: =V39/P39 -> 0.0871 | V39: =R39+T39 -> 871 | W39: =P39+V39 -> 10871 | X39: 10700 | Y39: =X39-P39 -> 700 | Z39: =ROUND(X39/P39-1,4) -> 0.07 | AA39: =IF(OR(N39=1,N39=2,N39=4),TEXT(U39*0.8,"0.00%")&"-"&TEXT(U39*1.2,"0.00%"),IF(OR(N39=3,N39=6),TEXT(0,"0.00%")&"-"&TEXT(7%*1.2,"0.00%"),IF(OR(N39=5,N39=7),TEXT((T39/P39),"0.00%")&"-"&TEXT((T39/P39)+7%,"0.00%"),""))) -> 6.97%-10.45% | AF39: =ROUND(P39*AE39,0) -> 0 | AG39: =X39+AF39 -> 10700 | AH39: =AG39-P39 -> 700 | AI39: =AG39/P39-1 -> 0.07 | AJ39: 14 | AK39: 450 | AM39: 688 | AN39: =AG39*AJ39+AK39*12+AM39+IF(AD39="",AL39,IF(AD39="D",5000,IF(AD39="C",1000,0)))*12 -> 155888 | AO39: 3 | AS39: Ding Xudong（15000307） | AT39: Xu Lan（11013544） | AU39: Zhao Chujun | AY39: =_xlfn.LET(_xlpm.actual,Z39,_xlpm.low,VALUE(_xlfn.TEXTBEFORE(AA39,"-")),_xlpm.high,VALUE(_xlfn.TEXTAFTER(AA39,"-")),IF(AND(_xlpm.actual=0,OR(_xlpm.low<>0,_xlpm.high<>0)),"0 increase",IF(_xlpm.actual>_xlpm.high*1.2,">20",IF(_xlpm.actual<_xlpm.low*0.8,"<20","OK")))) -> OK
A40: CN15 | B40: 15022682 | C40: 董 小语 | D40: Dong Xiaoyu | E40: Indirect Active | F40: OP | G40: SNa | H40: SNa-ES | I40: 290125 | J40: 45910 | K40: Senior Engineer | L40: Senior EHS Engineer | M40: BAND A5 | N40: 2 | O40: 3 | P40: 13550 | Q40: 0 | R40: =ROUND(P40*Q40,0) -> 0 | S40: 0 | T40: =ROUND(P40*S40,0) -> 0 | U40: =V40/P40 -> 0 | V40: =R40+T40 -> 0 | W40: =P40+V40 -> 13550 | X40: =W40 -> 13550 | Y40: =X40-P40 -> 0 | Z40: =ROUND(X40/P40-1,4) -> 0 | AA40: =IF(OR(N40=1,N40=2,N40=4),TEXT(U40*0.8,"0.00%")&"-"&TEXT(U40*1.2,"0.00%"),IF(OR(N40=3,N40=6),TEXT(0,"0.00%")&"-"&TEXT(7%*1.2,"0.00%"),IF(OR(N40=5,N40=7),TEXT((T40/P40),"0.00%")&"-"&TEXT((T40/P40)+7%,"0.00%"),""))) -> 0.00%-0.00% | AF40: =ROUND(P40*AE40,0) -> 0 | AG40: =X40+AF40 -> 13550 | AH40: =AG40-P40 -> 0 | AI40: =AG40/P40-1 -> 0 | AJ40: 14 | AK40: 450 | AM40: 688 | AN40: =AG40*AJ40+AK40*12+AM40+IF(AD40="",AL40,IF(AD40="D",5000,IF(AD40="C",1000,0)))*12 -> 195788 | AO40: #N/A | AS40: Yao Da (15022352) | AT40: Xu Lan（11013544） | AU40: Zhao Chujun | AY40: =_xlfn.LET(_xlpm.actual,Z40,_xlpm.low,VALUE(_xlfn.TEXTBEFORE(AA40,"-")),_xlpm.high,VALUE(_xlfn.TEXTAFTER(AA40,"-")),IF(AND(_xlpm.actual=0,OR(_xlpm.low<>0,_xlpm.high<>0)),"0 increase",IF(_xlpm.actual>_xlpm.high*1.2,">20",IF(_xlpm.actual<_xlpm.low*0.8,"<20","OK")))) -> OK
A41: CN15 | B41: 15020704 | C41: 黄 丽华 | D41: Huang Lihua | E41: Indirect Active | F41: OP | G41: SNa | H41: SNa-ES | I41: 290125 | J41: 40057 | K41: Senior Engineer | L41: Senior EHS Engineer | M41: BAND A5 | N41: 2 | O41: 4 | P41: 15852 | Q41: 0.0225 | R41: =ROUND(P41*Q41,0) -> 357 | S41: 0 | T41: =ROUND(P41*S41,0) -> 0 | U41: =V41/P41 -> 0.022520818 | V41: =R41+T41 -> 357 | W41: =P41+V41 -> 16209 | X41: =W41 -> 16209 | Y41: =X41-P41 -> 357 | Z41: =ROUND(X41/P41-1,4) -> 0.0225 | AA41: =IF(OR(N41=1,N41=2,N41=4),TEXT(U41*0.8,"0.00%")&"-"&TEXT(U41*1.2,"0.00%"),IF(OR(N41=3,N41=6),TEXT(0,"0.00%")&"-"&TEXT(7%*1.2,"0.00%"),IF(OR(N41=5,N41=7),TEXT((T41/P41),"0.00%")&"-"&TEXT((T41/P41)+7%,"0.00%"),""))) -> 1.80%-2.70% | AF41: =ROUND(P41*AE41,0) -> 0 | AG41: =X41+AF41 -> 16209 | AH41: =AG41-P41 -> 357 | AI41: =AG41/P41-1 -> 0.022520818 | AJ41: 14 | AK41: 450 | AM41: 688 | AN41: =AG41*AJ41+AK41*12+AM41+IF(AD41="",AL41,IF(AD41="D",5000,IF(AD41="C",1000,0)))*12 -> 233014 | AO41: 3 | AS41: Yao Da (15022352) | AT41: Xu Lan（11013544） | AU41: Zhao Chujun | AY41: =_xlfn.LET(_xlpm.actual,Z41,_xlpm.low,VALUE(_xlfn.TEXTBEFORE(AA41,"-")),_xlpm.high,VALUE(_xlfn.TEXTAFTER(AA41,"-")),IF(AND(_xlpm.actual=0,OR(_xlpm.low<>0,_xlpm.high<>0)),"0 increase",IF(_xlpm.actual>_xlpm.high*1.2,">20",IF(_xlpm.actual<_xlpm.low*0.8,"<20","OK")))) -> OK
A42: CN15 | B42: 15022687 | C42: 马 航帆 | D42: Ma Hangfan | E42: Indirect Active | F42: OP | G42: SNa | H42: SNa-ES | I42: 290125 | J42: 45931 | K42: Senior Engineer | L42: Senior EHS Engineer | M42: BAND A5 | N42: 2 | O42: 3 | P42: 18000 | Q42: 0 | R42: =ROUND(P42*Q42,0) -> 0 | S42: 0 | T42: =ROUND(P42*S42,0) -> 0 | U42: =V42/P42 -> 0 | V42: =R42+T42 -> 0 | W42: =P42+V42 -> 18000 | X42: =W42 -> 18000 | Y42: =X42-P42 -> 0 | Z42: =ROUND(X42/P42-1,4) -> 0 | AA42: =IF(OR(N42=1,N42=2,N42=4),TEXT(U42*0.8,"0.00%")&"-"&TEXT(U42*1.2,"0.00%"),IF(OR(N42=3,N42=6),TEXT(0,"0.00%")&"-"&TEXT(7%*1.2,"0.00%"),IF(OR(N42=5,N42=7),TEXT((T42/P42),"0.00%")&"-"&TEXT((T42/P42)+7%,"0.00%"),""))) -> 0.00%-0.00% | AF42: =ROUND(P42*AE42,0) -> 0 | AG42: =X42+AF42 -> 18000 | AH42: =AG42-P42 -> 0 | AI42: =AG42/P42-1 -> 0 | AJ42: 14 | AK42: 450 | AM42: 688 | AN42: =AG42*AJ42+AK42*12+AM42+IF(AD42="",AL42,IF(AD42="D",5000,IF(AD42="C",1000,0)))*12 -> 258088 | AO42: #N/A | AS42: Yao Da (15022352) | AT42: Xu Lan（11013544） | AU42: Zhao Chujun | AY42: =_xlfn.LET(_xlpm.actual,Z42,_xlpm.low,VALUE(_xlfn.TEXTBEFORE(AA42,"-")),_xlpm.high,VALUE(_xlfn.TEXTAFTER(AA42,"-")),IF(AND(_xlpm.actual=0,OR(_xlpm.low<>0,_xlpm.high<>0)),"0 increase",IF(_xlpm.actual>_xlpm.high*1.2,">20",IF(_xlpm.actual<_xlpm.low*0.8,"<20","OK")))) -> OK
A43: CN15 | B43: 15020880 | C43: 徐 萍 | D43: Xu Ping | E43: Indirect Active | F43: OP | G43: SNa | H43: SNa-ES | I43: 290125 | J43: 44230 | K43: Engineer | L43: EHS Engineer | M43: BAND A4 | N43: 2 | O43: 1 | P43: 10113 | Q43: 0 | R43: =ROUND(P43*Q43,0) -> 0 | S43: 0 | T43: =ROUND(P43*S43,0) -> 0 | U43: =V43/P43 -> 0 | V43: =R43+T43 -> 0 | W43: =P43+V43 -> 10113 | X43: =W43 -> 10113 | Y43: =X43-P43 -> 0 | Z43: =ROUND(X43/P43-1,4) -> 0 | AA43: =IF(OR(N43=1,N43=2,N43=4),TEXT(U43*0.8,"0.00%")&"-"&TEXT(U43*1.2,"0.00%"),IF(OR(N43=3,N43=6),TEXT(0,"0.00%")&"-"&TEXT(7%*1.2,"0.00%"),IF(OR(N43=5,N43=7),TEXT((T43/P43),"0.00%")&"-"&TEXT((T43/P43)+7%,"0.00%"),""))) -> 0.00%-0.00% | AF43: =ROUND(P43*AE43,0) -> 0 | AG43: =X43+AF43 -> 10113 | AH43: =AG43-P43 -> 0 | AI43: =AG43/P43-1 -> 0 | AJ43: 14 | AK43: 550 | AM43: 688 | AN43: =AG43*AJ43+AK43*12+AM43+IF(AD43="",AL43,IF(AD43="D",5000,IF(AD43="C",1000,0)))*12 -> 148870 | AO43: 3 | AS43: Yao Da (15022352) | AT43: Xu Lan（11013544） | AU43: Zhao Chujun | AY43: =_xlfn.LET(_xlpm.actual,Z43,_xlpm.low,VALUE(_xlfn.TEXTBEFORE(AA43,"-")),_xlpm.high,VALUE(_xlfn.TEXTAFTER(AA43,"-")),IF(AND(_xlpm.actual=0,OR(_xlpm.low<>0,_xlpm.high<>0)),"0 increase",IF(_xlpm.actual>_xlpm.high*1.2,">20",IF(_xlpm.actual<_xlpm.low*0.8,"<20","OK")))) -> OK
A44: CN15 | B44: 15022527 | C44: 于 涛 | D44: Yu Tao | E44: Indirect Active | F44: OP | G44: SNa | H44: SNa-ES | I44: 290125 | J44: 45300 | K44: Senior Engineer | L44: Senior EHS Engineer | M44: BAND A5 | N44: 2 | O44: 3 | P44: 20066 | Q44: 0 | R44: =ROUND(P44*Q44,0) -> 0 | S44: 0 | T44: =ROUND(P44*S44,0) -> 0 | U44: =V44/P44 -> 0 | V44: =R44+T44 -> 0 | W44: =P44+V44 -> 20066 | X44: =W44 -> 20066 | Y44: =X44-P44 -> 0 | Z44: =ROUND(X44/P44-1,4) -> 0 | AA44: =IF(OR(N44=1,N44=2,N44=4),TEXT(U44*0.8,"0.00%")&"-"&TEXT(U44*1.2,"0.00%"),IF(OR(N44=3,N44=6),TEXT(0,"0.00%")&"-"&TEXT(7%*1.2,"0.00%"),IF(OR(N44=5,N44=7),TEXT((T44/P44),"0.00%")&"-"&TEXT((T44/P44)+7%,"0.00%"),""))) -> 0.00%-0.00% | AF44: =ROUND(P44*AE44,0) -> 0 | AG44: =X44+AF44 -> 20066 | AH44: =AG44-P44 -> 0 | AI44: =AG44/P44-1 -> 0 | AJ44: 14 | AK44: 450 | AM44: 688 | AN44: =AG44*AJ44+AK44*12+AM44+IF(AD44="",AL44,IF(AD44="D",5000,IF(AD44="C",1000,0)))*12 -> 287012 | AO44: 3 | AS44: Yao Da (15022352) | AT44: Xu Lan（11013544） | AU44: Zhao Chujun | AY44: =_xlfn.LET(_xlpm.actual,Z44,_xlpm.low,VALUE(_xlfn.TEXTBEFORE(AA44,"-")),_xlpm.high,VALUE(_xlfn.TEXTAFTER(AA44,"-")),IF(AND(_xlpm.actual=0,OR(_xlpm.low<>0,_xlpm.high<>0)),"0 increase",IF(_xlpm.actual>_xlpm.high*1.2,">20",IF(_xlpm.actual<_xlpm.low*0.8,"<20","OK")))) -> OK
A45: CN15 | B45: 15022528 | C45: 张 万良 | D45: Zhang Wanliang | E45: Indirect Active | F45: OP | G45: SNa | H45: SNa-ES | I45: 290125 | J45: 45314 | K45: Engineer | L45: EHS Engineer | M45: BAND A4 | N45: 2 | O45: 4 | P45: 15000 | Q45: 0.015 | R45: =ROUND(P45*Q45,0) -> 225 | S45: 0 | T45: =ROUND(P45*S45,0) -> 0 | U45: =V45/P45 -> 0.015 | V45: =R45+T45 -> 225 | W45: =P45+V45 -> 15225 | X45: =W45 -> 15225 | Y45: =X45-P45 -> 225 | Z45: =ROUND(X45/P45-1,4) -> 0.015 | AA45: =IF(OR(N45=1,N45=2,N45=4),TEXT(U45*0.8,"0.00%")&"-"&TEXT(U45*1.2,"0.00%"),IF(OR(N45=3,N45=6),TEXT(0,"0.00%")&"-"&TEXT(7%*1.2,"0.00%"),IF(OR(N45=5,N45=7),TEXT((T45/P45),"0.00%")&"-"&TEXT((T45/P45)+7%,"0.00%"),""))) -> 1.20%-1.80% | AF45: =ROUND(P45*AE45,0) -> 0 | AG45: =X45+AF45 -> 15225 | AH45: =AG45-P45 -> 225 | AI45: =AG45/P45-1 -> 0.015 | AJ45: 14 | AK45: 550 | AM45: 688 | AN45: =AG45*AJ45+AK45*12+AM45+IF(AD45="",AL45,IF(AD45="D",5000,IF(AD45="C",1000,0)))*12 -> 220438 | AO45: 4 | AS45: Yao Da (15022352) | AT45: Xu Lan（11013544） | AU45: Zhao Chujun | AY45: =_xlfn.LET(_xlpm.actual,Z45,_xlpm.low,VALUE(_xlfn.TEXTBEFORE(AA45,"-")),_xlpm.high,VALUE(_xlfn.TEXTAFTER(AA45,"-")),IF(AND(_xlpm.actual=0,OR(_xlpm.low<>0,_xlpm.high<>0)),"0 increase",IF(_xlpm.actual>_xlpm.high*1.2,">20",IF(_xlpm.actual<_xlpm.low*0.8,"<20","OK")))) -> OK
A46: CN15 | B46: 15021556 | C46: 张 云静 | D46: Zhang Yunjing | E46: Indirect Active | F46: OP | G46: SNa | H46: SNa-ES | I46: 290125 | J46: 44398 | K46: Engineer | L46: EHS Engineer | M46: BAND A4 | N46: 2 | O46: 2 | P46: 10599 | Q46: 0 | R46: =ROUND(P46*Q46,0) -> 0 | S46: 0 | T46: =ROUND(P46*S46,0) -> 0 | U46: =V46/P46 -> 0 | V46: =R46+T46 -> 0 | W46: =P46+V46 -> 10599 | X46: =W46 -> 10599 | Y46: =X46-P46 -> 0 | Z46: =ROUND(X46/P46-1,4) -> 0 | AA46: =IF(OR(N46=1,N46=2,N46=4),TEXT(U46*0.8,"0.00%")&"-"&TEXT(U46*1.2,"0.00%"),IF(OR(N46=3,N46=6),TEXT(0,"0.00%")&"-"&TEXT(7%*1.2,"0.00%"),IF(OR(N46=5,N46=7),TEXT((T46/P46),"0.00%")&"-"&TEXT((T46/P46)+7%,"0.00%"),""))) -> 0.00%-0.00% | AF46: =ROUND(P46*AE46,0) -> 0 | AG46: =X46+AF46 -> 10599 | AH46: =AG46-P46 -> 0 | AI46: =AG46/P46-1 -> 0 | AJ46: 14 | AK46: 450 | AM46: 688 | AN46: =AG46*AJ46+AK46*12+AM46+IF(AD46="",AL46,IF(AD46="D",5000,IF(AD46="C",1000,0)))*12 -> 154474 | AO46: 3 | AS46: Yao Da (15022352) | AT46: Xu Lan（11013544） | AU46: Zhao Chujun | AY46: =_xlfn.LET(_xlpm.actual,Z46,_xlpm.low,VALUE(_xlfn.TEXTBEFORE(AA46,"-")),_xlpm.high,VALUE(_xlfn.TEXTAFTER(AA46,"-")),IF(AND(_xlpm.actual=0,OR(_xlpm.low<>0,_xlpm.high<>0)),"0 increase",IF(_xlpm.actual>_xlpm.high*1.2,">20",IF(_xlpm.actual<_xlpm.low*0.8,"<20","OK")))) -> OK
A47: CN15 | B47: 15013780 | C47: 陈 超 | D47: Chen Chao | E47: Indirect Active | F47: OP | G47: SNa | H47: FLCNa-MEA | I47: 340200 | J47: 41976 | K47: Functional Specialist | L47: Injection Functional Specialist | M47: BAND A6 | N47: 2 | O47: 3 | P47: 14666 | Q47: 0.03 | R47: =ROUND(P47*Q47,0) -> 440 | S47: 0 | T47: =ROUND(P47*S47,0) -> 0 | U47: =V47/P47 -> 0.030001364 | V47: =R47+T47 -> 440 | W47: =P47+V47 -> 15106 | X47: 15017.984 | Y47: =X47-P47 -> 351.984 | Z47: =ROUND(X47/P47-1,4) -> 0.024 | AA47: =IF(OR(N47=1,N47=2,N47=4),TEXT(U47*0.8,"0.00%")&"-"&TEXT(U47*1.2,"0.00%"),IF(OR(N47=3,N47=6),TEXT(0,"0.00%")&"-"&TEXT(7%*1.2,"0.00%"),IF(OR(N47=5,N47=7),TEXT((T47/P47),"0.00%")&"-"&TEXT((T47/P47)+7%,"0.00%"),""))) -> 2.40%-3.60% | AF47: =ROUND(P47*AE47,0) -> 0 | AG47: =X47+AF47 -> 15017.984 | AH47: =AG47-P47 -> 351.984 | AI47: =AG47/P47-1 -> 0.024 | AJ47: 14 | AK47: 450 | AM47: 688 | AN47: =AG47*AJ47+AK47*12+AM47+IF(AD47="",AL47,IF(AD47="D",5000,IF(AD47="C",1000,0)))*12 -> 216339.78 | AO47: 5 | AS47: Hu Jun（51202067） | AT47: Mo Xiaohong（11005372） | AU47: Zhao Chujun | AY47: =_xlfn.LET(_xlpm.actual,Z47,_xlpm.low,VALUE(_xlfn.TEXTBEFORE(AA47,"-")),_xlpm.high,VALUE(_xlfn.TEXTAFTER(AA47,"-")),IF(AND(_xlpm.actual=0,OR(_xlpm.low<>0,_xlpm.high<>0)),"0 increase",IF(_xlpm.actual>_xlpm.high*1.2,">20",IF(_xlpm.actual<_xlpm.low*0.8,"<20","OK")))) -> OK
A48: CN15 | B48: 15004180 | C48: 桂 如刚 | D48: Gui Rugang | E48: Indirect Active | F48: OP | G48: SNa | H48: FLCNa-MEF | I48: 340200 | J48: 40373 | K48: Expert (CN) | L48: Expert (CN) | M48: BAND B | N48: 2 | O48: 4 | P48: 23000 | Q48: 0.0375 | R48: =ROUND(P48*Q48,0) -> 863 | S48: 0.0155 | T48: =ROUND(P48*S48,0) -> 357 | U48: =V48/P48 -> 0.053043478 | V48: =R48+T48 -> 1220 | W48: =P48+V48 -> 24220 | X48: 23989 | Y48: =X48-P48 -> 989 | Z48: =ROUND(X48/P48-1,4) -> 0.043 | AA48: =IF(OR(N48=1,N48=2,N48=4),TEXT(U48*0.8,"0.00%")&"-"&TEXT(U48*1.2,"0.00%"),IF(OR(N48=3,N48=6),TEXT(0,"0.00%")&"-"&TEXT(7%*1.2,"0.00%"),IF(OR(N48=5,N48=7),TEXT((T48/P48),"0.00%")&"-"&TEXT((T48/P48)+7%,"0.00%"),""))) -> 4.24%-6.37% | AF48: =ROUND(P48*AE48,0) -> 0 | AG48: =X48+AF48 -> 23989 | AH48: =AG48-P48 -> 989 | AI48: =AG48/P48-1 -> 0.043 | AJ48: 14 | AK48: 450 | AM48: 688 | AN48: =AG48*AJ48+AK48*12+AM48+IF(AD48="",AL48,IF(AD48="D",5000,IF(AD48="C",1000,0)))*12 -> 341934 | AO48: 4 | AS48: Hu Jun（51202067） | AT48: Mo Xiaohong（11005372） | AU48: Zhao Chujun | AY48: =_xlfn.LET(_xlpm.actual,Z48,_xlpm.low,VALUE(_xlfn.TEXTBEFORE(AA48,"-")),_xlpm.high,VALUE(_xlfn.TEXTAFTER(AA48,"-")),IF(AND(_xlpm.actual=0,OR(_xlpm.low<>0,_xlpm.high<>0)),"0 increase",IF(_xlpm.actual>_xlpm.high*1.2,">20",IF(_xlpm.actual<_xlpm.low*0.8,"<20","OK")))) -> OK
A49: CN15 | B49: 15022173 | C49: 韩 业康 | D49: Han Yekang | E49: Indirect Active | F49: OP | G49: SNa | H49: FLCNa-MEA | I49: 340200 | J49: 44671 | K49: Engineer | L49: Electrical Engineer | M49: BAND A4 | N49: 2 | O49: 3 | P49: 10712 | Q49: 0 | R49: =ROUND(P49*Q49,0) -> 0 | S49: 0 | T49: =ROUND(P49*S49,0) -> 0 | U49: =V49/P49 -> 0 | V49: =R49+T49 -> 0 | W49: =P49+V49 -> 10712 | X49: 11067 | Y49: =X49-P49 -> 355 | Z49: =ROUND(X49/P49-1,4) -> 0.0331 | AA49: =IF(OR(N49=1,N49=2,N49=4),TEXT(U49*0.8,"0.00%")&"-"&TEXT(U49*1.2,"0.00%"),IF(OR(N49=3,N49=6),TEXT(0,"0.00%")&"-"&TEXT(7%*1.2,"0.00%"),IF(OR(N49=5,N49=7),TEXT((T49/P49),"0.00%")&"-"&TEXT((T49/P49)+7%,"0.00%"),""))) -> 0.00%-0.00% | AF49: =ROUND(P49*AE49,0) -> 0 | AG49: =X49+AF49 -> 11067 | AH49: =AG49-P49 -> 355 | AI49: =AG49/P49-1 -> 0.033140403 | AJ49: 14 | AK49: 450 | AM49: 688 | AN49: =AG49*AJ49+AK49*12+AM49+IF(AD49="",AL49,IF(AD49="D",5000,IF(AD49="C",1000,0)))*12 -> 161026 | AO49: 2 | AQ49: very professional PLC engineer, lower salary | AR49: Good performers with relatively lower salary | AS49: Hu Jun（51202067） | AT49: Mo Xiaohong（11005372） | AU49: Zhao Chujun | AW49: exceed +/-20% adjustment | AX49: >20 | AY49: =_xlfn.LET(_xlpm.actual,Z49,_xlpm.low,VALUE(_xlfn.TEXTBEFORE(AA49,"-")),_xlpm.high,VALUE(_xlfn.TEXTAFTER(AA49,"-")),IF(AND(_xlpm.actual=0,OR(_xlpm.low<>0,_xlpm.high<>0)),"0 increase",IF(_xlpm.actual>_xlpm.high*1.2,">20",IF(_xlpm.actual<_xlpm.low*0.8,"<20","OK")))) -> >20
A50: CN15 | B50: 15017727 | C50: 胡 邦国 | D50: Hu Bangguo | E50: Indirect Active | F50: OP | G50: SNa | H50: FLCNa-MEA | I50: 340200 | J50: 42935 | K50: Associate Expert (CN) | L50: Associate Expert (C) | M50: BAND A6 | N50: 2 | O50: 3 | P50: 13202 | Q50: 0.03 | R50: =ROUND(P50*Q50,0) -> 396 | S50: 0 | T50: =ROUND(P50*S50,0) -> 0 | U50: =V50/P50 -> 0.029995455 | V50: =R50+T50 -> 396 | W50: =P50+V50 -> 13598 | X50: =P50+100 -> 13302 | Y50: =X50-P50 -> 100 | Z50: =ROUND(X50/P50-1,4) -> 0.0076 | AA50: =IF(OR(N50=1,N50=2,N50=4),TEXT(U50*0.8,"0.00%")&"-"&TEXT(U50*1.2,"0.00%"),IF(OR(N50=3,N50=6),TEXT(0,"0.00%")&"-"&TEXT(7%*1.2,"0.00%"),IF(OR(N50=5,N50=7),TEXT((T50/P50),"0.00%")&"-"&TEXT((T50/P50)+7%,"0.00%"),""))) -> 2.40%-3.60% | AF50: =ROUND(P50*AE50,0) -> 0 | AG50: =X50+AF50 -> 13302 | AH50: =AG50-P50 -> 100 | AI50: =AG50/P50-1 -> 0.0075746099 | AJ50: 14 | AK50: 450 | AM50: 688 | AN50: =AG50*AJ50+AK50*12+AM50+IF(AD50="",AL50,IF(AD50="D",5000,IF(AD50="C",1000,0)))*12 -> 192316 | AO50: 3 | AQ50: Less responsibility compare with job level with relative low performance | AR50: Less responsibility compare with job level | AS50: Hu Jun（51202067） | AT50: Mo Xiaohong（11005372） | AU50: Zhao Chujun | AW50: exceed +/-20% adjustment | AX50: <20 | AY50: =_xlfn.LET(_xlpm.actual,Z50,_xlpm.low,VALUE(_xlfn.TEXTBEFORE(AA50,"-")),_xlpm.high,VALUE(_xlfn.TEXTAFTER(AA50,"-")),IF(AND(_xlpm.actual=0,OR(_xlpm.low<>0,_xlpm.high<>0)),"0 increase",IF(_xlpm.actual>_xlpm.high*1.2,">20",IF(_xlpm.actual<_xlpm.low*0.8,"<20","OK")))) -> <20
A51: CN15 | B51: 51200268 | C51: 纪 锡林 | D51: Ji Xilin | E51: Indirect Active | F51: OP | G51: SNa | H51: FLCNa-MEA | I51: 340200 | J51: 35977 | K51: Manager | L51: Head of Assembly | M51: BAND B | N51: 2 | O51: 3 | P51: 24800 | Q51: 0.025 | R51: =ROUND(P51*Q51,0) -> 620 | S51: 0 | T51: =ROUND(P51*S51,0) -> 0 | U51: =V51/P51 -> 0.025 | V51: =R51+T51 -> 620 | W51: =P51+V51 -> 25420 | X51: =W51-120 -> 25300 | Y51: =X51-P51 -> 500 | Z51: =ROUND(X51/P51-1,4) -> 0.0202 | AA51: =IF(OR(N51=1,N51=2,N51=4),TEXT(U51*0.8,"0.00%")&"-"&TEXT(U51*1.2,"0.00%"),IF(OR(N51=3,N51=6),TEXT(0,"0.00%")&"-"&TEXT(7%*1.2,"0.00%"),IF(OR(N51=5,N51=7),TEXT((T51/P51),"0.00%")&"-"&TEXT((T51/P51)+7%,"0.00%"),""))) -> 2.00%-3.00% | AF51: =ROUND(P51*AE51,0) -> 0 | AG51: =X51+AF51 -> 25300 | AH51: =AG51-P51 -> 500 | AI51: =AG51/P51-1 -> 0.02016129 | AJ51: 14 | AK51: 3450 | AM51: 688 | AN51: =AG51*AJ51+AK51*12+AM51+IF(AD51="",AL51,IF(AD51="D",5000,IF(AD51="C",1000,0)))*12 -> 396288 | AO51: 5 | AS51: Hu Jun（51202067） | AT51: Mo Xiaohong（11005372） | AU51: Zhao Chujun | AY51: =_xlfn.LET(_xlpm.actual,Z51,_xlpm.low,VALUE(_xlfn.TEXTBEFORE(AA51,"-")),_xlpm.high,VALUE(_xlfn.TEXTAFTER(AA51,"-")),IF(AND(_xlpm.actual=0,OR(_xlpm.low<>0,_xlpm.high<>0)),"0 increase",IF(_xlpm.actual>_xlpm.high*1.2,">20",IF(_xlpm.actual<_xlpm.low*0.8,"<20","OK")))) -> OK
A52: CN15 | B52: 15014437 | C52: 贾 大勇 | D52: Jia Dayong | E52: Indirect Active | F52: OP | G52: SNa | H52: FLCNa-ME | I52: 340200 | J52: 42149 | K52: Manager | L52: Manager | M52: BAND B | N52: 2 | O52: 3 | P52: 28188 | Q52: 0.025 | R52: =ROUND(P52*Q52,0) -> 705 | S52: 0 | T52: =ROUND(P52*S52,0) -> 0 | U52: =V52/P52 -> 0.025010643 | V52: =R52+T52 -> 705 | W52: =P52+V52 -> 28893 | X52: 28751.76 | Y52: =X52-P52 -> 563.76 | Z52: =ROUND(X52/P52-1,4) -> 0.02 | AA52: =IF(OR(N52=1,N52=2,N52=4),TEXT(U52*0.8,"0.00%")&"-"&TEXT(U52*1.2,"0.00%"),IF(OR(N52=3,N52=6),TEXT(0,"0.00%")&"-"&TEXT(7%*1.2,"0.00%"),IF(OR(N52=5,N52=7),TEXT((T52/P52),"0.00%")&"-"&TEXT((T52/P52)+7%,"0.00%"),""))) -> 2.00%-3.00% | AF52: =ROUND(P52*AE52,0) -> 0 | AG52: =X52+AF52 -> 28751.76 | AH52: =AG52-P52 -> 563.76 | AI52: =AG52/P52-1 -> 0.02 | AJ52: 14 | AK52: 450 | AM52: 688 | AN52: =AG52*AJ52+AK52*12+AM52+IF(AD52="",AL52,IF(AD52="D",5000,IF(AD52="C",1000,0)))*12 -> 408612.64 | AO52: 3 | AS52: Hu Jun（51202067） | AT52: Mo Xiaohong（11005372） | AU52: Zhao Chujun | AY52: =_xlfn.LET(_xlpm.actual,Z52,_xlpm.low,VALUE(_xlfn.TEXTBEFORE(AA52,"-")),_xlpm.high,VALUE(_xlfn.TEXTAFTER(AA52,"-")),IF(AND(_xlpm.actual=0,OR(_xlpm.low<>0,_xlpm.high<>0)),"0 increase",IF(_xlpm.actual>_xlpm.high*1.2,">20",IF(_xlpm.actual<_xlpm.low*0.8,"<20","OK")))) -> OK
A53: CN15 | B53: 15022075 | C53: 李 言东 | D53: Li Yandong | E53: Indirect Active | F53: OP | G53: SNa | H53: FLCNa-MEA | I53: 340200 | J53: 44524 | K53: Engineer | L53: Assembly Process Engineer | M53: BAND A4 | N53: 2 | O53: 4 | P53: 12645 | Q53: 0.03 | R53: =ROUND(P53*Q53,0) -> 379 | S53: 0 | T53: =ROUND(P53*S53,0) -> 0 | U53: =V53/P53 -> 0.029972321 | V53: =R53+T53 -> 379 | W53: =P53+V53 -> 13024 | X53: =P53 -> 12645 | Y53: =X53-P53 -> 0 | Z53: =ROUND(X53/P53-1,4) -> 0 | AA53: =IF(OR(N53=1,N53=2,N53=4),TEXT(U53*0.8,"0.00%")&"-"&TEXT(U53*1.2,"0.00%"),IF(OR(N53=3,N53=6),TEXT(0,"0.00%")&"-"&TEXT(7%*1.2,"0.00%"),IF(OR(N53=5,N53=7),TEXT((T53/P53),"0.00%")&"-"&TEXT((T53/P53)+7%,"0.00%"),""))) -> 2.40%-3.60% | AB53: Promotion | AC53: Senior Assembly Process Engineer | AD53: A5 | AE53: 0.1 | AF53: =ROUND(P53*AE53,0) -> 1265 | AG53: =X53+AF53 -> 13910 | AH53: =AG53-P53 -> 1265 | AI53: =AG53/P53-1 -> 0.10003954 | AJ53: 14 | AK53: 450 | AM53: 688 | AN53: =AG53*AJ53+AK53*12+AM53+IF(AD53="",AL53,IF(AD53="D",5000,IF(AD53="C",1000,0)))*12 -> 200828 | AO53: 4 | AQ53: Very positive feedback from VS and high potential in assembly team，combined with promotion | AR53: Combined with promotion | AS53: Hu Jun（51202067） | AT53: Mo Xiaohong（11005372） | AU53: Zhao Chujun | AW53: recommend increasing but propose zero increase | AY53: =_xlfn.LET(_xlpm.actual,Z53,_xlpm.low,VALUE(_xlfn.TEXTBEFORE(AA53,"-")),_xlpm.high,VALUE(_xlfn.TEXTAFTER(AA53,"-")),IF(AND(_xlpm.actual=0,OR(_xlpm.low<>0,_xlpm.high<>0)),"0 increase",IF(_xlpm.actual>_xlpm.high*1.2,">20",IF(_xlpm.actual<_xlpm.low*0.8,"<20","OK")))) -> 0 increase
A54: CN15 | B54: 15001880 | C54: 林 文森 | D54: Lin Wensen | E54: Indirect Active | F54: OP | G54: SNa | H54: FLCNa-MEF | I54: 340200 | J54: 39657 | K54: Junior Engineer | L54: Junior Engineer | M54: BAND A3 | N54: 2 | O54: 3 | P54: 7538 | Q54: 0.025 | R54: =ROUND(P54*Q54,0) -> 188 | S54: 0 | T54: =ROUND(P54*S54,0) -> 0 | U54: =V54/P54 -> 0.024940302 | V54: =R54+T54 -> 188 | W54: =P54+V54 -> 7726 | X54: 7726 | Y54: =X54-P54 -> 188 | Z54: =ROUND(X54/P54-1,4) -> 0.0249 | AA54: =IF(OR(N54=1,N54=2,N54=4),TEXT(U54*0.8,"0.00%")&"-"&TEXT(U54*1.2,"0.00%"),IF(OR(N54=3,N54=6),TEXT(0,"0.00%")&"-"&TEXT(7%*1.2,"0.00%"),IF(OR(N54=5,N54=7),TEXT((T54/P54),"0.00%")&"-"&TEXT((T54/P54)+7%,"0.00%"),""))) -> 2.00%-2.99% | AF54: =ROUND(P54*AE54,0) -> 0 | AG54: =X54+AF54 -> 7726 | AH54: =AG54-P54 -> 188 | AI54: =AG54/P54-1 -> 0.024940302 | AJ54: 14 | AK54: 450 | AM54: 688 | AN54: =AG54*AJ54+AK54*12+AM54+IF(AD54="",AL54,IF(AD54="D",5000,IF(AD54="C",1000,0)))*12 -> 114252 | AO54: NA | AS54: Hu Jun（51202067） | AT54: Mo Xiaohong（11005372） | AU54: Zhao Chujun | AY54: =_xlfn.LET(_xlpm.actual,Z54,_xlpm.low,VALUE(_xlfn.TEXTBEFORE(AA54,"-")),_xlpm.high,VALUE(_xlfn.TEXTAFTER(AA54,"-")),IF(AND(_xlpm.actual=0,OR(_xlpm.low<>0,_xlpm.high<>0)),"0 increase",IF(_xlpm.actual>_xlpm.high*1.2,">20",IF(_xlpm.actual<_xlpm.low*0.8,"<20","OK")))) -> OK
A55: CN15 | B55: 15001698 | C55: 马 广义 | D55: Ma Guangyi | E55: Indirect Active | F55: OP | G55: SNa | H55: FLCNa-MEF | I55: 340200 | J55: 39616 | K55: Senior Engineer | L55: Senior Manufacturing Engineer | M55: BAND A5 | N55: 2 | O55: 4 | P55: 11737 | Q55: 0.0375 | R55: =ROUND(P55*Q55,0) -> 440 | S55: 0.0155 | T55: =ROUND(P55*S55,0) -> 182 | U55: =V55/P55 -> 0.052994803 | V55: =R55+T55 -> 622 | W55: =P55+V55 -> 12359 | X55: 12659 | Y55: =X55-P55 -> 922 | Z55: =ROUND(X55/P55-1,4) -> 0.0786 | AA55: =IF(OR(N55=1,N55=2,N55=4),TEXT(U55*0.8,"0.00%")&"-"&TEXT(U55*1.2,"0.00%"),IF(OR(N55=3,N55=6),TEXT(0,"0.00%")&"-"&TEXT(7%*1.2,"0.00%"),IF(OR(N55=5,N55=7),TEXT((T55/P55),"0.00%")&"-"&TEXT((T55/P55)+7%,"0.00%"),""))) -> 4.24%-6.36% | AF55: =ROUND(P55*AE55,0) -> 0 | AG55: =X55+AF55 -> 12659 | AH55: =AG55-P55 -> 922 | AI55: =AG55/P55-1 -> 0.078554997 | AJ55: 14 | AK55: 450 | AM55: 688 | AN55: =AG55*AJ55+AK55*12+AM55+IF(AD55="",AL55,IF(AD55="D",5000,IF(AD55="C",1000,0)))*12 -> 183314 | AO55: 3 | AQ55: Excellent performance in laser welding relocation。同时兼任FLCNa,FLCCh 两家工厂的内筒激光焊接 | AR55: Significantly enlarged responsibilities with proven performance | AS55: Hu Jun（51202067） | AT55: Mo Xiaohong（11005372） | AU55: Zhao Chujun | AW55: exceed +/-20% adjustment | AX55: >20 | AY55: =_xlfn.LET(_xlpm.actual,Z55,_xlpm.low,VALUE(_xlfn.TEXTBEFORE(AA55,"-")),_xlpm.high,VALUE(_xlfn.TEXTAFTER(AA55,"-")),IF(AND(_xlpm.actual=0,OR(_xlpm.low<>0,_xlpm.high<>0)),"0 increase",IF(_xlpm.actual>_xlpm.high*1.2,">20",IF(_xlpm.actual<_xlpm.low*0.8,"<20","OK")))) -> >20
A56: CN15 | B56: 15003323 | C56: 马 维静 | D56: Ma Weijing | E56: Indirect Active | F56: OP | G56: SNa | H56: FLCNa-MEM | I56: 340433 | J56: 40238 | K56: Supervisor | L56: Supervisor | M56: BAND A6 | N56: 2 | O56: 3 | P56: 18000 | Q56: 0 | R56: =ROUND(P56*Q56,0) -> 0 | S56: 0 | T56: =ROUND(P56*S56,0) -> 0 | U56: =V56/P56 -> 0 | V56: =R56+T56 -> 0 | W56: =P56+V56 -> 18000 | X56: 18000 | Y56: =X56-P56 -> 0 | Z56: =ROUND(X56/P56-1,4) -> 0 | AA56: =IF(OR(N56=1,N56=2,N56=4),TEXT(U56*0.8,"0.00%")&"-"&TEXT(U56*1.2,"0.00%"),IF(OR(N56=3,N56=6),TEXT(0,"0.00%")&"-"&TEXT(7%*1.2,"0.00%"),IF(OR(N56=5,N56=7),TEXT((T56/P56),"0.00%")&"-"&TEXT((T56/P56)+7%,"0.00%"),""))) -> 0.00%-0.00% | AF56: =ROUND(P56*AE56,0) -> 0 | AG56: =X56+AF56 -> 18000 | AH56: =AG56-P56 -> 0 | AI56: =AG56/P56-1 -> 0 | AJ56: 14 | AK56: 450 | AM56: 688 | AN56: =AG56*AJ56+AK56*12+AM56+IF(AD56="",AL56,IF(AD56="D",5000,IF(AD56="C",1000,0)))*12 -> 258088 | AO56: 4 | AS56: Hu Jun（51202067） | AT56: Mo Xiaohong（11005372） | AU56: Zhao Chujun | AY56: =_xlfn.LET(_xlpm.actual,Z56,_xlpm.low,VALUE(_xlfn.TEXTBEFORE(AA56,"-")),_xlpm.high,VALUE(_xlfn.TEXTAFTER(AA56,"-")),IF(AND(_xlpm.actual=0,OR(_xlpm.low<>0,_xlpm.high<>0)),"0 increase",IF(_xlpm.actual>_xlpm.high*1.2,">20",IF(_xlpm.actual<_xlpm.low*0.8,"<20","OK")))) -> OK
A57: CN15 | B57: 15021416 | C57: 石 曙曙 | D57: Shi Shushu | E57: Indirect Active | F57: OP | G57: SNa | H57: FLCNa-MEA | I57: 340200 | J57: 44370 | K57: Engineer | L57: Automation Engineer | M57: BAND A4 | N57: 2 | O57: 5 | P57: 12793 | Q57: 0.04 | R57: =ROUND(P57*Q57,0) -> 512 | S57: 0 | T57: =ROUND(P57*S57,0) -> 0 | U57: =V57/P57 -> 0.040021887 | V57: =R57+T57 -> 512 | W57: =P57+V57 -> 13305 | X57: =P57 -> 12793 | Y57: =X57-P57 -> 0 | Z57: =ROUND(X57/P57-1,4) -> 0 | AA57: =IF(OR(N57=1,N57=2,N57=4),TEXT(U57*0.8,"0.00%")&"-"&TEXT(U57*1.2,"0.00%"),IF(OR(N57=3,N57=6),TEXT(0,"0.00%")&"-"&TEXT(7%*1.2,"0.00%"),IF(OR(N57=5,N57=7),TEXT((T57/P57),"0.00%")&"-"&TEXT((T57/P57)+7%,"0.00%"),""))) -> 3.20%-4.80% | AB57: Promotion | AC57: Senior Automation Engineer | AD57: A5 | AE57: 0.11 | AF57: =ROUND(P57*AE57,0) -> 1407 | AG57: =X57+AF57 -> 14200 | AH57: =AG57-P57 -> 1407 | AI57: =AG57/P57-1 -> 0.10998202 | AJ57: 14 | AK57: 450 | AM57: 688 | AN57: =AG57*AJ57+AK57*12+AM57+IF(AD57="",AL57,IF(AD57="D",5000,IF(AD57="C",1000,0)))*12 -> 204888 | AO57: 3 | AQ57: Testing expert: critical and urgently needed in the factory, combined with promotion. | AR57: Combined with promotion | AS57: Hu Jun（51202067） | AT57: Mo Xiaohong（11005372） | AU57: Zhao Chujun | AW57: recommend increasing but propose zero increase | AY57: =_xlfn.LET(_xlpm.actual,Z57,_xlpm.low,VALUE(_xlfn.TEXTBEFORE(AA57,"-")),_xlpm.high,VALUE(_xlfn.TEXTAFTER(AA57,"-")),IF(AND(_xlpm.actual=0,OR(_xlpm.low<>0,_xlpm.high<>0)),"0 increase",IF(_xlpm.actual>_xlpm.high*1.2,">20",IF(_xlpm.actual<_xlpm.low*0.8,"<20","OK")))) -> 0 increase
A58: CN15 | B58: 15020868 | C58: 孙 荣华 | D58: Sun Ronghua | E58: Indirect Active | F58: OP | G58: SNa | H58: FLCNa-MEF | I58: 340200 | J58: 44209 | K58: Senior Engineer | L58: Senior Injection Engineer | M58: BAND A5 | N58: 2 | O58: 3 | P58: 13285 | Q58: 0.025 | R58: =ROUND(P58*Q58,0) -> 332 | S58: 0 | T58: =ROUND(P58*S58,0) -> 0 | U58: =V58/P58 -> 0.024990591 | V58: =R58+T58 -> 332 | W58: =P58+V58 -> 13617 | X58: =W58-66 -> 13551 | Y58: =X58-P58 -> 266 | Z58: =ROUND(X58/P58-1,4) -> 0.02 | AA58: =IF(OR(N58=1,N58=2,N58=4),TEXT(U58*0.8,"0.00%")&"-"&TEXT(U58*1.2,"0.00%"),IF(OR(N58=3,N58=6),TEXT(0,"0.00%")&"-"&TEXT(7%*1.2,"0.00%"),IF(OR(N58=5,N58=7),TEXT((T58/P58),"0.00%")&"-"&TEXT((T58/P58)+7%,"0.00%"),""))) -> 2.00%-3.00% | AF58: =ROUND(P58*AE58,0) -> 0 | AG58: =X58+AF58 -> 13551 | AH58: =AG58-P58 -> 266 | AI58: =AG58/P58-1 -> 0.020022582 | AJ58: 14 | AK58: 450 | AM58: 688 | AN58: =AG58*AJ58+AK58*12+AM58+IF(AD58="",AL58,IF(AD58="D",5000,IF(AD58="C",1000,0)))*12 -> 195802 | AO58: 2 | AS58: Hu Jun（51202067） | AT58: Mo Xiaohong（11005372） | AU58: Zhao Chujun | AY58: =_xlfn.LET(_xlpm.actual,Z58,_xlpm.low,VALUE(_xlfn.TEXTBEFORE(AA58,"-")),_xlpm.high,VALUE(_xlfn.TEXTAFTER(AA58,"-")),IF(AND(_xlpm.actual=0,OR(_xlpm.low<>0,_xlpm.high<>0)),"0 increase",IF(_xlpm.actual>_xlpm.high*1.2,">20",IF(_xlpm.actual<_xlpm.low*0.8,"<20","OK")))) -> OK
A59: CN15 | B59: 15004889 | C59: 王 兴春 | D59: Wang Xingchun | E59: Indirect Active | F59: OP | G59: SNa | H59: FLCNa-MEF | I59: 340200 | J59: 40490 | K59: Senior Engineer | L59: Senior Mould Managment Engineer | M59: BAND A5 | N59: 2 | O59: 3 | P59: 15150 | Q59: 0 | R59: =ROUND(P59*Q59,0) -> 0 | S59: 0 | T59: =ROUND(P59*S59,0) -> 0 | U59: =V59/P59 -> 0 | V59: =R59+T59 -> 0 | W59: =P59+V59 -> 15150 | X59: 15150 | Y59: =X59-P59 -> 0 | Z59: =ROUND(X59/P59-1,4) -> 0 | AA59: =IF(OR(N59=1,N59=2,N59=4),TEXT(U59*0.8,"0.00%")&"-"&TEXT(U59*1.2,"0.00%"),IF(OR(N59=3,N59=6),TEXT(0,"0.00%")&"-"&TEXT(7%*1.2,"0.00%"),IF(OR(N59=5,N59=7),TEXT((T59/P59),"0.00%")&"-"&TEXT((T59/P59)+7%,"0.00%"),""))) -> 0.00%-0.00% | AF59: =ROUND(P59*AE59,0) -> 0 | AG59: =X59+AF59 -> 15150 | AH59: =AG59-P59 -> 0 | AI59: =AG59/P59-1 -> 0 | AJ59: 14 | AK59: 450 | AM59: 688 | AN59: =AG59*AJ59+AK59*12+AM59+IF(AD59="",AL59,IF(AD59="D",5000,IF(AD59="C",1000,0)))*12 -> 218188 | AO59: 4 | AS59: Hu Jun（51202067） | AT59: Mo Xiaohong（11005372） | AU59: Zhao Chujun | AY59: =_xlfn.LET(_xlpm.actual,Z59,_xlpm.low,VALUE(_xlfn.TEXTBEFORE(AA59,"-")),_xlpm.high,VALUE(_xlfn.TEXTAFTER(AA59,"-")),IF(AND(_xlpm.actual=0,OR(_xlpm.low<>0,_xlpm.high<>0)),"0 increase",IF(_xlpm.actual>_xlpm.high*1.2,">20",IF(_xlpm.actual<_xlpm.low*0.8,"<20","OK")))) -> OK
A60: CN15 | B60: 15022143 | C60: 王 雪松 | D60: Wang Xuesong | E60: Indirect Active | F60: OP | G60: SNa | H60: FLCNa-MEA | I60: 340200 | J60: 44615 | K60: Engineer | L60: Testing Engineer | M60: BAND A4 | N60: 2 | O60: 3 | P60: 9205 | Q60: 0.025 | R60: =ROUND(P60*Q60,0) -> 230 | S60: 0 | T60: =ROUND(P60*S60,0) -> 0 | U60: =V60/P60 -> 0.02498642 | V60: =R60+T60 -> 230 | W60: =P60+V60 -> 9435 | X60: 9205 | Y60: =X60-P60 -> 0 | Z60: =ROUND(X60/P60-1,4) -> 0 | AA60: =IF(OR(N60=1,N60=2,N60=4),TEXT(U60*0.8,"0.00%")&"-"&TEXT(U60*1.2,"0.00%"),IF(OR(N60=3,N60=6),TEXT(0,"0.00%")&"-"&TEXT(7%*1.2,"0.00%"),IF(OR(N60=5,N60=7),TEXT((T60/P60),"0.00%")&"-"&TEXT((T60/P60)+7%,"0.00%"),""))) -> 2.00%-3.00% | AF60: =ROUND(P60*AE60,0) -> 0 | AG60: =X60+AF60 -> 9205 | AH60: =AG60-P60 -> 0 | AI60: =AG60/P60-1 -> 0 | AJ60: 14 | AK60: 450 | AM60: 688 | AN60: =AG60*AJ60+AK60*12+AM60+IF(AD60="",AL60,IF(AD60="D",5000,IF(AD60="C",1000,0)))*12 -> 134958 | AO60: 3 | AQ60: Leave BSH in July | AR60: Left/will leave/retire soon | AS60: Hu Jun（51202067） | AT60: Mo Xiaohong（11005372） | AU60: Zhao Chujun | AW60: recommend increasing but propose zero increase | AY60: =_xlfn.LET(_xlpm.actual,Z60,_xlpm.low,VALUE(_xlfn.TEXTBEFORE(AA60,"-")),_xlpm.high,VALUE(_xlfn.TEXTAFTER(AA60,"-")),IF(AND(_xlpm.actual=0,OR(_xlpm.low<>0,_xlpm.high<>0)),"0 increase",IF(_xlpm.actual>_xlpm.high*1.2,">20",IF(_xlpm.actual<_xlpm.low*0.8,"<20","OK")))) -> 0 increase
A61: CN15 | B61: 51200356 | C61: 吴 惟一 | D61: Wu Weiyi | E61: Indirect Active | F61: OP | G61: SNa | H61: FLCNa-MEF | I61: 340200 | J61: 35660 | K61: Senior Engineer | L61: Senior Engineer | M61: BAND A5 | N61: 2 | O61: 3 | P61: 12985 | Q61: 0 | R61: =ROUND(P61*Q61,0) -> 0 | S61: 0 | T61: =ROUND(P61*S61,0) -> 0 | U61: =V61/P61 -> 0 | V61: =R61+T61 -> 0 | W61: =P61+V61 -> 12985 | X61: 12985 | Y61: =X61-P61 -> 0 | Z61: =ROUND(X61/P61-1,4) -> 0 | AA61: =IF(OR(N61=1,N61=2,N61=4),TEXT(U61*0.8,"0.00%")&"-"&TEXT(U61*1.2,"0.00%"),IF(OR(N61=3,N61=6),TEXT(0,"0.00%")&"-"&TEXT(7%*1.2,"0.00%"),IF(OR(N61=5,N61=7),TEXT((T61/P61),"0.00%")&"-"&TEXT((T61/P61)+7%,"0.00%"),""))) -> 0.00%-0.00% | AF61: =ROUND(P61*AE61,0) -> 0 | AG61: =X61+AF61 -> 12985 | AH61: =AG61-P61 -> 0 | AI61: =AG61/P61-1 -> 0 | AJ61: 14 | AK61: 3050 | AM61: 688 | AN61: =AG61*AJ61+AK61*12+AM61+IF(AD61="",AL61,IF(AD61="D",5000,IF(AD61="C",1000,0)))*12 -> 219078 | AO61: 3 | AS61: Hu Jun（51202067） | AT61: Mo Xiaohong（11005372） | AU61: Zhao Chujun | AY61: =_xlfn.LET(_xlpm.actual,Z61,_xlpm.low,VALUE(_xlfn.TEXTBEFORE(AA61,"-")),_xlpm.high,VALUE(_xlfn.TEXTAFTER(AA61,"-")),IF(AND(_xlpm.actual=0,OR(_xlpm.low<>0,_xlpm.high<>0)),"0 increase",IF(_xlpm.actual>_xlpm.high*1.2,">20",IF(_xlpm.actual<_xlpm.low*0.8,"<20","OK")))) -> OK
A62: CN15 | B62: 15021286 | C62: 邢 建 | D62: Xing Jian | E62: Indirect Active | F62: OP | G62: SNa | H62: FLCNa-MEM | I62: 340433 | J62: 44328 | K62: Senior Engineer | L62: Senior Equipment Engineer | M62: BAND A5 | N62: 2 | O62: 5 | P62: 17480 | Q62: 0.03 | R62: =ROUND(P62*Q62,0) -> 524 | S62: 0 | T62: =ROUND(P62*S62,0) -> 0 | U62: =V62/P62 -> 0.029977117 | V62: =R62+T62 -> 524 | W62: =P62+V62 -> 18004 | X62: 18110 | Y62: =X62-P62 -> 630 | Z62: =ROUND(X62/P62-1,4) -> 0.036 | AA62: =IF(OR(N62=1,N62=2,N62=4),TEXT(U62*0.8,"0.00%")&"-"&TEXT(U62*1.2,"0.00%"),IF(OR(N62=3,N62=6),TEXT(0,"0.00%")&"-"&TEXT(7%*1.2,"0.00%"),IF(OR(N62=5,N62=7),TEXT((T62/P62),"0.00%")&"-"&TEXT((T62/P62)+7%,"0.00%"),""))) -> 2.40%-3.60% | AF62: =ROUND(P62*AE62,0) -> 0 | AG62: =X62+AF62 -> 18110 | AH62: =AG62-P62 -> 630 | AI62: =AG62/P62-1 -> 0.03604119 | AJ62: 14 | AK62: 450 | AM62: 688 | AN62: =AG62*AJ62+AK62*12+AM62+IF(AD62="",AL62,IF(AD62="D",5000,IF(AD62="C",1000,0)))*12 -> 259628 | AO62: 4 | AS62: Hu Jun（51202067） | AT62: Mo Xiaohong（11005372） | AU62: Zhao Chujun | AY62: =_xlfn.LET(_xlpm.actual,Z62,_xlpm.low,VALUE(_xlfn.TEXTBEFORE(AA62,"-")),_xlpm.high,VALUE(_xlfn.TEXTAFTER(AA62,"-")),IF(AND(_xlpm.actual=0,OR(_xlpm.low<>0,_xlpm.high<>0)),"0 increase",IF(_xlpm.actual>_xlpm.high*1.2,">20",IF(_xlpm.actual<_xlpm.low*0.8,"<20","OK")))) -> OK
A63: CN15 | B63: 15001700 | C63: 徐 云飞 | D63: Xu Yunfei | E63: Indirect Active | F63: OP | G63: SNa | H63: FLCNa-MEM | I63: 340433 | J63: 39616 | K63: Senior Engineer | L63: Senior Engineer | M63: BAND A5 | N63: 2 | O63: 4 | P63: 12391 | Q63: 0.0375 | R63: =ROUND(P63*Q63,0) -> 465 | S63: 0.0155 | T63: =ROUND(P63*S63,0) -> 192 | U63: =V63/P63 -> 0.053022355 | V63: =R63+T63 -> 657 | W63: =P63+V63 -> 13048 | X63: 13048 | Y63: =X63-P63 -> 657 | Z63: =ROUND(X63/P63-1,4) -> 0.053 | AA63: =IF(OR(N63=1,N63=2,N63=4),TEXT(U63*0.8,"0.00%")&"-"&TEXT(U63*1.2,"0.00%"),IF(OR(N63=3,N63=6),TEXT(0,"0.00%")&"-"&TEXT(7%*1.2,"0.00%"),IF(OR(N63=5,N63=7),TEXT((T63/P63),"0.00%")&"-"&TEXT((T63/P63)+7%,"0.00%"),""))) -> 4.24%-6.36% | AF63: =ROUND(P63*AE63,0) -> 0 | AG63: =X63+AF63 -> 13048 | AH63: =AG63-P63 -> 657 | AI63: =AG63/P63-1 -> 0.053022355 | AJ63: 14 | AK63: 500 | AM63: 688 | AN63: =AG63*AJ63+AK63*12+AM63+IF(AD63="",AL63,IF(AD63="D",5000,IF(AD63="C",1000,0)))*12 -> 189360 | AO63: 2 | AS63: Hu Jun（51202067） | AT63: Mo Xiaohong（11005372） | AU63: Zhao Chujun | AY63: =_xlfn.LET(_xlpm.actual,Z63,_xlpm.low,VALUE(_xlfn.TEXTBEFORE(AA63,"-")),_xlpm.high,VALUE(_xlfn.TEXTAFTER(AA63,"-")),IF(AND(_xlpm.actual=0,OR(_xlpm.low<>0,_xlpm.high<>0)),"0 increase",IF(_xlpm.actual>_xlpm.high*1.2,">20",IF(_xlpm.actual<_xlpm.low*0.8,"<20","OK")))) -> OK
A64: CN15 | B64: 15015379 | C64: 杨 园园 | D64: Yang Yuanyuan | E64: Indirect Active | F64: OP | G64: SNa | H64: FLCNa-MEM | I64: 340433 | J64: 42543 | K64: Senior Engineer | L64: Senior Engineer | M64: BAND A5 | N64: 2 | O64: 4 | P64: 16100 | Q64: 0.03 | R64: =ROUND(P64*Q64,0) -> 483 | S64: 0 | T64: =ROUND(P64*S64,0) -> 0 | U64: =V64/P64 -> 0.03 | V64: =R64+T64 -> 483 | W64: =P64+V64 -> 16583 | X64: 16583 | Y64: =X64-P64 -> 483 | Z64: =ROUND(X64/P64-1,4) -> 0.03 | AA64: =IF(OR(N64=1,N64=2,N64=4),TEXT(U64*0.8,"0.00%")&"-"&TEXT(U64*1.2,"0.00%"),IF(OR(N64=3,N64=6),TEXT(0,"0.00%")&"-"&TEXT(7%*1.2,"0.00%"),IF(OR(N64=5,N64=7),TEXT((T64/P64),"0.00%")&"-"&TEXT((T64/P64)+7%,"0.00%"),""))) -> 2.40%-3.60% | AF64: =ROUND(P64*AE64,0) -> 0 | AG64: =X64+AF64 -> 16583 | AH64: =AG64-P64 -> 483 | AI64: =AG64/P64-1 -> 0.03 | AJ64: 14 | AK64: 500 | AM64: 688 | AN64: =AG64*AJ64+AK64*12+AM64+IF(AD64="",AL64,IF(AD64="D",5000,IF(AD64="C",1000,0)))*12 -> 238850 | AO64: 4 | AS64: Hu Jun（51202067） | AT64: Mo Xiaohong（11005372） | AU64: Zhao Chujun | AY64: =_xlfn.LET(_xlpm.actual,Z64,_xlpm.low,VALUE(_xlfn.TEXTBEFORE(AA64,"-")),_xlpm.high,VALUE(_xlfn.TEXTAFTER(AA64,"-")),IF(AND(_xlpm.actual=0,OR(_xlpm.low<>0,_xlpm.high<>0)),"0 increase",IF(_xlpm.actual>_xlpm.high*1.2,">20",IF(_xlpm.actual<_xlpm.low*0.8,"<20","OK")))) -> OK
A65: CN15 | B65: 15015653 | C65: 禹 大成 | D65: Yu Dacheng | E65: Indirect Active | F65: OP | G65: SNa | H65: FLCNa-MEF | I65: 340200 | J65: 42634 | K65: Manager | L65: Head of Pre-Fabrication | M65: BAND B | N65: 2 | O65: 5 | P65: 21554 | Q65: 0.06 | R65: =ROUND(P65*Q65,0) -> 1293 | S65: 0.0778 | T65: =ROUND(P65*S65,0) -> 1677 | U65: =V65/P65 -> 0.13779345 | V65: =R65+T65 -> 2970 | W65: =P65+V65 -> 24524 | X65: 24221 | Y65: =X65-P65 -> 2667 | Z65: =ROUND(X65/P65-1,4) -> 0.1237 | AA65: =IF(OR(N65=1,N65=2,N65=4),TEXT(U65*0.8,"0.00%")&"-"&TEXT(U65*1.2,"0.00%"),IF(OR(N65=3,N65=6),TEXT(0,"0.00%")&"-"&TEXT(7%*1.2,"0.00%"),IF(OR(N65=5,N65=7),TEXT((T65/P65),"0.00%")&"-"&TEXT((T65/P65)+7%,"0.00%"),""))) -> 11.02%-16.54% | AF65: =ROUND(P65*AE65,0) -> 0 | AG65: =X65+AF65 -> 24221 | AH65: =AG65-P65 -> 2667 | AI65: =AG65/P65-1 -> 0.12373573 | AJ65: 14 | AK65: 450 | AM65: 688 | AN65: =AG65*AJ65+AK65*12+AM65+IF(AD65="",AL65,IF(AD65="D",5000,IF(AD65="C",1000,0)))*12 -> 345182 | AO65: 5 | AS65: Hu Jun（51202067） | AT65: Mo Xiaohong（11005372） | AU65: Zhao Chujun | AY65: =_xlfn.LET(_xlpm.actual,Z65,_xlpm.low,VALUE(_xlfn.TEXTBEFORE(AA65,"-")),_xlpm.high,VALUE(_xlfn.TEXTAFTER(AA65,"-")),IF(AND(_xlpm.actual=0,OR(_xlpm.low<>0,_xlpm.high<>0)),"0 increase",IF(_xlpm.actual>_xlpm.high*1.2,">20",IF(_xlpm.actual<_xlpm.low*0.8,"<20","OK")))) -> OK
A66: CN15 | B66: 15020094 | C66: 张 健 | D66: Zhang Jian | E66: Indirect Active | F66: OP | G66: SNa | H66: FLCNa-MEM | I66: 340433 | J66: 43908 | K66: Manager | L66: Head of Maintenance | M66: BAND B | N66: 2 | O66: 3 | P66: 20400 | Q66: 0.03 | R66: =ROUND(P66*Q66,0) -> 612 | S66: 0 | T66: =ROUND(P66*S66,0) -> 0 | U66: =V66/P66 -> 0.03 | V66: =R66+T66 -> 612 | W66: =P66+V66 -> 21012 | X66: 21012 | Y66: =X66-P66 -> 612 | Z66: =ROUND(X66/P66-1,4) -> 0.03 | AA66: =IF(OR(N66=1,N66=2,N66=4),TEXT(U66*0.8,"0.00%")&"-"&TEXT(U66*1.2,"0.00%"),IF(OR(N66=3,N66=6),TEXT(0,"0.00%")&"-"&TEXT(7%*1.2,"0.00%"),IF(OR(N66=5,N66=7),TEXT((T66/P66),"0.00%")&"-"&TEXT((T66/P66)+7%,"0.00%"),""))) -> 2.40%-3.60% | AF66: =ROUND(P66*AE66,0) -> 0 | AG66: =X66+AF66 -> 21012 | AH66: =AG66-P66 -> 612 | AI66: =AG66/P66-1 -> 0.03 | AJ66: 14 | AK66: 450 | AM66: 688 | AN66: =AG66*AJ66+AK66*12+AM66+IF(AD66="",AL66,IF(AD66="D",5000,IF(AD66="C",1000,0)))*12 -> 300256 | AO66: 4 | AS66: Hu Jun（51202067） | AT66: Mo Xiaohong（11005372） | AU66: Zhao Chujun | AY66: =_xlfn.LET(_xlpm.actual,Z66,_xlpm.low,VALUE(_xlfn.TEXTBEFORE(AA66,"-")),_xlpm.high,VALUE(_xlfn.TEXTAFTER(AA66,"-")),IF(AND(_xlpm.actual=0,OR(_xlpm.low<>0,_xlpm.high<>0)),"0 increase",IF(_xlpm.actual>_xlpm.high*1.2,">20",IF(_xlpm.actual<_xlpm.low*0.8,"<20","OK")))) -> OK
A67: CN15 | B67: 15022179 | C67: 朱 和伟 | D67: Zhu Hewei | E67: Indirect Active | F67: OP | G67: SNa | H67: FLCNa-MEM | I67: 340433 | J67: 44686 | K67: Engineer | L67: Tooling Engineer | M67: BAND A4 | N67: 2 | O67: 3 | P67: 12472 | Q67: 0 | R67: =ROUND(P67*Q67,0) -> 0 | S67: 0 | T67: =ROUND(P67*S67,0) -> 0 | U67: =V67/P67 -> 0 | V67: =R67+T67 -> 0 | W67: =P67+V67 -> 12472 | X67: 12700 | Y67: =X67-P67 -> 228 | Z67: =ROUND(X67/P67-1,4) -> 0.0183 | AA67: =IF(OR(N67=1,N67=2,N67=4),TEXT(U67*0.8,"0.00%")&"-"&TEXT(U67*1.2,"0.00%"),IF(OR(N67=3,N67=6),TEXT(0,"0.00%")&"-"&TEXT(7%*1.2,"0.00%"),IF(OR(N67=5,N67=7),TEXT((T67/P67),"0.00%")&"-"&TEXT((T67/P67)+7%,"0.00%"),""))) -> 0.00%-0.00% | AF67: =ROUND(P67*AE67,0) -> 0 | AG67: =X67+AF67 -> 12700 | AH67: =AG67-P67 -> 228 | AI67: =AG67/P67-1 -> 0.018280949 | AJ67: 14 | AK67: 450 | AM67: 688 | AN67: =AG67*AJ67+AK67*12+AM67+IF(AD67="",AL67,IF(AD67="D",5000,IF(AD67="C",1000,0)))*12 -> 183888 | AO67: 3 | AQ67: critical position in Mold with excellence performance in localization | AR67: Top critical position/player | AS67: Hu Jun（51202067） | AT67: Mo Xiaohong（11005372） | AU67: Zhao Chujun | AW67: exceed +/-20% adjustment | AX67: >20 | AY67: =_xlfn.LET(_xlpm.actual,Z67,_xlpm.low,VALUE(_xlfn.TEXTBEFORE(AA67,"-")),_xlpm.high,VALUE(_xlfn.TEXTAFTER(AA67,"-")),IF(AND(_xlpm.actual=0,OR(_xlpm.low<>0,_xlpm.high<>0)),"0 increase",IF(_xlpm.actual>_xlpm.high*1.2,">20",IF(_xlpm.actual<_xlpm.low*0.8,"<20","OK")))) -> >20
A68: CN15 | B68: 15022342 | C68: 朱 庆棚 | D68: Zhu Qingpeng | E68: Indirect Active | F68: OP | G68: SNa | H68: FLCNa-MEA | I68: 340200 | J68: 45035 | K68: Senior Engineer | L68: Senior Assembly Engineer | M68: BAND A5 | N68: 2 | O68: 3 | P68: 11020 | Q68: 0.03 | R68: =ROUND(P68*Q68,0) -> 331 | S68: 0 | T68: =ROUND(P68*S68,0) -> 0 | U68: =V68/P68 -> 0.030036298 | V68: =R68+T68 -> 331 | W68: =P68+V68 -> 11351 | X68: 11751 | Y68: =X68-P68 -> 731 | Z68: =ROUND(X68/P68-1,4) -> 0.0663 | AA68: =IF(OR(N68=1,N68=2,N68=4),TEXT(U68*0.8,"0.00%")&"-"&TEXT(U68*1.2,"0.00%"),IF(OR(N68=3,N68=6),TEXT(0,"0.00%")&"-"&TEXT(7%*1.2,"0.00%"),IF(OR(N68=5,N68=7),TEXT((T68/P68),"0.00%")&"-"&TEXT((T68/P68)+7%,"0.00%"),""))) -> 2.40%-3.60% | AF68: =ROUND(P68*AE68,0) -> 0 | AG68: =X68+AF68 -> 11751 | AH68: =AG68-P68 -> 731 | AI68: =AG68/P68-1 -> 0.066333938 | AJ68: 14 | AK68: 550 | AM68: 688 | AN68: =AG68*AJ68+AK68*12+AM68+IF(AD68="",AL68,IF(AD68="D",5000,IF(AD68="C",1000,0)))*12 -> 171802 | AO68: 5 | AQ68: Excellent performance in India SKD project and new line rampup | AR68: Good performers with relatively lower salary | AS68: Hu Jun（51202067） | AT68: Mo Xiaohong（11005372） | AU68: Zhao Chujun | AW68: exceed +/-20% adjustment | AX68: >20 | AY68: =_xlfn.LET(_xlpm.actual,Z68,_xlpm.low,VALUE(_xlfn.TEXTBEFORE(AA68,"-")),_xlpm.high,VALUE(_xlfn.TEXTAFTER(AA68,"-")),IF(AND(_xlpm.actual=0,OR(_xlpm.low<>0,_xlpm.high<>0)),"0 increase",IF(_xlpm.actual>_xlpm.high*1.2,">20",IF(_xlpm.actual<_xlpm.low*0.8,"<20","OK")))) -> >20
A69: CN15 | B69: 15001449 | C69: 朱 小忠 | D69: Zhu Xiaozhong | E69: Indirect Active | F69: OP | G69: SNa | H69: FLCNa-ME | I69: 340200 | J69: 39525 | K69: Engineer | L69: Electrical Engineer | M69: BAND A4 | N69: 2 | O69: 3 | P69: 12190 | Q69: 0 | R69: =ROUND(P69*Q69,0) -> 0 | S69: 0 | T69: =ROUND(P69*S69,0) -> 0 | U69: =V69/P69 -> 0 | V69: =R69+T69 -> 0 | W69: =P69+V69 -> 12190 | X69: 12190 | Y69: =X69-P69 -> 0 | Z69: =ROUND(X69/P69-1,4) -> 0 | AA69: =IF(OR(N69=1,N69=2,N69=4),TEXT(U69*0.8,"0.00%")&"-"&TEXT(U69*1.2,"0.00%"),IF(OR(N69=3,N69=6),TEXT(0,"0.00%")&"-"&TEXT(7%*1.2,"0.00%"),IF(OR(N69=5,N69=7),TEXT((T69/P69),"0.00%")&"-"&TEXT((T69/P69)+7%,"0.00%"),""))) -> 0.00%-0.00% | AF69: =ROUND(P69*AE69,0) -> 0 | AG69: =X69+AF69 -> 12190 | AH69: =AG69-P69 -> 0 | AI69: =AG69/P69-1 -> 0 | AJ69: 14 | AK69: 450 | AM69: 688 | AN69: =AG69*AJ69+AK69*12+AM69+IF(AD69="",AL69,IF(AD69="D",5000,IF(AD69="C",1000,0)))*12 -> 176748 | AO69: 1 | AS69: Hu Jun（51202067） | AT69: Mo Xiaohong（11005372） | AU69: Zhao Chujun | AY69: =_xlfn.LET(_xlpm.actual,Z69,_xlpm.low,VALUE(_xlfn.TEXTBEFORE(AA69,"-")),_xlpm.high,VALUE(_xlfn.TEXTAFTER(AA69,"-")),IF(AND(_xlpm.actual=0,OR(_xlpm.low<>0,_xlpm.high<>0)),"0 increase",IF(_xlpm.actual>_xlpm.high*1.2,">20",IF(_xlpm.actual<_xlpm.low*0.8,"<20","OK")))) -> OK
A70: CN15 | B70: 51202067 | C70: 胡 军 | D70: Hu Jun | E70: Indirect Active | F70: OP | G70: SNa | H70: FLCNa-ME | I70: 340100 | J70: 38292 | K70: Director | L70: Head of Manufacturing Engineering | M70: BAND C | N70: 2 | O70: 4 | P70: 49800 | Q70: 0.03 | R70: =ROUND(P70*Q70,0) -> 1494 | S70: 0 | T70: =ROUND(P70*S70,0) -> 0 | U70: =V70/P70 -> 0.03 | V70: =R70+T70 -> 1494 | W70: =P70+V70 -> 51294 | X70: 50100 | Y70: =X70-P70 -> 300 | Z70: =ROUND(X70/P70-1,4) -> 0.006 | AA70: =IF(OR(N70=1,N70=2,N70=4),TEXT(U70*0.8,"0.00%")&"-"&TEXT(U70*1.2,"0.00%"),IF(OR(N70=3,N70=6),TEXT(0,"0.00%")&"-"&TEXT(7%*1.2,"0.00%"),IF(OR(N70=5,N70=7),TEXT((T70/P70),"0.00%")&"-"&TEXT((T70/P70)+7%,"0.00%"),""))) -> 2.40%-3.60% | AF70: =ROUND(P70*AE70,0) -> 0 | AG70: =X70+AF70 -> 50100 | AH70: =AG70-P70 -> 300 | AI70: =AG70/P70-1 -> 0.0060240964 | AJ70: 14 | AK70: 450 | AL70: 1000 | AM70: 688 | AN70: =AG70*AJ70+AK70*12+AM70+IF(AD70="",AL70,IF(AD70="D",5000,IF(AD70="C",1000,0)))*12 -> 719488 | AO70: 4 | AQ70: higher salary within same level in the factory | AR70: Internal balance | AS70: Jiang Xiujuan（11012739） | AT70: Mo Xiaohong（11005372） | AU70: Zhao Chujun | AW70: exceed +/-20% adjustment | AX70: <20 | AY70: =_xlfn.LET(_xlpm.actual,Z70,_xlpm.low,VALUE(_xlfn.TEXTBEFORE(AA70,"-")),_xlpm.high,VALUE(_xlfn.TEXTAFTER(AA70,"-")),IF(AND(_xlpm.actual=0,OR(_xlpm.low<>0,_xlpm.high<>0)),"0 increase",IF(_xlpm.actual>_xlpm.high*1.2,">20",IF(_xlpm.actual<_xlpm.low*0.8,"<20","OK")))) -> <20
A71: CN15 | B71: 15002547 | C71: 郎 力 | D71: Lang Li | E71: Indirect Active | F71: OP | G71: SNa | H71: FLCNa-V2 | I71: 340100 | J71: 39993 | K71: Director | L71: Head of FLCNa-V2 | M71: BAND C | N71: 2 | O71: 3 | P71: 43250 | Q71: 0 | R71: =ROUND(P71*Q71,0) -> 0 | S71: 0 | T71: =ROUND(P71*S71,0) -> 0 | U71: =V71/P71 -> 0 | V71: =R71+T71 -> 0 | W71: =P71+V71 -> 43250 | X71: 43550 | Y71: =X71-P71 -> 300 | Z71: =ROUND(X71/P71-1,4) -> 0.0069 | AA71: =IF(OR(N71=1,N71=2,N71=4),TEXT(U71*0.8,"0.00%")&"-"&TEXT(U71*1.2,"0.00%"),IF(OR(N71=3,N71=6),TEXT(0,"0.00%")&"-"&TEXT(7%*1.2,"0.00%"),IF(OR(N71=5,N71=7),TEXT((T71/P71),"0.00%")&"-"&TEXT((T71/P71)+7%,"0.00%"),""))) -> 0.00%-0.00% | AF71: =ROUND(P71*AE71,0) -> 0 | AG71: =X71+AF71 -> 43550 | AH71: =AG71-P71 -> 300 | AI71: =AG71/P71-1 -> 0.0069364162 | AJ71: 14 | AK71: 450 | AL71: 1000 | AM71: 688 | AN71: =AG71*AJ71+AK71*12+AM71+IF(AD71="",AL71,IF(AD71="D",5000,IF(AD71="C",1000,0)))*12 -> 627788 | AO71: 4 | AQ71: lead new VS with proven performance | AR71: Enlarged responsibilities with proven performance | AS71: Jiang Xiujuan（11012739） | AT71: Mo Xiaohong（11005372） | AU71: Zhao Chujun | AW71: exceed +/-20% adjustment | AX71: >20 | AY71: =_xlfn.LET(_xlpm.actual,Z71,_xlpm.low,VALUE(_xlfn.TEXTBEFORE(AA71,"-")),_xlpm.high,VALUE(_xlfn.TEXTAFTER(AA71,"-")),IF(AND(_xlpm.actual=0,OR(_xlpm.low<>0,_xlpm.high<>0)),"0 increase",IF(_xlpm.actual>_xlpm.high*1.2,">20",IF(_xlpm.actual<_xlpm.low*0.8,"<20","OK")))) -> >20
A72: CN15 | B72: 15001516 | C72: 钱 荣兵 | D72: Qian Rongbing | E72: Indirect Active | F72: OP | G72: SNa | H72: FLCNa | I72: 340100 | J72: 39553 | K72: Senior Engineer | L72: Senior Production Engineer | M72: BAND A5 | N72: 2 | O72: 4 | P72: 10020 | Q72: 0.0375 | R72: =ROUND(P72*Q72,0) -> 376 | S72: 0.0155 | T72: =ROUND(P72*S72,0) -> 155 | U72: =V72/P72 -> 0.052994012 | V72: =R72+T72 -> 531 | W72: =P72+V72 -> 10551 | X72: =W72-100 -> 10451 | Y72: =X72-P72 -> 431 | Z72: =ROUND(X72/P72-1,4) -> 0.043 | AA72: =IF(OR(N72=1,N72=2,N72=4),TEXT(U72*0.8,"0.00%")&"-"&TEXT(U72*1.2,"0.00%"),IF(OR(N72=3,N72=6),TEXT(0,"0.00%")&"-"&TEXT(7%*1.2,"0.00%"),IF(OR(N72=5,N72=7),TEXT((T72/P72),"0.00%")&"-"&TEXT((T72/P72)+7%,"0.00%"),""))) -> 4.24%-6.36% | AF72: =ROUND(P72*AE72,0) -> 0 | AG72: =X72+AF72 -> 10451 | AH72: =AG72-P72 -> 431 | AI72: =AG72/P72-1 -> 0.043013972 | AJ72: 14 | AK72: 450 | AM72: 688 | AN72: =AG72*AJ72+AK72*12+AM72+IF(AD72="",AL72,IF(AD72="D",5000,IF(AD72="C",1000,0)))*12 -> 152402 | AO72: 2 | AS72: Jiang Xiujuan（11012739） | AT72: Mo Xiaohong（11005372） | AU72: Zhao Chujun | AY72: =_xlfn.LET(_xlpm.actual,Z72,_xlpm.low,VALUE(_xlfn.TEXTBEFORE(AA72,"-")),_xlpm.high,VALUE(_xlfn.TEXTAFTER(AA72,"-")),IF(AND(_xlpm.actual=0,OR(_xlpm.low<>0,_xlpm.high<>0)),"0 increase",IF(_xlpm.actual>_xlpm.high*1.2,">20",IF(_xlpm.actual<_xlpm.low*0.8,"<20","OK")))) -> OK
A73: CN15 | B73: 15001801 | C73: 孙 秀建 | D73: Sun Xiujian | E73: Indirect Active | F73: OP | G73: SNa | H73: FLCNa | I73: 340100 | J73: 39637 | K73: Manager | L73: Manager | M73: BAND B | N73: 2 | O73: 3 | P73: 30000 | Q73: 0 | R73: =ROUND(P73*Q73,0) -> 0 | S73: 0 | T73: =ROUND(P73*S73,0) -> 0 | U73: =V73/P73 -> 0 | V73: =R73+T73 -> 0 | W73: =P73+V73 -> 30000 | X73: =W73 -> 30000 | Y73: =X73-P73 -> 0 | Z73: =ROUND(X73/P73-1,4) -> 0 | AA73: =IF(OR(N73=1,N73=2,N73=4),TEXT(U73*0.8,"0.00%")&"-"&TEXT(U73*1.2,"0.00%"),IF(OR(N73=3,N73=6),TEXT(0,"0.00%")&"-"&TEXT(7%*1.2,"0.00%"),IF(OR(N73=5,N73=7),TEXT((T73/P73),"0.00%")&"-"&TEXT((T73/P73)+7%,"0.00%"),""))) -> 0.00%-0.00% | AF73: =ROUND(P73*AE73,0) -> 0 | AG73: =X73+AF73 -> 30000 | AH73: =AG73-P73 -> 0 | AI73: =AG73/P73-1 -> 0 | AJ73: 14 | AK73: 450 | AM73: 688 | AN73: =AG73*AJ73+AK73*12+AM73+IF(AD73="",AL73,IF(AD73="D",5000,IF(AD73="C",1000,0)))*12 -> 426088 | AO73: 3 | AS73: Jiang Xiujuan（11012739） | AT73: Mo Xiaohong（11005372） | AU73: Zhao Chujun | AY73: =_xlfn.LET(_xlpm.actual,Z73,_xlpm.low,VALUE(_xlfn.TEXTBEFORE(AA73,"-")),_xlpm.high,VALUE(_xlfn.TEXTAFTER(AA73,"-")),IF(AND(_xlpm.actual=0,OR(_xlpm.low<>0,_xlpm.high<>0)),"0 increase",IF(_xlpm.actual>_xlpm.high*1.2,">20",IF(_xlpm.actual<_xlpm.low*0.8,"<20","OK")))) -> OK
A74: CN15 | B74: 15000580 | C74: 姚 雷雷 | D74: Yao Leilei | E74: Indirect Active | F74: OP | G74: SNa | H74: FLCNa-VF | I74: 340100 | J74: 38916 | K74: Director | L74: Head of FLCNa-VF | M74: BAND C | N74: 2 | O74: 3 | P74: 42080 | Q74: 0 | R74: =ROUND(P74*Q74,0) -> 0 | S74: 0 | T74: =ROUND(P74*S74,0) -> 0 | U74: =V74/P74 -> 0 | V74: =R74+T74 -> 0 | W74: =P74+V74 -> 42080 | X74: =W74+606 -> 42686 | Y74: =X74-P74 -> 606 | Z74: =ROUND(X74/P74-1,4) -> 0.0144 | AA74: =IF(OR(N74=1,N74=2,N74=4),TEXT(U74*0.8,"0.00%")&"-"&TEXT(U74*1.2,"0.00%"),IF(OR(N74=3,N74=6),TEXT(0,"0.00%")&"-"&TEXT(7%*1.2,"0.00%"),IF(OR(N74=5,N74=7),TEXT((T74/P74),"0.00%")&"-"&TEXT((T74/P74)+7%,"0.00%"),""))) -> 0.00%-0.00% | AF74: =ROUND(P74*AE74,0) -> 0 | AG74: =X74+AF74 -> 42686 | AH74: =AG74-P74 -> 606 | AI74: =AG74/P74-1 -> 0.014401141 | AJ74: 14 | AK74: 450 | AL74: 1000 | AM74: 688 | AN74: =AG74*AJ74+AK74*12+AM74+IF(AD74="",AL74,IF(AD74="D",5000,IF(AD74="C",1000,0)))*12 -> 615692 | AO74: 3 | AQ74: enlarged responsibilities with CP management | AR74: Enlarged responsibilities with proven performance | AS74: Jiang Xiujuan（11012739） | AT74: Mo Xiaohong（11005372） | AU74: Zhao Chujun | AW74: exceed +/-20% adjustment | AX74: >20 | AY74: =_xlfn.LET(_xlpm.actual,Z74,_xlpm.low,VALUE(_xlfn.TEXTBEFORE(AA74,"-")),_xlpm.high,VALUE(_xlfn.TEXTAFTER(AA74,"-")),IF(AND(_xlpm.actual=0,OR(_xlpm.low<>0,_xlpm.high<>0)),"0 increase",IF(_xlpm.actual>_xlpm.high*1.2,">20",IF(_xlpm.actual<_xlpm.low*0.8,"<20","OK")))) -> >20
A75: CN15 | B75: 15003586 | C75: 叶 友军 | D75: Ye Youjun | E75: Indirect Active | F75: OP | G75: SNa | H75: FLCNa | I75: 340100 | J75: 40269 | K75: Senior Engineer | L75: Senior Engineer | M75: BAND A5 | N75: 2 | O75: 3 | P75: 12200 | Q75: 0 | R75: =ROUND(P75*Q75,0) -> 0 | S75: 0 | T75: =ROUND(P75*S75,0) -> 0 | U75: =V75/P75 -> 0 | V75: =R75+T75 -> 0 | W75: =P75+V75 -> 12200 | X75: =W75+274 -> 12474 | Y75: =X75-P75 -> 274 | Z75: =ROUND(X75/P75-1,4) -> 0.0225 | AA75: =IF(OR(N75=1,N75=2,N75=4),TEXT(U75*0.8,"0.00%")&"-"&TEXT(U75*1.2,"0.00%"),IF(OR(N75=3,N75=6),TEXT(0,"0.00%")&"-"&TEXT(7%*1.2,"0.00%"),IF(OR(N75=5,N75=7),TEXT((T75/P75),"0.00%")&"-"&TEXT((T75/P75)+7%,"0.00%"),""))) -> 0.00%-0.00% | AF75: =ROUND(P75*AE75,0) -> 0 | AG75: =X75+AF75 -> 12474 | AH75: =AG75-P75 -> 274 | AI75: =AG75/P75-1 -> 0.022459016 | AJ75: 14 | AK75: 450 | AM75: 688 | AN75: =AG75*AJ75+AK75*12+AM75+IF(AD75="",AL75,IF(AD75="D",5000,IF(AD75="C",1000,0)))*12 -> 180724 | AO75: 3 | AQ75: enlarged responsibilities, add BPS management | AR75: Enlarged responsibilities with proven performance | AS75: Jiang Xiujuan（11012739） | AT75: Mo Xiaohong（11005372） | AU75: Zhao Chujun | AW75: exceed +/-20% adjustment | AX75: >20 | AY75: =_xlfn.LET(_xlpm.actual,Z75,_xlpm.low,VALUE(_xlfn.TEXTBEFORE(AA75,"-")),_xlpm.high,VALUE(_xlfn.TEXTAFTER(AA75,"-")),IF(AND(_xlpm.actual=0,OR(_xlpm.low<>0,_xlpm.high<>0)),"0 increase",IF(_xlpm.actual>_xlpm.high*1.2,">20",IF(_xlpm.actual<_xlpm.low*0.8,"<20","OK")))) -> >20
A76: CN15 | B76: 15006800 | C76: 张 辉宇 | D76: Zhang Huiyu | E76: Indirect Active | F76: OP | G76: SNa | H76: FLCNa-V1 | I76: 340100 | J76: 40744 | K76: Manager | L76: Head of FLCNa-V1 | M76: BAND B | N76: 2 | O76: 3 | P76: 15455 | Q76: 0.03 | R76: =ROUND(P76*Q76,0) -> 464 | S76: 0 | T76: =ROUND(P76*S76,0) -> 0 | U76: =V76/P76 -> 0.030022646 | V76: =R76+T76 -> 464 | W76: =P76+V76 -> 15919 | X76: =W76+1091 -> 17010 | Y76: =X76-P76 -> 1555 | Z76: =ROUND(X76/P76-1,4) -> 0.1006 | AA76: =IF(OR(N76=1,N76=2,N76=4),TEXT(U76*0.8,"0.00%")&"-"&TEXT(U76*1.2,"0.00%"),IF(OR(N76=3,N76=6),TEXT(0,"0.00%")&"-"&TEXT(7%*1.2,"0.00%"),IF(OR(N76=5,N76=7),TEXT((T76/P76),"0.00%")&"-"&TEXT((T76/P76)+7%,"0.00%"),""))) -> 2.40%-3.60% | AF76: =ROUND(P76*AE76,0) -> 0 | AG76: =X76+AF76 -> 17010 | AH76: =AG76-P76 -> 1555 | AI76: =AG76/P76-1 -> 0.10061469 | AJ76: 14 | AK76: 450 | AM76: 688 | AN76: =AG76*AJ76+AK76*12+AM76+IF(AD76="",AL76,IF(AD76="D",5000,IF(AD76="C",1000,0)))*12 -> 244228 | AO76: 5 | AQ76: took VS head with excellent performance. Lower salary. | AR76: Enlarged responsibilities with proven performance | AS76: Jiang Xiujuan（11012739） | AT76: Mo Xiaohong（11005372） | AU76: Zhao Chujun | AW76: exceed +/-20% adjustment | AX76: >20 | AY76: =_xlfn.LET(_xlpm.actual,Z76,_xlpm.low,VALUE(_xlfn.TEXTBEFORE(AA76,"-")),_xlpm.high,VALUE(_xlfn.TEXTAFTER(AA76,"-")),IF(AND(_xlpm.actual=0,OR(_xlpm.low<>0,_xlpm.high<>0)),"0 increase",IF(_xlpm.actual>_xlpm.high*1.2,">20",IF(_xlpm.actual<_xlpm.low*0.8,"<20","OK")))) -> >20
A77: CN15 | B77: 15014010 | C77: 王 毅 | D77: Wang Yi | E77: Indirect Active | F77: OP | G77: RM | H77: CN/OP-RMNG | I77: 290104 | J77: 42081 | K77: Manager | L77: Manager | M77: BAND B | N77: 2 | O77: 5 | P77: 22000 | Q77: 0.06 | R77: 1320 | S77: 0.027 | T77: 594 | U77: 0.087 | V77: 1914 | W77: 23914 | X77: 23540 | Y77: 1540 | Z77: 0.07 | AA77: 6.96%-10.44% | AF77: 0 | AG77: 23540 | AH77: 1540 | AI77: 0.07 | AJ77: 14 | AK77: 450 | AM77: 688 | AN77: 335648 | AO77: 4 | AS77: Chen Lianrong（15022534） | AT77: Mo Xiaohong（11005372） | AU77: Wu Ellen | AY77: =_xlfn.LET(_xlpm.actual,Z77,_xlpm.low,VALUE(_xlfn.TEXTBEFORE(AA77,"-")),_xlpm.high,VALUE(_xlfn.TEXTAFTER(AA77,"-")),IF(AND(_xlpm.actual=0,OR(_xlpm.low<>0,_xlpm.high<>0)),"0 increase",IF(_xlpm.actual>_xlpm.high*1.2,">20",IF(_xlpm.actual<_xlpm.low*0.8,"<20","OK")))) -> OK
A78: CN15 | B78: 15022076 | C78: 陈 海宁 | D78: Chen Haining | E78: Indirect Active | F78: OP | G78: RM | H78: CN/OP-RMNF | I78: 290300 | J78: 44545 | K78: Senior Engineer | L78: MEP Engineer | M78: BAND A5 | N78: 2 | O78: 4 | P78: 12700 | Q78: 0.0375 | R78: 476 | S78: 0.0155 | T78: 197 | U78: 0.052992126 | V78: 673 | W78: 13373 | X78: 13240 | Y78: 540 | Z78: 0.0425 | AA78: 4.24%-6.36% | AF78: 0 | AG78: 13240 | AH78: 540 | AI78: 0.042519685 | AJ78: 14 | AK78: 450 | AM78: 688 | AN78: 191448 | AO78: 3 | AS78: Chen Lianrong（15022534） | AT78: Mo Xiaohong（11005372） | AU78: Wu Ellen | AY78: =_xlfn.LET(_xlpm.actual,Z78,_xlpm.low,VALUE(_xlfn.TEXTBEFORE(AA78,"-")),_xlpm.high,VALUE(_xlfn.TEXTAFTER(AA78,"-")),IF(AND(_xlpm.actual=0,OR(_xlpm.low<>0,_xlpm.high<>0)),"0 increase",IF(_xlpm.actual>_xlpm.high*1.2,">20",IF(_xlpm.actual<_xlpm.low*0.8,"<20","OK")))) -> OK
A79: CN15 | B79: 15001949 | C79: 葛 加国 | D79: Ge Jiaguo | E79: Indirect Active | F79: OP | G79: RM | H79: CN/OP-RMNG | I79: 290104 | J79: 39682 | K79: Shift Leader | L79: Security Shift Leader | M79: BAND A3 | N79: 2 | O79: 3 | P79: 9870 | Q79: 0 | R79: 0 | S79: 0 | T79: 0 | U79: 0 | V79: 0 | W79: 9870 | X79: 9870 | Y79: 0 | Z79: 0 | AA79: 0.00%-0.00% | AF79: 0 | AG79: 9870 | AH79: 0 | AI79: 0 | AJ79: 14 | AK79: 450 | AM79: 688 | AN79: 144268 | AO79: 3 | AS79: Chen Lianrong（15022534） | AT79: Mo Xiaohong（11005372） | AU79: Wu Ellen | AY79: =_xlfn.LET(_xlpm.actual,Z79,_xlpm.low,VALUE(_xlfn.TEXTBEFORE(AA79,"-")),_xlpm.high,VALUE(_xlfn.TEXTAFTER(AA79,"-")),IF(AND(_xlpm.actual=0,OR(_xlpm.low<>0,_xlpm.high<>0)),"0 increase",IF(_xlpm.actual>_xlpm.high*1.2,">20",IF(_xlpm.actual<_xlpm.low*0.8,"<20","OK")))) -> OK
A80: CN15 | B80: 15018456 | C80: 罗 慧 | D80: Luo Hui | E80: Indirect Active | F80: OP | G80: RM | H80: CN/OP-RMNG | I80: 290104 | J80: 43042 | K80: Specialist | L80: Specialist | M80: BAND A4 | N80: 2 | O80: 4 | P80: 6679 | Q80: 0.0375 | R80: 250 | S80: 0 | T80: 0 | U80: 0.037430753 | V80: 250 | W80: 6929 | X80: 7150 | Y80: 471 | Z80: 0.0705 | AA80: 2.99%-4.49% | AF80: 0 | AG80: 7150 | AH80: 471 | AI80: 0.070519539 | AJ80: 14 | AK80: 450 | AM80: 688 | AN80: 106188 | AO80: 3 | AQ80: 1.Optimized RMN internal purchasing process 2.Frame contract utility rate is top 3 3.SC order follow up professionally. | AR80: Good performers with extremely lower salary | AS80: Chen Lianrong（15022534） | AT80: Mo Xiaohong（11005372） | AU80: Wu Ellen | AW80: exceed +/-20% adjustment | AX80: >20 | AY80: =_xlfn.LET(_xlpm.actual,Z80,_xlpm.low,VALUE(_xlfn.TEXTBEFORE(AA80,"-")),_xlpm.high,VALUE(_xlfn.TEXTAFTER(AA80,"-")),IF(AND(_xlpm.actual=0,OR(_xlpm.low<>0,_xlpm.high<>0)),"0 increase",IF(_xlpm.actual>_xlpm.high*1.2,">20",IF(_xlpm.actual<_xlpm.low*0.8,"<20","OK")))) -> >20
A81: CN15 | B81: 15022106 | C81: 申 彧 | D81: Shen Yu | E81: Indirect Active | F81: OP | G81: RM | H81: CN/OP-RMNF | I81: 290300 | J81: 44573 | K81: Senior Engineer | L81: Civil Engineer | M81: BAND A5 | N81: 2 | O81: 2 | P81: 13520 | Q81: 0 | R81: 0 | S81: 0 | T81: 0 | U81: 0 | V81: 0 | W81: 13520 | X81: 13520 | Y81: 0 | Z81: 0 | AA81: 0.00%-0.00% | AF81: 0 | AG81: 13520 | AH81: 0 | AI81: 0 | AJ81: 14 | AK81: 550 | AM81: 688 | AN81: 196568 | AO81: 5 | AS81: Chen Lianrong（15022534） | AT81: Mo Xiaohong（11005372） | AU81: Wu Ellen | AY81: =_xlfn.LET(_xlpm.actual,Z81,_xlpm.low,VALUE(_xlfn.TEXTBEFORE(AA81,"-")),_xlpm.high,VALUE(_xlfn.TEXTAFTER(AA81,"-")),IF(AND(_xlpm.actual=0,OR(_xlpm.low<>0,_xlpm.high<>0)),"0 increase",IF(_xlpm.actual>_xlpm.high*1.2,">20",IF(_xlpm.actual<_xlpm.low*0.8,"<20","OK")))) -> OK
A82: CN15 | B82: 15000274 | C82: 盛 忠明 | D82: Sheng Zhongming | E82: Indirect Active | F82: OP | G82: RM | H82: CN/OP-RMNF | I82: 290300 | J82: 38645 | K82: Engineer | L82: Engineer | M82: BAND A4 | N82: 2 | O82: 1 | P82: 12735 | Q82: 0 | R82: 0 | S82: 0 | T82: 0 | U82: 0 | V82: 0 | W82: 12735 | X82: 12735 | Y82: 0 | Z82: 0 | AA82: 0.00%-0.00% | AF82: 0 | AG82: 12735 | AH82: 0 | AI82: 0 | AJ82: 14 | AK82: 450 | AM82: 688 | AN82: 184378 | AO82: 4 | AS82: Chen Lianrong（15022534） | AT82: Mo Xiaohong（11005372） | AU82: Wu Ellen | AY82: =_xlfn.LET(_xlpm.actual,Z82,_xlpm.low,VALUE(_xlfn.TEXTBEFORE(AA82,"-")),_xlpm.high,VALUE(_xlfn.TEXTAFTER(AA82,"-")),IF(AND(_xlpm.actual=0,OR(_xlpm.low<>0,_xlpm.high<>0)),"0 increase",IF(_xlpm.actual>_xlpm.high*1.2,">20",IF(_xlpm.actual<_xlpm.low*0.8,"<20","OK")))) -> OK
A83: CN15 | B83: 15018979 | C83: 臧 伟 | D83: Zang Wei | E83: Indirect Active | F83: OP | G83: RM | H83: CN/OP-RMNF | I83: 290300 | J83: 41124 | K83: Engineer | L83: DDC Engineer | M83: BAND A4 | N83: 2 | O83: 3 | P83: 10588 | Q83: 0.025 | R83: 265 | S83: 0 | T83: 0 | U83: 0.025028334 | V83: 265 | W83: 10853 | X83: 10853 | Y83: 265 | Z83: 0.025 | AA83: 2.00%-3.00% | AF83: 0 | AG83: 10853 | AH83: 265 | AI83: 0.025028334 | AJ83: 14 | AK83: 450 | AM83: 688 | AN83: 158030 | AO83: 3 | AS83: Chen Lianrong（15022534） | AT83: Mo Xiaohong（11005372） | AU83: Wu Ellen | AY83: =_xlfn.LET(_xlpm.actual,Z83,_xlpm.low,VALUE(_xlfn.TEXTBEFORE(AA83,"-")),_xlpm.high,VALUE(_xlfn.TEXTAFTER(AA83,"-")),IF(AND(_xlpm.actual=0,OR(_xlpm.low<>0,_xlpm.high<>0)),"0 increase",IF(_xlpm.actual>_xlpm.high*1.2,">20",IF(_xlpm.actual<_xlpm.low*0.8,"<20","OK")))) -> OK
A84: CN15 | B84: 15004177 | C84: 张 宏权 | D84: Zhang Hongquan | E84: Indirect Active | F84: OP | G84: RM | H84: CN/OP-RMNF | I84: 290300 | J84: 40373 | K84: Junior Engineer | L84: Junior Engineer | M84: BAND A3 | N84: 2 | O84: 3 | P84: 6725 | Q84: 0.03 | R84: 202 | S84: 0 | T84: 0 | U84: 0.030037175 | V84: 202 | W84: 6927 | X84: 7150 | Y84: 425 | Z84: 0.0632 | AA84: 2.40%-3.60% | AF84: 0 | AG84: 7150 | AH84: 425 | AI84: 0.063197026 | AJ84: 14 | AK84: 450 | AM84: 688 | AN84: 106188 | AO84: 2 | AQ84: 1.Took over additional management work for special equipment, with excellent on-site management and implementation. | AR84: Enlarged responsibilities with proven performance | AS84: Chen Lianrong（15022534） | AT84: Mo Xiaohong（11005372） | AU84: Wu Ellen | AW84: exceed +/-20% adjustment | AX84: >20 | AY84: =_xlfn.LET(_xlpm.actual,Z84,_xlpm.low,VALUE(_xlfn.TEXTBEFORE(AA84,"-")),_xlpm.high,VALUE(_xlfn.TEXTAFTER(AA84,"-")),IF(AND(_xlpm.actual=0,OR(_xlpm.low<>0,_xlpm.high<>0)),"0 increase",IF(_xlpm.actual>_xlpm.high*1.2,">20",IF(_xlpm.actual<_xlpm.low*0.8,"<20","OK")))) -> >20
A85: CN15 | B85: 15013653 | C85: 章 彬彬 | D85: Zhang Binbin | E85: Indirect Active | F85: OP | G85: RM | H85: CN/OP-RMNF | I85: 290300 | J85: 41899 | K85: Senior Engineer | L85: Senior Civil Engineer | M85: BAND A5 | N85: 2 | O85: 4 | P85: 12400 | Q85: 0.0375 | R85: 465 | S85: 0.0155 | T85: 192 | U85: 0.052983871 | V85: 657 | W85: 13057 | X85: 13100 | Y85: 700 | Z85: 0.0565 | AA85: 4.24%-6.36% | AF85: 0 | AG85: 13100 | AH85: 700 | AI85: 0.056451613 | AJ85: 14 | AK85: 450 | AM85: 688 | AN85: 189488 | AO85: 3 | AS85: Chen Lianrong（15022534） | AT85: Mo Xiaohong（11005372） | AU85: Wu Ellen | AY85: =_xlfn.LET(_xlpm.actual,Z85,_xlpm.low,VALUE(_xlfn.TEXTBEFORE(AA85,"-")),_xlpm.high,VALUE(_xlfn.TEXTAFTER(AA85,"-")),IF(AND(_xlpm.actual=0,OR(_xlpm.low<>0,_xlpm.high<>0)),"0 increase",IF(_xlpm.actual>_xlpm.high*1.2,">20",IF(_xlpm.actual<_xlpm.low*0.8,"<20","OK")))) -> OK
A86: CN15 | B86: 15013014 | C86: 郑 玉阳 | D86: Zheng Yuyang | E86: Indirect Active | F86: OP | G86: RM | H86: CN/OP-RMNF | I86: 290300 | J86: 41766 | K86: Senior Engineer | L86: Senior Facility Engineer | M86: BAND A5 | N86: 2 | O86: 5 | P86: 12600 | Q86: 0.05 | R86: 630 | S86: 0.027 | T86: 340 | U86: 0.076984127 | V86: 970 | W86: 13570 | X86: 13400 | Y86: 800 | Z86: 0.0635 | AA86: 6.16%-9.24% | AB86: Promotion | AC86: Functional specialist | AD86: A6 | AE86: 0.084 | AF86: 1058 | AG86: 14458 | AH86: 1858 | AI86: 0.14746032 | AJ86: 14 | AK86: 450 | AM86: 688 | AN86: 208500 | AO86: 4 | AQ86: Good performance and high potential | AR86: Good performance and high potential | AS86: Chen Lianrong（15022534） | AT86: Mo Xiaohong（11005372） | AU86: Wu Ellen | AY86: =_xlfn.LET(_xlpm.actual,Z86,_xlpm.low,VALUE(_xlfn.TEXTBEFORE(AA86,"-")),_xlpm.high,VALUE(_xlfn.TEXTAFTER(AA86,"-")),IF(AND(_xlpm.actual=0,OR(_xlpm.low<>0,_xlpm.high<>0)),"0 increase",IF(_xlpm.actual>_xlpm.high*1.2,">20",IF(_xlpm.actual<_xlpm.low*0.8,"<20","OK")))) -> OK
A87: CN15 | B87: 15016258 | C87: 宗 楚玉 | D87: Zong Chuyu | E87: Indirect Active | F87: OP | G87: RM | H87: CN/OP-RMNG | I87: 290104 | J87: 42723 | K87: Senior Specialist | L87: Senior Specialist | M87: BAND A5 | N87: 2 | O87: 3 | P87: 9400 | Q87: 0.025 | R87: 235 | S87: 0 | T87: 0 | U87: 0.025 | V87: 235 | W87: 9635 | X87: 9650 | Y87: 250 | Z87: 0.0266 | AA87: 2.00%-3.00% | AF87: 0 | AG87: 9650 | AH87: 250 | AI87: 0.026595745 | AJ87: 14 | AK87: 450 | AM87: 688 | AN87: 141188 | AO87: 4 | AS87: Chen Lianrong（15022534） | AT87: Mo Xiaohong（11005372） | AU87: Wu Ellen | AY87: =_xlfn.LET(_xlpm.actual,Z87,_xlpm.low,VALUE(_xlfn.TEXTBEFORE(AA87,"-")),_xlpm.high,VALUE(_xlfn.TEXTAFTER(AA87,"-")),IF(AND(_xlpm.actual=0,OR(_xlpm.low<>0,_xlpm.high<>0)),"0 increase",IF(_xlpm.actual>_xlpm.high*1.2,">20",IF(_xlpm.actual<_xlpm.low*0.8,"<20","OK")))) -> OK
A88: CN15 | B88: 11000452 | C88: 李 蕾 | D88: Li Lei | E88: Indirect Active | F88: OP | G88: SC | H88: SNa-SC4MP | I88: 390501 | J88: 36297 | K88: Planner | L88: Material Planner | M88: BAND A4 | N88: 2 | O88: 3 | P88: 10091 | Q88: 0 | R88: 0 | S88: 0 | T88: 0 | U88: 0 | V88: 0 | W88: 10091 | X88: 10091 | Y88: 0 | Z88: 0 | AA88: 0.00%-0.00% | AF88: 0 | AG88: 10091 | AH88: 0 | AI88: 0 | AJ88: 14 | AK88: 450 | AM88: 688 | AN88: 147362 | AO88: 3 | AS88: Zhou Chuancui（1520041） | AT88: Shao Xiao（11018043） | AU88: Cheng Cheng | AY88: =_xlfn.LET(_xlpm.actual,Z88,_xlpm.low,VALUE(_xlfn.TEXTBEFORE(AA88,"-")),_xlpm.high,VALUE(_xlfn.TEXTAFTER(AA88,"-")),IF(AND(_xlpm.actual=0,OR(_xlpm.low<>0,_xlpm.high<>0)),"0 increase",IF(_xlpm.actual>_xlpm.high*1.2,">20",IF(_xlpm.actual<_xlpm.low*0.8,"<20","OK")))) -> OK
A89: CN15 | B89: 15021389 | C89: 刘 超 | D89: Liu Chao | E89: Indirect Active | F89: OP | G89: SC | H89: SNa-SC4MS | I89: 390501 | J89: 44356 | K89: Planner | L89: Material Planner | M89: BAND A4 | N89: 2 | O89: 3 | P89: 10091 | Q89: 0 | R89: 0 | S89: 0 | T89: 0 | U89: 0 | V89: 0 | W89: 10091 | X89: 10091 | Y89: 0 | Z89: 0 | AA89: 0.00%-0.00% | AF89: 0 | AG89: 10091 | AH89: 0 | AI89: 0 | AJ89: 14 | AK89: 450 | AM89: 688 | AN89: 147362 | AO89: 3 | AS89: Zhou Chuancui（1520041） | AT89: Shao Xiao（11018043） | AU89: Cheng Cheng | AY89: =_xlfn.LET(_xlpm.actual,Z89,_xlpm.low,VALUE(_xlfn.TEXTBEFORE(AA89,"-")),_xlpm.high,VALUE(_xlfn.TEXTAFTER(AA89,"-")),IF(AND(_xlpm.actual=0,OR(_xlpm.low<>0,_xlpm.high<>0)),"0 increase",IF(_xlpm.actual>_xlpm.high*1.2,">20",IF(_xlpm.actual<_xlpm.low*0.8,"<20","OK")))) -> OK
A90: CN15 | B90: 15013869 | C90: 阮 婷 | D90: Ruan Ting | E90: Indirect Active | F90: OP | G90: SC | H90: SNa-SC4ME | I90: 390501 | J90: 41990 | K90: Senior Planner | L90: Senior Material Planner | M90: BAND A5 | N90: 2 | O90: 3 | P90: 8250 | Q90: 0.03 | R90: 248 | S90: 0 | T90: 0 | U90: 0.030060606 | V90: 248 | W90: 8498 | X90: 8600 | Y90: 350 | Z90: 0.0424 | AA90: 2.40%-3.61% | AF90: 0 | AG90: 8600 | AH90: 350 | AI90: 0.042424242 | AJ90: 14 | AK90: 450 | AM90: 688 | AN90: 126488 | AO90: 2 | AQ90: Internal balance | AR90: Internal balance | AS90: Zhou Chuancui（1520041） | AT90: Shao Xiao（11018043） | AU90: Cheng Cheng | AY90: =_xlfn.LET(_xlpm.actual,Z90,_xlpm.low,VALUE(_xlfn.TEXTBEFORE(AA90,"-")),_xlpm.high,VALUE(_xlfn.TEXTAFTER(AA90,"-")),IF(AND(_xlpm.actual=0,OR(_xlpm.low<>0,_xlpm.high<>0)),"0 increase",IF(_xlpm.actual>_xlpm.high*1.2,">20",IF(_xlpm.actual<_xlpm.low*0.8,"<20","OK")))) -> OK
A91: CN15 | B91: 15018916 | C91: 申 萍 | D91: Shen Ping | E91: Indirect Active | F91: OP | G91: SC | H91: SNa-SC4MX | I91: 390501 | J91: 43194 | K91: Supervisor | L91: Head of SNa-SC4MX | M91: BAND A6 | N91: 2 | O91: 4 | P91: 14330 | Q91: 0.0375 | R91: 537 | S91: 0.0155 | T91: 222 | U91: 0.052965806 | V91: 759 | W91: 15089 | X91: 15089 | Y91: 759 | Z91: 0.053 | AA91: 4.24%-6.36% | AF91: 0 | AG91: 15089 | AH91: 759 | AI91: 0.052965806 | AJ91: 14 | AK91: 450 | AM91: 688 | AN91: 217334 | AO91: 4 | AS91: Zhou Chuancui（1520041） | AT91: Shao Xiao（11018043） | AU91: Cheng Cheng | AY91: =_xlfn.LET(_xlpm.actual,Z91,_xlpm.low,VALUE(_xlfn.TEXTBEFORE(AA91,"-")),_xlpm.high,VALUE(_xlfn.TEXTAFTER(AA91,"-")),IF(AND(_xlpm.actual=0,OR(_xlpm.low<>0,_xlpm.high<>0)),"0 increase",IF(_xlpm.actual>_xlpm.high*1.2,">20",IF(_xlpm.actual<_xlpm.low*0.8,"<20","OK")))) -> OK
A92: CN15 | B92: 15022000 | C92: 王 听听 | D92: Wang Tingting | E92: Indirect Active | F92: OP | G92: SC | H92: SNa-SC4MM | I92: 390501 | J92: 44510 | K92: Planner | L92: Material planner | M92: BAND A4 | N92: 2 | O92: 3 | P92: 8432 | Q92: 0.025 | R92: 211 | S92: 0 | T92: 0 | U92: 0.025023719 | V92: 211 | W92: 8643 | X92: 8643 | Y92: 211 | Z92: 0.025 | AA92: 2.00%-3.00% | AF92: 0 | AG92: 8643 | AH92: 211 | AI92: 0.025023719 | AJ92: 14 | AK92: 450 | AM92: 688 | AN92: 127090 | AO92: 3 | AS92: Zhou Chuancui（1520041） | AT92: Shao Xiao（11018043） | AU92: Cheng Cheng | AY92: =_xlfn.LET(_xlpm.actual,Z92,_xlpm.low,VALUE(_xlfn.TEXTBEFORE(AA92,"-")),_xlpm.high,VALUE(_xlfn.TEXTAFTER(AA92,"-")),IF(AND(_xlpm.actual=0,OR(_xlpm.low<>0,_xlpm.high<>0)),"0 increase",IF(_xlpm.actual>_xlpm.high*1.2,">20",IF(_xlpm.actual<_xlpm.low*0.8,"<20","OK")))) -> OK
A93: CN15 | B93: 15006182 | C93: 吴 晓峰 | D93: Wu Xiaofeng | E93: Indirect Active | F93: OP | G93: SC | H93: SNa-SC4MP | I93: 390501 | J93: 40695 | K93: Senior Specialist | L93: Senior Material Specialist | M93: BAND A5 | N93: 2 | O93: 3 | P93: 9780 | Q93: 0.03 | R93: 293 | S93: 0 | T93: 0 | U93: 0.0299591 | V93: 293 | W93: 10073 | X93: 10073 | Y93: 293 | Z93: 0.03 | AA93: 2.40%-3.60% | AF93: 0 | AG93: 10073 | AH93: 293 | AI93: 0.0299591 | AJ93: 14 | AK93: 450 | AM93: 688 | AN93: 147110 | AO93: 4 | AS93: Zhou Chuancui（1520041） | AT93: Shao Xiao（11018043） | AU93: Cheng Cheng | AY93: =_xlfn.LET(_xlpm.actual,Z93,_xlpm.low,VALUE(_xlfn.TEXTBEFORE(AA93,"-")),_xlpm.high,VALUE(_xlfn.TEXTAFTER(AA93,"-")),IF(AND(_xlpm.actual=0,OR(_xlpm.low<>0,_xlpm.high<>0)),"0 increase",IF(_xlpm.actual>_xlpm.high*1.2,">20",IF(_xlpm.actual<_xlpm.low*0.8,"<20","OK")))) -> OK
A94: CN15 | B94: 15003608 | C94: 杨 小波 | D94: Yang Xiaobo | E94: Indirect Active | F94: OP | G94: SC | H94: SNa-SC4MX | I94: 390501 | J94: 40276 | K94: Planner | L94: Material Planner | M94: BAND A4 | N94: 2 | O94: 3 | P94: 9055 | Q94: 0.025 | R94: 226 | S94: 0 | T94: 0 | U94: 0.024958586 | V94: 226 | W94: 9281 | X94: 9281 | Y94: 226 | Z94: 0.025 | AA94: 2.00%-3.00% | AF94: 0 | AG94: 9281 | AH94: 226 | AI94: 0.024958586 | AJ94: 14 | AK94: 450 | AM94: 688 | AN94: 136022 | AO94: 3 | AS94: Zhou Chuancui（1520041） | AT94: Shao Xiao（11018043） | AU94: Cheng Cheng | AY94: =_xlfn.LET(_xlpm.actual,Z94,_xlpm.low,VALUE(_xlfn.TEXTBEFORE(AA94,"-")),_xlpm.high,VALUE(_xlfn.TEXTAFTER(AA94,"-")),IF(AND(_xlpm.actual=0,OR(_xlpm.low<>0,_xlpm.high<>0)),"0 increase",IF(_xlpm.actual>_xlpm.high*1.2,">20",IF(_xlpm.actual<_xlpm.low*0.8,"<20","OK")))) -> OK
A95: CN15 | B95: 15016766 | C95: 张 玲玲 | D95: Zhang Lingling | E95: Indirect Active | F95: OP | G95: SC | H95: SNa-SC4MM | I95: 390501 | J95: 42816 | K95: Senior Planner | L95: Senior Material Planner | M95: BAND A5 | N95: 2 | O95: 4 | P95: 10250 | Q95: 0.0375 | R95: 384 | S95: 0.0155 | T95: 159 | U95: 0.05297561 | V95: 543 | W95: 10793 | X95: 11000 | Y95: 750 | Z95: 0.0732 | AA95: 4.24%-6.36% | AF95: 0 | AG95: 11000 | AH95: 750 | AI95: 0.073170732 | AJ95: 14 | AK95: 450 | AM95: 688 | AN95: 160088 | AO95: 3 | AQ95: 1. Excellent in managing e-mechanics suppliers, with significant contributions following the MP group consolidation. 2. Leading SAP solutions in MP – Key deliverables:  Resolved inaccuracies in FCGNa chemical parts BOM. Collaborated with IT to adjust MRP (excluding stock of 100) to ensure smooth production. This solution is expected to be rolled out to other factories.  Set up automated email reminders for planners to change MRP controllers from "Series One" to "Phase-out" or "CS" MRP controllers. 3. Backup speaker role in FEDNa:  Served as SC MP lead for all new product projects in FEDNa, responsible for parts ordering and risk control.  Acted as backup for Weiwei, handling all MP-related issues in FEDNa. | AR95: Good performance/talent | AS95: Zhou Chuancui（1520041） | AT95: Shao Xiao（11018043） | AU95: Cheng Cheng | AY95: =_xlfn.LET(_xlpm.actual,Z95,_xlpm.low,VALUE(_xlfn.TEXTBEFORE(AA95,"-")),_xlpm.high,VALUE(_xlfn.TEXTAFTER(AA95,"-")),IF(AND(_xlpm.actual=0,OR(_xlpm.low<>0,_xlpm.high<>0)),"0 increase",IF(_xlpm.actual>_xlpm.high*1.2,">20",IF(_xlpm.actual<_xlpm.low*0.8,"<20","OK")))) -> OK
A96: CN15 | B96: 15000227 | C96: 张 强 | D96: Zhang Qiang | E96: Indirect Active | F96: OP | G96: SC | H96: SNa-SC4MX | I96: 390501 | J96: 38614 | K96: Senior Planner | L96: Senior Material Planner | M96: BAND A5 | N96: 2 | O96: 3 | P96: 13114 | Q96: 0.025 | R96: 328 | S96: 0 | T96: 0 | U96: 0.025011438 | V96: 328 | W96: 13442 | X96: 13393 | Y96: 279 | Z96: 0.0213 | AA96: 2.00%-3.00% | AF96: 0 | AG96: 13393 | AH96: 279 | AI96: 0.021274973 | AJ96: 14 | AK96: 450 | AM96: 688 | AN96: 193590 | AO96: 2 | AS96: Zhou Chuancui（1520041） | AT96: Shao Xiao（11018043） | AU96: Cheng Cheng | AY96: =_xlfn.LET(_xlpm.actual,Z96,_xlpm.low,VALUE(_xlfn.TEXTBEFORE(AA96,"-")),_xlpm.high,VALUE(_xlfn.TEXTAFTER(AA96,"-")),IF(AND(_xlpm.actual=0,OR(_xlpm.low<>0,_xlpm.high<>0)),"0 increase",IF(_xlpm.actual>_xlpm.high*1.2,">20",IF(_xlpm.actual<_xlpm.low*0.8,"<20","OK")))) -> OK
A97: CN15 | B97: 1120274 | C97: 张 琴 | D97: Zhang Qin | E97: Indirect Active | F97: OP | G97: SC | H97: SNa-SC4MM | I97: 390501 | J97: 44130 | K97: Specialist | L97: Material Planning Specialist | M97: BAND A4 | N97: 2 | O97: 3 | P97: 8155 | Q97: 0.025 | R97: 204 | S97: 0 | T97: 0 | U97: 0.025015328 | V97: 204 | W97: 8359 | X97: 8359 | Y97: 204 | Z97: 0.025 | AA97: 2.00%-3.00% | AF97: 0 | AG97: 8359 | AH97: 204 | AI97: 0.025015328 | AJ97: 14 | AK97: 450 | AM97: 688 | AN97: 123114 | AO97: 3 | AS97: Zhou Chuancui（1520041） | AT97: Shao Xiao（11018043） | AU97: Cheng Cheng | AY97: =_xlfn.LET(_xlpm.actual,Z97,_xlpm.low,VALUE(_xlfn.TEXTBEFORE(AA97,"-")),_xlpm.high,VALUE(_xlfn.TEXTAFTER(AA97,"-")),IF(AND(_xlpm.actual=0,OR(_xlpm.low<>0,_xlpm.high<>0)),"0 increase",IF(_xlpm.actual>_xlpm.high*1.2,">20",IF(_xlpm.actual<_xlpm.low*0.8,"<20","OK")))) -> OK
A98: CN15 | B98: 15002550 | C98: 周 维维 | D98: Zhou Weiwei | E98: Indirect Active | F98: OP | G98: SC | H98: SNa-SC4MM | I98: 390501 | J98: 39995 | K98: Supervisor | L98: Head of SNa-SC4MM | M98: BAND A6 | N98: 2 | O98: 5 | P98: 18800 | Q98: 0.04 | R98: 752 | S98: 0 | T98: 0 | U98: 0.04 | V98: 752 | W98: 19552 | X98: 19425 | Y98: 625 | Z98: 0.0332 | AA98: 3.20%-4.80% | AF98: 0 | AG98: 19425 | AH98: 625 | AI98: 0.033244681 | AJ98: 14 | AK98: 510 | AM98: 688 | AN98: 278758 | AO98: 5 | AS98: Zhou Chuancui（1520041） | AT98: Shao Xiao（11018043） | AU98: Cheng Cheng | AY98: =_xlfn.LET(_xlpm.actual,Z98,_xlpm.low,VALUE(_xlfn.TEXTBEFORE(AA98,"-")),_xlpm.high,VALUE(_xlfn.TEXTAFTER(AA98,"-")),IF(AND(_xlpm.actual=0,OR(_xlpm.low<>0,_xlpm.high<>0)),"0 increase",IF(_xlpm.actual>_xlpm.high*1.2,">20",IF(_xlpm.actual<_xlpm.low*0.8,"<20","OK")))) -> OK
A99: CN15 | B99: 15001696 | C99: 刘 静 | D99: Liu Jing | E99: Indirect Active | F99: OP | G99: SC | H99: SNa-SC4 | I99: 390500 | J99: 39616 | K99: Supervisor | L99: Project Management | M99: BAND A6 | N99: 2 | O99: 4 | P99: 14903 | Q99: 0.045 | R99: 671 | S99: 0.0421 | T99: 627 | U99: 0.087096558 | V99: 1298 | W99: 16201 | X99: 16000 | Y99: 1097 | Z99: 0.0736 | AA99: 6.97%-10.45% | AF99: 0 | AG99: 16000 | AH99: 1097 | AI99: 0.07360934 | AJ99: 14 | AK99: 450 | AM99: 688 | AN99: 230088 | AO99: 3 | AS99: Cao Xuelian（15020877） | AT99: Shao Xiao（11018043） | AU99: Cheng Cheng | AY99: =_xlfn.LET(_xlpm.actual,Z99,_xlpm.low,VALUE(_xlfn.TEXTBEFORE(AA99,"-")),_xlpm.high,VALUE(_xlfn.TEXTAFTER(AA99,"-")),IF(AND(_xlpm.actual=0,OR(_xlpm.low<>0,_xlpm.high<>0)),"0 increase",IF(_xlpm.actual>_xlpm.high*1.2,">20",IF(_xlpm.actual<_xlpm.low*0.8,"<20","OK")))) -> OK
A100: CN15 | B100: 15020877 | C100: 曹 雪莲 | D100: Cao Xuelian | E100: Indirect Active | F100: OP | G100: SC | H100: SNa-SC4 | I100: 390500 | J100: 43346 | K100: Senior Project Manager | L100: Senior Project Manager | M100: BAND B | N100: 2 | O100: 5 | P100: 24381 | Q100: 0.05 | R100: 1219 | S100: 0.027 | T100: 658 | U100: 0.076986178 | V100: 1877 | W100: 26258 | X100: 26000 | Y100: 1619 | Z100: 0.0664 | AA100: 6.16%-9.24% | AF100: 0 | AG100: 26000 | AH100: 1619 | AI100: 0.066404167 | AJ100: 14 | AK100: 450 | AM100: 688 | AN100: 370088 | AO100: 5 | AS100: Pastirmaci Ali Kaan（1600047） | AT100: Shao Xiao（11018043） | AU100: Cheng Cheng | AY100: =_xlfn.LET(_xlpm.actual,Z100,_xlpm.low,VALUE(_xlfn.TEXTBEFORE(AA100,"-")),_xlpm.high,VALUE(_xlfn.TEXTAFTER(AA100,"-")),IF(AND(_xlpm.actual=0,OR(_xlpm.low<>0,_xlpm.high<>0)),"0 increase",IF(_xlpm.actual>_xlpm.high*1.2,">20",IF(_xlpm.actual<_xlpm.low*0.8,"<20","OK")))) -> OK
...

Sheet data analysis
A1: Area | B1: Number of eligibility | C1: Total Salary Increase budget | D1: Person of increase | E1: Salary Increase budget used | G1: Person of increase | H1: Merit budget Balance | I1: Promotion Budget | J1: Promotion budget usage | K1: Number of promotion | L1: Promotion budget balance
A2: GOM-CGC | B2: 38 | C2: =SUMIF('Indirect Active'!E:E,'data analysis'!$A2,'Indirect Active'!T1:T1937) -> 9315 | D2: =COUNTIFS('Indirect Active'!E:E,$A2,'Indirect Active'!X:X,"<>0") -> 11 | E2: =SUMIF('Indirect Active'!E:E,'data analysis'!$A2,'Indirect Active'!W:W) -> 9315 | F2: =E2/C2 -> 1
A3: GOM-CLC | B3: 16 | C3: =SUMIF('Indirect Active'!E:E,'data analysis'!$A3,'Indirect Active'!T2:T1938) -> 14481 | D3: =COUNTIFS('Indirect Active'!E:E,$A3,'Indirect Active'!X:X,"<>0") -> 10 | E3: =SUMIF('Indirect Active'!E:E,'data analysis'!$A3,'Indirect Active'!W:W) -> 12320 | F3: =E3/C3 -> 0.85076997
A4: GOM-DCC | B4: 15 | C4: =SUMIF('Indirect Active'!E:E,'data analysis'!$A4,'Indirect Active'!T3:T1939) -> 6572 | D4: =COUNTIFS('Indirect Active'!E:E,$A4,'Indirect Active'!X:X,"<>0") -> 9 | E4: =SUMIF('Indirect Active'!E:E,'data analysis'!$A4,'Indirect Active'!W:W) -> 7067 | F4: =E4/C4 -> 1.0753195
A5: GOM-LCC | B5: 9 | C5: =SUMIF('Indirect Active'!E:E,'data analysis'!$A5,'Indirect Active'!T4:T1940) -> 18276 | D5: =COUNTIFS('Indirect Active'!E:E,$A5,'Indirect Active'!X:X,"<>0") -> 18 | E5: =SUMIF('Indirect Active'!E:E,'data analysis'!$A5,'Indirect Active'!W:W) -> 16165 | F5: =E5/C5 -> 0.88449332
A6: GPL-CN | B6: 23 | C6: =SUMIF('Indirect Active'!E:E,'data analysis'!$A6,'Indirect Active'!T5:T1941) -> 45803 | D6: =COUNTIFS('Indirect Active'!E:E,$A6,'Indirect Active'!X:X,"<>0") -> 87 | E6: =SUMIF('Indirect Active'!E:E,'data analysis'!$A6,'Indirect Active'!W:W) -> 50456 | F6: =E6/C6 -> 1.1015872
A7: GQM | B7: 152 | C7: =SUMIF('Indirect Active'!E:E,'data analysis'!$A7,'Indirect Active'!T6:T1942) -> 66324 | D7: =COUNTIFS('Indirect Active'!E:E,$A7,'Indirect Active'!X:X,"<>0") -> 110 | E7: =SUMIF('Indirect Active'!E:E,'data analysis'!$A7,'Indirect Active'!W:W) -> 72365 | F7: =E7/C7 -> 1.0910832
A8: PCP | B8: 151 | C8: =SUMIF('Indirect Active'!E:E,'data analysis'!$A8,'Indirect Active'!T7:T1943) -> 35317 | D8: =COUNTIFS('Indirect Active'!E:E,$A8,'Indirect Active'!X:X,"<>0") -> 59 | E8: =SUMIF('Indirect Active'!E:E,'data analysis'!$A8,'Indirect Active'!W:W) -> 33643 | F8: =E8/C8 -> 0.95260073
A9: CN/OP-RM | B9: 14 | C9: =SUMIF('Indirect Active'!E:E,'data analysis'!$A9,'Indirect Active'!T8:T1944) -> 24910 | D9: =COUNTIFS('Indirect Active'!E:E,$A9,'Indirect Active'!X:X,"<>0") -> 25 | E9: =SUMIF('Indirect Active'!E:E,'data analysis'!$A9,'Indirect Active'!W:W) -> 14433 | F9: =E9/C9 -> 0.57940586
A10: SC | B10: 86 | C10: =SUMIF('Indirect Active'!E:E,'data analysis'!$A10,'Indirect Active'!T9:T1945) -> 26305 | D10: =COUNTIFS('Indirect Active'!E:E,$A10,'Indirect Active'!X:X,"<>0") -> 51 | E10: =SUMIF('Indirect Active'!E:E,'data analysis'!$A10,'Indirect Active'!W:W) -> 26345 | F10: =E10/C10 -> 1.0015206
A11: SNa | B11: 29 | C11: =SUMIF('Indirect Active'!E:E,'data analysis'!$A11,'Indirect Active'!T10:T1946) -> 50713 | D11: =COUNTIFS('Indirect Active'!E:E,$A11,'Indirect Active'!X:X,"<>0") -> 61 | E11: =SUMIF('Indirect Active'!E:E,'data analysis'!$A11,'Indirect Active'!W:W) -> 38426.744 | F11: =E11/C11 -> 0.75772966
A12: SCh | B12: 82 | C12: =SUMIF('Indirect Active'!E:E,'data analysis'!$A12,'Indirect Active'!T11:T1947) -> 64901
A13: ALL | C13: =SUM(C2:C12) -> 362917
J14: 0.005
A15: 行标签 | B15: 求和项:Total Recommended Increase amount | C15: 求和项:Adjutsed increased/decreased basic salary by DH | D15: Surpus | E15: Usage | F15: No | G15: Person of Increase | I15: Basic Salary | J15: Promotion Budget | K15: Promotion Budget Used | M15: No of Promoted | O15: Thereof Special
A16: CN/OP-RM | B16: 14433 | C16: 14433 | D16: =B16-C16 -> 0 | E16: =C16/B16 -> 1 | F16: 38 | G16: 25 | H16: =G16/F16 -> 0.65789474 | I16: 565057 | J16: =I16*$J$14 -> 2825.285 | K16: 2825 | L16: =K16/J16 -> 0.99989913 | M16: 3 | N16: =M16/F16 -> 0.078947368
A17: GOM-CGC | B17: 9315 | C17: 9315 | D17: =B17-C17 -> 0 | E17: =C17/B17 -> 1 | F17: 16 | G17: 11 | H17: =G17/F17 -> 0.6875 | I17: 391477 | J17: =I17*$J$14 -> 1957.385 | K17: 1952 | L17: =K17/J17 -> 0.99724888 | M17: 1 | N17: =M17/F17 -> 0.0625
A18: GOM-CLC | B18: 12320 | C18: 12320 | D18: =B18-C18 -> 0 | E18: =C18/B18 -> 1 | F18: 15 | G18: 10 | H18: =G18/F18 -> 0.66666667 | I18: 415631 | J18: =I18*$J$14 -> 2078.155 | K18: 0 | L18: 0 | N18: =M18/F18 -> 0
A19: GOM-DCC | B19: 7067 | C19: 7067 | D19: =B19-C19 -> 0 | E19: =C19/B19 -> 1 | F19: 9 | G19: 9 | H19: =G19/F19 -> 1 | I19: 202173 | J19: =I19*$J$14 -> 1010.865 | K19: 1010 | L19: =K19/J19 -> 0.9991443 | M19: 1 | N19: =M19/F19 -> 0.11111111
A20: GOM-LCC | B20: 16166 | C20: 16165 | D20: =B20-C20 -> 1 | E20: =C20/B20 -> 0.99993814 | F20: 23 | G20: 18 | H20: =G20/F20 -> 0.7826087 | I20: 605993 | J20: =I20*$J$14 -> 3029.965 | K20: 3023 | L20: =K20/J20 -> 0.99770129 | M20: 2 | N20: =M20/F20 -> 0.086956522
A21: GPL-CN | B21: 50456 | C21: 50456 | D21: =B21-C21 -> 0 | E21: =C21/B21 -> 1 | F21: 152 | G21: 87 | H21: =G21/F21 -> 0.57236842 | I21: 2057648 | J21: =I21*$J$14 -> 10288.24 | K21: 9474 | L21: =K21/J21 -> 0.92085721 | M21: 8 | N21: =M21/F21 -> 0.052631579 | O21: 0
A22: GQM | B22: 68266 | C22: 72365 | D22: =B22-C22 -> -4099 | E22: =C22/B22 -> 1.0600445 | F22: 151 | G22: 110 | H22: =G22/F22 -> 0.72847682 | I22: 2138146 | J22: =I22*$J$14 -> 10690.73 | K22: 10691 | L22: =K22/J22 -> 1.0000253 | M22: 13 | N22: =M22/F22 -> 0.086092715
A23: OP-TE | B23: 9953 | C23: 9953 | D23: =B23-C23 -> 0 | E23: =C23/B23 -> 1 | F23: 14 | G23: 10 | H23: =G23/F23 -> 0.71428571 | I23: 281769 | J23: =I23*$J$14 -> 1408.845 | K23: 1436 | L23: =K23/J23 -> 1.0192747 | M23: 1 | N23: =M23/F23 -> 0.071428571
A24: PCP | B24: 33643 | C24: 33643 | D24: =B24-C24 -> 0 | E24: =C24/B24 -> 1 | F24: 86 | G24: 59 | H24: =G24/F24 -> 0.68604651 | I24: 1418496 | J24: =I24*$J$14 -> 7092.48 | K24: 7089 | L24: =K24/J24 -> 0.99950934 | M24: 7 | N24: =M24/F24 -> 0.081395349
A25: SC | B25: 26990 | C25: 26345 | D25: =B25-C25 -> 645 | E25: =C25/B25 -> 0.97610226 | F25: 66 | G25: 51 | H25: =G25/F25 -> 0.77272727 | I25: 841434 | J25: =I25*$J$14 -> 4207.17 | K25: 4048 | L25: =K25/J25 -> 0.96216697 | M25: 6 | N25: =M25/F25 -> 0.090909091
A26: SNa | B26: 38293 | C26: 38476.744 | D26: =B26-C26 -> -183.744 | E26: =C26/B26 -> 1.0047984 | F26: 82 | G26: 62 | H26: =G26/F26 -> 0.75609756 | I26: 1370342 | J26: =I26*$J$14 -> 6851.71 | K26: 8701 | L26: =K26/J26 -> 1.269902 | M26: 6 | N26: =M26/F26 -> 0.073170732
A27: SCh | B27: 74651 | C27: 73144 | D27: =B27-C27 -> 1507 | E27: =C27/B27 -> 0.97981273 | F27: 142 | G27: 92 | H27: =G27/F27 -> 0.64788732 | I27: 2083527 | J27: =I27*$J$14 -> 10417.635 | K27: 8341 | L27: =K27/J27 -> 0.80066157 | M27: 9 | N27: =M27/F27 -> 0.063380282
A28: Overall | B28: 361553 | C28: 363682.74 | D28: =B28-C28 -> -2129.744 | E28: =C28/B28 -> 1.0058905 | F28: 794 | G28: 544 | H28: =G28/F28 -> 0.68513854 | I28: 12371693 | J28: =I28*$J$14 -> 61858.465 | K28: 58590 | L28: =K28/J28 -> 0.9471622 | M28: 57 | N28: =M28/F28 -> 0.071788413
G30: Remark
A31: PL1 | B31: 14 | C31: 1 | D31: =C31/B31 -> 0.071428571 | E31: -0.022 | F31: 1 | G31: demotion
A32: PL2 | B32: 47 | C32: 6 | D32: =C32/B32 -> 0.12765957 | E32: 0.02016 | F32: 5 | G32: 1 new comer, 4 newly promoted
A33: PL3 | B33: 482 | C33: 305 | D33: =C33/B33 -> 0.63278008 | E33: 0.029135082 | F33: 305
A34: PL4 | B34: 170 | C34: 163 | D34: =C34/B34 -> 0.95882353 | E34: 0.054025153 | F34: 163
A35: PL5 | B35: 75 | C35: 67 | D35: =C35/B35 -> 0.89333333 | E35: 0.083274627 | F35: 67
B36: 794 | C36: 544 | D36: =C36/B36 -> 0.68513854 | E36: 0.043243831 | F36: 543
A37: Band A | B37: 607 | C37: 398 | D37: =C37/B37 -> 0.65568369 | E37: 0.044312312
A38: Band B | B38: 138 | C38: 109 | D38: =C38/B38 -> 0.78985507 | E38: 0.039050459
A39: Band C | B39: 42 | C39: 34 | D39: =C39/B39 -> 0.80952381 | E39: 0.040932353
A40: Band D | B40: 7 | C40: 3 | D40: =C40/B40 -> 0.42857143 | E40: 0.0672 | G40: due to a great porportion of Band D below CR85%
A41: Overall | B41: 794 | C41: 544 | D41: =C41/B41 -> 0.68513854 | E41: 0.043172978

Sheet Pivot
A3: Adjusted basic increase/decreased % by DH | B3: (多项)
A5: 行标签 | B5: 平均值项:Adjusted basic increase/decreased % by DH | C5: 计数项:Pers.no. | D5: 求和项: Basic salary
A6: 1 | B6: -0.022 | C6: 1 | D6: 8937
A7: 2 | B7: 0.02016 | C7: 5 | D7: 74430
A8: 3 | B8: 0.029135082 | C8: 305 | D8: 4773822
A9: 4 | B9: 0.054025153 | C9: 163 | D9: 2641918
A10: 5 | B10: 0.083274627 | C10: 67 | D10: 1314375
A11: NA | B11: 0.06545 | C11: 2 | D11: 13420
A12: 总计 | B12: 0.043243831 | C12: 543 | D12: 8826902

Sheet Indirect Active
A1: Company code | B1: Pers.no. | C1: Subgroup | D1: Area | E1: Subarea | F1: Dept. | G1: Cost ctr | H1: Join date | I1: Job | J1: Position | K1: Band Level | L1: Workplan type | M1: 2025 Performance Level | N1: Basic salary | O1: ① Merit increase % | P1: Merit Increase amount | Q1: ② Equity Increase% | R1: Equity Increase amount | S1: Total recommended Increase % (①+②) | T1: Total Recommended Increase amount | U1: Recommended new basic salary | V1: Adjutsed basic salary (input by DH) | W1: Adjutsed increased/decreased basic salary by DH | X1: Adjusted basic increase/decreased % by DH | Y1: Adjustment range reference | Z1: Promotion or demotion | AA1: New position title | AB1: New band | AC1: ③ Promotion increase/Demotion decrease % (±5%-±20%) | AD1: Promotion increase/Demotion decrease amount | AE1: Final new basic salary | AF1: Final increase/decrease amount | AG1: Final increase/decrease rate | AH1: Pay months | AI1: Monthly allowance/bonus | AJ1: Monthly Car Allowance | AK1: Other income(e.g.:festival bonus) | AL1: Annual target cash | AM1: 2024 Performance Level | AN1: Disciplinary Records | AO1: Justifications by DH | AP1: HR Remark | AQ1: Responsible ASR Manager | AR1: Responsible ASR HRBP | AS1: PY | AT1: 85% of LMW (for Technician/Counsellor) | AU1: Editable column 1 | AV1: Editable column 2 | AW1: - | AX1: Market CR | AY1: OP CR Before | AZ1: Dept CR Befire | BA1: Dept CR After
A2: CN15 | B2: 15000447 | C2: Indirect Active | D2: OP | E2: SNa | F2: FCGNa-VVP | G2: 330404 | H2: 38808 | I2: Workshop Leader | J2: Head of FCGNa-VVP | K2: BAND A6 | L2: 2 | M2: 5 | N2: 15840 | O2: 0.05 | P2: =ROUND(N2*O2,0) -> 792 | Q2: 0 | R2: =ROUND(N2*Q2,0) -> 0 | S2: =T2/N2 -> 0.05 | T2: =P2+R2 -> 792 | U2: =N2+T2 -> 16632 | V2: 16780 | W2: =V2-N2 -> 940 | X2: =ROUND(V2/N2-1,4) -> 0.0593 | Y2: =IF(OR(L2=1,L2=2,L2=4), TEXT(S2*0.8,"0.00%") & "-" & TEXT(S2*1.2,"0.00%"), IF(OR(L2=3,L2=6), TEXT(0,"0.00%") & "-" & TEXT(7%*1.2,"0.00%"), IF(OR(L2=5,L2=7), TEXT((R2/N2),"0.00%") & "-" & TEXT((R2/N2)+7%,"0.00%"), "" ) ) ) -> 4.00%-6.00% | AD2: =ROUND(N2*AC2,0) -> 0 | AE2: =V2+AD2 -> 16780 | AF2: =AE2-N2 -> 940 | AG2: =AE2/N2-1 -> 0.059343434 | AH2: 14 | AI2: 450 | AK2: 688 | AL2: =AE2*AH2+AI2*12+AK2+IF(AB2="",AJ2,IF(AB2="D",5000,IF(AB2="C",1000,0)))*12 -> 241008 | AM2: 4 | AQ2: Miao Siyuan（15005811） | AR2: Zhu Qianqian（11016705） | AS2: Zhao Chujun | AW2: =_xlfn.LET(_xlpm.actual,X2,_xlpm.low,VALUE(_xlfn.TEXTBEFORE(Y2,"-")),_xlpm.high,VALUE(_xlfn.TEXTAFTER(Y2,"-")),IF(AND(_xlpm.actual=0,OR(_xlpm.low<>0,_xlpm.high<>0)),"0 increase",IF(_xlpm.actual>_xlpm.high*1.2,">20",IF(_xlpm.actual<_xlpm.low*0.8,"<20","OK")))) -> #NAME? | AX2: =VLOOKUP(表1[[#This Row],[Pers.no.]],'[6]Person Detail'!$B:$L,11,0) -> 70-90 | AY2: =VLOOKUP(表1[[#This Row],[Pers.no.]],'[6]Person Detail'!$B:$R,17,0) -> 1.0015175 | AZ2: =VLOOKUP(表1[[#This Row],[Pers.no.]],'[6]Person Detail'!$B:$W,21,0) -> 1.0025316 | BA2: =VLOOKUP(表1[[#This Row],[Pers.no.]],'[6]Person Detail'!$B:$W,22,0) -> 1.0312193
A3: CN15 | B3: 15014416 | C3: Indirect Active | D3: OP | E3: SNa | F3: FCGNa-VVE | G3: 330404 | H3: 45063 | I3: Supervisor | J3: Head of Engineering Ventilation | K3: BAND A6 | L3: 2 | M3: 4 | N3: 16456 | O3: 0.045 | P3: =ROUND(N3*O3,0) -> 741 | Q3: 0.0155 | R3: =ROUND(N3*Q3,0) -> 255 | S3: =T3/N3 -> 0.060525036 | T3: =P3+R3 -> 996 | U3: =N3+T3 -> 17452 | V3: 17456 | W3: =V3-N3 -> 1000 | X3: =ROUND(V3/N3-1,4) -> 0.0608 | Y3: =IF(OR(L3=1,L3=2,L3=4), TEXT(S3*0.8,"0.00%") & "-" & TEXT(S3*1.2,"0.00%"), IF(OR(L3=3,L3=6), TEXT(0,"0.00%") & "-" & TEXT(7%*1.2,"0.00%"), IF(OR(L3=5,L3=7), TEXT((R3/N3),"0.00%") & "-" & TEXT((R3/N3)+7%,"0.00%"), "" ) ) ) -> 4.84%-7.26% | AD3: =ROUND(N3*AC3,0) -> 0 | AE3: =V3+AD3 -> 17456 | AF3: =AE3-N3 -> 1000 | AG3: =AE3/N3-1 -> 0.060768109 | AH3: 14 | AI3: 450 | AK3: 688 | AL3: =AE3*AH3+AI3*12+AK3+IF(AB3="",AJ3,IF(AB3="D",5000,IF(AB3="C",1000,0)))*12 -> 250472 | AM3: 5 | AQ3: Miao Siyuan（15005811） | AR3: Zhu Qianqian（11016705） | AS3: Zhao Chujun | AW3: =_xlfn.LET(_xlpm.actual,X3,_xlpm.low,VALUE(_xlfn.TEXTBEFORE(Y3,"-")),_xlpm.high,VALUE(_xlfn.TEXTAFTER(Y3,"-")),IF(AND(_xlpm.actual=0,OR(_xlpm.low<>0,_xlpm.high<>0)),"0 increase",IF(_xlpm.actual>_xlpm.high*1.2,">20",IF(_xlpm.actual<_xlpm.low*0.8,"<20","OK")))) -> #NAME? | AX3: =VLOOKUP(表1[[#This Row],[Pers.no.]],'[6]Person Detail'!$B:$L,11,0) -> 50-70 | AY3: =VLOOKUP(表1[[#This Row],[Pers.no.]],'[6]Person Detail'!$B:$R,17,0) -> 1.0404654 | AZ3: =VLOOKUP(表1[[#This Row],[Pers.no.]],'[6]Person Detail'!$B:$W,21,0) -> 1.041519 | BA3: =VLOOKUP(表1[[#This Row],[Pers.no.]],'[6]Person Detail'!$B:$W,22,0) -> 1.072763
A4: CN15 | B4: 15014868 | C4: Indirect Active | D4: OP | E4: SNa | F4: FCGNa-VVE | G4: 330404 | H4: 42291 | I4: Project Manager | J4: Project Manager | K4: BAND A6 | L4: 2 | M4: 3 | N4: 13630 | O4: 0.03 | P4: =ROUND(N4*O4,0) -> 409 | Q4: 0 | R4: =ROUND(N4*Q4,0) -> 0 | S4: =T4/N4 -> 0.030007337 | T4: =P4+R4 -> 409 | U4: =N4+T4 -> 14039 | V4: 14038 | W4: =V4-N4 -> 408 | X4: =ROUND(V4/N4-1,4) -> 0.0299 | Y4: =IF(OR(L4=1,L4=2,L4=4), TEXT(S4*0.8,"0.00%") & "-" & TEXT(S4*1.2,"0.00%"), IF(OR(L4=3,L4=6), TEXT(0,"0.00%") & "-" & TEXT(7%*1.2,"0.00%"), IF(OR(L4=5,L4=7), TEXT((R4/N4),"0.00%") & "-" & TEXT((R4/N4)+7%,"0.00%"), "" ) ) ) -> 2.40%-3.60% | AD4: =ROUND(N4*AC4,0) -> 0 | AE4: =V4+AD4 -> 14038 | AF4: =AE4-N4 -> 408 | AG4: =AE4/N4-1 -> 0.029933969 | AH4: 14 | AI4: 450 | AK4: 688 | AL4: =AE4*AH4+AI4*12+AK4+IF(AB4="",AJ4,IF(AB4="D",5000,IF(AB4="C",1000,0)))*12 -> 202620 | AM4: 4 | AQ4: Miao Siyuan（15005811） | AR4: Zhu Qianqian（11016705） | AS4: Zhao Chujun | AW4: =_xlfn.LET(_xlpm.actual,X4,_xlpm.low,VALUE(_xlfn.TEXTBEFORE(Y4,"-")),_xlpm.high,VALUE(_xlfn.TEXTAFTER(Y4,"-")),IF(AND(_xlpm.actual=0,OR(_xlpm.low<>0,_xlpm.high<>0)),"0 increase",IF(_xlpm.actual>_xlpm.high*1.2,">20",IF(_xlpm.actual<_xlpm.low*0.8,"<20","OK")))) -> #NAME? | AX4: =VLOOKUP(表1[[#This Row],[Pers.no.]],'[6]Person Detail'!$B:$L,11,0) -> 50-70 | AY4: =VLOOKUP(表1[[#This Row],[Pers.no.]],'[6]Person Detail'!$B:$R,17,0) -> 0.86178553 | AZ4: =VLOOKUP(表1[[#This Row],[Pers.no.]],'[6]Person Detail'!$B:$W,21,0) -> 0.86265823 | BA4: =VLOOKUP(表1[[#This Row],[Pers.no.]],'[6]Person Detail'!$B:$W,22,0) -> 0.86270895
A5: CN15 | B5: 15022166 | C5: Indirect Active | D5: OP | E5: SNa | F5: FCGNa-VVE | G5: 330404 | H5: 44664 | I5: Senior Engineer | J5: Senior Electrical Engineer | K5: BAND A5 | L5: 2 | M5: 4 | N5: 14440 | O5: 0.0375 | P5: =ROUND(N5*O5,0) -> 542 | Q5: 0 | R5: =ROUND(N5*Q5,0) -> 0 | S5: =T5/N5 -> 0.037534626 | T5: =P5+R5 -> 542 | U5: =N5+T5 -> 14982 | V5: 15000 | W5: =V5-N5 -> 560 | X5: =ROUND(V5/N5-1,4) -> 0.0388 | Y5: =IF(OR(L5=1,L5=2,L5=4), TEXT(S5*0.8,"0.00%") & "-" & TEXT(S5*1.2,"0.00%"), IF(OR(L5=3,L5=6), TEXT(0,"0.00%") & "-" & TEXT(7%*1.2,"0.00%"), IF(OR(L5=5,L5=7), TEXT((R5/N5),"0.00%") & "-" & TEXT((R5/N5)+7%,"0.00%"), "" ) ) ) -> 3.00%-4.50% | AD5: =ROUND(N5*AC5,0) -> 0 | AE5: =V5+AD5 -> 15000 | AF5: =AE5-N5 -> 560 | AG5: =AE5/N5-1 -> 0.038781163 | AH5: 14 | AI5: 450 | AK5: 688 | AL5: =AE5*AH5+AI5*12+AK5+IF(AB5="",AJ5,IF(AB5="D",5000,IF(AB5="C",1000,0)))*12 -> 216088 | AM5: 2 | AQ5: Miao Siyuan（15005811） | AR5: Zhu Qianqian（11016705） | AS5: Zhao Chujun | AW5: =_xlfn.LET(_xlpm.actual,X5,_xlpm.low,VALUE(_xlfn.TEXTBEFORE(Y5,"-")),_xlpm.high,VALUE(_xlfn.TEXTAFTER(Y5,"-")),IF(AND(_xlpm.actual=0,OR(_xlpm.low<>0,_xlpm.high<>0)),"0 increase",IF(_xlpm.actual>_xlpm.high*1.2,">20",IF(_xlpm.actual<_xlpm.low*0.8,"<20","OK")))) -> #NAME? | AX5: =VLOOKUP(表1[[#This Row],[Pers.no.]],'[6]Person Detail'!$B:$L,11,0) -> 70-90 | AY5: =VLOOKUP(表1[[#This Row],[Pers.no.]],'[6]Person Detail'!$B:$R,17,0) -> 1.1685211 | AZ5: =VLOOKUP(表1[[#This Row],[Pers.no.]],'[6]Person Detail'!$B:$W,21,0) -> 1.0744048 | BA5: =VLOOKUP(表1[[#This Row],[Pers.no.]],'[6]Person Detail'!$B:$W,22,0) -> 1.1049317
A6: CN15 | B6: 15016337 | C6: Indirect Active | D6: OP | E6: SNa | F6: FCGNa-VVE | G6: 330404 | H6: 42795 | I6: Functional Specialist | J6: Functional Specialist | K6: BAND A6 | L6: 2 | M6: 3 | N6: 14284 | O6: 0.03 | P6: =ROUND(N6*O6,0) -> 429 | Q6: 0 | R6: =ROUND(N6*Q6,0) -> 0 | S6: =T6/N6 -> 0.030033604 | T6: =P6+R6 -> 429 | U6: =N6+T6 -> 14713 | V6: 14688 | W6: =V6-N6 -> 404 | X6: =ROUND(V6/N6-1,4) -> 0.0283 | Y6: =IF(OR(L6=1,L6=2,L6=4), TEXT(S6*0.8,"0.00%") & "-" & TEXT(S6*1.2,"0.00%"), IF(OR(L6=3,L6=6), TEXT(0,"0.00%") & "-" & TEXT(7%*1.2,"0.00%"), IF(OR(L6=5,L6=7), TEXT((R6/N6),"0.00%") & "-" & TEXT((R6/N6)+7%,"0.00%"), "" ) ) ) -> 2.40%-3.60% | AD6: =ROUND(N6*AC6,0) -> 0 | AE6: =V6+AD6 -> 14688 | AF6: =AE6-N6 -> 404 | AG6: =AE6/N6-1 -> 0.028283394 | AH6: 14 | AI6: 450 | AK6: 688 | AL6: =AE6*AH6+AI6*12+AK6+IF(AB6="",AJ6,IF(AB6="D",5000,IF(AB6="C",1000,0)))*12 -> 211720 | AM6: 2 | AQ6: Miao Siyuan（15005811） | AR6: Zhu Qianqian（11016705） | AS6: Zhao Chujun | AW6: =_xlfn.LET(_xlpm.actual,X6,_xlpm.low,VALUE(_xlfn.TEXTBEFORE(Y6,"-")),_xlpm.high,VALUE(_xlfn.TEXTAFTER(Y6,"-")),IF(AND(_xlpm.actual=0,OR(_xlpm.low<>0,_xlpm.high<>0)),"0 increase",IF(_xlpm.actual>_xlpm.high*1.2,">20",IF(_xlpm.actual<_xlpm.low*0.8,"<20","OK")))) -> #NAME? | AX6: =VLOOKUP(表1[[#This Row],[Pers.no.]],'[6]Person Detail'!$B:$L,11,0) -> 50-70 | AY6: =VLOOKUP(表1[[#This Row],[Pers.no.]],'[6]Person Detail'!$B:$R,17,0) -> 0.90313606 | AZ6: =VLOOKUP(表1[[#This Row],[Pers.no.]],'[6]Person Detail'!$B:$W,21,0) -> 0.90405063 | BA6: =VLOOKUP(表1[[#This Row],[Pers.no.]],'[6]Person Detail'!$B:$W,22,0) -> 0.90265487
A7: CN15 | B7: 15022630 | C7: Indirect Active | D7: OP | E7: SNa | F7: FCGNa-VVE | G7: 330408 | H7: 45854 | I7: Functional Specialist | J7: Painting Functional Specialist | K7: BAND A6 | L7: 2 | M7: 3 | N7: 23000 | O7: 0 | P7: =ROUND(N7*O7,0) -> 0 | Q7: 0 | R7: =ROUND(N7*Q7,0) -> 0 | S7: =T7/N7 -> 0 | T7: =P7+R7 -> 0 | U7: =N7+T7 -> 23000 | V7: 23000 | W7: =V7-N7 -> 0 | X7: =ROUND(V7/N7-1,4) -> 0 | Y7: =IF(OR(L7=1,L7=2,L7=4), TEXT(S7*0.8,"0.00%") & "-" & TEXT(S7*1.2,"0.00%"), IF(OR(L7=3,L7=6), TEXT(0,"0.00%") & "-" & TEXT(7%*1.2,"0.00%"), IF(OR(L7=5,L7=7), TEXT((R7/N7),"0.00%") & "-" & TEXT((R7/N7)+7%,"0.00%"), "" ) ) ) -> 0.00%-0.00% | AD7: =ROUND(N7*AC7,0) -> 0 | AE7: =V7+AD7 -> 23000 | AF7: =AE7-N7 -> 0 | AG7: =AE7/N7-1 -> 0 | AH7: 14 | AI7: 450 | AK7: 688 | AL7: =AE7*AH7+AI7*12+AK7+IF(AB7="",AJ7,IF(AB7="D",5000,IF(AB7="C",1000,0)))*12 -> 328088 | AM7: #N/A | AQ7: Miao Siyuan（15005811） | AR7: Zhu Qianqian（11016705） | AS7: Zhao Chujun | AW7: =_xlfn.LET(_xlpm.actual,X7,_xlpm.low,VALUE(_xlfn.TEXTBEFORE(Y7,"-")),_xlpm.high,VALUE(_xlfn.TEXTAFTER(Y7,"-")),IF(AND(_xlpm.actual=0,OR(_xlpm.low<>0,_xlpm.high<>0)),"0 increase",IF(_xlpm.actual>_xlpm.high*1.2,">20",IF(_xlpm.actual<_xlpm.low*0.8,"<20","OK")))) -> #NAME? | AX7: =VLOOKUP(表1[[#This Row],[Pers.no.]],'[6]Person Detail'!$B:$L,11,0) -> >90 | AY7: =VLOOKUP(表1[[#This Row],[Pers.no.]],'[6]Person Detail'!$B:$R,17,0) -> 1.4542236 | AZ7: =VLOOKUP(表1[[#This Row],[Pers.no.]],'[6]Person Detail'!$B:$W,21,0) -> 1.4556962 | BA7: =VLOOKUP(表1[[#This Row],[Pers.no.]],'[6]Person Detail'!$B:$W,22,0) -> 1.413471
A8: CN15 | B8: 15007556 | C8: Indirect Active | D8: OP | E8: SNa | F8: FCGNa-VVM | G8: 330204 | H8: 40962 | I8: Supervisor | J8: Head of FCGNa-VVM | K8: BAND A6 | L8: 2 | M8: 3 | N8: 16100 | O8: 0.025 | P8: =ROUND(N8*O8,0) -> 403 | Q8: 0 | R8: =ROUND(N8*Q8,0) -> 0 | S8: =T8/N8 -> 0.025031056 | T8: =P8+R8 -> 403 | U8: =N8+T8 -> 16503 | V8: 16518 | W8: =V8-N8 -> 418 | X8: =ROUND(V8/N8-1,4) -> 0.026 | Y8: =IF(OR(L8=1,L8=2,L8=4), TEXT(S8*0.8,"0.00%") & "-" & TEXT(S8*1.2,"0.00%"), IF(OR(L8=3,L8=6), TEXT(0,"0.00%") & "-" & TEXT(7%*1.2,"0.00%"), IF(OR(L8=5,L8=7), TEXT((R8/N8),"0.00%") & "-" & TEXT((R8/N8)+7%,"0.00%"), "" ) ) ) -> 2.00%-3.00% | AD8: =ROUND(N8*AC8,0) -> 0 | AE8: =V8+AD8 -> 16518 | AF8: =AE8-N8 -> 418 | AG8: =AE8/N8-1 -> 0.025962733 | AH8: 14 | AI8: 450 | AK8: 688 | AL8: =AE8*AH8+AI8*12+AK8+IF(AB8="",AJ8,IF(AB8="D",5000,IF(AB8="C",1000,0)))*12 -> 237340 | AM8: 3 | AQ8: Miao Siyuan（15005811） | AR8: Zhu Qianqian（11016705） | AS8: Zhao Chujun | AW8: =_xlfn.LET(_xlpm.actual,X8,_xlpm.low,VALUE(_xlfn.TEXTBEFORE(Y8,"-")),_xlpm.high,VALUE(_xlfn.TEXTAFTER(Y8,"-")),IF(AND(_xlpm.actual=0,OR(_xlpm.low<>0,_xlpm.high<>0)),"0 increase",IF(_xlpm.actual>_xlpm.high*1.2,">20",IF(_xlpm.actual<_xlpm.low*0.8,"<20","OK")))) -> #NAME? | AX8: =VLOOKUP(表1[[#This Row],[Pers.no.]],'[6]Person Detail'!$B:$L,11,0) -> 70-90 | AY8: =VLOOKUP(表1[[#This Row],[Pers.no.]],'[6]Person Detail'!$B:$R,17,0) -> 1.0179565 | AZ8: =VLOOKUP(表1[[#This Row],[Pers.no.]],'[6]Person Detail'!$B:$W,21,0) -> 1.0189873 | BA8: =VLOOKUP(表1[[#This Row],[Pers.no.]],'[6]Person Detail'!$B:$W,22,0) -> 1.015118
A9: CN15 | B9: 1120246 | C9: Indirect Active | D9: OP | E9: SNa | F9: FCGNa-VVE | G9: 330404 | H9: 43864 | I9: Functional Specialist | J9: Functional Specialist | K9: BAND A6 | L9: 2 | M9: 4 | N9: 13111 | O9: 0.045 | P9: =ROUND(N9*O9,0) -> 590 | Q9: 0.0421 | R9: =ROUND(N9*Q9,0) -> 552 | S9: =T9/N9 -> 0.087102433 | T9: =P9+R9 -> 1142 | U9: =N9+T9 -> 14253 | V9: 14066 | W9: =V9-N9 -> 955 | X9: =ROUND(V9/N9-1,4) -> 0.0728 | Y9: =IF(OR(L9=1,L9=2,L9=4), TEXT(S9*0.8,"0.00%") & "-" & TEXT(S9*1.2,"0.00%"), IF(OR(L9=3,L9=6), TEXT(0,"0.00%") & "-" & TEXT(7%*1.2,"0.00%"), IF(OR(L9=5,L9=7), TEXT((R9/N9),"0.00%") & "-" & TEXT((R9/N9)+7%,"0.00%"), "" ) ) ) -> 6.97%-10.45% | AD9: =ROUND(N9*AC9,0) -> 0 | AE9: =V9+AD9 -> 14066 | AF9: =AE9-N9 -> 955 | AG9: =AE9/N9-1 -> 0.0728396 | AH9: 14 | AI9: 850 | AK9: 688 | AL9: =AE9*AH9+AI9*12+AK9+IF(AB9="",AJ9,IF(AB9="D",5000,IF(AB9="C",1000,0)))*12 -> 207812 | AM9: 3 | AQ9: Miao Siyuan（15005811） | AR9: Zhu Qianqian（11016705） | AS9: Zhao Chujun | AW9: =_xlfn.LET(_xlpm.actual,X9,_xlpm.low,VALUE(_xlfn.TEXTBEFORE(Y9,"-")),_xlpm.high,VALUE(_xlfn.TEXTAFTER(Y9,"-")),IF(AND(_xlpm.actual=0,OR(_xlpm.low<>0,_xlpm.high<>0)),"0 increase",IF(_xlpm.actual>_xlpm.high*1.2,">20",IF(_xlpm.actual<_xlpm.low*0.8,"<20","OK")))) -> #NAME? | AX9: =VLOOKUP(表1[[#This Row],[Pers.no.]],'[6]Person Detail'!$B:$L,11,0) -> 50-70 | AY9: =VLOOKUP(表1[[#This Row],[Pers.no.]],'[6]Person Detail'!$B:$R,17,0) -> 0.82897066 | AZ9: =VLOOKUP(表1[[#This Row],[Pers.no.]],'[6]Person Detail'!$B:$W,21,0) -> 0.82981013 | BA9: =VLOOKUP(表1[[#This Row],[Pers.no.]],'[6]Person Detail'!$B:$W,22,0) -> 0.8644297
A10: CN15 | B10: 15000219 | C10: Indirect Active | D10: OP | E10: SNa | F10: FCGNa-VVE | G10: 330404 | H10: 38608 | I10: Engineer | J10: Project Engineer | K10: BAND A4 | L10: 2 | M10: 2 | N10: 12256 | O10: 0 | P10: =ROUND(N10*O10,0) -> 0 | Q10: 0 | R10: =ROUND(N10*Q10,0) -> 0 | S10: =T10/N10 -> 0 | T10: =P10+R10 -> 0 | U10: =N10+T10 -> 12256 | V10: 12256 | W10: =V10-N10 -> 0 | X10: =ROUND(V10/N10-1,4) -> 0 | Y10: =IF(OR(L10=1,L10=2,L10=4), TEXT(S10*0.8,"0.00%") & "-" & TEXT(S10*1.2,"0.00%"), IF(OR(L10=3,L10=6), TEXT(0,"0.00%") & "-" & TEXT(7%*1.2,"0.00%"), IF(OR(L10=5,L10=7), TEXT((R10/N10),"0.00%") & "-" & TEXT((R10/N10)+7%,"0.00%"), "" ) ) ) -> 0.00%-0.00% | AD10: =ROUND(N10*AC10,0) -> 0 | AE10: =V10+AD10 -> 12256 | AF10: =AE10-N10 -> 0 | AG10: =AE10/N10-1 -> 0 | AH10: 14 | AI10: 450 | AK10: 688 | AL10: =AE10*AH10+AI10*12+AK10+IF(AB10="",AJ10,IF(AB10="D",5000,IF(AB10="C",1000,0)))*12 -> 177672 | AM10: 3 | AQ10: Miao Siyuan（15005811） | AR10: Zhu Qianqian（11016705） | AS10: Zhao Chujun | AW10: =_xlfn.LET(_xlpm.actual,X10,_xlpm.low,VALUE(_xlfn.TEXTBEFORE(Y10,"-")),_xlpm.high,VALUE(_xlfn.TEXTAFTER(Y10,"-")),IF(AND(_xlpm.actual=0,OR(_xlpm.low<>0,_xlpm.high<>0)),"0 increase",IF(_xlpm.actual>_xlpm.high*1.2,">20",IF(_xlpm.actual<_xlpm.low*0.8,"<20","OK")))) -> #NAME? | AX10: =VLOOKUP(表1[[#This Row],[Pers.no.]],'[6]Person Detail'!$B:$L,11,0) -> 0 | AY10: =VLOOKUP(表1[[#This Row],[Pers.no.]],'[6]Person Detail'!$B:$R,17,0) -> 1.2969312 | AZ10: =VLOOKUP(表1[[#This Row],[Pers.no.]],'[6]Person Detail'!$B:$W,21,0) -> 1.1617612 | BA10: =VLOOKUP(表1[[#This Row],[Pers.no.]],'[6]Person Detail'!$B:$W,22,0) -> 1.1313579
A11: CN15 | B11: 15014810 | C11: Indirect Active | D11: OP | E11: SNa | F11: FCGNa-VVE | G11: 330404 | H11: 42248 | I11: Senior Specialist | J11: Senior IE Specialist | K11: BAND A5 | L11: 2 | M11: 4 | N11: 11666 | O11: 0.0375 | P11: =ROUND(N11*O11,0) -> 437 | Q11: 0.0155 | R11: =ROUND(N11*Q11,0) -> 181 | S11: =T11/N11 -> 0.052974456 | T11: =P11+R11 -> 618 | U11: =N11+T11 -> 12284 | V11: 12312 | W11: =V11-N11 -> 646 | X11: =ROUND(V11/N11-1,4) -> 0.0554 | Y11: =IF(OR(L11=1,L11=2,L11=4), TEXT(S11*0.8,"0.00%") & "-" & TEXT(S11*1.2,"0.00%"), IF(OR(L11=3,L11=6), TEXT(0,"0.00%") & "-" & TEXT(7%*1.2,"0.00%"), IF(OR(L11=5,L11=7), TEXT((R11/N11),"0.00%") & "-" & TEXT((R11/N11)+7%,"0.00%"), "" ) ) ) -> 4.24%-6.36% | Z11: Promotion | AA11: Function specialist | AB11: A6 | AC11: 0.0646 | AD11: =ROUND(N11*AC11,0) -> 754 | AE11: =V11+AD11 -> 13066 | AF11: =AE11-N11 -> 1400 | AG11: =AE11/N11-1 -> 0.12000686 | AH11: 14 | AI11: 550 | AK11: 688 | AL11: =AE11*AH11+AI11*12+AK11+IF(AB11="",AJ11,IF(AB11="D",5000,IF(AB11="C",1000,0)))*12 -> 190212 | AM11: 4 | AO11: Good performance and high competence | AP11: Good performance and high competence | AQ11: Miao Siyuan（15005811） | AR11: Zhu Qianqian（11016705） | AS11: Zhao Chujun | AW11: =_xlfn.LET(_xlpm.actual,X11,_xlpm.low,VALUE(_xlfn.TEXTBEFORE(Y11,"-")),_xlpm.high,VALUE(_xlfn.TEXTAFTER(Y11,"-")),IF(AND(_xlpm.actual=0,OR(_xlpm.low<>0,_xlpm.high<>0)),"0 increase",IF(_xlpm.actual>_xlpm.high*1.2,">20",IF(_xlpm.actual<_xlpm.low*0.8,"<20","OK")))) -> #NAME? | AX11: =VLOOKUP(表1[[#This Row],[Pers.no.]],'[6]Person Detail'!$B:$L,11,0) -> 70-90 | AY11: =VLOOKUP(表1[[#This Row],[Pers.no.]],'[6]Person Detail'!$B:$R,17,0) -> 0.94404208 | AZ11: =VLOOKUP(表1[[#This Row],[Pers.no.]],'[6]Person Detail'!$B:$W,21,0) -> 0.86800595 | BA11: =VLOOKUP(表1[[#This Row],[Pers.no.]],'[6]Person Detail'!$B:$W,22,0) -> 0.96246915
A12: CN15 | B12: 15000226 | C12: Indirect Active | D12: OP | E12: SNa | F12: FCGNa-VCP | G12: 330405 | H12: 38614 | I12: Workshop Leader | J12: Head of FCGNa-VCP | K12: BAND A6 | L12: 2 | M12: 3 | N12: 15800 | O12: 0.025 | P12: =ROUND(N12*O12,0) -> 395 | Q12: 0 | R12: =ROUND(N12*Q12,0) -> 0 | S12: =T12/N12 -> 0.025 | T12: =P12+R12 -> 395 | U12: =N12+T12 -> 16195 | V12: 16272 | W12: =V12-N12 -> 472 | X12: =ROUND(V12/N12-1,4) -> 0.0299 | Y12: =IF(OR(L12=1,L12=2,L12=4), TEXT(S12*0.8,"0.00%") & "-" & TEXT(S12*1.2,"0.00%"), IF(OR(L12=3,L12=6), TEXT(0,"0.00%") & "-" & TEXT(7%*1.2,"0.00%"), IF(OR(L12=5,L12=7), TEXT((R12/N12),"0.00%") & "-" & TEXT((R12/N12)+7%,"0.00%"), "" ) ) ) -> 2.00%-3.00% | AD12: =ROUND(N12*AC12,0) -> 0 | AE12: =V12+AD12 -> 16272 | AF12: =AE12-N12 -> 472 | AG12: =AE12/N12-1 -> 0.029873418 | AH12: 14 | AI12: 450 | AK12: 688 | AL12: =AE12*AH12+AI12*12+AK12+IF(AB12="",AJ12,IF(AB12="D",5000,IF(AB12="C",1000,0)))*12 -> 233896 | AM12: 5 | AQ12: Liu Haigang（15013255） | AR12: Zhu Qianqian（11016705） | AS12: Zhao Chujun | AW12: =_xlfn.LET(_xlpm.actual,X12,_xlpm.low,VALUE(_xlfn.TEXTBEFORE(Y12,"-")),_xlpm.high,VALUE(_xlfn.TEXTAFTER(Y12,"-")),IF(AND(_xlpm.actual=0,OR(_xlpm.low<>0,_xlpm.high<>0)),"0 increase",IF(_xlpm.actual>_xlpm.high*1.2,">20",IF(_xlpm.actual<_xlpm.low*0.8,"<20","OK")))) -> #NAME? | AX12: =VLOOKUP(表1[[#This Row],[Pers.no.]],'[6]Person Detail'!$B:$L,11,0) -> 70-90 | AY12: =VLOOKUP(表1[[#This Row],[Pers.no.]],'[6]Person Detail'!$B:$R,17,0) -> 0.99898837 | AZ12: =VLOOKUP(表1[[#This Row],[Pers.no.]],'[6]Person Detail'!$B:$W,21,0) -> 1 | BA12: =VLOOKUP(表1[[#This Row],[Pers.no.]],'[6]Person Detail'!$B:$W,22,0) -> 1
A13: CN15 | B13: 15000166 | C13: Indirect Active | D13: OP | E13: SNa | F13: FCGNa-VCE | G13: 330405 | H13: 38600 | I13: Senior Engineer | J13: Senior Engineer | K13: BAND A5 | L13: 2 | M13: 3 | N13: 14610 | O13: 0.025 | P13: =ROUND(N13*O13,0) -> 365 | Q13: 0 | R13: =ROUND(N13*Q13,0) -> 0 | S13: =T13/N13 -> 0.024982888 | T13: =P13+R13 -> 365 | U13: =N13+T13 -> 14975 | V13: 14610 | W13: =V13-N13 -> 0 | X13: =ROUND(V13/N13-1,4) -> 0 | Y13: =IF(OR(L13=1,L13=2,L13=4), TEXT(S13*0.8,"0.00%") & "-" & TEXT(S13*1.2,"0.00%"), IF(OR(L13=3,L13=6), TEXT(0,"0.00%") & "-" & TEXT(7%*1.2,"0.00%"), IF(OR(L13=5,L13=7), TEXT((R13/N13),"0.00%") & "-" & TEXT((R13/N13)+7%,"0.00%"), "" ) ) ) -> 2.00%-3.00% | AD13: =ROUND(N13*AC13,0) -> 0 | AE13: =V13+AD13 -> 14610 | AF13: =AE13-N13 -> 0 | AG13: =AE13/N13-1 -> 0 | AH13: 14 | AI13: 450 | AK13: 688 | AL13: =AE13*AH13+AI13*12+AK13+IF(AB13="",AJ13,IF(AB13="D",5000,IF(AB13="C",1000,0)))*12 -> 210628 | AM13: 3 | AO13: Only focus on route tasks, lack of innovation and new product maturity improvement | AP13: Less responsibility compare with job level | AQ13: Liu Haigang（15013255） | AR13: Zhu Qianqian（11016705） | AS13: Zhao Chujun | AU13: recommend increasing but propose zero increase | AW13: =_xlfn.LET(_xlpm.actual,X13,_xlpm.low,VALUE(_xlfn.TEXTBEFORE(Y13,"-")),_xlpm.high,VALUE(_xlfn.TEXTAFTER(Y13,"-")),IF(AND(_xlpm.actual=0,OR(_xlpm.low<>0,_xlpm.high<>0)),"0 increase",IF(_xlpm.actual>_xlpm.high*1.2,">20",IF(_xlpm.actual<_xlpm.low*0.8,"<20","OK")))) -> #NAME? | AX13: =VLOOKUP(表1[[#This Row],[Pers.no.]],'[6]Person Detail'!$B:$L,11,0) -> 70-90 | AY13: =VLOOKUP(表1[[#This Row],[Pers.no.]],'[6]Person Detail'!$B:$R,17,0) -> 1.182278 | AZ13: =VLOOKUP(表1[[#This Row],[Pers.no.]],'[6]Person Detail'!$B:$W,21,0) -> 1.0870536 | BA13: =VLOOKUP(表1[[#This Row],[Pers.no.]],'[6]Person Detail'!$B:$W,22,0) -> 1.0762035
A14: CN15 | B14: 15007522 | C14: Indirect Active | D14: OP | E14: SNa | F14: FCGNa-VCE | G14: 330405 | H14: 41091 | I14: Supervisor | J14: Head of FCGNa-VCE | K14: BAND A6 | L14: 2 | M14: 3 | N14: 13100 | O14: 0.03 | P14: =ROUND(N14*O14,0) -> 393 | Q14: 0 | R14: =ROUND(N14*Q14,0) -> 0 | S14: =T14/N14 -> 0.03 | T14: =P14+R14 -> 393 | U14: =N14+T14 -> 13493 | V14: 14312 | W14: =V14-N14 -> 1212 | X14: =ROUND(V14/N14-1,4) -> 0.0925 | Y14: =IF(OR(L14=1,L14=2,L14=4), TEXT(S14*0.8,"0.00%") & "-" & TEXT(S14*1.2,"0.00%"), IF(OR(L14=3,L14=6), TEXT(0,"0.00%") & "-" & TEXT(7%*1.2,"0.00%"), IF(OR(L14=5,L14=7), TEXT((R14/N14),"0.00%") & "-" & TEXT((R14/N14)+7%,"0.00%"), "" ) ) ) -> 2.40%-3.60% | AD14: =ROUND(N14*AC14,0) -> 0 | AE14: =V14+AD14 -> 14312 | AF14: =AE14-N14 -> 1212 | AG14: =AE14/N14-1 -> 0.092519084 | AH14: 14 | AI14: 450 | AK14: 688 | AL14: =AE14*AH14+AI14*12+AK14+IF(AB14="",AJ14,IF(AB14="D",5000,IF(AB14="C",1000,0)))*12 -> 206456 | AM14: 2 | AO14: 1. In 2025, he achieved an 11% reduction in cooker SPC and cut silicone usage by 50%. 2. As a supervisor, his salary is the lowest in the team, so I need to catch up appropriately. | AP14: Good performers with relatively lower salary | AQ14: Liu Haigang（15013255） | AR14: Zhu Qianqian（11016705） | AS14: Zhao Chujun | AU14: exceed +/-20% adjustment | AV14: >20 | AW14: =_xlfn.LET(_xlpm.actual,X14,_xlpm.low,VALUE(_xlfn.TEXTBEFORE(Y14,"-")),_xlpm.high,VALUE(_xlfn.TEXTAFTER(Y14,"-")),IF(AND(_xlpm.actual=0,OR(_xlpm.low<>0,_xlpm.high<>0)),"0 increase",IF(_xlpm.actual>_xlpm.high*1.2,">20",IF(_xlpm.actual<_xlpm.low*0.8,"<20","OK")))) -> #NAME? | AX14: =VLOOKUP(表1[[#This Row],[Pers.no.]],'[6]Person Detail'!$B:$L,11,0) -> 50-70 | AY14: =VLOOKUP(表1[[#This Row],[Pers.no.]],'[6]Person Detail'!$B:$R,17,0) -> 0.82827516 | AZ14: =VLOOKUP(表1[[#This Row],[Pers.no.]],'[6]Person Detail'!$B:$W,21,0) -> 0.82911392 | BA14: =VLOOKUP(表1[[#This Row],[Pers.no.]],'[6]Person Detail'!$B:$W,22,0) -> 0.87954769
A15: CN15 | B15: 15001471 | C15: Indirect Active | D15: OP | E15: SNa | F15: FCGNa-VCM | G15: 330405 | H15: 39546 | I15: Supervisor | J15: Head of FCGNa-VCM | K15: BAND A6 | L15: 2 | M15: 3 | N15: 15326 | O15: 0.03 | P15: =ROUND(N15*O15,0) -> 460 | Q15: 0 | R15: =ROUND(N15*Q15,0) -> 0 | S15: =T15/N15 -> 0.030014355 | T15: =P15+R15 -> 460 | U15: =N15+T15 -> 15786 | V15: 15326 | W15: =V15-N15 -> 0 | X15: =ROUND(V15/N15-1,4) -> 0 | Y15: =IF(OR(L15=1,L15=2,L15=4), TEXT(S15*0.8,"0.00%") & "-" & TEXT(S15*1.2,"0.00%"), IF(OR(L15=3,L15=6), TEXT(0,"0.00%") & "-" & TEXT(7%*1.2,"0.00%"), IF(OR(L15=5,L15=7), TEXT((R15/N15),"0.00%") & "-" & TEXT((R15/N15)+7%,"0.00%"), "" ) ) ) -> 2.40%-3.60% | AD15: =ROUND(N15*AC15,0) -> 0 | AE15: =V15+AD15 -> 15326 | AF15: =AE15-N15 -> 0 | AG15: =AE15/N15-1 -> 0 | AH15: 14 | AI15: 450 | AK15: 688 | AL15: =AE15*AH15+AI15*12+AK15+IF(AB15="",AJ15,IF(AB15="D",5000,IF(AB15="C",1000,0)))*12 -> 220652 | AM15: 4 | AO15: Low performance as supervisor | AP15: Low performer | AQ15: Liu Haigang（15013255） | AR15: Zhu Qianqian（11016705） | AS15: Zhao Chujun | AU15: recommend increasing but propose zero increase | AW15: =_xlfn.LET(_xlpm.actual,X15,_xlpm.low,VALUE(_xlfn.TEXTBEFORE(Y15,"-")),_xlpm.high,VALUE(_xlfn.TEXTAFTER(Y15,"-")),IF(AND(_xlpm.actual=0,OR(_xlpm.low<>0,_xlpm.high<>0)),"0 increase",IF(_xlpm.actual>_xlpm.high*1.2,">20",IF(_xlpm.actual<_xlpm.low*0.8,"<20","OK")))) -> #NAME? | AX15: =VLOOKUP(表1[[#This Row],[Pers.no.]],'[6]Person Detail'!$B:$L,11,0) -> 50-70 | AY15: =VLOOKUP(表1[[#This Row],[Pers.no.]],'[6]Person Detail'!$B:$R,17,0) -> 0.96901872 | AZ15: =VLOOKUP(表1[[#This Row],[Pers.no.]],'[6]Person Detail'!$B:$W,21,0) -> 0.97 | BA15: =VLOOKUP(表1[[#This Row],[Pers.no.]],'[6]Person Detail'!$B:$W,22,0) -> 0.94186332
A16: CN15 | B16: 15022189 | C16: Indirect Active | D16: OP | E16: SNa | F16: FCGNa-VCE | G16: 330401 | H16: 44713 | I16: Senior Engineer | J16: Press Senior Engineer | K16: BAND A5 | L16: 2 | M16: 3 | N16: 14850 | O16: 0.025 | P16: =ROUND(N16*O16,0) -> 371 | Q16: 0 | R16: =ROUND(N16*Q16,0) -> 0 | S16: =T16/N16 -> 0.024983165 | T16: =P16+R16 -> 371 | U16: =N16+T16 -> 15221 | V16: 15150 | W16: =V16-N16 -> 300 | X16: =ROUND(V16/N16-1,4) -> 0.0202 | Y16: =IF(OR(L16=1,L16=2,L16=4), TEXT(S16*0.8,"0.00%") & "-" & TEXT(S16*1.2,"0.00%"), IF(OR(L16=3,L16=6), TEXT(0,"0.00%") & "-" & TEXT(7%*1.2,"0.00%"), IF(OR(L16=5,L16=7), TEXT((R16/N16),"0.00%") & "-" & TEXT((R16/N16)+7%,"0.00%"), "" ) ) ) -> 2.00%-3.00% | AD16: =ROUND(N16*AC16,0) -> 0 | AE16: =V16+AD16 -> 15150 | AF16: =AE16-N16 -> 300 | AG16: =AE16/N16-1 -> 0.02020202 | AH16: 14 | AI16: 450 | AK16: 688 | AL16: =AE16*AH16+AI16*12+AK16+IF(AB16="",AJ16,IF(AB16="D",5000,IF(AB16="C",1000,0)))*12 -> 218188 | AM16: 3 | AQ16: Liu Haigang（15013255） | AR16: Zhu Qianqian（11016705） | AS16: Zhao Chujun | AW16: =_xlfn.LET(_xlpm.actual,X16,_xlpm.low,VALUE(_xlfn.TEXTBEFORE(Y16,"-")),_xlpm.high,VALUE(_xlfn.TEXTAFTER(Y16,"-")),IF(AND(_xlpm.actual=0,OR(_xlpm.low<>0,_xlpm.high<>0)),"0 increase",IF(_xlpm.actual>_xlpm.high*1.2,">20",IF(_xlpm.actual<_xlpm.low*0.8,"<20","OK")))) -> #NAME? | AX16: =VLOOKUP(表1[[#This Row],[Pers.no.]],'[6]Person Detail'!$B:$L,11,0) -> 70-90 | AY16: =VLOOKUP(表1[[#This Row],[Pers.no.]],'[6]Person Detail'!$B:$R,17,0) -> 1.2016994 | AZ16: =VLOOKUP(表1[[#This Row],[Pers.no.]],'[6]Person Detail'!$B:$W,21,0) -> 1.1049107 | BA16: =VLOOKUP(表1[[#This Row],[Pers.no.]],'[6]Person Detail'!$B:$W,22,0) -> 1.115981
A17: CN15 | B17: 15017481 | C17: Indirect Active | D17: OP | E17: SNa | F17: FCGNa-VCE | G17: 330405 | H17: 42893 | I17: Senior Engineer | J17: Senior Engineer | K17: BAND A5 | L17: 2 | M17: 2 | N17: 13610 | O17: 0 | P17: =ROUND(N17*O17,0) -> 0 | Q17: 0 | R17: =ROUND(N17*Q17,0) -> 0 | S17: =T17/N17 -> 0 | T17: =P17+R17 -> 0 | U17: =N17+T17 -> 13610 | V17: 13610 | W17: =V17-N17 -> 0 | X17: =ROUND(V17/N17-1,4) -> 0 | Y17: =IF(OR(L17=1,L17=2,L17=4), TEXT(S17*0.8,"0.00%") & "-" & TEXT(S17*1.2,"0.00%"), IF(OR(L17=3,L17=6), TEXT(0,"0.00%") & "-" & TEXT(7%*1.2,"0.00%"), IF(OR(L17=5,L17=7), TEXT((R17/N17),"0.00%") & "-" & TEXT((R17/N17)+7%,"0.00%"), "" ) ) ) -> 0.00%-0.00% | AD17: =ROUND(N17*AC17,0) -> 0 | AE17: =V17+AD17 -> 13610 | AF17: =AE17-N17 -> 0 | AG17: =AE17/N17-1 -> 0 | AH17: 14 | AI17: 550 | AK17: 688 | AL17: =AE17*AH17+AI17*12+AK17+IF(AB17="",AJ17,IF(AB17="D",5000,IF(AB17="C",1000,0)))*12 -> 197828 | AM17: 3 | AQ17: Liu Haigang（15013255） | AR17: Zhu Qianqian（11016705） | AS17: Zhao Chujun | AW17: =_xlfn.LET(_xlpm.actual,X17,_xlpm.low,VALUE(_xlfn.TEXTBEFORE(Y17,"-")),_xlpm.high,VALUE(_xlfn.TEXTAFTER(Y17,"-")),IF(AND(_xlpm.actual=0,OR(_xlpm.low<>0,_xlpm.high<>0)),"0 increase",IF(_xlpm.actual>_xlpm.high*1.2,">20",IF(_xlpm.actual<_xlpm.low*0.8,"<20","OK")))) -> #NAME? | AX17: =VLOOKUP(表1[[#This Row],[Pers.no.]],'[6]Person Detail'!$B:$L,11,0) -> 0 | AY17: =VLOOKUP(表1[[#This Row],[Pers.no.]],'[6]Person Detail'!$B:$R,17,0) -> 1.1013555 | AZ17: =VLOOKUP(表1[[#This Row],[Pers.no.]],'[6]Person Detail'!$B:$W,21,0) -> 1.0126488 | BA17: =VLOOKUP(表1[[#This Row],[Pers.no.]],'[6]Person Detail'!$B:$W,22,0) -> 1.0025413
A18: CN15 | B18: 15014900 | C18: Indirect Active | D18: OP | E18: SNa | F18: FCGNa | G18: 330100 | H18: 42298 | I18: Manager | J18: Manager | K18: BAND B | L18: 2 | M18: 2 | N18: 20200 | O18: 0 | P18: =ROUND(N18*O18,0) -> 0 | Q18: 0 | R18: =ROUND(N18*Q18,0) -> 0 | S18: =T18/N18 -> 0 | T18: =P18+R18 -> 0 | U18: =N18+T18 -> 20200 | V18: =U18 -> 20200 | W18: =V18-N18 -> 0 | X18: =ROUND(V18/N18-1,4) -> 0 | Y18: =IF(OR(L18=1,L18=2,L18=4), TEXT(S18*0.8,"0.00%") & "-" & TEXT(S18*1.2,"0.00%"), IF(OR(L18=3,L18=6), TEXT(0,"0.00%") & "-" & TEXT(7%*1.2,"0.00%"), IF(OR(L18=5,L18=7), TEXT((R18/N18),"0.00%") & "-" & TEXT((R18/N18)+7%,"0.00%"), "" ) ) ) -> 0.00%-0.00% | AD18: =ROUND(N18*AC18,0) -> 0 | AE18: =V18+AD18 -> 20200 | AF18: =AE18-N18 -> 0 | AG18: =AE18/N18-1 -> 0 | AH18: 14 | AI18: 450 | AK18: 688 | AL18: =AE18*AH18+AI18*12+AK18+IF(AB18="",AJ18,IF(AB18="D",5000,IF(AB18="C",1000,0)))*12 -> 288888 | AM18: 3 | AQ18: Chen Chao（15005032） | AR18: Zhu Qianqian（11016705） | AS18: Zhao Chujun | AW18: =_xlfn.LET(_xlpm.actual,X18,_xlpm.low,VALUE(_xlfn.TEXTBEFORE(Y18,"-")),_xlpm.high,VALUE(_xlfn.TEXTAFTER(Y18,"-")),IF(AND(_xlpm.actual=0,OR(_xlpm.low<>0,_xlpm.high<>0)),"0 increase",IF(_xlpm.actual>_xlpm.high*1.2,">20",IF(_xlpm.actual<_xlpm.low*0.8,"<20","OK")))) -> #NAME? | AX18: =VLOOKUP(表1[[#This Row],[Pers.no.]],'[6]Person Detail'!$B:$L,11,0) -> 0 | AY18: =VLOOKUP(表1[[#This Row],[Pers.no.]],'[6]Person Detail'!$B:$R,17,0) -> 0.86907886 | AZ18: =VLOOKUP(表1[[#This Row],[Pers.no.]],'[6]Person Detail'!$B:$W,21,0) -> 0.8487395 | BA18: =VLOOKUP(表1[[#This Row],[Pers.no.]],'[6]Person Detail'!$B:$W,22,0) -> 0.79841897
A19: CN15 | B19: 15013255 | C19: Indirect Active | D19: OP | E19: SNa | F19: FCGNa-VC | G19: 330405 | H19: 41801 | I19: Manager | J19: Head of Value Stream Cooktop | K19: BAND B | L19: 2 | M19: 4 | N19: 23800 | O19: 0.03 | P19: =ROUND(N19*O19,0) -> 714 | Q19: 0 | R19: =ROUND(N19*Q19,0) -> 0 | S19: =T19/N19 -> 0.03 | T19: =P19+R19 -> 714 | U19: =N19+T19 -> 24514 | V19: =U19 -> 24514 | W19: =V19-N19 -> 714 | X19: =ROUND(V19/N19-1,4) -> 0.03 | Y19: =IF(OR(L19=1,L19=2,L19=4), TEXT(S19*0.8,"0.00%") & "-" & TEXT(S19*1.2,"0.00%"), IF(OR(L19=3,L19=6), TEXT(0,"0.00%") & "-" & TEXT(7%*1.2,"0.00%"), IF(OR(L19=5,L19=7), TEXT((R19/N19),"0.00%") & "-" & TEXT((R19/N19)+7%,"0.00%"), "" ) ) ) -> 2.40%-3.60% | Z19: Promotion | AA19: Head of Value Stream Cooktop | AB19: C | AC19: 0.09 | AD19: =ROUND(N19*AC19,0) -> 2142 | AE19: =V19+AD19 -> 26656 | AF19: =AE19-N19 -> 2856 | AG19: =AE19/N19-1 -> 0.12 | AH19: 14 | AI19: 450 | AK19: 688 | AL19: =AE19*AH19+AI19*12+AK19+IF(AB19="",AJ19,IF(AB19="D",5000,IF(AB19="C",1000,0)))*12 -> 391272 | AM19: 5 | AO19: Good performance and high competence | AP19: Good performance and high competence | AQ19: Chen Chao（15005032） | AR19: Zhu Qianqian（11016705） | AS19: Zhao Chujun | AW19: =_xlfn.LET(_xlpm.actual,X19,_xlpm.low,VALUE(_xlfn.TEXTBEFORE(Y19,"-")),_xlpm.high,VALUE(_xlfn.TEXTAFTER(Y19,"-")),IF(AND(_xlpm.actual=0,OR(_xlpm.low<>0,_xlpm.high<>0)),"0 increase",IF(_xlpm.actual>_xlpm.high*1.2,">20",IF(_xlpm.actual<_xlpm.low*0.8,"<20","OK")))) -> #NAME? | AX19: =VLOOKUP(表1[[#This Row],[Pers.no.]],'[6]Person Detail'!$B:$L,11,0) -> 90-110 | AY19: =VLOOKUP(表1[[#This Row],[Pers.no.]],'[6]Person Detail'!$B:$R,17,0) -> 1.0239642 | AZ19: =VLOOKUP(表1[[#This Row],[Pers.no.]],'[6]Person Detail'!$B:$W,21,0) -> 1 | BA19: =VLOOKUP(表1[[#This Row],[Pers.no.]],'[6]Person Detail'!$B:$W,22,0) -> 1.0535968
A20: CN15 | B20: 15005811 | C20: Indirect Active | D20: OP | E20: SNa | F20: FCGNa-VV | G20: 330404 | H20: 40646 | I20: Manager | J20: Head of Value Stream Ventilation | K20: BAND B | L20: 2 | M20: 5 | N20: 24500 | O20: 0.04 | P20: =ROUND(N20*O20,0) -> 980 | Q20: 0 | R20: =ROUND(N20*Q20,0) -> 0 | S20: =T20/N20 -> 0.04 | T20: =P20+R20 -> 980 | U20: =N20+T20 -> 25480 | V20: =U20 -> 25480 | W20: =V20-N20 -> 980 | X20: =ROUND(V20/N20-1,4) -> 0.04 | Y20: =IF(OR(L20=1,L20=2,L20=4), TEXT(S20*0.8,"0.00%") & "-" & TEXT(S20*1.2,"0.00%"), IF(OR(L20=3,L20=6), TEXT(0,"0.00%") & "-" & TEXT(7%*1.2,"0.00%"), IF(OR(L20=5,L20=7), TEXT((R20/N20),"0.00%") & "-" & TEXT((R20/N20)+7%,"0.00%"), "" ) ) ) -> 3.20%-4.80% | Z20: Promotion | AA20: Head of Value Stream Ventilation | AB20: C | AC20: 0.08 | AD20: =ROUND(N20*AC20,0) -> 1960 | AE20: =V20+AD20 -> 27440 | AF20: =AE20-N20 -> 2940 | AG20: =AE20/N20-1 -> 0.12 | AH20: 14 | AI20: 450 | AK20: 688 | AL20: =AE20*AH20+AI20*12+AK20+IF(AB20="",AJ20,IF(AB20="D",5000,IF(AB20="C",1000,0)))*12 -> 402248 | AM20: 3 | AO20: Good performance and high competence | AP20: Good performance and high competence | AQ20: Chen Chao（15005032） | AR20: Zhu Qianqian（11016705） | AS20: Zhao Chujun | AW20: =_xlfn.LET(_xlpm.actual,X20,_xlpm.low,VALUE(_xlfn.TEXTBEFORE(Y20,"-")),_xlpm.high,VALUE(_xlfn.TEXTAFTER(Y20,"-")),IF(AND(_xlpm.actual=0,OR(_xlpm.low<>0,_xlpm.high<>0)),"0 increase",IF(_xlpm.actual>_xlpm.high*1.2,">20",IF(_xlpm.actual<_xlpm.low*0.8,"<20","OK")))) -> #NAME? | AX20: =VLOOKUP(表1[[#This Row],[Pers.no.]],'[6]Person Detail'!$B:$L,11,0) -> 90-110 | AY20: =VLOOKUP(表1[[#This Row],[Pers.no.]],'[6]Person Detail'!$B:$R,17,0) -> 1.0540808 | AZ20: =VLOOKUP(表1[[#This Row],[Pers.no.]],'[6]Person Detail'!$B:$W,21,0) -> 1.0294118 | BA20: =VLOOKUP(表1[[#This Row],[Pers.no.]],'[6]Person Detail'!$B:$W,22,0) -> 1.084585
A21: CN15 | B21: 15022316 | C21: Indirect Active | D21: OP | E21: SNa | F21: FCGNa | G21: 330100 | H21: 44930 | I21: Senior Engineer | J21: Senior Testing and Programming Engineer | K21: BAND A5 | L21: 2 | M21: 3 | N21: 14375 | O21: 0.025 | P21: =ROUND(N21*O21,0) -> 359 | Q21: 0 | R21: =ROUND(N21*Q21,0) -> 0 | S21: =T21/N21 -> 0.024973913 | T21: =P21+R21 -> 359 | U21: =N21+T21 -> 14734 | V21: =U21 -> 14734 | W21: =V21-N21 -> 359 | X21: =ROUND(V21/N21-1,4) -> 0.025 | Y21: =IF(OR(L21=1,L21=2,L21=4), TEXT(S21*0.8,"0.00%") & "-" & TEXT(S21*1.2,"0.00%"), IF(OR(L21=3,L21=6), TEXT(0,"0.00%") & "-" & TEXT(7%*1.2,"0.00%"), IF(OR(L21=5,L21=7), TEXT((R21/N21),"0.00%") & "-" & TEXT((R21/N21)+7%,"0.00%"), "" ) ) ) -> 2.00%-3.00% | AD21: =ROUND(N21*AC21,0) -> 0 | AE21: =V21+AD21 -> 14734 | AF21: =AE21-N21 -> 359 | AG21: =AE21/N21-1 -> 0.024973913 | AH21: 14 | AI21: 450 | AK21: 688 | AL21: =AE21*AH21+AI21*12+AK21+IF(AB21="",AJ21,IF(AB21="D",5000,IF(AB21="C",1000,0)))*12 -> 212364 | AM21: 4 | AQ21: Chen Chao（15005032） | AR21: Zhu Qianqian（11016705） | AS21: Zhao Chujun | AW21: =_xlfn.LET(_xlpm.actual,X21,_xlpm.low,VALUE(_xlfn.TEXTBEFORE(Y21,"-")),_xlpm.high,VALUE(_xlfn.TEXTAFTER(Y21,"-")),IF(AND(_xlpm.actual=0,OR(_xlpm.low<>0,_xlpm.high<>0)),"0 increase",IF(_xlpm.actual>_xlpm.high*1.2,">20",IF(_xlpm.actual<_xlpm.low*0.8,"<20","OK")))) -> #NAME? | AX21: =VLOOKUP(表1[[#This Row],[Pers.no.]],'[6]Person Detail'!$B:$L,11,0) -> 70-90 | AY21: =VLOOKUP(表1[[#This Row],[Pers.no.]],'[6]Person Detail'!$B:$R,17,0) -> 1.1632612 | AZ21: =VLOOKUP(表1[[#This Row],[Pers.no.]],'[6]Person Detail'!$B:$W,21,0) -> 1.0695685 | BA21: =VLOOKUP(表1[[#This Row],[Pers.no.]],'[6]Person Detail'!$B:$W,22,0) -> 1.0853376
A22: CN15 | B22: 15001764 | C22: Indirect Active | D22: OP | E22: SNa | F22: FCGNa | G22: 330100 | H22: 40360 | I22: Senior Engineer | J22: Senior Engineer | K22: BAND A5 | L22: 2 | M22: 4 | N22: 9891 | O22: 0.045 | P22: =ROUND(N22*O22,0) -> 445 | Q22: 0.0421 | R22: =ROUND(N22*Q22,0) -> 416 | S22: =T22/N22 -> 0.087048832 | T22: =P22+R22 -> 861 | U22: =N22+T22 -> 10752 | V22: =U22 -> 10752 | W22: =V22-N22 -> 861 | X22: =ROUND(V22/N22-1,4) -> 0.087 | Y22: =IF(OR(L22=1,L22=2,L22=4), TEXT(S22*0.8,"0.00%") & "-" & TEXT(S22*1.2,"0.00%"), IF(OR(L22=3,L22=6), TEXT(0,"0.00%") & "-" & TEXT(7%*1.2,"0.00%"), IF(OR(L22=5,L22=7), TEXT((R22/N22),"0.00%") & "-" & TEXT((R22/N22)+7%,"0.00%"), "" ) ) ) -> 6.96%-10.45% | AD22: =ROUND(N22*AC22,0) -> 0 | AE22: =V22+AD22 -> 10752 | AF22: =AE22-N22 -> 861 | AG22: =AE22/N22-1 -> 0.087048832 | AH22: 14 | AI22: 450 | AK22: 688 | AL22: =AE22*AH22+AI22*12+AK22+IF(AB22="",AJ22,IF(AB22="D",5000,IF(AB22="C",1000,0)))*12 -> 156616 | AM22: 3 | AQ22: Chen Chao（15005032） | AR22: Zhu Qianqian（11016705） | AS22: Zhao Chujun | AW22: =_xlfn.LET(_xlpm.actual,X22,_xlpm.low,VALUE(_xlfn.TEXTBEFORE(Y22,"-")),_xlpm.high,VALUE(_xlfn.TEXTAFTER(Y22,"-")),IF(AND(_xlpm.actual=0,OR(_xlpm.low<>0,_xlpm.high<>0)),"0 increase",IF(_xlpm.actual>_xlpm.high*1.2,">20",IF(_xlpm.actual<_xlpm.low*0.8,"<20","OK")))) -> #NAME? | AX22: =VLOOKUP(表1[[#This Row],[Pers.no.]],'[6]Person Detail'!$B:$L,11,0) -> 50-70 | AY22: =VLOOKUP(表1[[#This Row],[Pers.no.]],'[6]Person Detail'!$B:$R,17,0) -> 0.80040461 | AZ22: =VLOOKUP(表1[[#This Row],[Pers.no.]],'[6]Person Detail'!$B:$W,21,0) -> 0.7359375 | BA22: =VLOOKUP(表1[[#This Row],[Pers.no.]],'[6]Person Detail'!$B:$W,22,0) -> 0.79201503
A23: CN15 | B23: 15022180 | C23: Indirect Active | D23: OP | E23: SNa | F23: FEDNa-MEP | G23: 370200 | H23: 44686 | I23: Engineer | J23: Process Engineer | K23: BAND A4 | L23: 2 | M23: 3 | N23: 8200 | O23: 0.025 | P23: =ROUND(N23*O23,0) -> 205 | Q23: 0 | R23: =ROUND(N23*Q23,0) -> 0 | S23: =T23/N23 -> 0.025 | T23: =P23+R23 -> 205 | U23: =N23+T23 -> 8405 | V23: 8415 | W23: =V23-N23 -> 215 | X23: =ROUND(V23/N23-1,4) -> 0.0262 | Y23: =IF(OR(L23=1,L23=2,L23=4),TEXT(S23*0.8,"0.00%")&"-"&TEXT(S23*1.2,"0.00%"),IF(OR(L23=3,L23=6),TEXT(0,"0.00%")&"-"&TEXT(7%*1.2,"0.00%"),IF(OR(L23=5,L23=7),TEXT((R23/N23),"0.00%")&"-"&TEXT((R23/N23)+7%,"0.00%"),""))) -> 2.00%-3.00% | AD23: =ROUND(N23*AC23,0) -> 0 | AE23: =V23+AD23 -> 8415 | AF23: =AE23-N23 -> 215 | AG23: =AE23/N23-1 -> 0.026219512 | AH23: 14 | AI23: 550 | AK23: 688 | AL23: =AE23*AH23+AI23*12+AK23+IF(AB23="",AJ23,IF(AB23="D",5000,IF(AB23="C",1000,0)))*12 -> 125098 | AM23: 3 | AQ23: Ding Xudong（15000307） | AR23: Xu Lan（11013544） | AS23: Zhao Chujun | AW23: =_xlfn.LET(_xlpm.actual,X23,_xlpm.low,VALUE(_xlfn.TEXTBEFORE(Y23,"-")),_xlpm.high,VALUE(_xlfn.TEXTAFTER(Y23,"-")),IF(AND(_xlpm.actual=0,OR(_xlpm.low<>0,_xlpm.high<>0)),"0 increase",IF(_xlpm.actual>_xlpm.high*1.2,">20",IF(_xlpm.actual<_xlpm.low*0.8,"<20","OK")))) -> #NAME? | AX23: =VLOOKUP(表1[[#This Row],[Pers.no.]],'[6]Person Detail'!$B:$L,11,0) -> 70-90 | AY23: =VLOOKUP(表1[[#This Row],[Pers.no.]],'[6]Person Detail'!$B:$R,17,0) -> 0.86772487 | AZ23: =VLOOKUP(表1[[#This Row],[Pers.no.]],'[6]Person Detail'!$B:$W,21,0) -> 0.77728802 | BA23: =VLOOKUP(表1[[#This Row],[Pers.no.]],'[6]Person Detail'!$B:$W,22,0) -> 0.77679313
A24: CN15 | B24: 15003790 | C24: Indirect Active | D24: OP | E24: SNa | F24: FEDNa-MEM | G24: 370201 | H24: 40310 | I24: Supervisor | J24: Head of Mechanical Support | K24: BAND A6 | L24: 2 | M24: 3 | N24: 15324 | O24: 0.03 | P24: =ROUND(N24*O24,0) -> 460 | Q24: 0 | R24: =ROUND(N24*Q24,0) -> 0 | S24: =T24/N24 -> 0.030018272 | T24: =P24+R24 -> 460 | U24: =N24+T24 -> 15784 | V24: 15600 | W24: =V24-N24 -> 276 | X24: =ROUND(V24/N24-1,4) -> 0.018 | Y24: =IF(OR(L24=1,L24=2,L24=4),TEXT(S24*0.8,"0.00%")&"-"&TEXT(S24*1.2,"0.00%"),IF(OR(L24=3,L24=6),TEXT(0,"0.00%")&"-"&TEXT(7%*1.2,"0.00%"),IF(OR(L24=5,L24=7),TEXT((R24/N24),"0.00%")&"-"&TEXT((R24/N24)+7%,"0.00%"),""))) -> 2.40%-3.60% | AD24: =ROUND(N24*AC24,0) -> 0 | AE24: =V24+AD24 -> 15600 | AF24: =AE24-N24 -> 276 | AG24: =AE24/N24-1 -> 0.018010963 | AH24: 14 | AI24: 450 | AK24: 688 | AL24: =AE24*AH24+AI24*12+AK24+IF(AB24="",AJ24,IF(AB24="D",5000,IF(AB24="C",1000,0)))*12 -> 224488 | AM24: 3 | AP24: Internal balance | AQ24: Ding Xudong（15000307） | AR24: Xu Lan（11013544） | AS24: Zhao Chujun | AU24: exceed +/-20% adjustment | AV24: <20 | AW24: =_xlfn.LET(_xlpm.actual,X24,_xlpm.low,VALUE(_xlfn.TEXTBEFORE(Y24,"-")),_xlpm.high,VALUE(_xlfn.TEXTAFTER(Y24,"-")),IF(AND(_xlpm.actual=0,OR(_xlpm.low<>0,_xlpm.high<>0)),"0 increase",IF(_xlpm.actual>_xlpm.high*1.2,">20",IF(_xlpm.actual<_xlpm.low*0.8,"<20","OK")))) -> #NAME? | AX24: =VLOOKUP(表1[[#This Row],[Pers.no.]],'[6]Person Detail'!$B:$L,11,0) -> 50-70 | AY24: =VLOOKUP(表1[[#This Row],[Pers.no.]],'[6]Person Detail'!$B:$R,17,0) -> 0.96889226 | AZ24: =VLOOKUP(表1[[#This Row],[Pers.no.]],'[6]Person Detail'!$B:$W,21,0) -> 0.96987342 | BA24: =VLOOKUP(表1[[#This Row],[Pers.no.]],'[6]Person Detail'!$B:$W,22,0) -> 0.95870206
A25: CN15 | B25: 15016330 | C25: Indirect Active | D25: OP | E25: SNa | F25: FEDNa-V2 | G25: 370400 | H25: 42781 | I25: Manager | J25: Head of FEDNa-V2 | K25: BAND B | L25: 2 | M25: 4 | N25: 20300 | O25: 0.0375 | P25: =ROUND(N25*O25,0) -> 761 | Q25: 0.0155 | R25: =ROUND(N25*Q25,0) -> 315 | S25: =T25/N25 -> 0.053004926 | T25: =P25+R25 -> 1076 | U25: =N25+T25 -> 21376 | V25: 21500 | W25: =V25-N25 -> 1200 | X25: =ROUND(V25/N25-1,4) -> 0.0591 | Y25: =IF(OR(L25=1,L25=2,L25=4),TEXT(S25*0.8,"0.00%")&"-"&TEXT(S25*1.2,"0.00%"),IF(OR(L25=3,L25=6),TEXT(0,"0.00%")&"-"&TEXT(7%*1.2,"0.00%"),IF(OR(L25=5,L25=7),TEXT((R25/N25),"0.00%")&"-"&TEXT((R25/N25)+7%,"0.00%"),""))) -> 4.24%-6.36% | AD25: =ROUND(N25*AC25,0) -> 0 | AE25: =V25+AD25 -> 21500 | AF25: =AE25-N25 -> 1200 | AG25: =AE25/N25-1 -> 0.0591133 | AH25: 14 | AI25: 450 | AK25: 688 | AL25: =AE25*AH25+AI25*12+AK25+IF(AB25="",AJ25,IF(AB25="D",5000,IF(AB25="C",1000,0)))*12 -> 307088 | AM25: 3 | AQ25: Ding Xudong（15000307） | AR25: Xu Lan（11013544） | AS25: Zhao Chujun | AW25: =_xlfn.LET(_xlpm.actual,X25,_xlpm.low,VALUE(_xlfn.TEXTBEFORE(Y25,"-")),_xlpm.high,VALUE(_xlfn.TEXTAFTER(Y25,"-")),IF(AND(_xlpm.actual=0,OR(_xlpm.low<>0,_xlpm.high<>0)),"0 increase",IF(_xlpm.actual>_xlpm.high*1.2,">20",IF(_xlpm.actual<_xlpm.low*0.8,"<20","OK")))) -> #NAME? | AX25: =VLOOKUP(表1[[#This Row],[Pers.no.]],'[6]Person Detail'!$B:$L,11,0) -> 70-90 | AY25: =VLOOKUP(表1[[#This Row],[Pers.no.]],'[6]Person Detail'!$B:$R,17,0) -> 0.87338123 | AZ25: =VLOOKUP(表1[[#This Row],[Pers.no.]],'[6]Person Detail'!$B:$W,21,0) -> 0.85294118 | BA25: =VLOOKUP(表1[[#This Row],[Pers.no.]],'[6]Person Detail'!$B:$W,22,0) -> 0.84980237
A26: CN15 | B26: 15001485 | C26: Indirect Active | D26: OP | E26: SNa | F26: FEDNa-ME | G26: 370200 | H26: 39547 | I26: Manager | J26: Head of Manufacturing Engineering | K26: BAND B | L26: 2 | M26: 3 | N26: 27011 | O26: 0.025 | P26: =ROUND(N26*O26,0) -> 675 | Q26: 0 | R26: =ROUND(N26*Q26,0) -> 0 | S26: =T26/N26 -> 0.024989819 | T26: =P26+R26 -> 675 | U26: =N26+T26 -> 27686 | V26: 27700 | W26: =V26-N26 -> 689 | X26: =ROUND(V26/N26-1,4) -> 0.0255 | Y26: =IF(OR(L26=1,L26=2,L26=4),TEXT(S26*0.8,"0.00%")&"-"&TEXT(S26*1.2,"0.00%"),IF(OR(L26=3,L26=6),TEXT(0,"0.00%")&"-"&TEXT(7%*1.2,"0.00%"),IF(OR(L26=5,L26=7),TEXT((R26/N26),"0.00%")&"-"&TEXT((R26/N26)+7%,"0.00%"),""))) -> 2.00%-3.00% | AD26: =ROUND(N26*AC26,0) -> 0 | AE26: =V26+AD26 -> 27700 | AF26: =AE26-N26 -> 689 | AG26: =AE26/N26-1 -> 0.025508126 | AH26: 14 | AI26: 450 | AK26: 688 | AL26: =AE26*AH26+AI26*12+AK26+IF(AB26="",AJ26,IF(AB26="D",5000,IF(AB26="C",1000,0)))*12 -> 393888 | AM26: 4 | AQ26: Ding Xudong（15000307） | AR26: Xu Lan（11013544） | AS26: Zhao Chujun | AW26: =_xlfn.LET(_xlpm.actual,X26,_xlpm.low,VALUE(_xlfn.TEXTBEFORE(Y26,"-")),_xlpm.high,VALUE(_xlfn.TEXTAFTER(Y26,"-")),IF(AND(_xlpm.actual=0,OR(_xlpm.low<>0,_xlpm.high<>0)),"0 increase",IF(_xlpm.actual>_xlpm.high*1.2,">20",IF(_xlpm.actual<_xlpm.low*0.8,"<20","OK")))) -> #NAME? | AX26: =VLOOKUP(表1[[#This Row],[Pers.no.]],'[6]Person Detail'!$B:$L,11,0) -> 70-90 | AY26: =VLOOKUP(表1[[#This Row],[Pers.no.]],'[6]Person Detail'!$B:$R,17,0) -> 1.1621133 | AZ26: =VLOOKUP(表1[[#This Row],[Pers.no.]],'[6]Person Detail'!$B:$W,21,0) -> 1.134916 | BA26: =VLOOKUP(表1[[#This Row],[Pers.no.]],'[6]Person Detail'!$B:$W,22,0) -> 1.0948617
A27: CN15 | B27: 1020358 | C27: Indirect Active | D27: OP | E27: SNa | F27: FEDNa-MEP | G27: 370200 | H27: 45000 | I27: Senior Engineer | J27: Senior Process Engineer | K27: BAND A5 | L27: 2 | M27: 5 | N27: 13610 | O27: 0.05 | P27: =ROUND(N27*O27,0) -> 681 | Q27: 0.027 | R27: =ROUND(N27*Q27,0) -> 367 | S27: =T27/N27 -> 0.077002204 | T27: =P27+R27 -> 1048 | U27: =N27+T27 -> 14658 | V27: 15000 | W27: =V27-N27 -> 1390 | X27: =ROUND(V27/N27-1,4) -> 0.1021 | Y27: =IF(OR(L27=1,L27=2,L27=4),TEXT(S27*0.8,"0.00%")&"-"&TEXT(S27*1.2,"0.00%"),IF(OR(L27=3,L27=6),TEXT(0,"0.00%")&"-"&TEXT(7%*1.2,"0.00%"),IF(OR(L27=5,L27=7),TEXT((R27/N27),"0.00%")&"-"&TEXT((R27/N27)+7%,"0.00%"),""))) -> 6.16%-9.24% | AD27: =ROUND(N27*AC27,0) -> 0 | AE27: =V27+AD27 -> 15000 | AF27: =AE27-N27 -> 1390 | AG27: =AE27/N27-1 -> 0.10213079 | AH27: 14 | AI27: 450 | AK27: 688 | AL27: =AE27*AH27+AI27*12+AK27+IF(AB27="",AJ27,IF(AB27="D",5000,IF(AB27="C",1000,0)))*12 -> 216088 | AM27: 3 | AP27: Rounding | AQ27: Ding Xudong（15000307） | AR27: Xu Lan（11013544） | AS27: Zhao Chujun | AU27: exceed +/-20% adjustment | AV27: >20 | AW27: =_xlfn.LET(_xlpm.actual,X27,_xlpm.low,VALUE(_xlfn.TEXTBEFORE(Y27,"-")),_xlpm.high,VALUE(_xlfn.TEXTAFTER(Y27,"-")),IF(AND(_xlpm.actual=0,OR(_xlpm.low<>0,_xlpm.high<>0)),"0 increase",IF(_xlpm.actual>_xlpm.high*1.2,">20",IF(_xlpm.actual<_xlpm.low*0.8,"<20","OK")))) -> #NAME? | AX27: =VLOOKUP(表1[[#This Row],[Pers.no.]],'[6]Person Detail'!$B:$L,11,0) -> 70-90 | AY27: =VLOOKUP(表1[[#This Row],[Pers.no.]],'[6]Person Detail'!$B:$R,17,0) -> 1.1013555 | AZ27: =VLOOKUP(表1[[#This Row],[Pers.no.]],'[6]Person Detail'!$B:$W,21,0) -> 1.0126488 | BA27: =VLOOKUP(表1[[#This Row],[Pers.no.]],'[6]Person Detail'!$B:$W,22,0) -> 1.1049317
A28: CN15 | B28: 15021547 | C28: Indirect Active | D28: OP | E28: SNa | F28: FEDNa-MEP | G28: 370200 | H28: 44391 | I28: Engineer | J28: Electrical Engineer | K28: BAND A4 | L28: 2 | M28: 4 | N28: 10500 | O28: 0.0375 | P28: =ROUND(N28*O28,0) -> 394 | Q28: 0 | R28: =ROUND(N28*Q28,0) -> 0 | S28: =T28/N28 -> 0.03752381 | T28: =P28+R28 -> 394 | U28: =N28+T28 -> 10894 | V28: 10827 | W28: =V28-N28 -> 327 | X28: =ROUND(V28/N28-1,4) -> 0.0311 | Y28: =IF(OR(L28=1,L28=2,L28=4),TEXT(S28*0.8,"0.00%")&"-"&TEXT(S28*1.2,"0.00%"),IF(OR(L28=3,L28=6),TEXT(0,"0.00%")&"-"&TEXT(7%*1.2,"0.00%"),IF(OR(L28=5,L28=7),TEXT((R28/N28),"0.00%")&"-"&TEXT((R28/N28)+7%,"0.00%"),""))) -> 3.00%-4.50% | Z28: Promotion | AA28: senior engineer | AB28: A5 | AC28: 0.1117 | AD28: =ROUND(N28*AC28,0) -> 1173 | AE28: =V28+AD28 -> 12000 | AF28: =AE28-N28 -> 1500 | AG28: =AE28/N28-1 -> 0.14285714 | AH28: 14 | AI28: 500 | AK28: 688 | AL28: =AE28*AH28+AI28*12+AK28+IF(AB28="",AJ28,IF(AB28="D",5000,IF(AB28="C",1000,0)))*12 -> 174688 | AM28: 3 | AP28: Good performance and high competence | AQ28: Ding Xudong（15000307） | AR28: Xu Lan（11013544） | AS28: Zhao Chujun | AW28: =_xlfn.LET(_xlpm.actual,X28,_xlpm.low,VALUE(_xlfn.TEXTBEFORE(Y28,"-")),_xlpm.high,VALUE(_xlfn.TEXTAFTER(Y28,"-")),IF(AND(_xlpm.actual=0,OR(_xlpm.low<>0,_xlpm.high<>0)),"0 increase",IF(_xlpm.actual>_xlpm.high*1.2,">20",IF(_xlpm.actual<_xlpm.low*0.8,"<20","OK")))) -> #NAME? | AX28: =VLOOKUP(表1[[#This Row],[Pers.no.]],'[6]Person Detail'!$B:$L,11,0) -> 70-90 | AY28: =VLOOKUP(表1[[#This Row],[Pers.no.]],'[6]Person Detail'!$B:$R,17,0) -> 1.1111111 | AZ28: =VLOOKUP(表1[[#This Row],[Pers.no.]],'[6]Person Detail'!$B:$W,21,0) -> 0.99530783 | BA28: =VLOOKUP(表1[[#This Row],[Pers.no.]],'[6]Person Detail'!$B:$W,22,0) -> 1.1077264
A29: CN15 | B29: 15012913 | C29: Indirect Active | D29: OP | E29: SNa | F29: FEDNa-ME | G29: 370200 | H29: 41738 | I29: Associate Expert (CN) | J29: Associate Expert (C) | K29: BAND A6 | L29: 2 | M29: 5 | N29: 16000 | O29: 0.06 | P29: =ROUND(N29*O29,0) -> 960 | Q29: 0.0778 | R29: =ROUND(N29*Q29,0) -> 1245 | S29: =T29/N29 -> 0.1378125 | T29: =P29+R29 -> 2205 | U29: =N29+T29 -> 18205 | V29: 18000 | W29: =V29-N29 -> 2000 | X29: =ROUND(V29/N29-1,4) -> 0.125 | Y29: =IF(OR(L29=1,L29=2,L29=4),TEXT(S29*0.8,"0.00%")&"-"&TEXT(S29*1.2,"0.00%"),IF(OR(L29=3,L29=6),TEXT(0,"0.00%")&"-"&TEXT(7%*1.2,"0.00%"),IF(OR(L29=5,L29=7),TEXT((R29/N29),"0.00%")&"-"&TEXT((R29/N29)+7%,"0.00%"),""))) -> 11.03%-16.54% | AD29: =ROUND(N29*AC29,0) -> 0 | AE29: =V29+AD29 -> 18000 | AF29: =AE29-N29 -> 2000 | AG29: =AE29/N29-1 -> 0.125 | AH29: 14 | AI29: 500 | AK29: 688 | AL29: =AE29*AH29+AI29*12+AK29+IF(AB29="",AJ29,IF(AB29="D",5000,IF(AB29="C",1000,0)))*12 -> 258688 | AM29: 4 | AQ29: Ding Xudong（15000307） | AR29: Xu Lan（11013544） | AS29: Zhao Chujun | AW29: =_xlfn.LET(_xlpm.actual,X29,_xlpm.low,VALUE(_xlfn.TEXTBEFORE(Y29,"-")),_xlpm.high,VALUE(_xlfn.TEXTAFTER(Y29,"-")),IF(AND(_xlpm.actual=0,OR(_xlpm.low<>0,_xlpm.high<>0)),"0 increase",IF(_xlpm.actual>_xlpm.high*1.2,">20",IF(_xlpm.actual<_xlpm.low*0.8,"<20","OK")))) -> #NAME? | AX29: =VLOOKUP(表1[[#This Row],[Pers.no.]],'[6]Person Detail'!$B:$L,11,0) -> 0 | AY29: =VLOOKUP(表1[[#This Row],[Pers.no.]],'[6]Person Detail'!$B:$R,17,0) -> 1.0116338 | AZ29: =VLOOKUP(表1[[#This Row],[Pers.no.]],'[6]Person Detail'!$B:$W,21,0) -> 1.0126582 | BA29: =VLOOKUP(表1[[#This Row],[Pers.no.]],'[6]Person Detail'!$B:$W,22,0) -> 1.1061947
A30: CN15 | B30: 15001306 | C30: Indirect Active | D30: OP | E30: SNa | F30: FEDNa-ME | G30: 370200 | H30: 39420 | I30: Functional Specialist | J30: Functional Specialist | K30: BAND A6 | L30: 2 | M30: 3 | N30: 20306 | O30: 0 | P30: =ROUND(N30*O30,0) -> 0 | Q30: 0 | R30: =ROUND(N30*Q30,0) -> 0 | S30: =T30/N30 -> 0 | T30: =P30+R30 -> 0 | U30: =N30+T30 -> 20306 | V30: 20500 | W30: =V30-N30 -> 194 | X30: =ROUND(V30/N30-1,4) -> 0.0096 | Y30: =IF(OR(L30=1,L30=2,L30=4),TEXT(S30*0.8,"0.00%")&"-"&TEXT(S30*1.2,"0.00%"),IF(OR(L30=3,L30=6),TEXT(0,"0.00%")&"-"&TEXT(7%*1.2,"0.00%"),IF(OR(L30=5,L30=7),TEXT((R30/N30),"0.00%")&"-"&TEXT((R30/N30)+7%,"0.00%"),""))) -> 0.00%-0.00% | AD30: =ROUND(N30*AC30,0) -> 0 | AE30: =V30+AD30 -> 20500 | AF30: =AE30-N30 -> 194 | AG30: =AE30/N30-1 -> 0.0095538265 | AH30: 14 | AI30: 600 | AK30: 688 | AL30: =AE30*AH30+AI30*12+AK30+IF(AB30="",AJ30,IF(AB30="D",5000,IF(AB30="C",1000,0)))*12 -> 294888 | AM30: 4 | AP30: Good performance and high competence | AQ30: Ding Xudong（15000307） | AR30: Xu Lan（11013544） | AS30: Zhao Chujun | AU30: exceed +/-20% adjustment | AV30: >20 | AW30: =_xlfn.LET(_xlpm.actual,X30,_xlpm.low,VALUE(_xlfn.TEXTBEFORE(Y30,"-")),_xlpm.high,VALUE(_xlfn.TEXTAFTER(Y30,"-")),IF(AND(_xlpm.actual=0,OR(_xlpm.low<>0,_xlpm.high<>0)),"0 increase",IF(_xlpm.actual>_xlpm.high*1.2,">20",IF(_xlpm.actual<_xlpm.low*0.8,"<20","OK")))) -> #NAME? | AX30: =VLOOKUP(表1[[#This Row],[Pers.no.]],'[6]Person Detail'!$B:$L,11,0) -> >90 | AY30: =VLOOKUP(表1[[#This Row],[Pers.no.]],'[6]Person Detail'!$B:$R,17,0) -> 1.2838897 | AZ30: =VLOOKUP(表1[[#This Row],[Pers.no.]],'[6]Person Detail'!$B:$W,21,0) -> 1.2851899 | BA30: =VLOOKUP(表1[[#This Row],[Pers.no.]],'[6]Person Detail'!$B:$W,22,0) -> 1.2598328
A31: CN15 | B31: 15021548 | C31: Indirect Active | D31: OP | E31: SNa | F31: FEDNa-ME | G31: 370200 | H31: 44391 | I31: Senior Engineer | J31: Senior Equipment Engineer | K31: BAND A5 | L31: 2 | M31: 3 | N31: 13330 | O31: 0.025 | P31: =ROUND(N31*O31,0) -> 333 | Q31: 0 | R31: =ROUND(N31*Q31,0) -> 0 | S31: =T31/N31 -> 0.024981245 | T31: =P31+R31 -> 333 | U31: =N31+T31 -> 13663 | V31: 13600 | W31: =V31-N31 -> 270 | X31: =ROUND(V31/N31-1,4) -> 0.0203 | Y31: =IF(OR(L31=1,L31=2,L31=4),TEXT(S31*0.8,"0.00%")&"-"&TEXT(S31*1.2,"0.00%"),IF(OR(L31=3,L31=6),TEXT(0,"0.00%")&"-"&TEXT(7%*1.2,"0.00%"),IF(OR(L31=5,L31=7),TEXT((R31/N31),"0.00%")&"-"&TEXT((R31/N31)+7%,"0.00%"),""))) -> 2.00%-3.00% | AD31: =ROUND(N31*AC31,0) -> 0 | AE31: =V31+AD31 -> 13600 | AF31: =AE31-N31 -> 270 | AG31: =AE31/N31-1 -> 0.020255064 | AH31: 14 | AI31: 450 | AK31: 688 | AL31: =AE31*AH31+AI31*12+AK31+IF(AB31="",AJ31,IF(AB31="D",5000,IF(AB31="C",1000,0)))*12 -> 196488 | AM31: 3 | AQ31: Ding Xudong（15000307） | AR31: Xu Lan（11013544） | AS31: Zhao Chujun | AW31: =_xlfn.LET(_xlpm.actual,X31,_xlpm.low,VALUE(_xlfn.TEXTBEFORE(Y31,"-")),_xlpm.high,VALUE(_xlfn.TEXTAFTER(Y31,"-")),IF(AND(_xlpm.actual=0,OR(_xlpm.low<>0,_xlpm.high<>0)),"0 increase",IF(_xlpm.actual>_xlpm.high*1.2,">20",IF(_xlpm.actual<_xlpm.low*0.8,"<20","OK")))) -> #NAME? | AX31: =VLOOKUP(表1[[#This Row],[Pers.no.]],'[6]Person Detail'!$B:$L,11,0) -> 70-90 | AY31: =VLOOKUP(表1[[#This Row],[Pers.no.]],'[6]Person Detail'!$B:$R,17,0) -> 1.0786971 | AZ31: =VLOOKUP(表1[[#This Row],[Pers.no.]],'[6]Person Detail'!$B:$W,21,0) -> 0.99181548 | BA31: =VLOOKUP(表1[[#This Row],[Pers.no.]],'[6]Person Detail'!$B:$W,22,0) -> 1.0018047
A32: CN15 | B32: 15021979 | C32: Indirect Active | D32: OP | E32: SNa | F32: FEDNa-V2 | G32: 370404 | H32: 44503 | I32: Engineer | J32: Production Engineer | K32: BAND A4 | L32: 2 | M32: 3 | N32: 9450 | O32: 0.025 | P32: =ROUND(N32*O32,0) -> 236 | Q32: 0 | R32: =ROUND(N32*Q32,0) -> 0 | S32: =T32/N32 -> 0.024973545 | T32: =P32+R32 -> 236 | U32: =N32+T32 -> 9686 | V32: 9700 | W32: =V32-N32 -> 250 | X32: =ROUND(V32/N32-1,4) -> 0.0265 | Y32: =IF(OR(L32=1,L32=2,L32=4),TEXT(S32*0.8,"0.00%")&"-"&TEXT(S32*1.2,"0.00%"),IF(OR(L32=3,L32=6),TEXT(0,"0.00%")&"-"&TEXT(7%*1.2,"0.00%"),IF(OR(L32=5,L32=7),TEXT((R32/N32),"0.00%")&"-"&TEXT((R32/N32)+7%,"0.00%"),""))) -> 2.00%-3.00% | AD32: =ROUND(N32*AC32,0) -> 0 | AE32: =V32+AD32 -> 9700 | AF32: =AE32-N32 -> 250 | AG32: =AE32/N32-1 -> 0.026455026 | AH32: 14 | AI32: 450 | AK32: 688 | AL32: =AE32*AH32+AI32*12+AK32+IF(AB32="",AJ32,IF(AB32="D",5000,IF(AB32="C",1000,0)))*12 -> 141888 | AM32: 2 | AQ32: Ding Xudong（15000307） | AR32: Xu Lan（11013544） | AS32: Zhao Chujun | AW32: =_xlfn.LET(_xlpm.actual,X32,_xlpm.low,VALUE(_xlfn.TEXTBEFORE(Y32,"-")),_xlpm.high,VALUE(_xlfn.TEXTAFTER(Y32,"-")),IF(AND(_xlpm.actual=0,OR(_xlpm.low<>0,_xlpm.high<>0)),"0 increase",IF(_xlpm.actual>_xlpm.high*1.2,">20",IF(_xlpm.actual<_xlpm.low*0.8,"<20","OK")))) -> #NAME? | AX32: =VLOOKUP(表1[[#This Row],[Pers.no.]],'[6]Person Detail'!$B:$L,11,0) -> 70-90 | AY32: =VLOOKUP(表1[[#This Row],[Pers.no.]],'[6]Person Detail'!$B:$R,17,0) -> 1 | AZ32: =VLOOKUP(表1[[#This Row],[Pers.no.]],'[6]Person Detail'!$B:$W,21,0) -> 0.89577705 | BA32: =VLOOKUP(表1[[#This Row],[Pers.no.]],'[6]Person Detail'!$B:$W,22,0) -> 0.89541217
A33: CN15 | B33: 15000525 | C33: Indirect Active | D33: OP | E33: SNa | F33: FEDNa-FS | G33: 370100 | H33: 38869 | I33: Coordinator | J33: TPM Coordinator | K33: BAND A4 | L33: 2 | M33: 3 | N33: 7900 | O33: 0 | P33: =ROUND(N33*O33,0) -> 0 | Q33: 0 | R33: =ROUND(N33*Q33,0) -> 0 | S33: =T33/N33 -> 0 | T33: =P33+R33 -> 0 | U33: =N33+T33 -> 7900 | V33: 8000 | W33: =V33-N33 -> 100 | X33: =ROUND(V33/N33-1,4) -> 0.0127 | Y33: =IF(OR(L33=1,L33=2,L33=4),TEXT(S33*0.8,"0.00%")&"-"&TEXT(S33*1.2,"0.00%"),IF(OR(L33=3,L33=6),TEXT(0,"0.00%")&"-"&TEXT(7%*1.2,"0.00%"),IF(OR(L33=5,L33=7),TEXT((R33/N33),"0.00%")&"-"&TEXT((R33/N33)+7%,"0.00%"),""))) -> 0.00%-0.00% | AD33: =ROUND(N33*AC33,0) -> 0 | AE33: =V33+AD33 -> 8000 | AF33: =AE33-N33 -> 100 | AG33: =AE33/N33-1 -> 0.012658228 | AH33: 14 | AI33: 650 | AK33: 688 | AL33: =AE33*AH33+AI33*12+AK33+IF(AB33="",AJ33,IF(AB33="D",5000,IF(AB33="C",1000,0)))*12 -> 120488 | AM33: 3 | AP33: Internal balance | AQ33: Ding Xudong（15000307） | AR33: Xu Lan（11013544） | AS33: Zhao Chujun | AU33: exceed +/-20% adjustment | AV33: >20 | AW33: =_xlfn.LET(_xlpm.actual,X33,_xlpm.low,VALUE(_xlfn.TEXTBEFORE(Y33,"-")),_xlpm.high,VALUE(_xlfn.TEXTAFTER(Y33,"-")),IF(AND(_xlpm.actual=0,OR(_xlpm.low<>0,_xlpm.high<>0)),"0 increase",IF(_xlpm.actual>_xlpm.high*1.2,">20",IF(_xlpm.actual<_xlpm.low*0.8,"<20","OK")))) -> #NAME? | AX33: =VLOOKUP(表1[[#This Row],[Pers.no.]],'[6]Person Detail'!$B:$L,11,0) -> >90 | AY33: =VLOOKUP(表1[[#This Row],[Pers.no.]],'[6]Person Detail'!$B:$R,17,0) -> 0.83597884 | AZ33: =VLOOKUP(表1[[#This Row],[Pers.no.]],'[6]Person Detail'!$B:$W,21,0) -> 0.74885066 | BA33: =VLOOKUP(表1[[#This Row],[Pers.no.]],'[6]Person Detail'!$B:$W,22,0) -> 0.73848426
A34: CN15 | B34: 15020089 | C34: Indirect Active | D34: OP | E34: SNa | F34: FEDNa-MEP | G34: 370200 | H34: 43908 | I34: Engineer | J34: Process Engineer | K34: BAND A4 | L34: 2 | M34: 3 | N34: 10100 | O34: 0.025 | P34: =ROUND(N34*O34,0) -> 253 | Q34: 0 | R34: =ROUND(N34*Q34,0) -> 0 | S34: =T34/N34 -> 0.025049505 | T34: =P34+R34 -> 253 | U34: =N34+T34 -> 10353 | V34: 10300 | W34: =V34-N34 -> 200 | X34: =ROUND(V34/N34-1,4) -> 0.0198 | Y34: =IF(OR(L34=1,L34=2,L34=4),TEXT(S34*0.8,"0.00%")&"-"&TEXT(S34*1.2,"0.00%"),IF(OR(L34=3,L34=6),TEXT(0,"0.00%")&"-"&TEXT(7%*1.2,"0.00%"),IF(OR(L34=5,L34=7),TEXT((R34/N34),"0.00%")&"-"&TEXT((R34/N34)+7%,"0.00%"),""))) -> 2.00%-3.01% | AD34: =ROUND(N34*AC34,0) -> 0 | AE34: =V34+AD34 -> 10300 | AF34: =AE34-N34 -> 200 | AG34: =AE34/N34-1 -> 0.01980198 | AH34: 14 | AI34: 450 | AK34: 688 | AL34: =AE34*AH34+AI34*12+AK34+IF(AB34="",AJ34,IF(AB34="D",5000,IF(AB34="C",1000,0)))*12 -> 150288 | AM34: 3 | AP34: Rounding | AQ34: Ding Xudong（15000307） | AR34: Xu Lan（11013544） | AS34: Zhao Chujun | AU34: exceed +/-20% adjustment | AV34: <20 | AW34: =_xlfn.LET(_xlpm.actual,X34,_xlpm.low,VALUE(_xlfn.TEXTBEFORE(Y34,"-")),_xlpm.high,VALUE(_xlfn.TEXTAFTER(Y34,"-")),IF(AND(_xlpm.actual=0,OR(_xlpm.low<>0,_xlpm.high<>0)),"0 increase",IF(_xlpm.actual>_xlpm.high*1.2,">20",IF(_xlpm.actual<_xlpm.low*0.8,"<20","OK")))) -> #NAME? | AX34: =VLOOKUP(表1[[#This Row],[Pers.no.]],'[6]Person Detail'!$B:$L,11,0) -> 70-90 | AY34: =VLOOKUP(表1[[#This Row],[Pers.no.]],'[6]Person Detail'!$B:$R,17,0) -> 1.0687831 | AZ34: =VLOOKUP(表1[[#This Row],[Pers.no.]],'[6]Person Detail'!$B:$W,21,0) -> 0.95739135 | BA34: =VLOOKUP(表1[[#This Row],[Pers.no.]],'[6]Person Detail'!$B:$W,22,0) -> 0.95079849
A35: CN15 | B35: 15000550 | C35: Indirect Active | D35: OP | E35: SNa | F35: FEDNa-V2 | G35: 370404 | H35: 38881 | I35: Engineer | J35: Engineer | K35: BAND A4 | L35: 2 | M35: 4 | N35: 9800 | O35: 0.0375 | P35: =ROUND(N35*O35,0) -> 368 | Q35: 0.0155 | R35: =ROUND(N35*Q35,0) -> 152 | S35: =T35/N35 -> 0.053061224 | T35: =P35+R35 -> 520 | U35: =N35+T35 -> 10320 | V35: 10300 | W35: =V35-N35 -> 500 | X35: =ROUND(V35/N35-1,4) -> 0.051 | Y35: =IF(OR(L35=1,L35=2,L35=4),TEXT(S35*0.8,"0.00%")&"-"&TEXT(S35*1.2,"0.00%"),IF(OR(L35=3,L35=6),TEXT(0,"0.00%")&"-"&TEXT(7%*1.2,"0.00%"),IF(OR(L35=5,L35=7),TEXT((R35/N35),"0.00%")&"-"&TEXT((R35/N35)+7%,"0.00%"),""))) -> 4.24%-6.37% | AD35: =ROUND(N35*AC35,0) -> 0 | AE35: =V35+AD35 -> 10300 | AF35: =AE35-N35 -> 500 | AG35: =AE35/N35-1 -> 0.051020408 | AH35: 14 | AI35: 550 | AK35: 688 | AL35: =AE35*AH35+AI35*12+AK35+IF(AB35="",AJ35,IF(AB35="D",5000,IF(AB35="C",1000,0)))*12 -> 151488 | AM35: 3 | AQ35: Ding Xudong（15000307） | AR35: Xu Lan（11013544） | AS35: Zhao Chujun | AW35: =_xlfn.LET(_xlpm.actual,X35,_xlpm.low,VALUE(_xlfn.TEXTBEFORE(Y35,"-")),_xlpm.high,VALUE(_xlfn.TEXTAFTER(Y35,"-")),IF(AND(_xlpm.actual=0,OR(_xlpm.low<>0,_xlpm.high<>0)),"0 increase",IF(_xlpm.actual>_xlpm.high*1.2,">20",IF(_xlpm.actual<_xlpm.low*0.8,"<20","OK")))) -> #NAME? | AX35: =VLOOKUP(表1[[#This Row],[Pers.no.]],'[6]Person Detail'!$B:$L,11,0) -> 70-90 | AY35: =VLOOKUP(表1[[#This Row],[Pers.no.]],'[6]Person Detail'!$B:$R,17,0) -> 1.037037 | AZ35: =VLOOKUP(表1[[#This Row],[Pers.no.]],'[6]Person Detail'!$B:$W,21,0) -> 0.92895398 | BA35: =VLOOKUP(表1[[#This Row],[Pers.no.]],'[6]Person Detail'!$B:$W,22,0) -> 0.95079849
A36: CN15 | B36: 15015967 | C36: Indirect Active | D36: OP | E36: SNa | F36: FEDNa-FS | G36: 370100 | H36: 42683 | I36: Associate Expert (CN) | J36: Associate Expert (C) | K36: BAND A6 | L36: 2 | M36: 4 | N36: 12360 | O36: 0.045 | P36: =ROUND(N36*O36,0) -> 556 | Q36: 0.0421 | R36: =ROUND(N36*Q36,0) -> 520 | S36: =T36/N36 -> 0.087055016 | T36: =P36+R36 -> 1076 | U36: =N36+T36 -> 13436 | V36: 13300 | W36: =V36-N36 -> 940 | X36: =ROUND(V36/N36-1,4) -> 0.0761 | Y36: =IF(OR(L36=1,L36=2,L36=4),TEXT(S36*0.8,"0.00%")&"-"&TEXT(S36*1.2,"0.00%"),IF(OR(L36=3,L36=6),TEXT(0,"0.00%")&"-"&TEXT(7%*1.2,"0.00%"),IF(OR(L36=5,L36=7),TEXT((R36/N36),"0.00%")&"-"&TEXT((R36/N36)+7%,"0.00%"),""))) -> 6.96%-10.45% | AD36: =ROUND(N36*AC36,0) -> 0 | AE36: =V36+AD36 -> 13300 | AF36: =AE36-N36 -> 940 | AG36: =AE36/N36-1 -> 0.07605178 | AH36: 14 | AI36: 450 | AK36: 688 | AL36: =AE36*AH36+AI36*12+AK36+IF(AB36="",AJ36,IF(AB36="D",5000,IF(AB36="C",1000,0)))*12 -> 192288 | AM36: 3 | AQ36: Ding Xudong（15000307） | AR36: Xu Lan（11013544） | AS36: Zhao Chujun | AW36: =_xlfn.LET(_xlpm.actual,X36,_xlpm.low,VALUE(_xlfn.TEXTBEFORE(Y36,"-")),_xlpm.high,VALUE(_xlfn.TEXTAFTER(Y36,"-")),IF(AND(_xlpm.actual=0,OR(_xlpm.low<>0,_xlpm.high<>0)),"0 increase",IF(_xlpm.actual>_xlpm.high*1.2,">20",IF(_xlpm.actual<_xlpm.low*0.8,"<20","OK")))) -> #NAME? | AX36: =VLOOKUP(表1[[#This Row],[Pers.no.]],'[6]Person Detail'!$B:$L,11,0) -> 50-70 | AY36: =VLOOKUP(表1[[#This Row],[Pers.no.]],'[6]Person Detail'!$B:$R,17,0) -> 0.7814871 | AZ36: =VLOOKUP(表1[[#This Row],[Pers.no.]],'[6]Person Detail'!$B:$W,21,0) -> 0.78227848 | BA36: =VLOOKUP(表1[[#This Row],[Pers.no.]],'[6]Person Detail'!$B:$W,22,0) -> 0.81735497
A37: CN15 | B37: 15001287 | C37: Indirect Active | D37: OP | E37: SNa | F37: FEDNa-MEP | G37: 370200 | H37: 39392 | I37: Senior Engineer | J37: Senior Electrical Engineer | K37: BAND A5 | L37: 2 | M37: 3 | N37: 12500 | O37: 0.025 | P37: =ROUND(N37*O37,0) -> 313 | Q37: 0 | R37: =ROUND(N37*Q37,0) -> 0 | S37: =T37/N37 -> 0.02504 | T37: =P37+R37 -> 313 | U37: =N37+T37 -> 12813 | V37: 12600 | W37: =V37-N37 -> 100 | X37: =ROUND(V37/N37-1,4) -> 0.008 | Y37: =IF(OR(L37=1,L37=2,L37=4),TEXT(S37*0.8,"0.00%")&"-"&TEXT(S37*1.2,"0.00%"),IF(OR(L37=3,L37=6),TEXT(0,"0.00%")&"-"&TEXT(7%*1.2,"0.00%"),IF(OR(L37=5,L37=7),TEXT((R37/N37),"0.00%")&"-"&TEXT((R37/N37)+7%,"0.00%"),""))) -> 2.00%-3.00% | AD37: =ROUND(N37*AC37,0) -> 0 | AE37: =V37+AD37 -> 12600 | AF37: =AE37-N37 -> 100 | AG37: =AE37/N37-1 -> 0.008 | AH37: 14 | AI37: 450 | AK37: 688 | AL37: =AE37*AH37+AI37*12+AK37+IF(AB37="",AJ37,IF(AB37="D",5000,IF(AB37="C",1000,0)))*12 -> 182488 | AM37: 3 | AP37: Left/will leave/retire soon | AQ37: Ding Xudong（15000307） | AR37: Xu Lan（11013544） | AS37: Zhao Chujun | AU37: exceed +/-20% adjustment | AV37: <20 | AW37: =_xlfn.LET(_xlpm.actual,X37,_xlpm.low,VALUE(_xlfn.TEXTBEFORE(Y37,"-")),_xlpm.high,VALUE(_xlfn.TEXTAFTER(Y37,"-")),IF(AND(_xlpm.actual=0,OR(_xlpm.low<>0,_xlpm.high<>0)),"0 increase",IF(_xlpm.actual>_xlpm.high*1.2,">20",IF(_xlpm.actual<_xlpm.low*0.8,"<20","OK")))) -> #NAME? | AX37: =VLOOKUP(表1[[#This Row],[Pers.no.]],'[6]Person Detail'!$B:$L,11,0) -> 70-90 | AY37: =VLOOKUP(表1[[#This Row],[Pers.no.]],'[6]Person Detail'!$B:$R,17,0) -> 1.0115315 | AZ37: =VLOOKUP(表1[[#This Row],[Pers.no.]],'[6]Person Detail'!$B:$W,21,0) -> 0.93005952 | BA37: =VLOOKUP(表1[[#This Row],[Pers.no.]],'[6]Person Detail'!$B:$W,22,0) -> 0.92814261
A38: CN15 | B38: 15016938 | C38: Indirect Active | D38: OP | E38: SNa | F38: FEDNa-MEP | G38: 370200 | H38: 42830 | I38: Supervisor | J38: Head of FEDNa-MEP | K38: BAND A6 | L38: 2 | M38: 5 | N38: 18000 | O38: 0.05 | P38: =ROUND(N38*O38,0) -> 900 | Q38: 0.027 | R38: =ROUND(N38*Q38,0) -> 486 | S38: =T38/N38 -> 0.077 | T38: =P38+R38 -> 1386 | U38: =N38+T38 -> 19386 | V38: 19700 | W38: =V38-N38 -> 1700 | X38: =ROUND(V38/N38-1,4) -> 0.0944 | Y38: =IF(OR(L38=1,L38=2,L38=4),TEXT(S38*0.8,"0.00%")&"-"&TEXT(S38*1.2,"0.00%"),IF(OR(L38=3,L38=6),TEXT(0,"0.00%")&"-"&TEXT(7%*1.2,"0.00%"),IF(OR(L38=5,L38=7),TEXT((R38/N38),"0.00%")&"-"&TEXT((R38/N38)+7%,"0.00%"),""))) -> 6.16%-9.24% | AD38: =ROUND(N38*AC38,0) -> 0 | AE38: =V38+AD38 -> 19700 | AF38: =AE38-N38 -> 1700 | AG38: =AE38/N38-1 -> 0.094444444 | AH38: 14 | AI38: 450 | AK38: 688 | AL38: =AE38*AH38+AI38*12+AK38+IF(AB38="",AJ38,IF(AB38="D",5000,IF(AB38="C",1000,0)))*12 -> 281888 | AM38: 5 | AP38: Good performance/talent | AQ38: Ding Xudong（15000307） | AR38: Xu Lan（11013544） | AS38: Zhao Chujun | AU38: exceed +/-20% adjustment | AV38: >20 | AW38: =_xlfn.LET(_xlpm.actual,X38,_xlpm.low,VALUE(_xlfn.TEXTBEFORE(Y38,"-")),_xlpm.high,VALUE(_xlfn.TEXTAFTER(Y38,"-")),IF(AND(_xlpm.actual=0,OR(_xlpm.low<>0,_xlpm.high<>0)),"0 increase",IF(_xlpm.actual>_xlpm.high*1.2,">20",IF(_xlpm.actual<_xlpm.low*0.8,"<20","OK")))) -> #NAME? | AX38: =VLOOKUP(表1[[#This Row],[Pers.no.]],'[6]Person Detail'!$B:$L,11,0) -> 70-90 | AY38: =VLOOKUP(表1[[#This Row],[Pers.no.]],'[6]Person Detail'!$B:$R,17,0) -> 1.138088 | AZ38: =VLOOKUP(表1[[#This Row],[Pers.no.]],'[6]Person Detail'!$B:$W,21,0) -> 1.1392405 | BA38: =VLOOKUP(表1[[#This Row],[Pers.no.]],'[6]Person Detail'!$B:$W,22,0) -> 1.2106686
