Workbook

Sheet 数据分析
A1: Area | B1: Number of eligibility | C1: Total Salary Increase budget | D1: Person of increase | E1: Salary Increase budget used | G1: Person of increase | H1: Merit budget Balance | I1: Promotion Budget | J1: Promotion budget usage | K1: Number of promotion | L1: Promotion budget balance
A2: GOM-CGC | B2: 38 | C2: =SUMIF(白领!E:E,数据分析!$A2,白领!T1:T1937) -> 9315 | D2: =COUNTIFS(白领!E:E,$A2,白领!X:X,"<>0") -> 11 | E2: =SUMIF(白领!E:E,数据分析!$A2,白领!W:W) -> 9315 | F2: =E2/C2 -> 1
A3: GOM-CLC | B3: 16 | C3: =SUMIF(白领!E:E,数据分析!$A3,白领!T2:T1938) -> 14481 | D3: =COUNTIFS(白领!E:E,$A3,白领!X:X,"<>0") -> 10 | E3: =SUMIF(白领!E:E,数据分析!$A3,白领!W:W) -> 12320 | F3: =E3/C3 -> 0.85076997
A4: GOM-DCC | B4: 15 | C4: =SUMIF(白领!E:E,数据分析!$A4,白领!T3:T1939) -> 6572 | D4: =COUNTIFS(白领!E:E,$A4,白领!X:X,"<>0") -> 9 | E4: =SUMIF(白领!E:E,数据分析!$A4,白领!W:W) -> 7067 | F4: =E4/C4 -> 1.0753195
A5: GOM-LCC | B5: 9 | C5: =SUMIF(白领!E:E,数据分析!$A5,白领!T4:T1940) -> 18276 | D5: =COUNTIFS(白领!E:E,$A5,白领!X:X,"<>0") -> 18 | E5: =SUMIF(白领!E:E,数据分析!$A5,白领!W:W) -> 16165 | F5: =E5/C5 -> 0.88449332
A6: GPL-CN | B6: 23 | C6: =SUMIF(白领!E:E,数据分析!$A6,白领!T5:T1941) -> 45803 | D6: =COUNTIFS(白领!E:E,$A6,白领!X:X,"<>0") -> 87 | E6: =SUMIF(白领!E:E,数据分析!$A6,白领!W:W) -> 50456 | F6: =E6/C6 -> 1.1015872
A7: GQM | B7: 152 | C7: =SUMIF(白领!E:E,数据分析!$A7,白领!T6:T1942) -> 66324 | D7: =COUNTIFS(白领!E:E,$A7,白领!X:X,"<>0") -> 110 | E7: =SUMIF(白领!E:E,数据分析!$A7,白领!W:W) -> 72365 | F7: =E7/C7 -> 1.0910832
A8: PCP | B8: 151 | C8: =SUMIF(白领!E:E,数据分析!$A8,白领!T7:T1943) -> 35317 | D8: =COUNTIFS(白领!E:E,$A8,白领!X:X,"<>0") -> 59 | E8: =SUMIF(白领!E:E,数据分析!$A8,白领!W:W) -> 33643 | F8: =E8/C8 -> 0.95260073
A9: CN/OP-RM | B9: 14 | C9: =SUMIF(白领!E:E,数据分析!$A9,白领!T8:T1944) -> 24910 | D9: =COUNTIFS(白领!E:E,$A9,白领!X:X,"<>0") -> 25 | E9: =SUMIF(白领!E:E,数据分析!$A9,白领!W:W) -> 14433 | F9: =E9/C9 -> 0.57940586
A10: SC | B10: 86 | C10: =SUMIF(白领!E:E,数据分析!$A10,白领!T9:T1945) -> 25597 | D10: =COUNTIFS(白领!E:E,$A10,白领!X:X,"<>0") -> 51 | E10: =SUMIF(白领!E:E,数据分析!$A10,白领!W:W) -> 26345 | F10: =E10/C10 -> 1.0292222
A11: SNa | B11: 29 | C11: =SUMIF(白领!E:E,数据分析!$A11,白领!T10:T1946) -> 38434 | D11: =COUNTIFS(白领!E:E,$A11,白领!X:X,"<>0") -> 61 | E11: =SUMIF(白领!E:E,数据分析!$A11,白领!W:W) -> 38426.744 | F11: =E11/C11 -> 0.99981121
A12: SCh | B12: 82 | C12: =SUMIF(白领!E:E,数据分析!$A12,白领!T11:T1947) -> 64901
A13: ALL | C13: =SUM(C2:C12) -> 349930
J14: 0.005
A15: 行标签 | B15: 求和项:Total Recommended Increase amount | C15: 求和项:Adjutsed increased/decreased basic salary by DH | D15: Surpus | E15: Usage | F15: No | G15: Person of Increase | I15: Basic Salary | J15: Promotion Budget | K15: Promotion Budget Used | M15: No of Promoted | O15: Thereof Special
A16: CN/OP-RM | B16: 14433 | C16: 14433 | D16: =B16-C16 -> 0 | E16: =C16/B16 -> 1 | F16: 38 | G16: 25 | H16: =G16/F16 -> 0.65789474 | I16: 565057 | J16: =I16*$J$14 -> 2825.285 | K16: 2825 | L16: =K16/J16 -> 0.99989913 | M16: 3 | N16: =M16/F16 -> 0.078947368
A17: GOM-CGC | B17: 9315 | C17: 9315 | D17: =B17-C17 -> 0 | E17: =C17/B17 -> 1 | F17: 16 | G17: 11 | H17: =G17/F17 -> 0.6875 | I17: 391477 | J17: =I17*$J$14 -> 1957.385 | K17: 1952 | L17: =K17/J17 -> 0.99724888 | M17: 1 | N17: =M17/F17 -> 0.0625
A18: GOM-CLC | B18: 12320 | C18: 12320 | D18: =B18-C18 -> 0 | E18: =C18/B18 -> 1 | F18: 15 | G18: 10 | H18: =G18/F18 -> 0.66666667 | I18: 415631 | J18: =I18*$J$14 -> 2078.155 | K18: 0 | L18: 0 | N18: =M18/F18 -> 0
A19: GOM-DCC | B19: 7067 | C19: 7067 | D19: =B19-C19 -> 0 | E19: =C19/B19 -> 1 | F19: 9 | G19: 9 | H19: =G19/F19 -> 1 | I19: 202173 | J19: =I19*$J$14 -> 1010.865 | K19: 1010 | L19: =K19/J19 -> 0.9991443 | M19: 1 | N19: =M19/F19 -> 0.11111111
A20: GOM-LCC | B20: 16166 | C20: 16165 | D20: =B20-C20 -> 1 | E20: =C20/B20 -> 0.99993814 | F20: 23 | G20: 18 | H20: =G20/F20 -> 0.7826087 | I20: 605993 | J20: =I20*$J$14 -> 3029.965 | K20: 3023 | L20: =K20/J20 -> 0.99770129 | M20: 2 | N20: =M20/F20 -> 0.086956522
A21: GPL-CN | B21: 50456 | C21: 50456 | D21: =B21-C21 -> 0 | E21: =C21/B21 -> 1 | F21: 152 | G21: 87 | H21: =G21/F21 -> 0.57236842 | I21: 2057648 | J21: =I21*$J$14 -> 10288.24 | K21: 9474 | L21: =K21/J21 -> 0.92085721 | M21: 8 | N21: =M21/F21 -> 0.052631579 | O21: 0
A22: GQM | B22: 68266 | C22: 72365 | D22: =B22-C22 -> -4099 | E22: =C22/B22 -> 1.0600445 | F22: 151 | G22: 110 | H22: =G22/F22 -> 0.72847682 | I22: 2138146 | J22: =I22*$J$14 -> 10690.73 | K22: 10691 | L22: =K22/J22 -> 1.0000253 | M22: 13 | N22: =M22/F22 -> 0.086092715
A23: OP-TE | B23: 9953 | C23: 9953 | D23: =B23-C23 -> 0 | E23: =C23/B23 -> 1 | F23: 14 | G23: 10 | H23: =G23/F23 -> 0.71428571 | I23: 281769 | J23: =I23*$J$14 -> 1408.845 | K23: 1436 | L23: =K23/J23 -> 1.0192747 | M23: 1 | N23: =M23/F23 -> 0.071428571
A24: PCP | B24: 33643 | C24: 33643 | D24: =B24-C24 -> 0 | E24: =C24/B24 -> 1 | F24: 86 | G24: 59 | H24: =G24/F24 -> 0.68604651 | I24: 1418496 | J24: =I24*$J$14 -> 7092.48 | K24: 7089 | L24: =K24/J24 -> 0.99950934 | M24: 7 | N24: =M24/F24 -> 0.081395349
A25: SC | B25: 26990 | C25: 26345 | D25: =B25-C25 -> 645 | E25: =C25/B25 -> 0.97610226 | F25: 66 | G25: 51 | H25: =G25/F25 -> 0.77272727 | I25: 841434 | J25: =I25*$J$14 -> 4207.17 | K25: 4048 | L25: =K25/J25 -> 0.96216697 | M25: 6 | N25: =M25/F25 -> 0.090909091
A26: SNa | B26: 38293 | C26: 38476.744 | D26: =B26-C26 -> -183.744 | E26: =C26/B26 -> 1.0047984 | F26: 82 | G26: 62 | H26: =G26/F26 -> 0.75609756 | I26: 1370342 | J26: =I26*$J$14 -> 6851.71 | K26: 8701 | L26: =K26/J26 -> 1.269902 | M26: 6 | N26: =M26/F26 -> 0.073170732
A27: SCh | B27: 74651 | C27: 73144 | D27: =B27-C27 -> 1507 | E27: =C27/B27 -> 0.97981273 | F27: 142 | G27: 92 | H27: =G27/F27 -> 0.64788732 | I27: 2083527 | J27: =I27*$J$14 -> 10417.635 | K27: 8341 | L27: =K27/J27 -> 0.80066157 | M27: 9 | N27: =M27/F27 -> 0.063380282
A28: Overall | B28: 361553 | C28: 363682.74 | D28: =B28-C28 -> -2129.744 | E28: =C28/B28 -> 1.0058905 | F28: 794 | G28: 544 | H28: =G28/F28 -> 0.68513854 | I28: 12371693 | J28: =I28*$J$14 -> 61858.465 | K28: 58590 | L28: =K28/J28 -> 0.9471622 | M28: 57 | N28: =M28/F28 -> 0.071788413
G30: Remark
A31: PL1 | B31: 14 | C31: 1 | D31: =C31/B31 -> 0.071428571 | E31: -0.022 | F31: 1 | G31: demotion
A32: PL2 | B32: 47 | C32: 6 | D32: =C32/B32 -> 0.12765957 | E32: 0.02016 | F32: 5 | G32: 1 new comer, 4 newly promoted
A33: PL3 | B33: 482 | C33: 305 | D33: =C33/B33 -> 0.63278008 | E33: 0.029135082 | F33: 305
A34: PL4 | B34: 170 | C34: 163 | D34: =C34/B34 -> 0.95882353 | E34: 0.054025153 | F34: 163
A35: PL5 | B35: 75 | C35: 67 | D35: =C35/B35 -> 0.89333333 | E35: 0.083274627 | F35: 67
A36: Overall | B36: 6 | C36: 2 | D36: =C36/B36 -> 0.33333333 | E36: 0.06545 | F36: 2
B37: 794 | C37: 544 | D37: =C37/B37 -> 0.68513854 | E37: 0.043243831 | F37: 543
A38: Band A | B38: 607 | C38: 398 | D38: =C38/B38 -> 0.65568369 | E38: 0.044312312
A39: Band B | B39: 138 | C39: 109 | D39: =C39/B39 -> 0.78985507 | E39: 0.039050459
A40: Band C | B40: 42 | C40: 34 | D40: =C40/B40 -> 0.80952381 | E40: 0.040932353
A41: Band D | B41: 7 | C41: 3 | D41: =C41/B41 -> 0.42857143 | E41: 0.0672 | G41: due to a great porportion of Band D below CR85%
A42: Overall | B42: 794 | C42: 544 | D42: =C42/B42 -> 0.68513854 | E42: 0.043172978

Sheet 数据透视
A3: Adjusted basic increase/decreased % by DH | B3: (多项)
A5: 行标签 | B5: 平均值项:Adjusted basic increase/decreased % by DH | C5: 计数项:Pers.no. | D5: 求和项: Basic salary
A6: 1 | B6: -0.022 | C6: 1 | D6: 8937
A7: 2 | B7: 0.02016 | C7: 5 | D7: 74430
A8: 3 | B8: 0.029135082 | C8: 305 | D8: 4773822
A9: 4 | B9: 0.054025153 | C9: 163 | D9: 2641918
A10: 5 | B10: 0.083274627 | C10: 67 | D10: 1314375
A11: NA | B11: 0.06545 | C11: 2 | D11: 13420
A12: 总计 | B12: 0.043243831 | C12: 543 | D12: 8826902

Sheet 白领
A1: Company code | B1: Pers.no. | C1: Subgroup | D1: Area | E1: Subarea | F1: Dept. | G1: Cost ctr | H1: Join date | I1: Job | J1: Position | K1: Band Level | L1: Workplan type | M1: 2025 Performance Level | N1: Basic salary | O1: ① Merit increase % | P1: Merit Increase amount | Q1: ② Equity Increase% | R1: Equity Increase amount | S1: Total recommended Increase % (①+②) | T1: Total Recommended Increase amount | U1: Recommended new basic salary | V1: Adjutsed basic salary (input by DH) | W1: Adjutsed increased/decreased basic salary by DH | X1: Adjusted basic increase/decreased % by DH | Y1: Adjustment range reference | Z1: Promotion or demotion | AA1: New position title | AB1: New band | AC1: ③ Promotion increase/Demotion decrease % (±5%-±20%) | AD1: Promotion increase/Demotion decrease amount | AE1: Final new basic salary | AF1: Final increase/decrease amount | AG1: Final increase/decrease rate | AH1: Pay months | AI1: Monthly allowance/bonus | AJ1: Monthly Car Allowance | AK1: Other income(e.g.:festival bonus) | AL1: Annual target cash | AM1: 2024 Performance Level | AN1: Disciplinary Records | AO1: Justifications by DH | AP1: HR Remark | AQ1: Responsible ASR Manager | AR1: Responsible ASR HRBP | AS1: PY | AT1: 85% of LMW (for Technician/Counsellor) | AU1: Editable column 1 | AV1: Editable column 2 | AW1: - | AX1: Service Year | AY1: CR | AZ1: BSH CR | BA1: Dept CR
A2: CN15 | B2: 15000447 | C2: Indirect Active | D2: OP | E2: SNa | F2: FCGNa-VVP | G2: 330404 | H2: 38808 | I2: Workshop Leader | J2: Head of FCGNa-VVP | K2: BAND A6 | L2: 2 | M2: 5 | N2: 15840 | O2: 0.05 | P2: =ROUND(N2*O2,0) -> 792 | Q2: 0 | R2: =ROUND(N2*Q2,0) -> 0 | S2: =T2/N2 -> 0.05 | T2: =P2+R2 -> 792 | U2: =N2+T2 -> 16632 | V2: 16780 | W2: =V2-N2 -> 940 | X2: =ROUND(V2/N2-1,4) -> 0.0593 | Y2: =IF(OR(L2=1,L2=2,L2=4), TEXT(S2*0.8,"0.00%") & "-" & TEXT(S2*1.2,"0.00%"), IF(OR(L2=3,L2=6), TEXT(0,"0.00%") & "-" & TEXT(7%*1.2,"0.00%"), IF(OR(L2=5,L2=7), TEXT((R2/N2),"0.00%") & "-" & TEXT((R2/N2)+7%,"0.00%"), "" ) ) ) -> 4.00%-6.00% | AD2: =ROUND(N2*AC2,0) -> 0 | AE2: =V2+AD2 -> 16780 | AF2: =AE2-N2 -> 940 | AG2: =AE2/N2-1 -> 0.059343434 | AH2: 14 | AI2: 450 | AK2: 688 | AL2: =AE2*AH2+AI2*12+AK2+IF(AB2="",AJ2,IF(AB2="D",5000,IF(AB2="C",1000,0)))*12 -> 241008 | AM2: 4 | AQ2: Miao Siyuan（15005811） | AR2: Zhu Qianqian（11016705） | AS2: Zhao Chujun | AW2: =_xlfn.LET(_xlpm.actual,X2,_xlpm.low,VALUE(_xlfn.TEXTBEFORE(Y2,"-")),_xlpm.high,VALUE(_xlfn.TEXTAFTER(Y2,"-")),IF(AND(_xlpm.actual=0,OR(_xlpm.low<>0,_xlpm.high<>0)),"0 increase",IF(_xlpm.actual>_xlpm.high*1.2,">20",IF(_xlpm.actual<_xlpm.low*0.8,"<20","OK")))) -> OK | AX2: 16-20 | AY2: 70-90
A3: CN15 | B3: 15014416 | C3: Indirect Active | D3: OP | E3: SNa | F3: FCGNa-VVE | G3: 330404 | H3: 45063 | I3: Supervisor | J3: Head of Engineering Ventilation | K3: BAND A6 | L3: 2 | M3: 4 | N3: 16456 | O3: 0.045 | P3: =ROUND(N3*O3,0) -> 741 | Q3: 0.0155 | R3: =ROUND(N3*Q3,0) -> 255 | S3: =T3/N3 -> 0.060525036 | T3: =P3+R3 -> 996 | U3: =N3+T3 -> 17452 | V3: 17456 | W3: =V3-N3 -> 1000 | X3: =ROUND(V3/N3-1,4) -> 0.0608 | Y3: =IF(OR(L3=1,L3=2,L3=4), TEXT(S3*0.8,"0.00%") & "-" & TEXT(S3*1.2,"0.00%"), IF(OR(L3=3,L3=6), TEXT(0,"0.00%") & "-" & TEXT(7%*1.2,"0.00%"), IF(OR(L3=5,L3=7), TEXT((R3/N3),"0.00%") & "-" & TEXT((R3/N3)+7%,"0.00%"), "" ) ) ) -> 4.84%-7.26% | AD3: =ROUND(N3*AC3,0) -> 0 | AE3: =V3+AD3 -> 17456 | AF3: =AE3-N3 -> 1000 | AG3: =AE3/N3-1 -> 0.060768109 | AH3: 14 | AI3: 450 | AK3: 688 | AL3: =AE3*AH3+AI3*12+AK3+IF(AB3="",AJ3,IF(AB3="D",5000,IF(AB3="C",1000,0)))*12 -> 250472 | AM3: 5 | AQ3: Miao Siyuan（15005811） | AR3: Zhu Qianqian（11016705） | AS3: Zhao Chujun | AW3: =_xlfn.LET(_xlpm.actual,X3,_xlpm.low,VALUE(_xlfn.TEXTBEFORE(Y3,"-")),_xlpm.high,VALUE(_xlfn.TEXTAFTER(Y3,"-")),IF(AND(_xlpm.actual=0,OR(_xlpm.low<>0,_xlpm.high<>0)),"0 increase",IF(_xlpm.actual>_xlpm.high*1.2,">20",IF(_xlpm.actual<_xlpm.low*0.8,"<20","OK")))) -> OK | AX3: 0-5 | AY3: 50-70
A4: CN15 | B4: 15014868 | C4: Indirect Active | D4: OP | E4: SNa | F4: FCGNa-VVE | G4: 330404 | H4: 42291 | I4: Project Manager | J4: Project Manager | K4: BAND A6 | L4: 2 | M4: 3 | N4: 13630 | O4: 0.03 | P4: =ROUND(N4*O4,0) -> 409 | Q4: 0 | R4: =ROUND(N4*Q4,0) -> 0 | S4: =T4/N4 -> 0.030007337 | T4: =P4+R4 -> 409 | U4: =N4+T4 -> 14039 | V4: 14038 | W4: =V4-N4 -> 408 | X4: =ROUND(V4/N4-1,4) -> 0.0299 | Y4: =IF(OR(L4=1,L4=2,L4=4), TEXT(S4*0.8,"0.00%") & "-" & TEXT(S4*1.2,"0.00%"), IF(OR(L4=3,L4=6), TEXT(0,"0.00%") & "-" & TEXT(7%*1.2,"0.00%"), IF(OR(L4=5,L4=7), TEXT((R4/N4),"0.00%") & "-" & TEXT((R4/N4)+7%,"0.00%"), "" ) ) ) -> 2.40%-3.60% | AD4: =ROUND(N4*AC4,0) -> 0 | AE4: =V4+AD4 -> 14038 | AF4: =AE4-N4 -> 408 | AG4: =AE4/N4-1 -> 0.029933969 | AH4: 14 | AI4: 450 | AK4: 688 | AL4: =AE4*AH4+AI4*12+AK4+IF(AB4="",AJ4,IF(AB4="D",5000,IF(AB4="C",1000,0)))*12 -> 202620 | AM4: 4 | AQ4: Miao Siyuan（15005811） | AR4: Zhu Qianqian（11016705） | AS4: Zhao Chujun | AW4: =_xlfn.LET(_xlpm.actual,X4,_xlpm.low,VALUE(_xlfn.TEXTBEFORE(Y4,"-")),_xlpm.high,VALUE(_xlfn.TEXTAFTER(Y4,"-")),IF(AND(_xlpm.actual=0,OR(_xlpm.low<>0,_xlpm.high<>0)),"0 increase",IF(_xlpm.actual>_xlpm.high*1.2,">20",IF(_xlpm.actual<_xlpm.low*0.8,"<20","OK")))) -> OK | AX4: 6-10 | AY4: 50-70
A5: CN15 | B5: 15022166 | C5: Indirect Active | D5: OP | E5: SNa | F5: FCGNa-VVE | G5: 330404 | H5: 44664 | I5: Senior Engineer | J5: Senior Electrical Engineer | K5: BAND A5 | L5: 2 | M5: 4 | N5: 14440 | O5: 0.0375 | P5: =ROUND(N5*O5,0) -> 542 | Q5: 0 | R5: =ROUND(N5*Q5,0) -> 0 | S5: =T5/N5 -> 0.037534626 | T5: =P5+R5 -> 542 | U5: =N5+T5 -> 14982 | V5: 15000 | W5: =V5-N5 -> 560 | X5: =ROUND(V5/N5-1,4) -> 0.0388 | Y5: =IF(OR(L5=1,L5=2,L5=4), TEXT(S5*0.8,"0.00%") & "-" & TEXT(S5*1.2,"0.00%"), IF(OR(L5=3,L5=6), TEXT(0,"0.00%") & "-" & TEXT(7%*1.2,"0.00%"), IF(OR(L5=5,L5=7), TEXT((R5/N5),"0.00%") & "-" & TEXT((R5/N5)+7%,"0.00%"), "" ) ) ) -> 3.00%-4.50% | AD5: =ROUND(N5*AC5,0) -> 0 | AE5: =V5+AD5 -> 15000 | AF5: =AE5-N5 -> 560 | AG5: =AE5/N5-1 -> 0.038781163 | AH5: 14 | AI5: 450 | AK5: 688 | AL5: =AE5*AH5+AI5*12+AK5+IF(AB5="",AJ5,IF(AB5="D",5000,IF(AB5="C",1000,0)))*12 -> 216088 | AM5: 2 | AQ5: Miao Siyuan（15005811） | AR5: Zhu Qianqian（11016705） | AS5: Zhao Chujun | AW5: =_xlfn.LET(_xlpm.actual,X5,_xlpm.low,VALUE(_xlfn.TEXTBEFORE(Y5,"-")),_xlpm.high,VALUE(_xlfn.TEXTAFTER(Y5,"-")),IF(AND(_xlpm.actual=0,OR(_xlpm.low<>0,_xlpm.high<>0)),"0 increase",IF(_xlpm.actual>_xlpm.high*1.2,">20",IF(_xlpm.actual<_xlpm.low*0.8,"<20","OK")))) -> OK | AX5: 0-5 | AY5: 70-90
A6: CN15 | B6: 15016337 | C6: Indirect Active | D6: OP | E6: SNa | F6: FCGNa-VVE | G6: 330404 | H6: 42795 | I6: Functional Specialist | J6: Functional Specialist | K6: BAND A6 | L6: 2 | M6: 3 | N6: 14284 | O6: 0.03 | P6: =ROUND(N6*O6,0) -> 429 | Q6: 0 | R6: =ROUND(N6*Q6,0) -> 0 | S6: =T6/N6 -> 0.030033604 | T6: =P6+R6 -> 429 | U6: =N6+T6 -> 14713 | V6: 14688 | W6: =V6-N6 -> 404 | X6: =ROUND(V6/N6-1,4) -> 0.0283 | Y6: =IF(OR(L6=1,L6=2,L6=4), TEXT(S6*0.8,"0.00%") & "-" & TEXT(S6*1.2,"0.00%"), IF(OR(L6=3,L6=6), TEXT(0,"0.00%") & "-" & TEXT(7%*1.2,"0.00%"), IF(OR(L6=5,L6=7), TEXT((R6/N6),"0.00%") & "-" & TEXT((R6/N6)+7%,"0.00%"), "" ) ) ) -> 2.40%-3.60% | AD6: =ROUND(N6*AC6,0) -> 0 | AE6: =V6+AD6 -> 14688 | AF6: =AE6-N6 -> 404 | AG6: =AE6/N6-1 -> 0.028283394 | AH6: 14 | AI6: 450 | AK6: 688 | AL6: =AE6*AH6+AI6*12+AK6+IF(AB6="",AJ6,IF(AB6="D",5000,IF(AB6="C",1000,0)))*12 -> 211720 | AM6: 2 | AQ6: Miao Siyuan（15005811） | AR6: Zhu Qianqian（11016705） | AS6: Zhao Chujun | AW6: =_xlfn.LET(_xlpm.actual,X6,_xlpm.low,VALUE(_xlfn.TEXTBEFORE(Y6,"-")),_xlpm.high,VALUE(_xlfn.TEXTAFTER(Y6,"-")),IF(AND(_xlpm.actual=0,OR(_xlpm.low<>0,_xlpm.high<>0)),"0 increase",IF(_xlpm.actual>_xlpm.high*1.2,">20",IF(_xlpm.actual<_xlpm.low*0.8,"<20","OK")))) -> OK | AX6: 6-10 | AY6: 50-70
A7: CN15 | B7: 15022630 | C7: Indirect Active | D7: OP | E7: SNa | F7: FCGNa-VVE | G7: 330408 | H7: 45854 | I7: Functional Specialist | J7: Painting Functional Specialist | K7: BAND A6 | L7: 2 | M7: 3 | N7: 23000 | O7: 0 | P7: =ROUND(N7*O7,0) -> 0 | Q7: 0 | R7: =ROUND(N7*Q7,0) -> 0 | S7: =T7/N7 -> 0 | T7: =P7+R7 -> 0 | U7: =N7+T7 -> 23000 | V7: 23000 | W7: =V7-N7 -> 0 | X7: =ROUND(V7/N7-1,4) -> 0 | Y7: =IF(OR(L7=1,L7=2,L7=4), TEXT(S7*0.8,"0.00%") & "-" & TEXT(S7*1.2,"0.00%"), IF(OR(L7=3,L7=6), TEXT(0,"0.00%") & "-" & TEXT(7%*1.2,"0.00%"), IF(OR(L7=5,L7=7), TEXT((R7/N7),"0.00%") & "-" & TEXT((R7/N7)+7%,"0.00%"), "" ) ) ) -> 0.00%-0.00% | AD7: =ROUND(N7*AC7,0) -> 0 | AE7: =V7+AD7 -> 23000 | AF7: =AE7-N7 -> 0 | AG7: =AE7/N7-1 -> 0 | AH7: 14 | AI7: 450 | AK7: 688 | AL7: =AE7*AH7+AI7*12+AK7+IF(AB7="",AJ7,IF(AB7="D",5000,IF(AB7="C",1000,0)))*12 -> 328088 | AM7: #N/A | AQ7: Miao Siyuan（15005811） | AR7: Zhu Qianqian（11016705） | AS7: Zhao Chujun | AW7: =_xlfn.LET(_xlpm.actual,X7,_xlpm.low,VALUE(_xlfn.TEXTBEFORE(Y7,"-")),_xlpm.high,VALUE(_xlfn.TEXTAFTER(Y7,"-")),IF(AND(_xlpm.actual=0,OR(_xlpm.low<>0,_xlpm.high<>0)),"0 increase",IF(_xlpm.actual>_xlpm.high*1.2,">20",IF(_xlpm.actual<_xlpm.low*0.8,"<20","OK")))) -> OK | AX7: 0-5 | AY7: >90
A8: CN15 | B8: 15007556 | C8: Indirect Active | D8: OP | E8: SNa | F8: FCGNa-VVM | G8: 330204 | H8: 40962 | I8: Supervisor | J8: Head of FCGNa-VVM | K8: BAND A6 | L8: 2 | M8: 3 | N8: 16100 | O8: 0.025 | P8: =ROUND(N8*O8,0) -> 403 | Q8: 0 | R8: =ROUND(N8*Q8,0) -> 0 | S8: =T8/N8 -> 0.025031056 | T8: =P8+R8 -> 403 | U8: =N8+T8 -> 16503 | V8: 16518 | W8: =V8-N8 -> 418 | X8: =ROUND(V8/N8-1,4) -> 0.026 | Y8: =IF(OR(L8=1,L8=2,L8=4), TEXT(S8*0.8,"0.00%") & "-" & TEXT(S8*1.2,"0.00%"), IF(OR(L8=3,L8=6), TEXT(0,"0.00%") & "-" & TEXT(7%*1.2,"0.00%"), IF(OR(L8=5,L8=7), TEXT((R8/N8),"0.00%") & "-" & TEXT((R8/N8)+7%,"0.00%"), "" ) ) ) -> 2.00%-3.00% | AD8: =ROUND(N8*AC8,0) -> 0 | AE8: =V8+AD8 -> 16518 | AF8: =AE8-N8 -> 418 | AG8: =AE8/N8-1 -> 0.025962733 | AH8: 14 | AI8: 450 | AK8: 688 | AL8: =AE8*AH8+AI8*12+AK8+IF(AB8="",AJ8,IF(AB8="D",5000,IF(AB8="C",1000,0)))*12 -> 237340 | AM8: 3 | AQ8: Miao Siyuan（15005811） | AR8: Zhu Qianqian（11016705） | AS8: Zhao Chujun | AW8: =_xlfn.LET(_xlpm.actual,X8,_xlpm.low,VALUE(_xlfn.TEXTBEFORE(Y8,"-")),_xlpm.high,VALUE(_xlfn.TEXTAFTER(Y8,"-")),IF(AND(_xlpm.actual=0,OR(_xlpm.low<>0,_xlpm.high<>0)),"0 increase",IF(_xlpm.actual>_xlpm.high*1.2,">20",IF(_xlpm.actual<_xlpm.low*0.8,"<20","OK")))) -> OK | AX8: 11-15 | AY8: 70-90
A9: CN15 | B9: 1120246 | C9: Indirect Active | D9: OP | E9: SNa | F9: FCGNa-VVE | G9: 330404 | H9: 43864 | I9: Functional Specialist | J9: Functional Specialist | K9: BAND A6 | L9: 2 | M9: 4 | N9: 13111 | O9: 0.045 | P9: =ROUND(N9*O9,0) -> 590 | Q9: 0.0421 | R9: =ROUND(N9*Q9,0) -> 552 | S9: =T9/N9 -> 0.087102433 | T9: =P9+R9 -> 1142 | U9: =N9+T9 -> 14253 | V9: 14066 | W9: =V9-N9 -> 955 | X9: =ROUND(V9/N9-1,4) -> 0.0728 | Y9: =IF(OR(L9=1,L9=2,L9=4), TEXT(S9*0.8,"0.00%") & "-" & TEXT(S9*1.2,"0.00%"), IF(OR(L9=3,L9=6), TEXT(0,"0.00%") & "-" & TEXT(7%*1.2,"0.00%"), IF(OR(L9=5,L9=7), TEXT((R9/N9),"0.00%") & "-" & TEXT((R9/N9)+7%,"0.00%"), "" ) ) ) -> 6.97%-10.45% | AD9: =ROUND(N9*AC9,0) -> 0 | AE9: =V9+AD9 -> 14066 | AF9: =AE9-N9 -> 955 | AG9: =AE9/N9-1 -> 0.0728396 | AH9: 14 | AI9: 850 | AK9: 688 | AL9: =AE9*AH9+AI9*12+AK9+IF(AB9="",AJ9,IF(AB9="D",5000,IF(AB9="C",1000,0)))*12 -> 207812 | AM9: 3 | AQ9: Miao Siyuan（15005811） | AR9: Zhu Qianqian（11016705） | AS9: Zhao Chujun | AW9: =_xlfn.LET(_xlpm.actual,X9,_xlpm.low,VALUE(_xlfn.TEXTBEFORE(Y9,"-")),_xlpm.high,VALUE(_xlfn.TEXTAFTER(Y9,"-")),IF(AND(_xlpm.actual=0,OR(_xlpm.low<>0,_xlpm.high<>0)),"0 increase",IF(_xlpm.actual>_xlpm.high*1.2,">20",IF(_xlpm.actual<_xlpm.low*0.8,"<20","OK")))) -> OK | AX9: 6-10 | AY9: 50-70
A10: CN15 | B10: 15000219 | C10: Indirect Active | D10: OP | E10: SNa | F10: FCGNa-VVE | G10: 330404 | H10: 38608 | I10: Engineer | J10: Project Engineer | K10: BAND A4 | L10: 2 | M10: 2 | N10: 12256 | O10: 0 | P10: =ROUND(N10*O10,0) -> 0 | Q10: 0 | R10: =ROUND(N10*Q10,0) -> 0 | S10: =T10/N10 -> 0 | T10: =P10+R10 -> 0 | U10: =N10+T10 -> 12256 | V10: 12256 | W10: =V10-N10 -> 0 | X10: =ROUND(V10/N10-1,4) -> 0 | Y10: =IF(OR(L10=1,L10=2,L10=4), TEXT(S10*0.8,"0.00%") & "-" & TEXT(S10*1.2,"0.00%"), IF(OR(L10=3,L10=6), TEXT(0,"0.00%") & "-" & TEXT(7%*1.2,"0.00%"), IF(OR(L10=5,L10=7), TEXT((R10/N10),"0.00%") & "-" & TEXT((R10/N10)+7%,"0.00%"), "" ) ) ) -> 0.00%-0.00% | AD10: =ROUND(N10*AC10,0) -> 0 | AE10: =V10+AD10 -> 12256 | AF10: =AE10-N10 -> 0 | AG10: =AE10/N10-1 -> 0 | AH10: 14 | AI10: 450 | AK10: 688 | AL10: =AE10*AH10+AI10*12+AK10+IF(AB10="",AJ10,IF(AB10="D",5000,IF(AB10="C",1000,0)))*12 -> 177672 | AM10: 3 | AQ10: Miao Siyuan（15005811） | AR10: Zhu Qianqian（11016705） | AS10: Zhao Chujun | AW10: =_xlfn.LET(_xlpm.actual,X10,_xlpm.low,VALUE(_xlfn.TEXTBEFORE(Y10,"-")),_xlpm.high,VALUE(_xlfn.TEXTAFTER(Y10,"-")),IF(AND(_xlpm.actual=0,OR(_xlpm.low<>0,_xlpm.high<>0)),"0 increase",IF(_xlpm.actual>_xlpm.high*1.2,">20",IF(_xlpm.actual<_xlpm.low*0.8,"<20","OK")))) -> OK | AX10: 16-20 | AY10: 0
A11: CN15 | B11: 15014810 | C11: Indirect Active | D11: OP | E11: SNa | F11: FCGNa-VVE | G11: 330404 | H11: 42248 | I11: Senior Specialist | J11: Senior IE Specialist | K11: BAND A5 | L11: 2 | M11: 4 | N11: 11666 | O11: 0.0375 | P11: =ROUND(N11*O11,0) -> 437 | Q11: 0.0155 | R11: =ROUND(N11*Q11,0) -> 181 | S11: =T11/N11 -> 0.052974456 | T11: =P11+R11 -> 618 | U11: =N11+T11 -> 12284 | V11: 12312 | W11: =V11-N11 -> 646 | X11: =ROUND(V11/N11-1,4) -> 0.0554 | Y11: =IF(OR(L11=1,L11=2,L11=4), TEXT(S11*0.8,"0.00%") & "-" & TEXT(S11*1.2,"0.00%"), IF(OR(L11=3,L11=6), TEXT(0,"0.00%") & "-" & TEXT(7%*1.2,"0.00%"), IF(OR(L11=5,L11=7), TEXT((R11/N11),"0.00%") & "-" & TEXT((R11/N11)+7%,"0.00%"), "" ) ) ) -> 4.24%-6.36% | Z11: Promotion | AA11: Function specialist | AB11: A6 | AC11: 0.0646 | AD11: =ROUND(N11*AC11,0) -> 754 | AE11: =V11+AD11 -> 13066 | AF11: =AE11-N11 -> 1400 | AG11: =AE11/N11-1 -> 0.12000686 | AH11: 14 | AI11: 550 | AK11: 688 | AL11: =AE11*AH11+AI11*12+AK11+IF(AB11="",AJ11,IF(AB11="D",5000,IF(AB11="C",1000,0)))*12 -> 190212 | AM11: 4 | AO11: Good performance and high competence | AP11: Good performance and high competence | AQ11: Miao Siyuan（15005811） | AR11: Zhu Qianqian（11016705） | AS11: Zhao Chujun | AW11: =_xlfn.LET(_xlpm.actual,X11,_xlpm.low,VALUE(_xlfn.TEXTBEFORE(Y11,"-")),_xlpm.high,VALUE(_xlfn.TEXTAFTER(Y11,"-")),IF(AND(_xlpm.actual=0,OR(_xlpm.low<>0,_xlpm.high<>0)),"0 increase",IF(_xlpm.actual>_xlpm.high*1.2,">20",IF(_xlpm.actual<_xlpm.low*0.8,"<20","OK")))) -> OK | AX11: 6-10 | AY11: 70-90
A12: CN15 | B12: 15000226 | C12: Indirect Active | D12: OP | E12: SNa | F12: FCGNa-VCP | G12: 330405 | H12: 38614 | I12: Workshop Leader | J12: Head of FCGNa-VCP | K12: BAND A6 | L12: 2 | M12: 3 | N12: 15800 | O12: 0.025 | P12: =ROUND(N12*O12,0) -> 395 | Q12: 0 | R12: =ROUND(N12*Q12,0) -> 0 | S12: =T12/N12 -> 0.025 | T12: =P12+R12 -> 395 | U12: =N12+T12 -> 16195 | V12: 16272 | W12: =V12-N12 -> 472 | X12: =ROUND(V12/N12-1,4) -> 0.0299 | Y12: =IF(OR(L12=1,L12=2,L12=4), TEXT(S12*0.8,"0.00%") & "-" & TEXT(S12*1.2,"0.00%"), IF(OR(L12=3,L12=6), TEXT(0,"0.00%") & "-" & TEXT(7%*1.2,"0.00%"), IF(OR(L12=5,L12=7), TEXT((R12/N12),"0.00%") & "-" & TEXT((R12/N12)+7%,"0.00%"), "" ) ) ) -> 2.00%-3.00% | AD12: =ROUND(N12*AC12,0) -> 0 | AE12: =V12+AD12 -> 16272 | AF12: =AE12-N12 -> 472 | AG12: =AE12/N12-1 -> 0.029873418 | AH12: 14 | AI12: 450 | AK12: 688 | AL12: =AE12*AH12+AI12*12+AK12+IF(AB12="",AJ12,IF(AB12="D",5000,IF(AB12="C",1000,0)))*12 -> 233896 | AM12: 5 | AQ12: Liu Haigang（15013255） | AR12: Zhu Qianqian（11016705） | AS12: Zhao Chujun | AW12: =_xlfn.LET(_xlpm.actual,X12,_xlpm.low,VALUE(_xlfn.TEXTBEFORE(Y12,"-")),_xlpm.high,VALUE(_xlfn.TEXTAFTER(Y12,"-")),IF(AND(_xlpm.actual=0,OR(_xlpm.low<>0,_xlpm.high<>0)),"0 increase",IF(_xlpm.actual>_xlpm.high*1.2,">20",IF(_xlpm.actual<_xlpm.low*0.8,"<20","OK")))) -> OK | AX12: 16-20 | AY12: 70-90
A13: CN15 | B13: 15000166 | C13: Indirect Active | D13: OP | E13: SNa | F13: FCGNa-VCE | G13: 330405 | H13: 38600 | I13: Senior Engineer | J13: Senior Engineer | K13: BAND A5 | L13: 2 | M13: 3 | N13: 14610 | O13: 0.025 | P13: =ROUND(N13*O13,0) -> 365 | Q13: 0 | R13: =ROUND(N13*Q13,0) -> 0 | S13: =T13/N13 -> 0.024982888 | T13: =P13+R13 -> 365 | U13: =N13+T13 -> 14975 | V13: 14610 | W13: =V13-N13 -> 0 | X13: =ROUND(V13/N13-1,4) -> 0 | Y13: =IF(OR(L13=1,L13=2,L13=4), TEXT(S13*0.8,"0.00%") & "-" & TEXT(S13*1.2,"0.00%"), IF(OR(L13=3,L13=6), TEXT(0,"0.00%") & "-" & TEXT(7%*1.2,"0.00%"), IF(OR(L13=5,L13=7), TEXT((R13/N13),"0.00%") & "-" & TEXT((R13/N13)+7%,"0.00%"), "" ) ) ) -> 2.00%-3.00% | AD13: =ROUND(N13*AC13,0) -> 0 | AE13: =V13+AD13 -> 14610 | AF13: =AE13-N13 -> 0 | AG13: =AE13/N13-1 -> 0 | AH13: 14 | AI13: 450 | AK13: 688 | AL13: =AE13*AH13+AI13*12+AK13+IF(AB13="",AJ13,IF(AB13="D",5000,IF(AB13="C",1000,0)))*12 -> 210628 | AM13: 3 | AO13: Only focus on route tasks, lack of innovation and new product maturity improvement | AP13: Less responsibility compare with job level | AQ13: Liu Haigang（15013255） | AR13: Zhu Qianqian（11016705） | AS13: Zhao Chujun | AU13: recommend increasing but propose zero increase | AW13: =_xlfn.LET(_xlpm.actual,X13,_xlpm.low,VALUE(_xlfn.TEXTBEFORE(Y13,"-")),_xlpm.high,VALUE(_xlfn.TEXTAFTER(Y13,"-")),IF(AND(_xlpm.actual=0,OR(_xlpm.low<>0,_xlpm.high<>0)),"0 increase",IF(_xlpm.actual>_xlpm.high*1.2,">20",IF(_xlpm.actual<_xlpm.low*0.8,"<20","OK")))) -> 0 increase | AX13: 16-20 | AY13: 70-90
A14: CN15 | B14: 15007522 | C14: Indirect Active | D14: OP | E14: SNa | F14: FCGNa-VCE | G14: 330405 | H14: 41091 | I14: Supervisor | J14: Head of FCGNa-VCE | K14: BAND A6 | L14: 2 | M14: 3 | N14: 13100 | O14: 0.03 | P14: =ROUND(N14*O14,0) -> 393 | Q14: 0 | R14: =ROUND(N14*Q14,0) -> 0 | S14: =T14/N14 -> 0.03 | T14: =P14+R14 -> 393 | U14: =N14+T14 -> 13493 | V14: 14312 | W14: =V14-N14 -> 1212 | X14: =ROUND(V14/N14-1,4) -> 0.0925 | Y14: =IF(OR(L14=1,L14=2,L14=4), TEXT(S14*0.8,"0.00%") & "-" & TEXT(S14*1.2,"0.00%"), IF(OR(L14=3,L14=6), TEXT(0,"0.00%") & "-" & TEXT(7%*1.2,"0.00%"), IF(OR(L14=5,L14=7), TEXT((R14/N14),"0.00%") & "-" & TEXT((R14/N14)+7%,"0.00%"), "" ) ) ) -> 2.40%-3.60% | AD14: =ROUND(N14*AC14,0) -> 0 | AE14: =V14+AD14 -> 14312 | AF14: =AE14-N14 -> 1212 | AG14: =AE14/N14-1 -> 0.092519084 | AH14: 14 | AI14: 450 | AK14: 688 | AL14: =AE14*AH14+AI14*12+AK14+IF(AB14="",AJ14,IF(AB14="D",5000,IF(AB14="C",1000,0)))*12 -> 206456 | AM14: 2 | AO14: 1. In 2025, he achieved an 11% reduction in cooker SPC and cut silicone usage by 50%. 2. As a supervisor, his salary is the lowest in the team, so I need to catch up appropriately. | AP14: Good performers with relatively lower salary | AQ14: Liu Haigang（15013255） | AR14: Zhu Qianqian（11016705） | AS14: Zhao Chujun | AU14: exceed +/-20% adjustment | AV14: >20 | AW14: =_xlfn.LET(_xlpm.actual,X14,_xlpm.low,VALUE(_xlfn.TEXTBEFORE(Y14,"-")),_xlpm.high,VALUE(_xlfn.TEXTAFTER(Y14,"-")),IF(AND(_xlpm.actual=0,OR(_xlpm.low<>0,_xlpm.high<>0)),"0 increase",IF(_xlpm.actual>_xlpm.high*1.2,">20",IF(_xlpm.actual<_xlpm.low*0.8,"<20","OK")))) -> >20 | AX14: 11-15 | AY14: 50-70
A15: CN15 | B15: 15001471 | C15: Indirect Active | D15: OP | E15: SNa | F15: FCGNa-VCM | G15: 330405 | H15: 39546 | I15: Supervisor | J15: Head of FCGNa-VCM | K15: BAND A6 | L15: 2 | M15: 3 | N15: 15326 | O15: 0.03 | P15: =ROUND(N15*O15,0) -> 460 | Q15: 0 | R15: =ROUND(N15*Q15,0) -> 0 | S15: =T15/N15 -> 0.030014355 | T15: =P15+R15 -> 460 | U15: =N15+T15 -> 15786 | V15: 15326 | W15: =V15-N15 -> 0 | X15: =ROUND(V15/N15-1,4) -> 0 | Y15: =IF(OR(L15=1,L15=2,L15=4), TEXT(S15*0.8,"0.00%") & "-" & TEXT(S15*1.2,"0.00%"), IF(OR(L15=3,L15=6), TEXT(0,"0.00%") & "-" & TEXT(7%*1.2,"0.00%"), IF(OR(L15=5,L15=7), TEXT((R15/N15),"0.00%") & "-" & TEXT((R15/N15)+7%,"0.00%"), "" ) ) ) -> 2.40%-3.60% | AD15: =ROUND(N15*AC15,0) -> 0 | AE15: =V15+AD15 -> 15326 | AF15: =AE15-N15 -> 0 | AG15: =AE15/N15-1 -> 0 | AH15: 14 | AI15: 450 | AK15: 688 | AL15: =AE15*AH15+AI15*12+AK15+IF(AB15="",AJ15,IF(AB15="D",5000,IF(AB15="C",1000,0)))*12 -> 220652 | AM15: 4 | AO15: Low performance as supervisor | AP15: Low performer | AQ15: Liu Haigang（15013255） | AR15: Zhu Qianqian（11016705） | AS15: Zhao Chujun | AU15: recommend increasing but propose zero increase | AW15: =_xlfn.LET(_xlpm.actual,X15,_xlpm.low,VALUE(_xlfn.TEXTBEFORE(Y15,"-")),_xlpm.high,VALUE(_xlfn.TEXTAFTER(Y15,"-")),IF(AND(_xlpm.actual=0,OR(_xlpm.low<>0,_xlpm.high<>0)),"0 increase",IF(_xlpm.actual>_xlpm.high*1.2,">20",IF(_xlpm.actual<_xlpm.low*0.8,"<20","OK")))) -> 0 increase | AX15: 16-20 | AY15: 50-70
A16: CN15 | B16: 15022189 | C16: Indirect Active | D16: OP | E16: SNa | F16: FCGNa-VCE | G16: 330401 | H16: 44713 | I16: Senior Engineer | J16: Press Senior Engineer | K16: BAND A5 | L16: 2 | M16: 3 | N16: 14850 | O16: 0.025 | P16: =ROUND(N16*O16,0) -> 371 | Q16: 0 | R16: =ROUND(N16*Q16,0) -> 0 | S16: =T16/N16 -> 0.024983165 | T16: =P16+R16 -> 371 | U16: =N16+T16 -> 15221 | V16: 15150 | W16: =V16-N16 -> 300 | X16: =ROUND(V16/N16-1,4) -> 0.0202 | Y16: =IF(OR(L16=1,L16=2,L16=4), TEXT(S16*0.8,"0.00%") & "-" & TEXT(S16*1.2,"0.00%"), IF(OR(L16=3,L16=6), TEXT(0,"0.00%") & "-" & TEXT(7%*1.2,"0.00%"), IF(OR(L16=5,L16=7), TEXT((R16/N16),"0.00%") & "-" & TEXT((R16/N16)+7%,"0.00%"), "" ) ) ) -> 2.00%-3.00% | AD16: =ROUND(N16*AC16,0) -> 0 | AE16: =V16+AD16 -> 15150 | AF16: =AE16-N16 -> 300 | AG16: =AE16/N16-1 -> 0.02020202 | AH16: 14 | AI16: 450 | AK16: 688 | AL16: =AE16*AH16+AI16*12+AK16+IF(AB16="",AJ16,IF(AB16="D",5000,IF(AB16="C",1000,0)))*12 -> 218188 | AM16: 3 | AQ16: Liu Haigang（15013255） | AR16: Zhu Qianqian（11016705） | AS16: Zhao Chujun | AW16: =_xlfn.LET(_xlpm.actual,X16,_xlpm.low,VALUE(_xlfn.TEXTBEFORE(Y16,"-")),_xlpm.high,VALUE(_xlfn.TEXTAFTER(Y16,"-")),IF(AND(_xlpm.actual=0,OR(_xlpm.low<>0,_xlpm.high<>0)),"0 increase",IF(_xlpm.actual>_xlpm.high*1.2,">20",IF(_xlpm.actual<_xlpm.low*0.8,"<20","OK")))) -> OK | AX16: 0-5 | AY16: 70-90
A17: CN15 | B17: 15017481 | C17: Indirect Active | D17: OP | E17: SNa | F17: FCGNa-VCE | G17: 330405 | H17: 42893 | I17: Senior Engineer | J17: Senior Engineer | K17: BAND A5 | L17: 2 | M17: 2 | N17: 13610 | O17: 0 | P17: =ROUND(N17*O17,0) -> 0 | Q17: 0 | R17: =ROUND(N17*Q17,0) -> 0 | S17: =T17/N17 -> 0 | T17: =P17+R17 -> 0 | U17: =N17+T17 -> 13610 | V17: 13610 | W17: =V17-N17 -> 0 | X17: =ROUND(V17/N17-1,4) -> 0 | Y17: =IF(OR(L17=1,L17=2,L17=4), TEXT(S17*0.8,"0.00%") & "-" & TEXT(S17*1.2,"0.00%"), IF(OR(L17=3,L17=6), TEXT(0,"0.00%") & "-" & TEXT(7%*1.2,"0.00%"), IF(OR(L17=5,L17=7), TEXT((R17/N17),"0.00%") & "-" & TEXT((R17/N17)+7%,"0.00%"), "" ) ) ) -> 0.00%-0.00% | AD17: =ROUND(N17*AC17,0) -> 0 | AE17: =V17+AD17 -> 13610 | AF17: =AE17-N17 -> 0 | AG17: =AE17/N17-1 -> 0 | AH17: 14 | AI17: 550 | AK17: 688 | AL17: =AE17*AH17+AI17*12+AK17+IF(AB17="",AJ17,IF(AB17="D",5000,IF(AB17="C",1000,0)))*12 -> 197828 | AM17: 3 | AQ17: Liu Haigang（15013255） | AR17: Zhu Qianqian（11016705） | AS17: Zhao Chujun | AW17: =_xlfn.LET(_xlpm.actual,X17,_xlpm.low,VALUE(_xlfn.TEXTBEFORE(Y17,"-")),_xlpm.high,VALUE(_xlfn.TEXTAFTER(Y17,"-")),IF(AND(_xlpm.actual=0,OR(_xlpm.low<>0,_xlpm.high<>0)),"0 increase",IF(_xlpm.actual>_xlpm.high*1.2,">20",IF(_xlpm.actual<_xlpm.low*0.8,"<20","OK")))) -> OK | AX17: 6-10 | AY17: 0
A18: CN15 | B18: 15014900 | C18: Indirect Active | D18: OP | E18: SNa | F18: FCGNa | G18: 330100 | H18: 42298 | I18: Manager | J18: Manager | K18: BAND B | L18: 2 | M18: 2 | N18: 20200 | O18: 0 | P18: =ROUND(N18*O18,0) -> 0 | Q18: 0 | R18: =ROUND(N18*Q18,0) -> 0 | S18: =T18/N18 -> 0 | T18: =P18+R18 -> 0 | U18: =N18+T18 -> 20200 | V18: =U18 -> 20200 | W18: =V18-N18 -> 0 | X18: =ROUND(V18/N18-1,4) -> 0 | Y18: =IF(OR(L18=1,L18=2,L18=4), TEXT(S18*0.8,"0.00%") & "-" & TEXT(S18*1.2,"0.00%"), IF(OR(L18=3,L18=6), TEXT(0,"0.00%") & "-" & TEXT(7%*1.2,"0.00%"), IF(OR(L18=5,L18=7), TEXT((R18/N18),"0.00%") & "-" & TEXT((R18/N18)+7%,"0.00%"), "" ) ) ) -> 0.00%-0.00% | AD18: =ROUND(N18*AC18,0) -> 0 | AE18: =V18+AD18 -> 20200 | AF18: =AE18-N18 -> 0 | AG18: =AE18/N18-1 -> 0 | AH18: 14 | AI18: 450 | AK18: 688 | AL18: =AE18*AH18+AI18*12+AK18+IF(AB18="",AJ18,IF(AB18="D",5000,IF(AB18="C",1000,0)))*12 -> 288888 | AM18: 3 | AQ18: Chen Chao（15005032） | AR18: Zhu Qianqian（11016705） | AS18: Zhao Chujun | AW18: =_xlfn.LET(_xlpm.actual,X18,_xlpm.low,VALUE(_xlfn.TEXTBEFORE(Y18,"-")),_xlpm.high,VALUE(_xlfn.TEXTAFTER(Y18,"-")),IF(AND(_xlpm.actual=0,OR(_xlpm.low<>0,_xlpm.high<>0)),"0 increase",IF(_xlpm.actual>_xlpm.high*1.2,">20",IF(_xlpm.actual<_xlpm.low*0.8,"<20","OK")))) -> OK | AX18: 6-10 | AY18: 0
A19: CN15 | B19: 15013255 | C19: Indirect Active | D19: OP | E19: SNa | F19: FCGNa-VC | G19: 330405 | H19: 41801 | I19: Manager | J19: Head of Value Stream Cooktop | K19: BAND B | L19: 2 | M19: 4 | N19: 23800 | O19: 0.03 | P19: =ROUND(N19*O19,0) -> 714 | Q19: 0 | R19: =ROUND(N19*Q19,0) -> 0 | S19: =T19/N19 -> 0.03 | T19: =P19+R19 -> 714 | U19: =N19+T19 -> 24514 | V19: =U19 -> 24514 | W19: =V19-N19 -> 714 | X19: =ROUND(V19/N19-1,4) -> 0.03 | Y19: =IF(OR(L19=1,L19=2,L19=4), TEXT(S19*0.8,"0.00%") & "-" & TEXT(S19*1.2,"0.00%"), IF(OR(L19=3,L19=6), TEXT(0,"0.00%") & "-" & TEXT(7%*1.2,"0.00%"), IF(OR(L19=5,L19=7), TEXT((R19/N19),"0.00%") & "-" & TEXT((R19/N19)+7%,"0.00%"), "" ) ) ) -> 2.40%-3.60% | Z19: Promotion | AA19: Head of Value Stream Cooktop | AB19: C | AC19: 0.09 | AD19: =ROUND(N19*AC19,0) -> 2142 | AE19: =V19+AD19 -> 26656 | AF19: =AE19-N19 -> 2856 | AG19: =AE19/N19-1 -> 0.12 | AH19: 14 | AI19: 450 | AK19: 688 | AL19: =AE19*AH19+AI19*12+AK19+IF(AB19="",AJ19,IF(AB19="D",5000,IF(AB19="C",1000,0)))*12 -> 391272 | AM19: 5 | AO19: Good performance and high competence | AP19: Good performance and high competence | AQ19: Chen Chao（15005032） | AR19: Zhu Qianqian（11016705） | AS19: Zhao Chujun | AW19: =_xlfn.LET(_xlpm.actual,X19,_xlpm.low,VALUE(_xlfn.TEXTBEFORE(Y19,"-")),_xlpm.high,VALUE(_xlfn.TEXTAFTER(Y19,"-")),IF(AND(_xlpm.actual=0,OR(_xlpm.low<>0,_xlpm.high<>0)),"0 increase",IF(_xlpm.actual>_xlpm.high*1.2,">20",IF(_xlpm.actual<_xlpm.low*0.8,"<20","OK")))) -> OK | AX19: 11-15 | AY19: 90-110
A20: CN15 | B20: 15005811 | C20: Indirect Active | D20: OP | E20: SNa | F20: FCGNa-VV | G20: 330404 | H20: 40646 | I20: Manager | J20: Head of Value Stream Ventilation | K20: BAND B | L20: 2 | M20: 5 | N20: 24500 | O20: 0.04 | P20: =ROUND(N20*O20,0) -> 980 | Q20: 0 | R20: =ROUND(N20*Q20,0) -> 0 | S20: =T20/N20 -> 0.04 | T20: =P20+R20 -> 980 | U20: =N20+T20 -> 25480 | V20: =U20 -> 25480 | W20: =V20-N20 -> 980 | X20: =ROUND(V20/N20-1,4) -> 0.04 | Y20: =IF(OR(L20=1,L20=2,L20=4), TEXT(S20*0.8,"0.00%") & "-" & TEXT(S20*1.2,"0.00%"), IF(OR(L20=3,L20=6), TEXT(0,"0.00%") & "-" & TEXT(7%*1.2,"0.00%"), IF(OR(L20=5,L20=7), TEXT((R20/N20),"0.00%") & "-" & TEXT((R20/N20)+7%,"0.00%"), "" ) ) ) -> 3.20%-4.80% | Z20: Promotion | AA20: Head of Value Stream Ventilation | AB20: C | AC20: 0.08 | AD20: =ROUND(N20*AC20,0) -> 1960 | AE20: =V20+AD20 -> 27440 | AF20: =AE20-N20 -> 2940 | AG20: =AE20/N20-1 -> 0.12 | AH20: 14 | AI20: 450 | AK20: 688 | AL20: =AE20*AH20+AI20*12+AK20+IF(AB20="",AJ20,IF(AB20="D",5000,IF(AB20="C",1000,0)))*12 -> 402248 | AM20: 3 | AO20: Good performance and high competence | AP20: Good performance and high competence | AQ20: Chen Chao（15005032） | AR20: Zhu Qianqian（11016705） | AS20: Zhao Chujun | AW20: =_xlfn.LET(_xlpm.actual,X20,_xlpm.low,VALUE(_xlfn.TEXTBEFORE(Y20,"-")),_xlpm.high,VALUE(_xlfn.TEXTAFTER(Y20,"-")),IF(AND(_xlpm.actual=0,OR(_xlpm.low<>0,_xlpm.high<>0)),"0 increase",IF(_xlpm.actual>_xlpm.high*1.2,">20",IF(_xlpm.actual<_xlpm.low*0.8,"<20","OK")))) -> OK | AX20: 11-15 | AY20: 90-110
A21: CN15 | B21: 15022316 | C21: Indirect Active | D21: OP | E21: SNa | F21: FCGNa | G21: 330100 | H21: 44930 | I21: Senior Engineer | J21: Senior Testing and Programming Engineer | K21: BAND A5 | L21: 2 | M21: 3 | N21: 14375 | O21: 0.025 | P21: =ROUND(N21*O21,0) -> 359 | Q21: 0 | R21: =ROUND(N21*Q21,0) -> 0 | S21: =T21/N21 -> 0.024973913 | T21: =P21+R21 -> 359 | U21: =N21+T21 -> 14734 | V21: =U21 -> 14734 | W21: =V21-N21 -> 359 | X21: =ROUND(V21/N21-1,4) -> 0.025 | Y21: =IF(OR(L21=1,L21=2,L21=4), TEXT(S21*0.8,"0.00%") & "-" & TEXT(S21*1.2,"0.00%"), IF(OR(L21=3,L21=6), TEXT(0,"0.00%") & "-" & TEXT(7%*1.2,"0.00%"), IF(OR(L21=5,L21=7), TEXT((R21/N21),"0.00%") & "-" & TEXT((R21/N21)+7%,"0.00%"), "" ) ) ) -> 2.00%-3.00% | AD21: =ROUND(N21*AC21,0) -> 0 | AE21: =V21+AD21 -> 14734 | AF21: =AE21-N21 -> 359 | AG21: =AE21/N21-1 -> 0.024973913 | AH21: 14 | AI21: 450 | AK21: 688 | AL21: =AE21*AH21+AI21*12+AK21+IF(AB21="",AJ21,IF(AB21="D",5000,IF(AB21="C",1000,0)))*12 -> 212364 | AM21: 4 | AQ21: Chen Chao（15005032） | AR21: Zhu Qianqian（11016705） | AS21: Zhao Chujun | AW21: =_xlfn.LET(_xlpm.actual,X21,_xlpm.low,VALUE(_xlfn.TEXTBEFORE(Y21,"-")),_xlpm.high,VALUE(_xlfn.TEXTAFTER(Y21,"-")),IF(AND(_xlpm.actual=0,OR(_xlpm.low<>0,_xlpm.high<>0)),"0 increase",IF(_xlpm.actual>_xlpm.high*1.2,">20",IF(_xlpm.actual<_xlpm.low*0.8,"<20","OK")))) -> OK | AX21: 0-5 | AY21: 70-90
A22: CN15 | B22: 15001764 | C22: Indirect Active | D22: OP | E22: SNa | F22: FCGNa | G22: 330100 | H22: 40360 | I22: Senior Engineer | J22: Senior Engineer | K22: BAND A5 | L22: 2 | M22: 4 | N22: 9891 | O22: 0.045 | P22: =ROUND(N22*O22,0) -> 445 | Q22: 0.0421 | R22: =ROUND(N22*Q22,0) -> 416 | S22: =T22/N22 -> 0.087048832 | T22: =P22+R22 -> 861 | U22: =N22+T22 -> 10752 | V22: =U22 -> 10752 | W22: =V22-N22 -> 861 | X22: =ROUND(V22/N22-1,4) -> 0.087 | Y22: =IF(OR(L22=1,L22=2,L22=4), TEXT(S22*0.8,"0.00%") & "-" & TEXT(S22*1.2,"0.00%"), IF(OR(L22=3,L22=6), TEXT(0,"0.00%") & "-" & TEXT(7%*1.2,"0.00%"), IF(OR(L22=5,L22=7), TEXT((R22/N22),"0.00%") & "-" & TEXT((R22/N22)+7%,"0.00%"), "" ) ) ) -> 6.96%-10.45% | AD22: =ROUND(N22*AC22,0) -> 0 | AE22: =V22+AD22 -> 10752 | AF22: =AE22-N22 -> 861 | AG22: =AE22/N22-1 -> 0.087048832 | AH22: 14 | AI22: 450 | AK22: 688 | AL22: =AE22*AH22+AI22*12+AK22+IF(AB22="",AJ22,IF(AB22="D",5000,IF(AB22="C",1000,0)))*12 -> 156616 | AM22: 3 | AQ22: Chen Chao（15005032） | AR22: Zhu Qianqian（11016705） | AS22: Zhao Chujun | AW22: =_xlfn.LET(_xlpm.actual,X22,_xlpm.low,VALUE(_xlfn.TEXTBEFORE(Y22,"-")),_xlpm.high,VALUE(_xlfn.TEXTAFTER(Y22,"-")),IF(AND(_xlpm.actual=0,OR(_xlpm.low<>0,_xlpm.high<>0)),"0 increase",IF(_xlpm.actual>_xlpm.high*1.2,">20",IF(_xlpm.actual<_xlpm.low*0.8,"<20","OK")))) -> OK | AX22: 11-15 | AY22: 50-70
A23: CN15 | B23: 15022180 | C23: Indirect Active | D23: OP | E23: SNa | F23: FEDNa-MEP | G23: 370200 | H23: 44686 | I23: Engineer | J23: Process Engineer | K23: BAND A4 | L23: 2 | M23: 3 | N23: 8200 | O23: 0.025 | P23: =ROUND(N23*O23,0) -> 205 | Q23: 0 | R23: =ROUND(N23*Q23,0) -> 0 | S23: =T23/N23 -> 0.025 | T23: =P23+R23 -> 205 | U23: =N23+T23 -> 8405 | V23: 8415 | W23: =V23-N23 -> 215 | X23: =ROUND(V23/N23-1,4) -> 0.0262 | Y23: =IF(OR(L23=1,L23=2,L23=4),TEXT(S23*0.8,"0.00%")&"-"&TEXT(S23*1.2,"0.00%"),IF(OR(L23=3,L23=6),TEXT(0,"0.00%")&"-"&TEXT(7%*1.2,"0.00%"),IF(OR(L23=5,L23=7),TEXT((R23/N23),"0.00%")&"-"&TEXT((R23/N23)+7%,"0.00%"),""))) -> 2.00%-3.00% | AD23: =ROUND(N23*AC23,0) -> 0 | AE23: =V23+AD23 -> 8415 | AF23: =AE23-N23 -> 215 | AG23: =AE23/N23-1 -> 0.026219512 | AH23: 14 | AI23: 550 | AK23: 688 | AL23: =AE23*AH23+AI23*12+AK23+IF(AB23="",AJ23,IF(AB23="D",5000,IF(AB23="C",1000,0)))*12 -> 125098 | AM23: 3 | AQ23: Ding Xudong（15000307） | AR23: Xu Lan（11013544） | AS23: Zhao Chujun | AW23: =_xlfn.LET(_xlpm.actual,X23,_xlpm.low,VALUE(_xlfn.TEXTBEFORE(Y23,"-")),_xlpm.high,VALUE(_xlfn.TEXTAFTER(Y23,"-")),IF(AND(_xlpm.actual=0,OR(_xlpm.low<>0,_xlpm.high<>0)),"0 increase",IF(_xlpm.actual>_xlpm.high*1.2,">20",IF(_xlpm.actual<_xlpm.low*0.8,"<20","OK")))) -> OK | AX23: 0-5 | AY23: 70-90
A24: CN15 | B24: 15003790 | C24: Indirect Active | D24: OP | E24: SNa | F24: FEDNa-MEM | G24: 370201 | H24: 40310 | I24: Supervisor | J24: Head of Mechanical Support | K24: BAND A6 | L24: 2 | M24: 3 | N24: 15324 | O24: 0.03 | P24: =ROUND(N24*O24,0) -> 460 | Q24: 0 | R24: =ROUND(N24*Q24,0) -> 0 | S24: =T24/N24 -> 0.030018272 | T24: =P24+R24 -> 460 | U24: =N24+T24 -> 15784 | V24: 15600 | W24: =V24-N24 -> 276 | X24: =ROUND(V24/N24-1,4) -> 0.018 | Y24: =IF(OR(L24=1,L24=2,L24=4),TEXT(S24*0.8,"0.00%")&"-"&TEXT(S24*1.2,"0.00%"),IF(OR(L24=3,L24=6),TEXT(0,"0.00%")&"-"&TEXT(7%*1.2,"0.00%"),IF(OR(L24=5,L24=7),TEXT((R24/N24),"0.00%")&"-"&TEXT((R24/N24)+7%,"0.00%"),""))) -> 2.40%-3.60% | AD24: =ROUND(N24*AC24,0) -> 0 | AE24: =V24+AD24 -> 15600 | AF24: =AE24-N24 -> 276 | AG24: =AE24/N24-1 -> 0.018010963 | AH24: 14 | AI24: 450 | AK24: 688 | AL24: =AE24*AH24+AI24*12+AK24+IF(AB24="",AJ24,IF(AB24="D",5000,IF(AB24="C",1000,0)))*12 -> 224488 | AM24: 3 | AP24: Internal balance | AQ24: Ding Xudong（15000307） | AR24: Xu Lan（11013544） | AS24: Zhao Chujun | AU24: exceed +/-20% adjustment | AV24: <20 | AW24: =_xlfn.LET(_xlpm.actual,X24,_xlpm.low,VALUE(_xlfn.TEXTBEFORE(Y24,"-")),_xlpm.high,VALUE(_xlfn.TEXTAFTER(Y24,"-")),IF(AND(_xlpm.actual=0,OR(_xlpm.low<>0,_xlpm.high<>0)),"0 increase",IF(_xlpm.actual>_xlpm.high*1.2,">20",IF(_xlpm.actual<_xlpm.low*0.8,"<20","OK")))) -> <20 | AX24: 16-20 | AY24: 50-70
A25: CN15 | B25: 15016330 | C25: Indirect Active | D25: OP | E25: SNa | F25: FEDNa-V2 | G25: 370400 | H25: 42781 | I25: Manager | J25: Head of FEDNa-V2 | K25: BAND B | L25: 2 | M25: 4 | N25: 20300 | O25: 0.0375 | P25: =ROUND(N25*O25,0) -> 761 | Q25: 0.0155 | R25: =ROUND(N25*Q25,0) -> 315 | S25: =T25/N25 -> 0.053004926 | T25: =P25+R25 -> 1076 | U25: =N25+T25 -> 21376 | V25: 21500 | W25: =V25-N25 -> 1200 | X25: =ROUND(V25/N25-1,4) -> 0.0591 | Y25: =IF(OR(L25=1,L25=2,L25=4),TEXT(S25*0.8,"0.00%")&"-"&TEXT(S25*1.2,"0.00%"),IF(OR(L25=3,L25=6),TEXT(0,"0.00%")&"-"&TEXT(7%*1.2,"0.00%"),IF(OR(L25=5,L25=7),TEXT((R25/N25),"0.00%")&"-"&TEXT((R25/N25)+7%,"0.00%"),""))) -> 4.24%-6.36% | AD25: =ROUND(N25*AC25,0) -> 0 | AE25: =V25+AD25 -> 21500 | AF25: =AE25-N25 -> 1200 | AG25: =AE25/N25-1 -> 0.0591133 | AH25: 14 | AI25: 450 | AK25: 688 | AL25: =AE25*AH25+AI25*12+AK25+IF(AB25="",AJ25,IF(AB25="D",5000,IF(AB25="C",1000,0)))*12 -> 307088 | AM25: 3 | AQ25: Ding Xudong（15000307） | AR25: Xu Lan（11013544） | AS25: Zhao Chujun | AW25: =_xlfn.LET(_xlpm.actual,X25,_xlpm.low,VALUE(_xlfn.TEXTBEFORE(Y25,"-")),_xlpm.high,VALUE(_xlfn.TEXTAFTER(Y25,"-")),IF(AND(_xlpm.actual=0,OR(_xlpm.low<>0,_xlpm.high<>0)),"0 increase",IF(_xlpm.actual>_xlpm.high*1.2,">20",IF(_xlpm.actual<_xlpm.low*0.8,"<20","OK")))) -> OK | AX25: 6-10 | AY25: 70-90
A26: CN15 | B26: 15001485 | C26: Indirect Active | D26: OP | E26: SNa | F26: FEDNa-ME | G26: 370200 | H26: 39547 | I26: Manager | J26: Head of Manufacturing Engineering | K26: BAND B | L26: 2 | M26: 3 | N26: 27011 | O26: 0.025 | P26: =ROUND(N26*O26,0) -> 675 | Q26: 0 | R26: =ROUND(N26*Q26,0) -> 0 | S26: =T26/N26 -> 0.024989819 | T26: =P26+R26 -> 675 | U26: =N26+T26 -> 27686 | V26: 27700 | W26: =V26-N26 -> 689 | X26: =ROUND(V26/N26-1,4) -> 0.0255 | Y26: =IF(OR(L26=1,L26=2,L26=4),TEXT(S26*0.8,"0.00%")&"-"&TEXT(S26*1.2,"0.00%"),IF(OR(L26=3,L26=6),TEXT(0,"0.00%")&"-"&TEXT(7%*1.2,"0.00%"),IF(OR(L26=5,L26=7),TEXT((R26/N26),"0.00%")&"-"&TEXT((R26/N26)+7%,"0.00%"),""))) -> 2.00%-3.00% | AD26: =ROUND(N26*AC26,0) -> 0 | AE26: =V26+AD26 -> 27700 | AF26: =AE26-N26 -> 689 | AG26: =AE26/N26-1 -> 0.025508126 | AH26: 14 | AI26: 450 | AK26: 688 | AL26: =AE26*AH26+AI26*12+AK26+IF(AB26="",AJ26,IF(AB26="D",5000,IF(AB26="C",1000,0)))*12 -> 393888 | AM26: 4 | AQ26: Ding Xudong（15000307） | AR26: Xu Lan（11013544） | AS26: Zhao Chujun | AW26: =_xlfn.LET(_xlpm.actual,X26,_xlpm.low,VALUE(_xlfn.TEXTBEFORE(Y26,"-")),_xlpm.high,VALUE(_xlfn.TEXTAFTER(Y26,"-")),IF(AND(_xlpm.actual=0,OR(_xlpm.low<>0,_xlpm.high<>0)),"0 increase",IF(_xlpm.actual>_xlpm.high*1.2,">20",IF(_xlpm.actual<_xlpm.low*0.8,"<20","OK")))) -> OK | AX26: 16-20 | AY26: 70-90
A27: CN15 | B27: 1020358 | C27: Indirect Active | D27: OP | E27: SNa | F27: FEDNa-MEP | G27: 370200 | H27: 45000 | I27: Senior Engineer | J27: Senior Process Engineer | K27: BAND A5 | L27: 2 | M27: 5 | N27: 13610 | O27: 0.05 | P27: =ROUND(N27*O27,0) -> 681 | Q27: 0.027 | R27: =ROUND(N27*Q27,0) -> 367 | S27: =T27/N27 -> 0.077002204 | T27: =P27+R27 -> 1048 | U27: =N27+T27 -> 14658 | V27: 15000 | W27: =V27-N27 -> 1390 | X27: =ROUND(V27/N27-1,4) -> 0.1021 | Y27: =IF(OR(L27=1,L27=2,L27=4),TEXT(S27*0.8,"0.00%")&"-"&TEXT(S27*1.2,"0.00%"),IF(OR(L27=3,L27=6),TEXT(0,"0.00%")&"-"&TEXT(7%*1.2,"0.00%"),IF(OR(L27=5,L27=7),TEXT((R27/N27),"0.00%")&"-"&TEXT((R27/N27)+7%,"0.00%"),""))) -> 6.16%-9.24% | AD27: =ROUND(N27*AC27,0) -> 0 | AE27: =V27+AD27 -> 15000 | AF27: =AE27-N27 -> 1390 | AG27: =AE27/N27-1 -> 0.10213079 | AH27: 14 | AI27: 450 | AK27: 688 | AL27: =AE27*AH27+AI27*12+AK27+IF(AB27="",AJ27,IF(AB27="D",5000,IF(AB27="C",1000,0)))*12 -> 216088 | AM27: 3 | AP27: Rounding | AQ27: Ding Xudong（15000307） | AR27: Xu Lan（11013544） | AS27: Zhao Chujun | AU27: exceed +/-20% adjustment | AV27: >20 | AW27: =_xlfn.LET(_xlpm.actual,X27,_xlpm.low,VALUE(_xlfn.TEXTBEFORE(Y27,"-")),_xlpm.high,VALUE(_xlfn.TEXTAFTER(Y27,"-")),IF(AND(_xlpm.actual=0,OR(_xlpm.low<>0,_xlpm.high<>0)),"0 increase",IF(_xlpm.actual>_xlpm.high*1.2,">20",IF(_xlpm.actual<_xlpm.low*0.8,"<20","OK")))) -> OK | AX27: 0-5 | AY27: 70-90
A28: CN15 | B28: 15021547 | C28: Indirect Active | D28: OP | E28: SNa | F28: FEDNa-MEP | G28: 370200 | H28: 44391 | I28: Engineer | J28: Electrical Engineer | K28: BAND A4 | L28: 2 | M28: 4 | N28: 10500 | O28: 0.0375 | P28: =ROUND(N28*O28,0) -> 394 | Q28: 0 | R28: =ROUND(N28*Q28,0) -> 0 | S28: =T28/N28 -> 0.03752381 | T28: =P28+R28 -> 394 | U28: =N28+T28 -> 10894 | V28: 10827 | W28: =V28-N28 -> 327 | X28: =ROUND(V28/N28-1,4) -> 0.0311 | Y28: =IF(OR(L28=1,L28=2,L28=4),TEXT(S28*0.8,"0.00%")&"-"&TEXT(S28*1.2,"0.00%"),IF(OR(L28=3,L28=6),TEXT(0,"0.00%")&"-"&TEXT(7%*1.2,"0.00%"),IF(OR(L28=5,L28=7),TEXT((R28/N28),"0.00%")&"-"&TEXT((R28/N28)+7%,"0.00%"),""))) -> 3.00%-4.50% | Z28: Promotion | AA28: senior engineer | AB28: A5 | AC28: 0.1117 | AD28: =ROUND(N28*AC28,0) -> 1173 | AE28: =V28+AD28 -> 12000 | AF28: =AE28-N28 -> 1500 | AG28: =AE28/N28-1 -> 0.14285714 | AH28: 14 | AI28: 500 | AK28: 688 | AL28: =AE28*AH28+AI28*12+AK28+IF(AB28="",AJ28,IF(AB28="D",5000,IF(AB28="C",1000,0)))*12 -> 174688 | AM28: 3 | AP28: Good performance and high competence | AQ28: Ding Xudong（15000307） | AR28: Xu Lan（11013544） | AS28: Zhao Chujun | AW28: =_xlfn.LET(_xlpm.actual,X28,_xlpm.low,VALUE(_xlfn.TEXTBEFORE(Y28,"-")),_xlpm.high,VALUE(_xlfn.TEXTAFTER(Y28,"-")),IF(AND(_xlpm.actual=0,OR(_xlpm.low<>0,_xlpm.high<>0)),"0 increase",IF(_xlpm.actual>_xlpm.high*1.2,">20",IF(_xlpm.actual<_xlpm.low*0.8,"<20","OK")))) -> OK | AX28: 0-5 | AY28: 70-90
A29: CN15 | B29: 15012913 | C29: Indirect Active | D29: OP | E29: SNa | F29: FEDNa-ME | G29: 370200 | H29: 41738 | I29: Associate Expert (CN) | J29: Associate Expert (C) | K29: BAND A6 | L29: 2 | M29: 5 | N29: 16000 | O29: 0.06 | P29: =ROUND(N29*O29,0) -> 960 | Q29: 0.0778 | R29: =ROUND(N29*Q29,0) -> 1245 | S29: =T29/N29 -> 0.1378125 | T29: =P29+R29 -> 2205 | U29: =N29+T29 -> 18205 | V29: 18000 | W29: =V29-N29 -> 2000 | X29: =ROUND(V29/N29-1,4) -> 0.125 | Y29: =IF(OR(L29=1,L29=2,L29=4),TEXT(S29*0.8,"0.00%")&"-"&TEXT(S29*1.2,"0.00%"),IF(OR(L29=3,L29=6),TEXT(0,"0.00%")&"-"&TEXT(7%*1.2,"0.00%"),IF(OR(L29=5,L29=7),TEXT((R29/N29),"0.00%")&"-"&TEXT((R29/N29)+7%,"0.00%"),""))) -> 11.03%-16.54% | AD29: =ROUND(N29*AC29,0) -> 0 | AE29: =V29+AD29 -> 18000 | AF29: =AE29-N29 -> 2000 | AG29: =AE29/N29-1 -> 0.125 | AH29: 14 | AI29: 500 | AK29: 688 | AL29: =AE29*AH29+AI29*12+AK29+IF(AB29="",AJ29,IF(AB29="D",5000,IF(AB29="C",1000,0)))*12 -> 258688 | AM29: 4 | AQ29: Ding Xudong（15000307） | AR29: Xu Lan（11013544） | AS29: Zhao Chujun | AW29: =_xlfn.LET(_xlpm.actual,X29,_xlpm.low,VALUE(_xlfn.TEXTBEFORE(Y29,"-")),_xlpm.high,VALUE(_xlfn.TEXTAFTER(Y29,"-")),IF(AND(_xlpm.actual=0,OR(_xlpm.low<>0,_xlpm.high<>0)),"0 increase",IF(_xlpm.actual>_xlpm.high*1.2,">20",IF(_xlpm.actual<_xlpm.low*0.8,"<20","OK")))) -> OK | AX29: 11-15 | AY29: 0
A30: CN15 | B30: 15001306 | C30: Indirect Active | D30: OP | E30: SNa | F30: FEDNa-ME | G30: 370200 | H30: 39420 | I30: Functional Specialist | J30: Functional Specialist | K30: BAND A6 | L30: 2 | M30: 3 | N30: 20306 | O30: 0 | P30: =ROUND(N30*O30,0) -> 0 | Q30: 0 | R30: =ROUND(N30*Q30,0) -> 0 | S30: =T30/N30 -> 0 | T30: =P30+R30 -> 0 | U30: =N30+T30 -> 20306 | V30: 20500 | W30: =V30-N30 -> 194 | X30: =ROUND(V30/N30-1,4) -> 0.0096 | Y30: =IF(OR(L30=1,L30=2,L30=4),TEXT(S30*0.8,"0.00%")&"-"&TEXT(S30*1.2,"0.00%"),IF(OR(L30=3,L30=6),TEXT(0,"0.00%")&"-"&TEXT(7%*1.2,"0.00%"),IF(OR(L30=5,L30=7),TEXT((R30/N30),"0.00%")&"-"&TEXT((R30/N30)+7%,"0.00%"),""))) -> 0.00%-0.00% | AD30: =ROUND(N30*AC30,0) -> 0 | AE30: =V30+AD30 -> 20500 | AF30: =AE30-N30 -> 194 | AG30: =AE30/N30-1 -> 0.0095538265 | AH30: 14 | AI30: 600 | AK30: 688 | AL30: =AE30*AH30+AI30*12+AK30+IF(AB30="",AJ30,IF(AB30="D",5000,IF(AB30="C",1000,0)))*12 -> 294888 | AM30: 4 | AP30: Good performance and high competence | AQ30: Ding Xudong（15000307） | AR30: Xu Lan（11013544） | AS30: Zhao Chujun | AU30: exceed +/-20% adjustment | AV30: >20 | AW30: =_xlfn.LET(_xlpm.actual,X30,_xlpm.low,VALUE(_xlfn.TEXTBEFORE(Y30,"-")),_xlpm.high,VALUE(_xlfn.TEXTAFTER(Y30,"-")),IF(AND(_xlpm.actual=0,OR(_xlpm.low<>0,_xlpm.high<>0)),"0 increase",IF(_xlpm.actual>_xlpm.high*1.2,">20",IF(_xlpm.actual<_xlpm.low*0.8,"<20","OK")))) -> >20 | AX30: 16-20 | AY30: >90
A31: CN15 | B31: 15021548 | C31: Indirect Active | D31: OP | E31: SNa | F31: FEDNa-ME | G31: 370200 | H31: 44391 | I31: Senior Engineer | J31: Senior Equipment Engineer | K31: BAND A5 | L31: 2 | M31: 3 | N31: 13330 | O31: 0.025 | P31: =ROUND(N31*O31,0) -> 333 | Q31: 0 | R31: =ROUND(N31*Q31,0) -> 0 | S31: =T31/N31 -> 0.024981245 | T31: =P31+R31 -> 333 | U31: =N31+T31 -> 13663 | V31: 13600 | W31: =V31-N31 -> 270 | X31: =ROUND(V31/N31-1,4) -> 0.0203 | Y31: =IF(OR(L31=1,L31=2,L31=4),TEXT(S31*0.8,"0.00%")&"-"&TEXT(S31*1.2,"0.00%"),IF(OR(L31=3,L31=6),TEXT(0,"0.00%")&"-"&TEXT(7%*1.2,"0.00%"),IF(OR(L31=5,L31=7),TEXT((R31/N31),"0.00%")&"-"&TEXT((R31/N31)+7%,"0.00%"),""))) -> 2.00%-3.00% | AD31: =ROUND(N31*AC31,0) -> 0 | AE31: =V31+AD31 -> 13600 | AF31: =AE31-N31 -> 270 | AG31: =AE31/N31-1 -> 0.020255064 | AH31: 14 | AI31: 450 | AK31: 688 | AL31: =AE31*AH31+AI31*12+AK31+IF(AB31="",AJ31,IF(AB31="D",5000,IF(AB31="C",1000,0)))*12 -> 196488 | AM31: 3 | AQ31: Ding Xudong（15000307） | AR31: Xu Lan（11013544） | AS31: Zhao Chujun | AW31: =_xlfn.LET(_xlpm.actual,X31,_xlpm.low,VALUE(_xlfn.TEXTBEFORE(Y31,"-")),_xlpm.high,VALUE(_xlfn.TEXTAFTER(Y31,"-")),IF(AND(_xlpm.actual=0,OR(_xlpm.low<>0,_xlpm.high<>0)),"0 increase",IF(_xlpm.actual>_xlpm.high*1.2,">20",IF(_xlpm.actual<_xlpm.low*0.8,"<20","OK")))) -> OK | AX31: 0-5 | AY31: 70-90
A32: CN15 | B32: 15021979 | C32: Indirect Active | D32: OP | E32: SNa | F32: FEDNa-V2 | G32: 370404 | H32: 44503 | I32: Engineer | J32: Production Engineer | K32: BAND A4 | L32: 2 | M32: 3 | N32: 9450 | O32: 0.025 | P32: =ROUND(N32*O32,0) -> 236 | Q32: 0 | R32: =ROUND(N32*Q32,0) -> 0 | S32: =T32/N32 -> 0.024973545 | T32: =P32+R32 -> 236 | U32: =N32+T32 -> 9686 | V32: 9700 | W32: =V32-N32 -> 250 | X32: =ROUND(V32/N32-1,4) -> 0.0265 | Y32: =IF(OR(L32=1,L32=2,L32=4),TEXT(S32*0.8,"0.00%")&"-"&TEXT(S32*1.2,"0.00%"),IF(OR(L32=3,L32=6),TEXT(0,"0.00%")&"-"&TEXT(7%*1.2,"0.00%"),IF(OR(L32=5,L32=7),TEXT((R32/N32),"0.00%")&"-"&TEXT((R32/N32)+7%,"0.00%"),""))) -> 2.00%-3.00% | AD32: =ROUND(N32*AC32,0) -> 0 | AE32: =V32+AD32 -> 9700 | AF32: =AE32-N32 -> 250 | AG32: =AE32/N32-1 -> 0.026455026 | AH32: 14 | AI32: 450 | AK32: 688 | AL32: =AE32*AH32+AI32*12+AK32+IF(AB32="",AJ32,IF(AB32="D",5000,IF(AB32="C",1000,0)))*12 -> 141888 | AM32: 2 | AQ32: Ding Xudong（15000307） | AR32: Xu Lan（11013544） | AS32: Zhao Chujun | AW32: =_xlfn.LET(_xlpm.actual,X32,_xlpm.low,VALUE(_xlfn.TEXTBEFORE(Y32,"-")),_xlpm.high,VALUE(_xlfn.TEXTAFTER(Y32,"-")),IF(AND(_xlpm.actual=0,OR(_xlpm.low<>0,_xlpm.high<>0)),"0 increase",IF(_xlpm.actual>_xlpm.high*1.2,">20",IF(_xlpm.actual<_xlpm.low*0.8,"<20","OK")))) -> OK | AX32: 0-5 | AY32: 70-90
A33: CN15 | B33: 15000525 | C33: Indirect Active | D33: OP | E33: SNa | F33: FEDNa-FS | G33: 370100 | H33: 38869 | I33: Coordinator | J33: TPM Coordinator | K33: BAND A4 | L33: 2 | M33: 3 | N33: 7900 | O33: 0 | P33: =ROUND(N33*O33,0) -> 0 | Q33: 0 | R33: =ROUND(N33*Q33,0) -> 0 | S33: =T33/N33 -> 0 | T33: =P33+R33 -> 0 | U33: =N33+T33 -> 7900 | V33: 8000 | W33: =V33-N33 -> 100 | X33: =ROUND(V33/N33-1,4) -> 0.0127 | Y33: =IF(OR(L33=1,L33=2,L33=4),TEXT(S33*0.8,"0.00%")&"-"&TEXT(S33*1.2,"0.00%"),IF(OR(L33=3,L33=6),TEXT(0,"0.00%")&"-"&TEXT(7%*1.2,"0.00%"),IF(OR(L33=5,L33=7),TEXT((R33/N33),"0.00%")&"-"&TEXT((R33/N33)+7%,"0.00%"),""))) -> 0.00%-0.00% | AD33: =ROUND(N33*AC33,0) -> 0 | AE33: =V33+AD33 -> 8000 | AF33: =AE33-N33 -> 100 | AG33: =AE33/N33-1 -> 0.012658228 | AH33: 14 | AI33: 650 | AK33: 688 | AL33: =AE33*AH33+AI33*12+AK33+IF(AB33="",AJ33,IF(AB33="D",5000,IF(AB33="C",1000,0)))*12 -> 120488 | AM33: 3 | AP33: Internal balance | AQ33: Ding Xudong（15000307） | AR33: Xu Lan（11013544） | AS33: Zhao Chujun | AU33: exceed +/-20% adjustment | AV33: >20 | AW33: =_xlfn.LET(_xlpm.actual,X33,_xlpm.low,VALUE(_xlfn.TEXTBEFORE(Y33,"-")),_xlpm.high,VALUE(_xlfn.TEXTAFTER(Y33,"-")),IF(AND(_xlpm.actual=0,OR(_xlpm.low<>0,_xlpm.high<>0)),"0 increase",IF(_xlpm.actual>_xlpm.high*1.2,">20",IF(_xlpm.actual<_xlpm.low*0.8,"<20","OK")))) -> >20 | AX33: 16-20 | AY33: >90
A34: CN15 | B34: 15020089 | C34: Indirect Active | D34: OP | E34: SNa | F34: FEDNa-MEP | G34: 370200 | H34: 43908 | I34: Engineer | J34: Process Engineer | K34: BAND A4 | L34: 2 | M34: 3 | N34: 10100 | O34: 0.025 | P34: =ROUND(N34*O34,0) -> 253 | Q34: 0 | R34: =ROUND(N34*Q34,0) -> 0 | S34: =T34/N34 -> 0.025049505 | T34: =P34+R34 -> 253 | U34: =N34+T34 -> 10353 | V34: 10300 | W34: =V34-N34 -> 200 | X34: =ROUND(V34/N34-1,4) -> 0.0198 | Y34: =IF(OR(L34=1,L34=2,L34=4),TEXT(S34*0.8,"0.00%")&"-"&TEXT(S34*1.2,"0.00%"),IF(OR(L34=3,L34=6),TEXT(0,"0.00%")&"-"&TEXT(7%*1.2,"0.00%"),IF(OR(L34=5,L34=7),TEXT((R34/N34),"0.00%")&"-"&TEXT((R34/N34)+7%,"0.00%"),""))) -> 2.00%-3.01% | AD34: =ROUND(N34*AC34,0) -> 0 | AE34: =V34+AD34 -> 10300 | AF34: =AE34-N34 -> 200 | AG34: =AE34/N34-1 -> 0.01980198 | AH34: 14 | AI34: 450 | AK34: 688 | AL34: =AE34*AH34+AI34*12+AK34+IF(AB34="",AJ34,IF(AB34="D",5000,IF(AB34="C",1000,0)))*12 -> 150288 | AM34: 3 | AP34: Rounding | AQ34: Ding Xudong（15000307） | AR34: Xu Lan（11013544） | AS34: Zhao Chujun | AU34: exceed +/-20% adjustment | AV34: <20 | AW34: =_xlfn.LET(_xlpm.actual,X34,_xlpm.low,VALUE(_xlfn.TEXTBEFORE(Y34,"-")),_xlpm.high,VALUE(_xlfn.TEXTAFTER(Y34,"-")),IF(AND(_xlpm.actual=0,OR(_xlpm.low<>0,_xlpm.high<>0)),"0 increase",IF(_xlpm.actual>_xlpm.high*1.2,">20",IF(_xlpm.actual<_xlpm.low*0.8,"<20","OK")))) -> OK | AX34: 6-10 | AY34: 70-90
A35: CN15 | B35: 15000550 | C35: Indirect Active | D35: OP | E35: SNa | F35: FEDNa-V2 | G35: 370404 | H35: 38881 | I35: Engineer | J35: Engineer | K35: BAND A4 | L35: 2 | M35: 4 | N35: 9800 | O35: 0.0375 | P35: =ROUND(N35*O35,0) -> 368 | Q35: 0.0155 | R35: =ROUND(N35*Q35,0) -> 152 | S35: =T35/N35 -> 0.053061224 | T35: =P35+R35 -> 520 | U35: =N35+T35 -> 10320 | V35: 10300 | W35: =V35-N35 -> 500 | X35: =ROUND(V35/N35-1,4) -> 0.051 | Y35: =IF(OR(L35=1,L35=2,L35=4),TEXT(S35*0.8,"0.00%")&"-"&TEXT(S35*1.2,"0.00%"),IF(OR(L35=3,L35=6),TEXT(0,"0.00%")&"-"&TEXT(7%*1.2,"0.00%"),IF(OR(L35=5,L35=7),TEXT((R35/N35),"0.00%")&"-"&TEXT((R35/N35)+7%,"0.00%"),""))) -> 4.24%-6.37% | AD35: =ROUND(N35*AC35,0) -> 0 | AE35: =V35+AD35 -> 10300 | AF35: =AE35-N35 -> 500 | AG35: =AE35/N35-1 -> 0.051020408 | AH35: 14 | AI35: 550 | AK35: 688 | AL35: =AE35*AH35+AI35*12+AK35+IF(AB35="",AJ35,IF(AB35="D",5000,IF(AB35="C",1000,0)))*12 -> 151488 | AM35: 3 | AQ35: Ding Xudong（15000307） | AR35: Xu Lan（11013544） | AS35: Zhao Chujun | AW35: =_xlfn.LET(_xlpm.actual,X35,_xlpm.low,VALUE(_xlfn.TEXTBEFORE(Y35,"-")),_xlpm.high,VALUE(_xlfn.TEXTAFTER(Y35,"-")),IF(AND(_xlpm.actual=0,OR(_xlpm.low<>0,_xlpm.high<>0)),"0 increase",IF(_xlpm.actual>_xlpm.high*1.2,">20",IF(_xlpm.actual<_xlpm.low*0.8,"<20","OK")))) -> OK | AX35: 16-20 | AY35: 70-90
A36: CN15 | B36: 15015967 | C36: Indirect Active | D36: OP | E36: SNa | F36: FEDNa-FS | G36: 370100 | H36: 42683 | I36: Associate Expert (CN) | J36: Associate Expert (C) | K36: BAND A6 | L36: 2 | M36: 4 | N36: 12360 | O36: 0.045 | P36: =ROUND(N36*O36,0) -> 556 | Q36: 0.0421 | R36: =ROUND(N36*Q36,0) -> 520 | S36: =T36/N36 -> 0.087055016 | T36: =P36+R36 -> 1076 | U36: =N36+T36 -> 13436 | V36: 13300 | W36: =V36-N36 -> 940 | X36: =ROUND(V36/N36-1,4) -> 0.0761 | Y36: =IF(OR(L36=1,L36=2,L36=4),TEXT(S36*0.8,"0.00%")&"-"&TEXT(S36*1.2,"0.00%"),IF(OR(L36=3,L36=6),TEXT(0,"0.00%")&"-"&TEXT(7%*1.2,"0.00%"),IF(OR(L36=5,L36=7),TEXT((R36/N36),"0.00%")&"-"&TEXT((R36/N36)+7%,"0.00%"),""))) -> 6.96%-10.45% | AD36: =ROUND(N36*AC36,0) -> 0 | AE36: =V36+AD36 -> 13300 | AF36: =AE36-N36 -> 940 | AG36: =AE36/N36-1 -> 0.07605178 | AH36: 14 | AI36: 450 | AK36: 688 | AL36: =AE36*AH36+AI36*12+AK36+IF(AB36="",AJ36,IF(AB36="D",5000,IF(AB36="C",1000,0)))*12 -> 192288 | AM36: 3 | AQ36: Ding Xudong（15000307） | AR36: Xu Lan（11013544） | AS36: Zhao Chujun | AW36: =_xlfn.LET(_xlpm.actual,X36,_xlpm.low,VALUE(_xlfn.TEXTBEFORE(Y36,"-")),_xlpm.high,VALUE(_xlfn.TEXTAFTER(Y36,"-")),IF(AND(_xlpm.actual=0,OR(_xlpm.low<>0,_xlpm.high<>0)),"0 increase",IF(_xlpm.actual>_xlpm.high*1.2,">20",IF(_xlpm.actual<_xlpm.low*0.8,"<20","OK")))) -> OK | AX36: 6-10 | AY36: 50-70
A37: CN15 | B37: 15001287 | C37: Indirect Active | D37: OP | E37: SNa | F37: FEDNa-MEP | G37: 370200 | H37: 39392 | I37: Senior Engineer | J37: Senior Electrical Engineer | K37: BAND A5 | L37: 2 | M37: 3 | N37: 12500 | O37: 0.025 | P37: =ROUND(N37*O37,0) -> 313 | Q37: 0 | R37: =ROUND(N37*Q37,0) -> 0 | S37: =T37/N37 -> 0.02504 | T37: =P37+R37 -> 313 | U37: =N37+T37 -> 12813 | V37: 12600 | W37: =V37-N37 -> 100 | X37: =ROUND(V37/N37-1,4) -> 0.008 | Y37: =IF(OR(L37=1,L37=2,L37=4),TEXT(S37*0.8,"0.00%")&"-"&TEXT(S37*1.2,"0.00%"),IF(OR(L37=3,L37=6),TEXT(0,"0.00%")&"-"&TEXT(7%*1.2,"0.00%"),IF(OR(L37=5,L37=7),TEXT((R37/N37),"0.00%")&"-"&TEXT((R37/N37)+7%,"0.00%"),""))) -> 2.00%-3.00% | AD37: =ROUND(N37*AC37,0) -> 0 | AE37: =V37+AD37 -> 12600 | AF37: =AE37-N37 -> 100 | AG37: =AE37/N37-1 -> 0.008 | AH37: 14 | AI37: 450 | AK37: 688 | AL37: =AE37*AH37+AI37*12+AK37+IF(AB37="",AJ37,IF(AB37="D",5000,IF(AB37="C",1000,0)))*12 -> 182488 | AM37: 3 | AP37: Left/will leave/retire soon | AQ37: Ding Xudong（15000307） | AR37: Xu Lan（11013544） | AS37: Zhao Chujun | AU37: exceed +/-20% adjustment | AV37: <20 | AW37: =_xlfn.LET(_xlpm.actual,X37,_xlpm.low,VALUE(_xlfn.TEXTBEFORE(Y37,"-")),_xlpm.high,VALUE(_xlfn.TEXTAFTER(Y37,"-")),IF(AND(_xlpm.actual=0,OR(_xlpm.low<>0,_xlpm.high<>0)),"0 increase",IF(_xlpm.actual>_xlpm.high*1.2,">20",IF(_xlpm.actual<_xlpm.low*0.8,"<20","OK")))) -> <20 | AX37: 16-20 | AY37: 70-90
A38: CN15 | B38: 15016938 | C38: Indirect Active | D38: OP | E38: SNa | F38: FEDNa-MEP | G38: 370200 | H38: 42830 | I38: Supervisor | J38: Head of FEDNa-MEP | K38: BAND A6 | L38: 2 | M38: 5 | N38: 18000 | O38: 0.05 | P38: =ROUND(N38*O38,0) -> 900 | Q38: 0.027 | R38: =ROUND(N38*Q38,0) -> 486 | S38: =T38/N38 -> 0.077 | T38: =P38+R38 -> 1386 | U38: =N38+T38 -> 19386 | V38: 19700 | W38: =V38-N38 -> 1700 | X38: =ROUND(V38/N38-1,4) -> 0.0944 | Y38: =IF(OR(L38=1,L38=2,L38=4),TEXT(S38*0.8,"0.00%")&"-"&TEXT(S38*1.2,"0.00%"),IF(OR(L38=3,L38=6),TEXT(0,"0.00%")&"-"&TEXT(7%*1.2,"0.00%"),IF(OR(L38=5,L38=7),TEXT((R38/N38),"0.00%")&"-"&TEXT((R38/N38)+7%,"0.00%"),""))) -> 6.16%-9.24% | AD38: =ROUND(N38*AC38,0) -> 0 | AE38: =V38+AD38 -> 19700 | AF38: =AE38-N38 -> 1700 | AG38: =AE38/N38-1 -> 0.094444444 | AH38: 14 | AI38: 450 | AK38: 688 | AL38: =AE38*AH38+AI38*12+AK38+IF(AB38="",AJ38,IF(AB38="D",5000,IF(AB38="C",1000,0)))*12 -> 281888 | AM38: 5 | AP38: Good performance/talent | AQ38: Ding Xudong（15000307） | AR38: Xu Lan（11013544） | AS38: Zhao Chujun | AU38: exceed +/-20% adjustment | AV38: >20 | AW38: =_xlfn.LET(_xlpm.actual,X38,_xlpm.low,VALUE(_xlfn.TEXTBEFORE(Y38,"-")),_xlpm.high,VALUE(_xlfn.TEXTAFTER(Y38,"-")),IF(AND(_xlpm.actual=0,OR(_xlpm.low<>0,_xlpm.high<>0)),"0 increase",IF(_xlpm.actual>_xlpm.high*1.2,">20",IF(_xlpm.actual<_xlpm.low*0.8,"<20","OK")))) -> OK | AX38: 6-10 | AY38: 70-90
A39: CN15 | B39: 15000503 | C39: Indirect Active | D39: OP | E39: SNa | F39: FEDNa-V1 | G39: 370402 | H39: 38852 | I39: Senior Engineer | J39: Senior Process Engineer | K39: BAND A5 | L39: 2 | M39: 4 | N39: 10000 | O39: 0.045 | P39: =ROUND(N39*O39,0) -> 450 | Q39: 0.0421 | R39: =ROUND(N39*Q39,0) -> 421 | S39: =T39/N39 -> 0.0871 | T39: =P39+R39 -> 871 | U39: =N39+T39 -> 10871 | V39: 10700 | W39: =V39-N39 -> 700 | X39: =ROUND(V39/N39-1,4) -> 0.07 | Y39: =IF(OR(L39=1,L39=2,L39=4),TEXT(S39*0.8,"0.00%")&"-"&TEXT(S39*1.2,"0.00%"),IF(OR(L39=3,L39=6),TEXT(0,"0.00%")&"-"&TEXT(7%*1.2,"0.00%"),IF(OR(L39=5,L39=7),TEXT((R39/N39),"0.00%")&"-"&TEXT((R39/N39)+7%,"0.00%"),""))) -> 6.97%-10.45% | AD39: =ROUND(N39*AC39,0) -> 0 | AE39: =V39+AD39 -> 10700 | AF39: =AE39-N39 -> 700 | AG39: =AE39/N39-1 -> 0.07 | AH39: 14 | AI39: 450 | AK39: 688 | AL39: =AE39*AH39+AI39*12+AK39+IF(AB39="",AJ39,IF(AB39="D",5000,IF(AB39="C",1000,0)))*12 -> 155888 | AM39: 3 | AQ39: Ding Xudong（15000307） | AR39: Xu Lan（11013544） | AS39: Zhao Chujun | AW39: =_xlfn.LET(_xlpm.actual,X39,_xlpm.low,VALUE(_xlfn.TEXTBEFORE(Y39,"-")),_xlpm.high,VALUE(_xlfn.TEXTAFTER(Y39,"-")),IF(AND(_xlpm.actual=0,OR(_xlpm.low<>0,_xlpm.high<>0)),"0 increase",IF(_xlpm.actual>_xlpm.high*1.2,">20",IF(_xlpm.actual<_xlpm.low*0.8,"<20","OK")))) -> OK | AX39: 16-20 | AY39: 50-70
A40: CN15 | B40: 15013780 | C40: Indirect Active | D40: OP | E40: SNa | F40: FLCNa-MEA | G40: 340200 | H40: 41976 | I40: Functional Specialist | J40: Injection Functional Specialist | K40: BAND A6 | L40: 2 | M40: 3 | N40: 14666 | O40: 0.03 | P40: =ROUND(N40*O40,0) -> 440 | Q40: 0 | R40: =ROUND(N40*Q40,0) -> 0 | S40: =T40/N40 -> 0.030001364 | T40: =P40+R40 -> 440 | U40: =N40+T40 -> 15106 | V40: 15017.984 | W40: =V40-N40 -> 351.984 | X40: =ROUND(V40/N40-1,4) -> 0.024 | Y40: =IF(OR(L40=1,L40=2,L40=4),TEXT(S40*0.8,"0.00%")&"-"&TEXT(S40*1.2,"0.00%"),IF(OR(L40=3,L40=6),TEXT(0,"0.00%")&"-"&TEXT(7%*1.2,"0.00%"),IF(OR(L40=5,L40=7),TEXT((R40/N40),"0.00%")&"-"&TEXT((R40/N40)+7%,"0.00%"),""))) -> 2.40%-3.60% | AD40: =ROUND(N40*AC40,0) -> 0 | AE40: =V40+AD40 -> 15017.984 | AF40: =AE40-N40 -> 351.984 | AG40: =AE40/N40-1 -> 0.024 | AH40: 14 | AI40: 450 | AK40: 688 | AL40: =AE40*AH40+AI40*12+AK40+IF(AB40="",AJ40,IF(AB40="D",5000,IF(AB40="C",1000,0)))*12 -> 216339.78 | AM40: 5 | AQ40: Hu Jun（51202067） | AR40: Mo Xiaohong（11005372） | AS40: Zhao Chujun | AW40: =_xlfn.LET(_xlpm.actual,X40,_xlpm.low,VALUE(_xlfn.TEXTBEFORE(Y40,"-")),_xlpm.high,VALUE(_xlfn.TEXTAFTER(Y40,"-")),IF(AND(_xlpm.actual=0,OR(_xlpm.low<>0,_xlpm.high<>0)),"0 increase",IF(_xlpm.actual>_xlpm.high*1.2,">20",IF(_xlpm.actual<_xlpm.low*0.8,"<20","OK")))) -> OK | AX40: 11-15 | AY40: 50-70
A41: CN15 | B41: 15004180 | C41: Indirect Active | D41: OP | E41: SNa | F41: FLCNa-MEF | G41: 340200 | H41: 40373 | I41: Expert (CN) | J41: Expert (CN) | K41: BAND B | L41: 2 | M41: 4 | N41: 23000 | O41: 0.0375 | P41: =ROUND(N41*O41,0) -> 863 | Q41: 0.0155 | R41: =ROUND(N41*Q41,0) -> 357 | S41: =T41/N41 -> 0.053043478 | T41: =P41+R41 -> 1220 | U41: =N41+T41 -> 24220 | V41: 23989 | W41: =V41-N41 -> 989 | X41: =ROUND(V41/N41-1,4) -> 0.043 | Y41: =IF(OR(L41=1,L41=2,L41=4),TEXT(S41*0.8,"0.00%")&"-"&TEXT(S41*1.2,"0.00%"),IF(OR(L41=3,L41=6),TEXT(0,"0.00%")&"-"&TEXT(7%*1.2,"0.00%"),IF(OR(L41=5,L41=7),TEXT((R41/N41),"0.00%")&"-"&TEXT((R41/N41)+7%,"0.00%"),""))) -> 4.24%-6.37% | AD41: =ROUND(N41*AC41,0) -> 0 | AE41: =V41+AD41 -> 23989 | AF41: =AE41-N41 -> 989 | AG41: =AE41/N41-1 -> 0.043 | AH41: 14 | AI41: 450 | AK41: 688 | AL41: =AE41*AH41+AI41*12+AK41+IF(AB41="",AJ41,IF(AB41="D",5000,IF(AB41="C",1000,0)))*12 -> 341934 | AM41: 4 | AQ41: Hu Jun（51202067） | AR41: Mo Xiaohong（11005372） | AS41: Zhao Chujun | AW41: =_xlfn.LET(_xlpm.actual,X41,_xlpm.low,VALUE(_xlfn.TEXTBEFORE(Y41,"-")),_xlpm.high,VALUE(_xlfn.TEXTAFTER(Y41,"-")),IF(AND(_xlpm.actual=0,OR(_xlpm.low<>0,_xlpm.high<>0)),"0 increase",IF(_xlpm.actual>_xlpm.high*1.2,">20",IF(_xlpm.actual<_xlpm.low*0.8,"<20","OK")))) -> OK | AX41: 11-15 | AY41: 70-90
A42: CN15 | B42: 15022173 | C42: Indirect Active | D42: OP | E42: SNa | F42: FLCNa-MEA | G42: 340200 | H42: 44671 | I42: Engineer | J42: Electrical Engineer | K42: BAND A4 | L42: 2 | M42: 3 | N42: 10712 | O42: 0 | P42: =ROUND(N42*O42,0) -> 0 | Q42: 0 | R42: =ROUND(N42*Q42,0) -> 0 | S42: =T42/N42 -> 0 | T42: =P42+R42 -> 0 | U42: =N42+T42 -> 10712 | V42: 11067 | W42: =V42-N42 -> 355 | X42: =ROUND(V42/N42-1,4) -> 0.0331 | Y42: =IF(OR(L42=1,L42=2,L42=4),TEXT(S42*0.8,"0.00%")&"-"&TEXT(S42*1.2,"0.00%"),IF(OR(L42=3,L42=6),TEXT(0,"0.00%")&"-"&TEXT(7%*1.2,"0.00%"),IF(OR(L42=5,L42=7),TEXT((R42/N42),"0.00%")&"-"&TEXT((R42/N42)+7%,"0.00%"),""))) -> 0.00%-0.00% | AD42: =ROUND(N42*AC42,0) -> 0 | AE42: =V42+AD42 -> 11067 | AF42: =AE42-N42 -> 355 | AG42: =AE42/N42-1 -> 0.033140403 | AH42: 14 | AI42: 450 | AK42: 688 | AL42: =AE42*AH42+AI42*12+AK42+IF(AB42="",AJ42,IF(AB42="D",5000,IF(AB42="C",1000,0)))*12 -> 161026 | AM42: 2 | AO42: very professional PLC engineer, lower salary | AP42: Good performers with relatively lower salary | AQ42: Hu Jun（51202067） | AR42: Mo Xiaohong（11005372） | AS42: Zhao Chujun | AU42: exceed +/-20% adjustment | AV42: >20 | AW42: =_xlfn.LET(_xlpm.actual,X42,_xlpm.low,VALUE(_xlfn.TEXTBEFORE(Y42,"-")),_xlpm.high,VALUE(_xlfn.TEXTAFTER(Y42,"-")),IF(AND(_xlpm.actual=0,OR(_xlpm.low<>0,_xlpm.high<>0)),"0 increase",IF(_xlpm.actual>_xlpm.high*1.2,">20",IF(_xlpm.actual<_xlpm.low*0.8,"<20","OK")))) -> >20 | AX42: 0-5 | AY42: >90
A43: CN15 | B43: 15017727 | C43: Indirect Active | D43: OP | E43: SNa | F43: FLCNa-MEA | G43: 340200 | H43: 42935 | I43: Associate Expert (CN) | J43: Associate Expert (C) | K43: BAND A6 | L43: 2 | M43: 3 | N43: 13202 | O43: 0.03 | P43: =ROUND(N43*O43,0) -> 396 | Q43: 0 | R43: =ROUND(N43*Q43,0) -> 0 | S43: =T43/N43 -> 0.029995455 | T43: =P43+R43 -> 396 | U43: =N43+T43 -> 13598 | V43: =N43+100 -> 13302 | W43: =V43-N43 -> 100 | X43: =ROUND(V43/N43-1,4) -> 0.0076 | Y43: =IF(OR(L43=1,L43=2,L43=4),TEXT(S43*0.8,"0.00%")&"-"&TEXT(S43*1.2,"0.00%"),IF(OR(L43=3,L43=6),TEXT(0,"0.00%")&"-"&TEXT(7%*1.2,"0.00%"),IF(OR(L43=5,L43=7),TEXT((R43/N43),"0.00%")&"-"&TEXT((R43/N43)+7%,"0.00%"),""))) -> 2.40%-3.60% | AD43: =ROUND(N43*AC43,0) -> 0 | AE43: =V43+AD43 -> 13302 | AF43: =AE43-N43 -> 100 | AG43: =AE43/N43-1 -> 0.0075746099 | AH43: 14 | AI43: 450 | AK43: 688 | AL43: =AE43*AH43+AI43*12+AK43+IF(AB43="",AJ43,IF(AB43="D",5000,IF(AB43="C",1000,0)))*12 -> 192316 | AM43: 3 | AO43: Less responsibility compare with job level with relative low performance | AP43: Less responsibility compare with job level | AQ43: Hu Jun（51202067） | AR43: Mo Xiaohong（11005372） | AS43: Zhao Chujun | AU43: exceed +/-20% adjustment | AV43: <20 | AW43: =_xlfn.LET(_xlpm.actual,X43,_xlpm.low,VALUE(_xlfn.TEXTBEFORE(Y43,"-")),_xlpm.high,VALUE(_xlfn.TEXTAFTER(Y43,"-")),IF(AND(_xlpm.actual=0,OR(_xlpm.low<>0,_xlpm.high<>0)),"0 increase",IF(_xlpm.actual>_xlpm.high*1.2,">20",IF(_xlpm.actual<_xlpm.low*0.8,"<20","OK")))) -> <20 | AX43: 6-10 | AY43: 50-70
A44: CN15 | B44: 51200268 | C44: Indirect Active | D44: OP | E44: SNa | F44: FLCNa-MEA | G44: 340200 | H44: 35977 | I44: Manager | J44: Head of Assembly | K44: BAND B | L44: 2 | M44: 3 | N44: 24800 | O44: 0.025 | P44: =ROUND(N44*O44,0) -> 620 | Q44: 0 | R44: =ROUND(N44*Q44,0) -> 0 | S44: =T44/N44 -> 0.025 | T44: =P44+R44 -> 620 | U44: =N44+T44 -> 25420 | V44: =U44-120 -> 25300 | W44: =V44-N44 -> 500 | X44: =ROUND(V44/N44-1,4) -> 0.0202 | Y44: =IF(OR(L44=1,L44=2,L44=4),TEXT(S44*0.8,"0.00%")&"-"&TEXT(S44*1.2,"0.00%"),IF(OR(L44=3,L44=6),TEXT(0,"0.00%")&"-"&TEXT(7%*1.2,"0.00%"),IF(OR(L44=5,L44=7),TEXT((R44/N44),"0.00%")&"-"&TEXT((R44/N44)+7%,"0.00%"),""))) -> 2.00%-3.00% | AD44: =ROUND(N44*AC44,0) -> 0 | AE44: =V44+AD44 -> 25300 | AF44: =AE44-N44 -> 500 | AG44: =AE44/N44-1 -> 0.02016129 | AH44: 14 | AI44: 3450 | AK44: 688 | AL44: =AE44*AH44+AI44*12+AK44+IF(AB44="",AJ44,IF(AB44="D",5000,IF(AB44="C",1000,0)))*12 -> 396288 | AM44: 5 | AQ44: Hu Jun（51202067） | AR44: Mo Xiaohong（11005372） | AS44: Zhao Chujun | AW44: =_xlfn.LET(_xlpm.actual,X44,_xlpm.low,VALUE(_xlfn.TEXTBEFORE(Y44,"-")),_xlpm.high,VALUE(_xlfn.TEXTAFTER(Y44,"-")),IF(AND(_xlpm.actual=0,OR(_xlpm.low<>0,_xlpm.high<>0)),"0 increase",IF(_xlpm.actual>_xlpm.high*1.2,">20",IF(_xlpm.actual<_xlpm.low*0.8,"<20","OK")))) -> OK | AX44: 26-30 | AY44: 70-90
A45: CN15 | B45: 15014437 | C45: Indirect Active | D45: OP | E45: SNa | F45: FLCNa-ME | G45: 340200 | H45: 42149 | I45: Manager | J45: Manager | K45: BAND B | L45: 2 | M45: 3 | N45: 28188 | O45: 0.025 | P45: =ROUND(N45*O45,0) -> 705 | Q45: 0 | R45: =ROUND(N45*Q45,0) -> 0 | S45: =T45/N45 -> 0.025010643 | T45: =P45+R45 -> 705 | U45: =N45+T45 -> 28893 | V45: 28751.76 | W45: =V45-N45 -> 563.76 | X45: =ROUND(V45/N45-1,4) -> 0.02 | Y45: =IF(OR(L45=1,L45=2,L45=4),TEXT(S45*0.8,"0.00%")&"-"&TEXT(S45*1.2,"0.00%"),IF(OR(L45=3,L45=6),TEXT(0,"0.00%")&"-"&TEXT(7%*1.2,"0.00%"),IF(OR(L45=5,L45=7),TEXT((R45/N45),"0.00%")&"-"&TEXT((R45/N45)+7%,"0.00%"),""))) -> 2.00%-3.00% | AD45: =ROUND(N45*AC45,0) -> 0 | AE45: =V45+AD45 -> 28751.76 | AF45: =AE45-N45 -> 563.76 | AG45: =AE45/N45-1 -> 0.02 | AH45: 14 | AI45: 450 | AK45: 688 | AL45: =AE45*AH45+AI45*12+AK45+IF(AB45="",AJ45,IF(AB45="D",5000,IF(AB45="C",1000,0)))*12 -> 408612.64 | AM45: 3 | AQ45: Hu Jun（51202067） | AR45: Mo Xiaohong（11005372） | AS45: Zhao Chujun | AW45: =_xlfn.LET(_xlpm.actual,X45,_xlpm.low,VALUE(_xlfn.TEXTBEFORE(Y45,"-")),_xlpm.high,VALUE(_xlfn.TEXTAFTER(Y45,"-")),IF(AND(_xlpm.actual=0,OR(_xlpm.low<>0,_xlpm.high<>0)),"0 increase",IF(_xlpm.actual>_xlpm.high*1.2,">20",IF(_xlpm.actual<_xlpm.low*0.8,"<20","OK")))) -> OK | AX45: 11-15 | AY45: 70-90
A46: CN15 | B46: 15022075 | C46: Indirect Active | D46: OP | E46: SNa | F46: FLCNa-MEA | G46: 340200 | H46: 44524 | I46: Engineer | J46: Assembly Process Engineer | K46: BAND A4 | L46: 2 | M46: 4 | N46: 12645 | O46: 0.03 | P46: =ROUND(N46*O46,0) -> 379 | Q46: 0 | R46: =ROUND(N46*Q46,0) -> 0 | S46: =T46/N46 -> 0.029972321 | T46: =P46+R46 -> 379 | U46: =N46+T46 -> 13024 | V46: =N46 -> 12645 | W46: =V46-N46 -> 0 | X46: =ROUND(V46/N46-1,4) -> 0 | Y46: =IF(OR(L46=1,L46=2,L46=4),TEXT(S46*0.8,"0.00%")&"-"&TEXT(S46*1.2,"0.00%"),IF(OR(L46=3,L46=6),TEXT(0,"0.00%")&"-"&TEXT(7%*1.2,"0.00%"),IF(OR(L46=5,L46=7),TEXT((R46/N46),"0.00%")&"-"&TEXT((R46/N46)+7%,"0.00%"),""))) -> 2.40%-3.60% | Z46: Promotion | AA46: Senior Assembly Process Engineer | AB46: A5 | AC46: 0.1 | AD46: =ROUND(N46*AC46,0) -> 1265 | AE46: =V46+AD46 -> 13910 | AF46: =AE46-N46 -> 1265 | AG46: =AE46/N46-1 -> 0.10003954 | AH46: 14 | AI46: 450 | AK46: 688 | AL46: =AE46*AH46+AI46*12+AK46+IF(AB46="",AJ46,IF(AB46="D",5000,IF(AB46="C",1000,0)))*12 -> 200828 | AM46: 4 | AO46: Very positive feedback from VS and high potential in assembly team，combined with promotion | AP46: Combined with promotion | AQ46: Hu Jun（51202067） | AR46: Mo Xiaohong（11005372） | AS46: Zhao Chujun | AU46: recommend increasing but propose zero increase | AW46: =_xlfn.LET(_xlpm.actual,X46,_xlpm.low,VALUE(_xlfn.TEXTBEFORE(Y46,"-")),_xlpm.high,VALUE(_xlfn.TEXTAFTER(Y46,"-")),IF(AND(_xlpm.actual=0,OR(_xlpm.low<>0,_xlpm.high<>0)),"0 increase",IF(_xlpm.actual>_xlpm.high*1.2,">20",IF(_xlpm.actual<_xlpm.low*0.8,"<20","OK")))) -> 0 increase | AX46: 0-5 | AY46: 90-110
A47: CN15 | B47: 15001880 | C47: Indirect Active | D47: OP | E47: SNa | F47: FLCNa-MEF | G47: 340200 | H47: 39657 | I47: Junior Engineer | J47: Junior Engineer | K47: BAND A3 | L47: 2 | M47: 3 | N47: 7538 | O47: 0.025 | P47: =ROUND(N47*O47,0) -> 188 | Q47: 0 | R47: =ROUND(N47*Q47,0) -> 0 | S47: =T47/N47 -> 0.024940302 | T47: =P47+R47 -> 188 | U47: =N47+T47 -> 7726 | V47: 7726 | W47: =V47-N47 -> 188 | X47: =ROUND(V47/N47-1,4) -> 0.0249 | Y47: =IF(OR(L47=1,L47=2,L47=4),TEXT(S47*0.8,"0.00%")&"-"&TEXT(S47*1.2,"0.00%"),IF(OR(L47=3,L47=6),TEXT(0,"0.00%")&"-"&TEXT(7%*1.2,"0.00%"),IF(OR(L47=5,L47=7),TEXT((R47/N47),"0.00%")&"-"&TEXT((R47/N47)+7%,"0.00%"),""))) -> 2.00%-2.99% | AD47: =ROUND(N47*AC47,0) -> 0 | AE47: =V47+AD47 -> 7726 | AF47: =AE47-N47 -> 188 | AG47: =AE47/N47-1 -> 0.024940302 | AH47: 14 | AI47: 450 | AK47: 688 | AL47: =AE47*AH47+AI47*12+AK47+IF(AB47="",AJ47,IF(AB47="D",5000,IF(AB47="C",1000,0)))*12 -> 114252 | AM47: NA | AQ47: Hu Jun（51202067） | AR47: Mo Xiaohong（11005372） | AS47: Zhao Chujun | AW47: =_xlfn.LET(_xlpm.actual,X47,_xlpm.low,VALUE(_xlfn.TEXTBEFORE(Y47,"-")),_xlpm.high,VALUE(_xlfn.TEXTAFTER(Y47,"-")),IF(AND(_xlpm.actual=0,OR(_xlpm.low<>0,_xlpm.high<>0)),"0 increase",IF(_xlpm.actual>_xlpm.high*1.2,">20",IF(_xlpm.actual<_xlpm.low*0.8,"<20","OK")))) -> OK | AX47: 16-20 | AY47: 70-90
A48: CN15 | B48: 15001698 | C48: Indirect Active | D48: OP | E48: SNa | F48: FLCNa-MEF | G48: 340200 | H48: 39616 | I48: Senior Engineer | J48: Senior Manufacturing Engineer | K48: BAND A5 | L48: 2 | M48: 4 | N48: 11737 | O48: 0.0375 | P48: =ROUND(N48*O48,0) -> 440 | Q48: 0.0155 | R48: =ROUND(N48*Q48,0) -> 182 | S48: =T48/N48 -> 0.052994803 | T48: =P48+R48 -> 622 | U48: =N48+T48 -> 12359 | V48: 12659 | W48: =V48-N48 -> 922 | X48: =ROUND(V48/N48-1,4) -> 0.0786 | Y48: =IF(OR(L48=1,L48=2,L48=4),TEXT(S48*0.8,"0.00%")&"-"&TEXT(S48*1.2,"0.00%"),IF(OR(L48=3,L48=6),TEXT(0,"0.00%")&"-"&TEXT(7%*1.2,"0.00%"),IF(OR(L48=5,L48=7),TEXT((R48/N48),"0.00%")&"-"&TEXT((R48/N48)+7%,"0.00%"),""))) -> 4.24%-6.36% | AD48: =ROUND(N48*AC48,0) -> 0 | AE48: =V48+AD48 -> 12659 | AF48: =AE48-N48 -> 922 | AG48: =AE48/N48-1 -> 0.078554997 | AH48: 14 | AI48: 450 | AK48: 688 | AL48: =AE48*AH48+AI48*12+AK48+IF(AB48="",AJ48,IF(AB48="D",5000,IF(AB48="C",1000,0)))*12 -> 183314 | AM48: 3 | AO48: Excellent performance in laser welding relocation。同时兼任FLCNa,FLCCh 两家工厂的内筒激光焊接 | AP48: Significantly enlarged responsibilities with proven performance | AQ48: Hu Jun（51202067） | AR48: Mo Xiaohong（11005372） | AS48: Zhao Chujun | AU48: exceed +/-20% adjustment | AV48: >20 | AW48: =_xlfn.LET(_xlpm.actual,X48,_xlpm.low,VALUE(_xlfn.TEXTBEFORE(Y48,"-")),_xlpm.high,VALUE(_xlfn.TEXTAFTER(Y48,"-")),IF(AND(_xlpm.actual=0,OR(_xlpm.low<>0,_xlpm.high<>0)),"0 increase",IF(_xlpm.actual>_xlpm.high*1.2,">20",IF(_xlpm.actual<_xlpm.low*0.8,"<20","OK")))) -> >20 | AX48: 16-20 | AY48: 70-90
A49: CN15 | B49: 15003323 | C49: Indirect Active | D49: OP | E49: SNa | F49: FLCNa-MEM | G49: 340433 | H49: 40238 | I49: Supervisor | J49: Supervisor | K49: BAND A6 | L49: 2 | M49: 3 | N49: 18000 | O49: 0 | P49: =ROUND(N49*O49,0) -> 0 | Q49: 0 | R49: =ROUND(N49*Q49,0) -> 0 | S49: =T49/N49 -> 0 | T49: =P49+R49 -> 0 | U49: =N49+T49 -> 18000 | V49: 18000 | W49: =V49-N49 -> 0 | X49: =ROUND(V49/N49-1,4) -> 0 | Y49: =IF(OR(L49=1,L49=2,L49=4),TEXT(S49*0.8,"0.00%")&"-"&TEXT(S49*1.2,"0.00%"),IF(OR(L49=3,L49=6),TEXT(0,"0.00%")&"-"&TEXT(7%*1.2,"0.00%"),IF(OR(L49=5,L49=7),TEXT((R49/N49),"0.00%")&"-"&TEXT((R49/N49)+7%,"0.00%"),""))) -> 0.00%-0.00% | AD49: =ROUND(N49*AC49,0) -> 0 | AE49: =V49+AD49 -> 18000 | AF49: =AE49-N49 -> 0 | AG49: =AE49/N49-1 -> 0 | AH49: 14 | AI49: 450 | AK49: 688 | AL49: =AE49*AH49+AI49*12+AK49+IF(AB49="",AJ49,IF(AB49="D",5000,IF(AB49="C",1000,0)))*12 -> 258088 | AM49: 4 | AQ49: Hu Jun（51202067） | AR49: Mo Xiaohong（11005372） | AS49: Zhao Chujun | AW49: =_xlfn.LET(_xlpm.actual,X49,_xlpm.low,VALUE(_xlfn.TEXTBEFORE(Y49,"-")),_xlpm.high,VALUE(_xlfn.TEXTAFTER(Y49,"-")),IF(AND(_xlpm.actual=0,OR(_xlpm.low<>0,_xlpm.high<>0)),"0 increase",IF(_xlpm.actual>_xlpm.high*1.2,">20",IF(_xlpm.actual<_xlpm.low*0.8,"<20","OK")))) -> OK | AX49: 16-20 | AY49: >90
A50: CN15 | B50: 15021416 | C50: Indirect Active | D50: OP | E50: SNa | F50: FLCNa-MEA | G50: 340200 | H50: 44370 | I50: Engineer | J50: Automation Engineer | K50: BAND A4 | L50: 2 | M50: 5 | N50: 12793 | O50: 0.04 | P50: =ROUND(N50*O50,0) -> 512 | Q50: 0 | R50: =ROUND(N50*Q50,0) -> 0 | S50: =T50/N50 -> 0.040021887 | T50: =P50+R50 -> 512 | U50: =N50+T50 -> 13305 | V50: =N50 -> 12793 | W50: =V50-N50 -> 0 | X50: =ROUND(V50/N50-1,4) -> 0 | Y50: =IF(OR(L50=1,L50=2,L50=4),TEXT(S50*0.8,"0.00%")&"-"&TEXT(S50*1.2,"0.00%"),IF(OR(L50=3,L50=6),TEXT(0,"0.00%")&"-"&TEXT(7%*1.2,"0.00%"),IF(OR(L50=5,L50=7),TEXT((R50/N50),"0.00%")&"-"&TEXT((R50/N50)+7%,"0.00%"),""))) -> 3.20%-4.80% | Z50: Promotion | AA50: Senior Automation Engineer | AB50: A5 | AC50: 0.11 | AD50: =ROUND(N50*AC50,0) -> 1407 | AE50: =V50+AD50 -> 14200 | AF50: =AE50-N50 -> 1407 | AG50: =AE50/N50-1 -> 0.10998202 | AH50: 14 | AI50: 450 | AK50: 688 | AL50: =AE50*AH50+AI50*12+AK50+IF(AB50="",AJ50,IF(AB50="D",5000,IF(AB50="C",1000,0)))*12 -> 204888 | AM50: 3 | AO50: Testing expert: critical and urgently needed in the factory, combined with promotion. | AP50: Combined with promotion | AQ50: Hu Jun（51202067） | AR50: Mo Xiaohong（11005372） | AS50: Zhao Chujun | AU50: recommend increasing but propose zero increase | AW50: =_xlfn.LET(_xlpm.actual,X50,_xlpm.low,VALUE(_xlfn.TEXTBEFORE(Y50,"-")),_xlpm.high,VALUE(_xlfn.TEXTAFTER(Y50,"-")),IF(AND(_xlpm.actual=0,OR(_xlpm.low<>0,_xlpm.high<>0)),"0 increase",IF(_xlpm.actual>_xlpm.high*1.2,">20",IF(_xlpm.actual<_xlpm.low*0.8,"<20","OK")))) -> 0 increase | AX50: 0-5 | AY50: 90-110
A51: CN15 | B51: 15020868 | C51: Indirect Active | D51: OP | E51: SNa | F51: FLCNa-MEF | G51: 340200 | H51: 44209 | I51: Senior Engineer | J51: Senior Injection Engineer | K51: BAND A5 | L51: 2 | M51: 3 | N51: 13285 | O51: 0.025 | P51: =ROUND(N51*O51,0) -> 332 | Q51: 0 | R51: =ROUND(N51*Q51,0) -> 0 | S51: =T51/N51 -> 0.024990591 | T51: =P51+R51 -> 332 | U51: =N51+T51 -> 13617 | V51: =U51-66 -> 13551 | W51: =V51-N51 -> 266 | X51: =ROUND(V51/N51-1,4) -> 0.02 | Y51: =IF(OR(L51=1,L51=2,L51=4),TEXT(S51*0.8,"0.00%")&"-"&TEXT(S51*1.2,"0.00%"),IF(OR(L51=3,L51=6),TEXT(0,"0.00%")&"-"&TEXT(7%*1.2,"0.00%"),IF(OR(L51=5,L51=7),TEXT((R51/N51),"0.00%")&"-"&TEXT((R51/N51)+7%,"0.00%"),""))) -> 2.00%-3.00% | AD51: =ROUND(N51*AC51,0) -> 0 | AE51: =V51+AD51 -> 13551 | AF51: =AE51-N51 -> 266 | AG51: =AE51/N51-1 -> 0.020022582 | AH51: 14 | AI51: 450 | AK51: 688 | AL51: =AE51*AH51+AI51*12+AK51+IF(AB51="",AJ51,IF(AB51="D",5000,IF(AB51="C",1000,0)))*12 -> 195802 | AM51: 2 | AQ51: Hu Jun（51202067） | AR51: Mo Xiaohong（11005372） | AS51: Zhao Chujun | AW51: =_xlfn.LET(_xlpm.actual,X51,_xlpm.low,VALUE(_xlfn.TEXTBEFORE(Y51,"-")),_xlpm.high,VALUE(_xlfn.TEXTAFTER(Y51,"-")),IF(AND(_xlpm.actual=0,OR(_xlpm.low<>0,_xlpm.high<>0)),"0 increase",IF(_xlpm.actual>_xlpm.high*1.2,">20",IF(_xlpm.actual<_xlpm.low*0.8,"<20","OK")))) -> OK | AX51: 0-5 | AY51: 70-90
A52: CN15 | B52: 15004889 | C52: Indirect Active | D52: OP | E52: SNa | F52: FLCNa-MEF | G52: 340200 | H52: 40490 | I52: Senior Engineer | J52: Senior Mould Managment Engineer | K52: BAND A5 | L52: 2 | M52: 3 | N52: 15150 | O52: 0 | P52: =ROUND(N52*O52,0) -> 0 | Q52: 0 | R52: =ROUND(N52*Q52,0) -> 0 | S52: =T52/N52 -> 0 | T52: =P52+R52 -> 0 | U52: =N52+T52 -> 15150 | V52: 15150 | W52: =V52-N52 -> 0 | X52: =ROUND(V52/N52-1,4) -> 0 | Y52: =IF(OR(L52=1,L52=2,L52=4),TEXT(S52*0.8,"0.00%")&"-"&TEXT(S52*1.2,"0.00%"),IF(OR(L52=3,L52=6),TEXT(0,"0.00%")&"-"&TEXT(7%*1.2,"0.00%"),IF(OR(L52=5,L52=7),TEXT((R52/N52),"0.00%")&"-"&TEXT((R52/N52)+7%,"0.00%"),""))) -> 0.00%-0.00% | AD52: =ROUND(N52*AC52,0) -> 0 | AE52: =V52+AD52 -> 15150 | AF52: =AE52-N52 -> 0 | AG52: =AE52/N52-1 -> 0 | AH52: 14 | AI52: 450 | AK52: 688 | AL52: =AE52*AH52+AI52*12+AK52+IF(AB52="",AJ52,IF(AB52="D",5000,IF(AB52="C",1000,0)))*12 -> 218188 | AM52: 4 | AQ52: Hu Jun（51202067） | AR52: Mo Xiaohong（11005372） | AS52: Zhao Chujun | AW52: =_xlfn.LET(_xlpm.actual,X52,_xlpm.low,VALUE(_xlfn.TEXTBEFORE(Y52,"-")),_xlpm.high,VALUE(_xlfn.TEXTAFTER(Y52,"-")),IF(AND(_xlpm.actual=0,OR(_xlpm.low<>0,_xlpm.high<>0)),"0 increase",IF(_xlpm.actual>_xlpm.high*1.2,">20",IF(_xlpm.actual<_xlpm.low*0.8,"<20","OK")))) -> OK | AX52: 11-15 | AY52: >90
A53: CN15 | B53: 15022143 | C53: Indirect Active | D53: OP | E53: SNa | F53: FLCNa-MEA | G53: 340200 | H53: 44615 | I53: Engineer | J53: Testing Engineer | K53: BAND A4 | L53: 2 | M53: 3 | N53: 9205 | O53: 0.025 | P53: =ROUND(N53*O53,0) -> 230 | Q53: 0 | R53: =ROUND(N53*Q53,0) -> 0 | S53: =T53/N53 -> 0.02498642 | T53: =P53+R53 -> 230 | U53: =N53+T53 -> 9435 | V53: 9205 | W53: =V53-N53 -> 0 | X53: =ROUND(V53/N53-1,4) -> 0 | Y53: =IF(OR(L53=1,L53=2,L53=4),TEXT(S53*0.8,"0.00%")&"-"&TEXT(S53*1.2,"0.00%"),IF(OR(L53=3,L53=6),TEXT(0,"0.00%")&"-"&TEXT(7%*1.2,"0.00%"),IF(OR(L53=5,L53=7),TEXT((R53/N53),"0.00%")&"-"&TEXT((R53/N53)+7%,"0.00%"),""))) -> 2.00%-3.00% | AD53: =ROUND(N53*AC53,0) -> 0 | AE53: =V53+AD53 -> 9205 | AF53: =AE53-N53 -> 0 | AG53: =AE53/N53-1 -> 0 | AH53: 14 | AI53: 450 | AK53: 688 | AL53: =AE53*AH53+AI53*12+AK53+IF(AB53="",AJ53,IF(AB53="D",5000,IF(AB53="C",1000,0)))*12 -> 134958 | AM53: 3 | AO53: Leave BSH in July | AP53: Left/will leave/retire soon | AQ53: Hu Jun（51202067） | AR53: Mo Xiaohong（11005372） | AS53: Zhao Chujun | AU53: recommend increasing but propose zero increase | AW53: =_xlfn.LET(_xlpm.actual,X53,_xlpm.low,VALUE(_xlfn.TEXTBEFORE(Y53,"-")),_xlpm.high,VALUE(_xlfn.TEXTAFTER(Y53,"-")),IF(AND(_xlpm.actual=0,OR(_xlpm.low<>0,_xlpm.high<>0)),"0 increase",IF(_xlpm.actual>_xlpm.high*1.2,">20",IF(_xlpm.actual<_xlpm.low*0.8,"<20","OK")))) -> 0 increase | AX53: 0-5 | AY53: 70-90
A54: CN15 | B54: 51200356 | C54: Indirect Active | D54: OP | E54: SNa | F54: FLCNa-MEF | G54: 340200 | H54: 35660 | I54: Senior Engineer | J54: Senior Engineer | K54: BAND A5 | L54: 2 | M54: 3 | N54: 12985 | O54: 0 | P54: =ROUND(N54*O54,0) -> 0 | Q54: 0 | R54: =ROUND(N54*Q54,0) -> 0 | S54: =T54/N54 -> 0 | T54: =P54+R54 -> 0 | U54: =N54+T54 -> 12985 | V54: 12985 | W54: =V54-N54 -> 0 | X54: =ROUND(V54/N54-1,4) -> 0 | Y54: =IF(OR(L54=1,L54=2,L54=4),TEXT(S54*0.8,"0.00%")&"-"&TEXT(S54*1.2,"0.00%"),IF(OR(L54=3,L54=6),TEXT(0,"0.00%")&"-"&TEXT(7%*1.2,"0.00%"),IF(OR(L54=5,L54=7),TEXT((R54/N54),"0.00%")&"-"&TEXT((R54/N54)+7%,"0.00%"),""))) -> 0.00%-0.00% | AD54: =ROUND(N54*AC54,0) -> 0 | AE54: =V54+AD54 -> 12985 | AF54: =AE54-N54 -> 0 | AG54: =AE54/N54-1 -> 0 | AH54: 14 | AI54: 3050 | AK54: 688 | AL54: =AE54*AH54+AI54*12+AK54+IF(AB54="",AJ54,IF(AB54="D",5000,IF(AB54="C",1000,0)))*12 -> 219078 | AM54: 3 | AQ54: Hu Jun（51202067） | AR54: Mo Xiaohong（11005372） | AS54: Zhao Chujun | AW54: =_xlfn.LET(_xlpm.actual,X54,_xlpm.low,VALUE(_xlfn.TEXTBEFORE(Y54,"-")),_xlpm.high,VALUE(_xlfn.TEXTAFTER(Y54,"-")),IF(AND(_xlpm.actual=0,OR(_xlpm.low<>0,_xlpm.high<>0)),"0 increase",IF(_xlpm.actual>_xlpm.high*1.2,">20",IF(_xlpm.actual<_xlpm.low*0.8,"<20","OK")))) -> OK | AX54: 26-30 | AY54: >90
A55: CN15 | B55: 15021286 | C55: Indirect Active | D55: OP | E55: SNa | F55: FLCNa-MEM | G55: 340433 | H55: 44328 | I55: Senior Engineer | J55: Senior Equipment Engineer | K55: BAND A5 | L55: 2 | M55: 5 | N55: 17480 | O55: 0.03 | P55: =ROUND(N55*O55,0) -> 524 | Q55: 0 | R55: =ROUND(N55*Q55,0) -> 0 | S55: =T55/N55 -> 0.029977117 | T55: =P55+R55 -> 524 | U55: =N55+T55 -> 18004 | V55: 18110 | W55: =V55-N55 -> 630 | X55: =ROUND(V55/N55-1,4) -> 0.036 | Y55: =IF(OR(L55=1,L55=2,L55=4),TEXT(S55*0.8,"0.00%")&"-"&TEXT(S55*1.2,"0.00%"),IF(OR(L55=3,L55=6),TEXT(0,"0.00%")&"-"&TEXT(7%*1.2,"0.00%"),IF(OR(L55=5,L55=7),TEXT((R55/N55),"0.00%")&"-"&TEXT((R55/N55)+7%,"0.00%"),""))) -> 2.40%-3.60% | AD55: =ROUND(N55*AC55,0) -> 0 | AE55: =V55+AD55 -> 18110 | AF55: =AE55-N55 -> 630 | AG55: =AE55/N55-1 -> 0.03604119 | AH55: 14 | AI55: 450 | AK55: 688 | AL55: =AE55*AH55+AI55*12+AK55+IF(AB55="",AJ55,IF(AB55="D",5000,IF(AB55="C",1000,0)))*12 -> 259628 | AM55: 4 | AQ55: Hu Jun（51202067） | AR55: Mo Xiaohong（11005372） | AS55: Zhao Chujun | AW55: =_xlfn.LET(_xlpm.actual,X55,_xlpm.low,VALUE(_xlfn.TEXTBEFORE(Y55,"-")),_xlpm.high,VALUE(_xlfn.TEXTAFTER(Y55,"-")),IF(AND(_xlpm.actual=0,OR(_xlpm.low<>0,_xlpm.high<>0)),"0 increase",IF(_xlpm.actual>_xlpm.high*1.2,">20",IF(_xlpm.actual<_xlpm.low*0.8,"<20","OK")))) -> OK | AX55: 0-5 | AY55: 110-130
A56: CN15 | B56: 15001700 | C56: Indirect Active | D56: OP | E56: SNa | F56: FLCNa-MEM | G56: 340433 | H56: 39616 | I56: Senior Engineer | J56: Senior Engineer | K56: BAND A5 | L56: 2 | M56: 4 | N56: 12391 | O56: 0.0375 | P56: =ROUND(N56*O56,0) -> 465 | Q56: 0.0155 | R56: =ROUND(N56*Q56,0) -> 192 | S56: =T56/N56 -> 0.053022355 | T56: =P56+R56 -> 657 | U56: =N56+T56 -> 13048 | V56: 13048 | W56: =V56-N56 -> 657 | X56: =ROUND(V56/N56-1,4) -> 0.053 | Y56: =IF(OR(L56=1,L56=2,L56=4),TEXT(S56*0.8,"0.00%")&"-"&TEXT(S56*1.2,"0.00%"),IF(OR(L56=3,L56=6),TEXT(0,"0.00%")&"-"&TEXT(7%*1.2,"0.00%"),IF(OR(L56=5,L56=7),TEXT((R56/N56),"0.00%")&"-"&TEXT((R56/N56)+7%,"0.00%"),""))) -> 4.24%-6.36% | AD56: =ROUND(N56*AC56,0) -> 0 | AE56: =V56+AD56 -> 13048 | AF56: =AE56-N56 -> 657 | AG56: =AE56/N56-1 -> 0.053022355 | AH56: 14 | AI56: 500 | AK56: 688 | AL56: =AE56*AH56+AI56*12+AK56+IF(AB56="",AJ56,IF(AB56="D",5000,IF(AB56="C",1000,0)))*12 -> 189360 | AM56: 2 | AQ56: Hu Jun（51202067） | AR56: Mo Xiaohong（11005372） | AS56: Zhao Chujun | AW56: =_xlfn.LET(_xlpm.actual,X56,_xlpm.low,VALUE(_xlfn.TEXTBEFORE(Y56,"-")),_xlpm.high,VALUE(_xlfn.TEXTAFTER(Y56,"-")),IF(AND(_xlpm.actual=0,OR(_xlpm.low<>0,_xlpm.high<>0)),"0 increase",IF(_xlpm.actual>_xlpm.high*1.2,">20",IF(_xlpm.actual<_xlpm.low*0.8,"<20","OK")))) -> OK | AX56: 16-20 | AY56: 70-90
A57: CN15 | B57: 15015379 | C57: Indirect Active | D57: OP | E57: SNa | F57: FLCNa-MEM | G57: 340433 | H57: 42543 | I57: Senior Engineer | J57: Senior Engineer | K57: BAND A5 | L57: 2 | M57: 4 | N57: 16100 | O57: 0.03 | P57: =ROUND(N57*O57,0) -> 483 | Q57: 0 | R57: =ROUND(N57*Q57,0) -> 0 | S57: =T57/N57 -> 0.03 | T57: =P57+R57 -> 483 | U57: =N57+T57 -> 16583 | V57: 16583 | W57: =V57-N57 -> 483 | X57: =ROUND(V57/N57-1,4) -> 0.03 | Y57: =IF(OR(L57=1,L57=2,L57=4),TEXT(S57*0.8,"0.00%")&"-"&TEXT(S57*1.2,"0.00%"),IF(OR(L57=3,L57=6),TEXT(0,"0.00%")&"-"&TEXT(7%*1.2,"0.00%"),IF(OR(L57=5,L57=7),TEXT((R57/N57),"0.00%")&"-"&TEXT((R57/N57)+7%,"0.00%"),""))) -> 2.40%-3.60% | AD57: =ROUND(N57*AC57,0) -> 0 | AE57: =V57+AD57 -> 16583 | AF57: =AE57-N57 -> 483 | AG57: =AE57/N57-1 -> 0.03 | AH57: 14 | AI57: 500 | AK57: 688 | AL57: =AE57*AH57+AI57*12+AK57+IF(AB57="",AJ57,IF(AB57="D",5000,IF(AB57="C",1000,0)))*12 -> 238850 | AM57: 4 | AQ57: Hu Jun（51202067） | AR57: Mo Xiaohong（11005372） | AS57: Zhao Chujun | AW57: =_xlfn.LET(_xlpm.actual,X57,_xlpm.low,VALUE(_xlfn.TEXTBEFORE(Y57,"-")),_xlpm.high,VALUE(_xlfn.TEXTAFTER(Y57,"-")),IF(AND(_xlpm.actual=0,OR(_xlpm.low<>0,_xlpm.high<>0)),"0 increase",IF(_xlpm.actual>_xlpm.high*1.2,">20",IF(_xlpm.actual<_xlpm.low*0.8,"<20","OK")))) -> OK | AX57: 6-10 | AY57: 90-110
A58: CN15 | B58: 15015653 | C58: Indirect Active | D58: OP | E58: SNa | F58: FLCNa-MEF | G58: 340200 | H58: 42634 | I58: Manager | J58: Head of Pre-Fabrication | K58: BAND B | L58: 2 | M58: 5 | N58: 21554 | O58: 0.06 | P58: =ROUND(N58*O58,0) -> 1293 | Q58: 0.0778 | R58: =ROUND(N58*Q58,0) -> 1677 | S58: =T58/N58 -> 0.13779345 | T58: =P58+R58 -> 2970 | U58: =N58+T58 -> 24524 | V58: 24221 | W58: =V58-N58 -> 2667 | X58: =ROUND(V58/N58-1,4) -> 0.1237 | Y58: =IF(OR(L58=1,L58=2,L58=4),TEXT(S58*0.8,"0.00%")&"-"&TEXT(S58*1.2,"0.00%"),IF(OR(L58=3,L58=6),TEXT(0,"0.00%")&"-"&TEXT(7%*1.2,"0.00%"),IF(OR(L58=5,L58=7),TEXT((R58/N58),"0.00%")&"-"&TEXT((R58/N58)+7%,"0.00%"),""))) -> 11.02%-16.54% | AD58: =ROUND(N58*AC58,0) -> 0 | AE58: =V58+AD58 -> 24221 | AF58: =AE58-N58 -> 2667 | AG58: =AE58/N58-1 -> 0.12373573 | AH58: 14 | AI58: 450 | AK58: 688 | AL58: =AE58*AH58+AI58*12+AK58+IF(AB58="",AJ58,IF(AB58="D",5000,IF(AB58="C",1000,0)))*12 -> 345182 | AM58: 5 | AQ58: Hu Jun（51202067） | AR58: Mo Xiaohong（11005372） | AS58: Zhao Chujun | AW58: =_xlfn.LET(_xlpm.actual,X58,_xlpm.low,VALUE(_xlfn.TEXTBEFORE(Y58,"-")),_xlpm.high,VALUE(_xlfn.TEXTAFTER(Y58,"-")),IF(AND(_xlpm.actual=0,OR(_xlpm.low<>0,_xlpm.high<>0)),"0 increase",IF(_xlpm.actual>_xlpm.high*1.2,">20",IF(_xlpm.actual<_xlpm.low*0.8,"<20","OK")))) -> OK | AX58: 6-10 | AY58: 0
A59: CN15 | B59: 15020094 | C59: Indirect Active | D59: OP | E59: SNa | F59: FLCNa-MEM | G59: 340433 | H59: 43908 | I59: Manager | J59: Head of Maintenance | K59: BAND B | L59: 2 | M59: 3 | N59: 20400 | O59: 0.03 | P59: =ROUND(N59*O59,0) -> 612 | Q59: 0 | R59: =ROUND(N59*Q59,0) -> 0 | S59: =T59/N59 -> 0.03 | T59: =P59+R59 -> 612 | U59: =N59+T59 -> 21012 | V59: 21012 | W59: =V59-N59 -> 612 | X59: =ROUND(V59/N59-1,4) -> 0.03 | Y59: =IF(OR(L59=1,L59=2,L59=4),TEXT(S59*0.8,"0.00%")&"-"&TEXT(S59*1.2,"0.00%"),IF(OR(L59=3,L59=6),TEXT(0,"0.00%")&"-"&TEXT(7%*1.2,"0.00%"),IF(OR(L59=5,L59=7),TEXT((R59/N59),"0.00%")&"-"&TEXT((R59/N59)+7%,"0.00%"),""))) -> 2.40%-3.60% | AD59: =ROUND(N59*AC59,0) -> 0 | AE59: =V59+AD59 -> 21012 | AF59: =AE59-N59 -> 612 | AG59: =AE59/N59-1 -> 0.03 | AH59: 14 | AI59: 450 | AK59: 688 | AL59: =AE59*AH59+AI59*12+AK59+IF(AB59="",AJ59,IF(AB59="D",5000,IF(AB59="C",1000,0)))*12 -> 300256 | AM59: 4 | AQ59: Hu Jun（51202067） | AR59: Mo Xiaohong（11005372） | AS59: Zhao Chujun | AW59: =_xlfn.LET(_xlpm.actual,X59,_xlpm.low,VALUE(_xlfn.TEXTBEFORE(Y59,"-")),_xlpm.high,VALUE(_xlfn.TEXTAFTER(Y59,"-")),IF(AND(_xlpm.actual=0,OR(_xlpm.low<>0,_xlpm.high<>0)),"0 increase",IF(_xlpm.actual>_xlpm.high*1.2,">20",IF(_xlpm.actual<_xlpm.low*0.8,"<20","OK")))) -> OK | AX59: 6-10 | AY59: 50-70
A60: CN15 | B60: 15022179 | C60: Indirect Active | D60: OP | E60: SNa | F60: FLCNa-MEM | G60: 340433 | H60: 44686 | I60: Engineer | J60: Tooling Engineer | K60: BAND A4 | L60: 2 | M60: 3 | N60: 12472 | O60: 0 | P60: =ROUND(N60*O60,0) -> 0 | Q60: 0 | R60: =ROUND(N60*Q60,0) -> 0 | S60: =T60/N60 -> 0 | T60: =P60+R60 -> 0 | U60: =N60+T60 -> 12472 | V60: 12700 | W60: =V60-N60 -> 228 | X60: =ROUND(V60/N60-1,4) -> 0.0183 | Y60: =IF(OR(L60=1,L60=2,L60=4),TEXT(S60*0.8,"0.00%")&"-"&TEXT(S60*1.2,"0.00%"),IF(OR(L60=3,L60=6),TEXT(0,"0.00%")&"-"&TEXT(7%*1.2,"0.00%"),IF(OR(L60=5,L60=7),TEXT((R60/N60),"0.00%")&"-"&TEXT((R60/N60)+7%,"0.00%"),""))) -> 0.00%-0.00% | AD60: =ROUND(N60*AC60,0) -> 0 | AE60: =V60+AD60 -> 12700 | AF60: =AE60-N60 -> 228 | AG60: =AE60/N60-1 -> 0.018280949 | AH60: 14 | AI60: 450 | AK60: 688 | AL60: =AE60*AH60+AI60*12+AK60+IF(AB60="",AJ60,IF(AB60="D",5000,IF(AB60="C",1000,0)))*12 -> 183888 | AM60: 3 | AO60: critical position in Mold with excellence performance in localization | AP60: Top critical position/player | AQ60: Hu Jun（51202067） | AR60: Mo Xiaohong（11005372） | AS60: Zhao Chujun | AU60: exceed +/-20% adjustment | AV60: >20 | AW60: =_xlfn.LET(_xlpm.actual,X60,_xlpm.low,VALUE(_xlfn.TEXTBEFORE(Y60,"-")),_xlpm.high,VALUE(_xlfn.TEXTAFTER(Y60,"-")),IF(AND(_xlpm.actual=0,OR(_xlpm.low<>0,_xlpm.high<>0)),"0 increase",IF(_xlpm.actual>_xlpm.high*1.2,">20",IF(_xlpm.actual<_xlpm.low*0.8,"<20","OK")))) -> >20 | AX60: 0-5 | AY60: >90
A61: CN15 | B61: 15022342 | C61: Indirect Active | D61: OP | E61: SNa | F61: FLCNa-MEA | G61: 340200 | H61: 45035 | I61: Senior Engineer | J61: Senior Assembly Engineer | K61: BAND A5 | L61: 2 | M61: 3 | N61: 11020 | O61: 0.03 | P61: =ROUND(N61*O61,0) -> 331 | Q61: 0 | R61: =ROUND(N61*Q61,0) -> 0 | S61: =T61/N61 -> 0.030036298 | T61: =P61+R61 -> 331 | U61: =N61+T61 -> 11351 | V61: 11751 | W61: =V61-N61 -> 731 | X61: =ROUND(V61/N61-1,4) -> 0.0663 | Y61: =IF(OR(L61=1,L61=2,L61=4),TEXT(S61*0.8,"0.00%")&"-"&TEXT(S61*1.2,"0.00%"),IF(OR(L61=3,L61=6),TEXT(0,"0.00%")&"-"&TEXT(7%*1.2,"0.00%"),IF(OR(L61=5,L61=7),TEXT((R61/N61),"0.00%")&"-"&TEXT((R61/N61)+7%,"0.00%"),""))) -> 2.40%-3.60% | AD61: =ROUND(N61*AC61,0) -> 0 | AE61: =V61+AD61 -> 11751 | AF61: =AE61-N61 -> 731 | AG61: =AE61/N61-1 -> 0.066333938 | AH61: 14 | AI61: 550 | AK61: 688 | AL61: =AE61*AH61+AI61*12+AK61+IF(AB61="",AJ61,IF(AB61="D",5000,IF(AB61="C",1000,0)))*12 -> 171802 | AM61: 5 | AO61: Excellent performance in India SKD project and new line rampup | AP61: Good performers with relatively lower salary | AQ61: Hu Jun（51202067） | AR61: Mo Xiaohong（11005372） | AS61: Zhao Chujun | AU61: exceed +/-20% adjustment | AV61: >20 | AW61: =_xlfn.LET(_xlpm.actual,X61,_xlpm.low,VALUE(_xlfn.TEXTBEFORE(Y61,"-")),_xlpm.high,VALUE(_xlfn.TEXTAFTER(Y61,"-")),IF(AND(_xlpm.actual=0,OR(_xlpm.low<>0,_xlpm.high<>0)),"0 increase",IF(_xlpm.actual>_xlpm.high*1.2,">20",IF(_xlpm.actual<_xlpm.low*0.8,"<20","OK")))) -> >20 | AX61: 0-5 | AY61: 50-70
A62: CN15 | B62: 15001449 | C62: Indirect Active | D62: OP | E62: SNa | F62: FLCNa-ME | G62: 340200 | H62: 39525 | I62: Engineer | J62: Electrical Engineer | K62: BAND A4 | L62: 2 | M62: 3 | N62: 12190 | O62: 0 | P62: =ROUND(N62*O62,0) -> 0 | Q62: 0 | R62: =ROUND(N62*Q62,0) -> 0 | S62: =T62/N62 -> 0 | T62: =P62+R62 -> 0 | U62: =N62+T62 -> 12190 | V62: 12190 | W62: =V62-N62 -> 0 | X62: =ROUND(V62/N62-1,4) -> 0 | Y62: =IF(OR(L62=1,L62=2,L62=4),TEXT(S62*0.8,"0.00%")&"-"&TEXT(S62*1.2,"0.00%"),IF(OR(L62=3,L62=6),TEXT(0,"0.00%")&"-"&TEXT(7%*1.2,"0.00%"),IF(OR(L62=5,L62=7),TEXT((R62/N62),"0.00%")&"-"&TEXT((R62/N62)+7%,"0.00%"),""))) -> 0.00%-0.00% | AD62: =ROUND(N62*AC62,0) -> 0 | AE62: =V62+AD62 -> 12190 | AF62: =AE62-N62 -> 0 | AG62: =AE62/N62-1 -> 0 | AH62: 14 | AI62: 450 | AK62: 688 | AL62: =AE62*AH62+AI62*12+AK62+IF(AB62="",AJ62,IF(AB62="D",5000,IF(AB62="C",1000,0)))*12 -> 176748 | AM62: 1 | AQ62: Hu Jun（51202067） | AR62: Mo Xiaohong（11005372） | AS62: Zhao Chujun | AW62: =_xlfn.LET(_xlpm.actual,X62,_xlpm.low,VALUE(_xlfn.TEXTBEFORE(Y62,"-")),_xlpm.high,VALUE(_xlfn.TEXTAFTER(Y62,"-")),IF(AND(_xlpm.actual=0,OR(_xlpm.low<>0,_xlpm.high<>0)),"0 increase",IF(_xlpm.actual>_xlpm.high*1.2,">20",IF(_xlpm.actual<_xlpm.low*0.8,"<20","OK")))) -> OK | AX62: 16-20 | AY62: >90
A63: CN15 | B63: 51202067 | C63: Indirect Active | D63: OP | E63: SNa | F63: FLCNa-ME | G63: 340100 | H63: 38292 | I63: Director | J63: Head of Manufacturing Engineering | K63: BAND C | L63: 2 | M63: 4 | N63: 49800 | O63: 0.03 | P63: =ROUND(N63*O63,0) -> 1494 | Q63: 0 | R63: =ROUND(N63*Q63,0) -> 0 | S63: =T63/N63 -> 0.03 | T63: =P63+R63 -> 1494 | U63: =N63+T63 -> 51294 | V63: 50100 | W63: =V63-N63 -> 300 | X63: =ROUND(V63/N63-1,4) -> 0.006 | Y63: =IF(OR(L63=1,L63=2,L63=4),TEXT(S63*0.8,"0.00%")&"-"&TEXT(S63*1.2,"0.00%"),IF(OR(L63=3,L63=6),TEXT(0,"0.00%")&"-"&TEXT(7%*1.2,"0.00%"),IF(OR(L63=5,L63=7),TEXT((R63/N63),"0.00%")&"-"&TEXT((R63/N63)+7%,"0.00%"),""))) -> 2.40%-3.60% | AD63: =ROUND(N63*AC63,0) -> 0 | AE63: =V63+AD63 -> 50100 | AF63: =AE63-N63 -> 300 | AG63: =AE63/N63-1 -> 0.0060240964 | AH63: 14 | AI63: 450 | AJ63: 1000 | AK63: 688 | AL63: =AE63*AH63+AI63*12+AK63+IF(AB63="",AJ63,IF(AB63="D",5000,IF(AB63="C",1000,0)))*12 -> 719488 | AM63: 4 | AO63: higher salary within same level in the factory | AP63: Internal balance | AQ63: Jiang Xiujuan（11012739） | AR63: Mo Xiaohong（11005372） | AS63: Zhao Chujun | AU63: exceed +/-20% adjustment | AV63: <20 | AW63: =_xlfn.LET(_xlpm.actual,X63,_xlpm.low,VALUE(_xlfn.TEXTBEFORE(Y63,"-")),_xlpm.high,VALUE(_xlfn.TEXTAFTER(Y63,"-")),IF(AND(_xlpm.actual=0,OR(_xlpm.low<>0,_xlpm.high<>0)),"0 increase",IF(_xlpm.actual>_xlpm.high*1.2,">20",IF(_xlpm.actual<_xlpm.low*0.8,"<20","OK")))) -> <20 | AX63: 21-25 | AY63: 90-110
A64: CN15 | B64: 15002547 | C64: Indirect Active | D64: OP | E64: SNa | F64: FLCNa-V2 | G64: 340100 | H64: 39993 | I64: Director | J64: Head of FLCNa-V2 | K64: BAND C | L64: 2 | M64: 3 | N64: 43250 | O64: 0 | P64: =ROUND(N64*O64,0) -> 0 | Q64: 0 | R64: =ROUND(N64*Q64,0) -> 0 | S64: =T64/N64 -> 0 | T64: =P64+R64 -> 0 | U64: =N64+T64 -> 43250 | V64: 43550 | W64: =V64-N64 -> 300 | X64: =ROUND(V64/N64-1,4) -> 0.0069 | Y64: =IF(OR(L64=1,L64=2,L64=4),TEXT(S64*0.8,"0.00%")&"-"&TEXT(S64*1.2,"0.00%"),IF(OR(L64=3,L64=6),TEXT(0,"0.00%")&"-"&TEXT(7%*1.2,"0.00%"),IF(OR(L64=5,L64=7),TEXT((R64/N64),"0.00%")&"-"&TEXT((R64/N64)+7%,"0.00%"),""))) -> 0.00%-0.00% | AD64: =ROUND(N64*AC64,0) -> 0 | AE64: =V64+AD64 -> 43550 | AF64: =AE64-N64 -> 300 | AG64: =AE64/N64-1 -> 0.0069364162 | AH64: 14 | AI64: 450 | AJ64: 1000 | AK64: 688 | AL64: =AE64*AH64+AI64*12+AK64+IF(AB64="",AJ64,IF(AB64="D",5000,IF(AB64="C",1000,0)))*12 -> 627788 | AM64: 4 | AO64: lead new VS with proven performance | AP64: Enlarged responsibilities with proven performance | AQ64: Jiang Xiujuan（11012739） | AR64: Mo Xiaohong（11005372） | AS64: Zhao Chujun | AU64: exceed +/-20% adjustment | AV64: >20 | AW64: =_xlfn.LET(_xlpm.actual,X64,_xlpm.low,VALUE(_xlfn.TEXTBEFORE(Y64,"-")),_xlpm.high,VALUE(_xlfn.TEXTAFTER(Y64,"-")),IF(AND(_xlpm.actual=0,OR(_xlpm.low<>0,_xlpm.high<>0)),"0 increase",IF(_xlpm.actual>_xlpm.high*1.2,">20",IF(_xlpm.actual<_xlpm.low*0.8,"<20","OK")))) -> >20 | AX64: 16-20 | AY64: >90
A65: CN15 | B65: 15001516 | C65: Indirect Active | D65: OP | E65: SNa | F65: FLCNa | G65: 340100 | H65: 39553 | I65: Senior Engineer | J65: Senior Production Engineer | K65: BAND A5 | L65: 2 | M65: 4 | N65: 10020 | O65: 0.0375 | P65: =ROUND(N65*O65,0) -> 376 | Q65: 0.0155 | R65: =ROUND(N65*Q65,0) -> 155 | S65: =T65/N65 -> 0.052994012 | T65: =P65+R65 -> 531 | U65: =N65+T65 -> 10551 | V65: =U65-100 -> 10451 | W65: =V65-N65 -> 431 | X65: =ROUND(V65/N65-1,4) -> 0.043 | Y65: =IF(OR(L65=1,L65=2,L65=4),TEXT(S65*0.8,"0.00%")&"-"&TEXT(S65*1.2,"0.00%"),IF(OR(L65=3,L65=6),TEXT(0,"0.00%")&"-"&TEXT(7%*1.2,"0.00%"),IF(OR(L65=5,L65=7),TEXT((R65/N65),"0.00%")&"-"&TEXT((R65/N65)+7%,"0.00%"),""))) -> 4.24%-6.36% | AD65: =ROUND(N65*AC65,0) -> 0 | AE65: =V65+AD65 -> 10451 | AF65: =AE65-N65 -> 431 | AG65: =AE65/N65-1 -> 0.043013972 | AH65: 14 | AI65: 450 | AK65: 688 | AL65: =AE65*AH65+AI65*12+AK65+IF(AB65="",AJ65,IF(AB65="D",5000,IF(AB65="C",1000,0)))*12 -> 152402 | AM65: 2 | AQ65: Jiang Xiujuan（11012739） | AR65: Mo Xiaohong（11005372） | AS65: Zhao Chujun | AW65: =_xlfn.LET(_xlpm.actual,X65,_xlpm.low,VALUE(_xlfn.TEXTBEFORE(Y65,"-")),_xlpm.high,VALUE(_xlfn.TEXTAFTER(Y65,"-")),IF(AND(_xlpm.actual=0,OR(_xlpm.low<>0,_xlpm.high<>0)),"0 increase",IF(_xlpm.actual>_xlpm.high*1.2,">20",IF(_xlpm.actual<_xlpm.low*0.8,"<20","OK")))) -> OK | AX65: 16-20 | AY65: 70-90
A66: CN15 | B66: 15001801 | C66: Indirect Active | D66: OP | E66: SNa | F66: FLCNa | G66: 340100 | H66: 39637 | I66: Manager | J66: Manager | K66: BAND B | L66: 2 | M66: 3 | N66: 30000 | O66: 0 | P66: =ROUND(N66*O66,0) -> 0 | Q66: 0 | R66: =ROUND(N66*Q66,0) -> 0 | S66: =T66/N66 -> 0 | T66: =P66+R66 -> 0 | U66: =N66+T66 -> 30000 | V66: =U66 -> 30000 | W66: =V66-N66 -> 0 | X66: =ROUND(V66/N66-1,4) -> 0 | Y66: =IF(OR(L66=1,L66=2,L66=4),TEXT(S66*0.8,"0.00%")&"-"&TEXT(S66*1.2,"0.00%"),IF(OR(L66=3,L66=6),TEXT(0,"0.00%")&"-"&TEXT(7%*1.2,"0.00%"),IF(OR(L66=5,L66=7),TEXT((R66/N66),"0.00%")&"-"&TEXT((R66/N66)+7%,"0.00%"),""))) -> 0.00%-0.00% | AD66: =ROUND(N66*AC66,0) -> 0 | AE66: =V66+AD66 -> 30000 | AF66: =AE66-N66 -> 0 | AG66: =AE66/N66-1 -> 0 | AH66: 14 | AI66: 450 | AK66: 688 | AL66: =AE66*AH66+AI66*12+AK66+IF(AB66="",AJ66,IF(AB66="D",5000,IF(AB66="C",1000,0)))*12 -> 426088 | AM66: 3 | AQ66: Jiang Xiujuan（11012739） | AR66: Mo Xiaohong（11005372） | AS66: Zhao Chujun | AW66: =_xlfn.LET(_xlpm.actual,X66,_xlpm.low,VALUE(_xlfn.TEXTBEFORE(Y66,"-")),_xlpm.high,VALUE(_xlfn.TEXTAFTER(Y66,"-")),IF(AND(_xlpm.actual=0,OR(_xlpm.low<>0,_xlpm.high<>0)),"0 increase",IF(_xlpm.actual>_xlpm.high*1.2,">20",IF(_xlpm.actual<_xlpm.low*0.8,"<20","OK")))) -> OK | AX66: 16-20 | AY66: >90
A67: CN15 | B67: 15000580 | C67: Indirect Active | D67: OP | E67: SNa | F67: FLCNa-VF | G67: 340100 | H67: 38916 | I67: Director | J67: Head of FLCNa-VF | K67: BAND C | L67: 2 | M67: 3 | N67: 42080 | O67: 0 | P67: =ROUND(N67*O67,0) -> 0 | Q67: 0 | R67: =ROUND(N67*Q67,0) -> 0 | S67: =T67/N67 -> 0 | T67: =P67+R67 -> 0 | U67: =N67+T67 -> 42080 | V67: =U67+606 -> 42686 | W67: =V67-N67 -> 606 | X67: =ROUND(V67/N67-1,4) -> 0.0144 | Y67: =IF(OR(L67=1,L67=2,L67=4),TEXT(S67*0.8,"0.00%")&"-"&TEXT(S67*1.2,"0.00%"),IF(OR(L67=3,L67=6),TEXT(0,"0.00%")&"-"&TEXT(7%*1.2,"0.00%"),IF(OR(L67=5,L67=7),TEXT((R67/N67),"0.00%")&"-"&TEXT((R67/N67)+7%,"0.00%"),""))) -> 0.00%-0.00% | AD67: =ROUND(N67*AC67,0) -> 0 | AE67: =V67+AD67 -> 42686 | AF67: =AE67-N67 -> 606 | AG67: =AE67/N67-1 -> 0.014401141 | AH67: 14 | AI67: 450 | AJ67: 1000 | AK67: 688 | AL67: =AE67*AH67+AI67*12+AK67+IF(AB67="",AJ67,IF(AB67="D",5000,IF(AB67="C",1000,0)))*12 -> 615692 | AM67: 3 | AO67: enlarged responsibilities with CP management | AP67: Enlarged responsibilities with proven performance | AQ67: Jiang Xiujuan（11012739） | AR67: Mo Xiaohong（11005372） | AS67: Zhao Chujun | AU67: exceed +/-20% adjustment | AV67: >20 | AW67: =_xlfn.LET(_xlpm.actual,X67,_xlpm.low,VALUE(_xlfn.TEXTBEFORE(Y67,"-")),_xlpm.high,VALUE(_xlfn.TEXTAFTER(Y67,"-")),IF(AND(_xlpm.actual=0,OR(_xlpm.low<>0,_xlpm.high<>0)),"0 increase",IF(_xlpm.actual>_xlpm.high*1.2,">20",IF(_xlpm.actual<_xlpm.low*0.8,"<20","OK")))) -> >20 | AX67: 16-20 | AY67: >90
A68: CN15 | B68: 15003586 | C68: Indirect Active | D68: OP | E68: SNa | F68: FLCNa | G68: 340100 | H68: 40269 | I68: Senior Engineer | J68: Senior Engineer | K68: BAND A5 | L68: 2 | M68: 3 | N68: 12200 | O68: 0 | P68: =ROUND(N68*O68,0) -> 0 | Q68: 0 | R68: =ROUND(N68*Q68,0) -> 0 | S68: =T68/N68 -> 0 | T68: =P68+R68 -> 0 | U68: =N68+T68 -> 12200 | V68: =U68+274 -> 12474 | W68: =V68-N68 -> 274 | X68: =ROUND(V68/N68-1,4) -> 0.0225 | Y68: =IF(OR(L68=1,L68=2,L68=4),TEXT(S68*0.8,"0.00%")&"-"&TEXT(S68*1.2,"0.00%"),IF(OR(L68=3,L68=6),TEXT(0,"0.00%")&"-"&TEXT(7%*1.2,"0.00%"),IF(OR(L68=5,L68=7),TEXT((R68/N68),"0.00%")&"-"&TEXT((R68/N68)+7%,"0.00%"),""))) -> 0.00%-0.00% | AD68: =ROUND(N68*AC68,0) -> 0 | AE68: =V68+AD68 -> 12474 | AF68: =AE68-N68 -> 274 | AG68: =AE68/N68-1 -> 0.022459016 | AH68: 14 | AI68: 450 | AK68: 688 | AL68: =AE68*AH68+AI68*12+AK68+IF(AB68="",AJ68,IF(AB68="D",5000,IF(AB68="C",1000,0)))*12 -> 180724 | AM68: 3 | AO68: enlarged responsibilities, add BPS management | AP68: Enlarged responsibilities with proven performance | AQ68: Jiang Xiujuan（11012739） | AR68: Mo Xiaohong（11005372） | AS68: Zhao Chujun | AU68: exceed +/-20% adjustment | AV68: >20 | AW68: =_xlfn.LET(_xlpm.actual,X68,_xlpm.low,VALUE(_xlfn.TEXTBEFORE(Y68,"-")),_xlpm.high,VALUE(_xlfn.TEXTAFTER(Y68,"-")),IF(AND(_xlpm.actual=0,OR(_xlpm.low<>0,_xlpm.high<>0)),"0 increase",IF(_xlpm.actual>_xlpm.high*1.2,">20",IF(_xlpm.actual<_xlpm.low*0.8,"<20","OK")))) -> >20 | AX68: 16-20 | AY68: >90
A69: CN15 | B69: 15006800 | C69: Indirect Active | D69: OP | E69: SNa | F69: FLCNa-V1 | G69: 340100 | H69: 40744 | I69: Manager | J69: Head of FLCNa-V1 | K69: BAND B | L69: 2 | M69: 3 | N69: 15455 | O69: 0.03 | P69: =ROUND(N69*O69,0) -> 464 | Q69: 0 | R69: =ROUND(N69*Q69,0) -> 0 | S69: =T69/N69 -> 0.030022646 | T69: =P69+R69 -> 464 | U69: =N69+T69 -> 15919 | V69: =U69+1091 -> 17010 | W69: =V69-N69 -> 1555 | X69: =ROUND(V69/N69-1,4) -> 0.1006 | Y69: =IF(OR(L69=1,L69=2,L69=4),TEXT(S69*0.8,"0.00%")&"-"&TEXT(S69*1.2,"0.00%"),IF(OR(L69=3,L69=6),TEXT(0,"0.00%")&"-"&TEXT(7%*1.2,"0.00%"),IF(OR(L69=5,L69=7),TEXT((R69/N69),"0.00%")&"-"&TEXT((R69/N69)+7%,"0.00%"),""))) -> 2.40%-3.60% | AD69: =ROUND(N69*AC69,0) -> 0 | AE69: =V69+AD69 -> 17010 | AF69: =AE69-N69 -> 1555 | AG69: =AE69/N69-1 -> 0.10061469 | AH69: 14 | AI69: 450 | AK69: 688 | AL69: =AE69*AH69+AI69*12+AK69+IF(AB69="",AJ69,IF(AB69="D",5000,IF(AB69="C",1000,0)))*12 -> 244228 | AM69: 5 | AO69: took VS head with excellent performance. Lower salary. | AP69: Enlarged responsibilities with proven performance | AQ69: Jiang Xiujuan（11012739） | AR69: Mo Xiaohong（11005372） | AS69: Zhao Chujun | AU69: exceed +/-20% adjustment | AV69: >20 | AW69: =_xlfn.LET(_xlpm.actual,X69,_xlpm.low,VALUE(_xlfn.TEXTBEFORE(Y69,"-")),_xlpm.high,VALUE(_xlfn.TEXTAFTER(Y69,"-")),IF(AND(_xlpm.actual=0,OR(_xlpm.low<>0,_xlpm.high<>0)),"0 increase",IF(_xlpm.actual>_xlpm.high*1.2,">20",IF(_xlpm.actual<_xlpm.low*0.8,"<20","OK")))) -> >20 | AX69: 11-15 | AY69: 50-70
A70: CN15 | B70: 11000452 | C70: Indirect Active | D70: OP | E70: SC | F70: SNa-SC4MP | G70: 390501 | H70: 36297 | I70: Planner | J70: Material Planner | K70: BAND A4 | L70: 2 | M70: 3 | N70: 10091 | O70: 0 | P70: 0 | Q70: 0 | R70: 0 | S70: 0 | T70: 0 | U70: 10091 | V70: 10091 | W70: 0 | X70: 0 | Y70: 0.00%-0.00% | AD70: 0 | AE70: 10091 | AF70: 0 | AG70: 0 | AH70: 14 | AI70: 450 | AK70: 688 | AL70: 147362 | AM70: 3 | AQ70: Zhou Chuancui（1520041） | AR70: Shao Xiao（11018043） | AS70: Cheng Cheng | AW70: =_xlfn.LET(_xlpm.actual,X70,_xlpm.low,VALUE(_xlfn.TEXTBEFORE(Y70,"-")),_xlpm.high,VALUE(_xlfn.TEXTAFTER(Y70,"-")),IF(AND(_xlpm.actual=0,OR(_xlpm.low<>0,_xlpm.high<>0)),"0 increase",IF(_xlpm.actual>_xlpm.high*1.2,">20",IF(_xlpm.actual<_xlpm.low*0.8,"<20","OK")))) -> OK | AX70: 26-30 | AY70: >90
A71: CN15 | B71: 15021389 | C71: Indirect Active | D71: OP | E71: SC | F71: SNa-SC4MS | G71: 390501 | H71: 44356 | I71: Planner | J71: Material Planner | K71: BAND A4 | L71: 2 | M71: 3 | N71: 10091 | O71: 0 | P71: 0 | Q71: 0 | R71: 0 | S71: 0 | T71: 0 | U71: 10091 | V71: 10091 | W71: 0 | X71: 0 | Y71: 0.00%-0.00% | AD71: 0 | AE71: 10091 | AF71: 0 | AG71: 0 | AH71: 14 | AI71: 450 | AK71: 688 | AL71: 147362 | AM71: 3 | AQ71: Zhou Chuancui（1520041） | AR71: Shao Xiao（11018043） | AS71: Cheng Cheng | AW71: =_xlfn.LET(_xlpm.actual,X71,_xlpm.low,VALUE(_xlfn.TEXTBEFORE(Y71,"-")),_xlpm.high,VALUE(_xlfn.TEXTAFTER(Y71,"-")),IF(AND(_xlpm.actual=0,OR(_xlpm.low<>0,_xlpm.high<>0)),"0 increase",IF(_xlpm.actual>_xlpm.high*1.2,">20",IF(_xlpm.actual<_xlpm.low*0.8,"<20","OK")))) -> OK | AX71: 0-5 | AY71: >90
A72: CN15 | B72: 15013869 | C72: Indirect Active | D72: OP | E72: SC | F72: SNa-SC4ME | G72: 390501 | H72: 41990 | I72: Senior Planner | J72: Senior Material Planner | K72: BAND A5 | L72: 2 | M72: 3 | N72: 8250 | O72: 0.03 | P72: 248 | Q72: 0 | R72: 0 | S72: 0.030060606 | T72: 248 | U72: 8498 | V72: 8600 | W72: 350 | X72: 0.0424 | Y72: 2.40%-3.61% | AD72: 0 | AE72: 8600 | AF72: 350 | AG72: 0.042424242 | AH72: 14 | AI72: 450 | AK72: 688 | AL72: 126488 | AM72: 2 | AO72: Internal balance | AP72: Internal balance | AQ72: Zhou Chuancui（1520041） | AR72: Shao Xiao（11018043） | AS72: Cheng Cheng | AW72: =_xlfn.LET(_xlpm.actual,X72,_xlpm.low,VALUE(_xlfn.TEXTBEFORE(Y72,"-")),_xlpm.high,VALUE(_xlfn.TEXTAFTER(Y72,"-")),IF(AND(_xlpm.actual=0,OR(_xlpm.low<>0,_xlpm.high<>0)),"0 increase",IF(_xlpm.actual>_xlpm.high*1.2,">20",IF(_xlpm.actual<_xlpm.low*0.8,"<20","OK")))) -> OK | AX72: 11-15 | AY72: 50-70
A73: CN15 | B73: 15018916 | C73: Indirect Active | D73: OP | E73: SC | F73: SNa-SC4MX | G73: 390501 | H73: 43194 | I73: Supervisor | J73: Head of SNa-SC4MX | K73: BAND A6 | L73: 2 | M73: 4 | N73: 14330 | O73: 0.0375 | P73: 537 | Q73: 0.0155 | R73: 222 | S73: 0.052965806 | T73: 759 | U73: 15089 | V73: 15089 | W73: 759 | X73: 0.053 | Y73: 4.24%-6.36% | AD73: 0 | AE73: 15089 | AF73: 759 | AG73: 0.052965806 | AH73: 14 | AI73: 450 | AK73: 688 | AL73: 217334 | AM73: 4 | AQ73: Zhou Chuancui（1520041） | AR73: Shao Xiao（11018043） | AS73: Cheng Cheng | AW73: =_xlfn.LET(_xlpm.actual,X73,_xlpm.low,VALUE(_xlfn.TEXTBEFORE(Y73,"-")),_xlpm.high,VALUE(_xlfn.TEXTAFTER(Y73,"-")),IF(AND(_xlpm.actual=0,OR(_xlpm.low<>0,_xlpm.high<>0)),"0 increase",IF(_xlpm.actual>_xlpm.high*1.2,">20",IF(_xlpm.actual<_xlpm.low*0.8,"<20","OK")))) -> OK | AX73: 6-10 | AY73: 70-90
A74: CN15 | B74: 15022000 | C74: Indirect Active | D74: OP | E74: SC | F74: SNa-SC4MM | G74: 390501 | H74: 44510 | I74: Planner | J74: Material planner | K74: BAND A4 | L74: 2 | M74: 3 | N74: 8432 | O74: 0.025 | P74: 211 | Q74: 0 | R74: 0 | S74: 0.025023719 | T74: 211 | U74: 8643 | V74: 8643 | W74: 211 | X74: 0.025 | Y74: 2.00%-3.00% | AD74: 0 | AE74: 8643 | AF74: 211 | AG74: 0.025023719 | AH74: 14 | AI74: 450 | AK74: 688 | AL74: 127090 | AM74: 3 | AQ74: Zhou Chuancui（1520041） | AR74: Shao Xiao（11018043） | AS74: Cheng Cheng | AW74: =_xlfn.LET(_xlpm.actual,X74,_xlpm.low,VALUE(_xlfn.TEXTBEFORE(Y74,"-")),_xlpm.high,VALUE(_xlfn.TEXTAFTER(Y74,"-")),IF(AND(_xlpm.actual=0,OR(_xlpm.low<>0,_xlpm.high<>0)),"0 increase",IF(_xlpm.actual>_xlpm.high*1.2,">20",IF(_xlpm.actual<_xlpm.low*0.8,"<20","OK")))) -> OK | AX74: 0-5 | AY74: 70-90
A75: CN15 | B75: 15006182 | C75: Indirect Active | D75: OP | E75: SC | F75: SNa-SC4MP | G75: 390501 | H75: 40695 | I75: Senior Specialist | J75: Senior Material Specialist | K75: BAND A5 | L75: 2 | M75: 3 | N75: 9780 | O75: 0.03 | P75: 293 | Q75: 0 | R75: 0 | S75: 0.0299591 | T75: 293 | U75: 10073 | V75: 10073 | W75: 293 | X75: 0.03 | Y75: 2.40%-3.60% | AD75: 0 | AE75: 10073 | AF75: 293 | AG75: 0.0299591 | AH75: 14 | AI75: 450 | AK75: 688 | AL75: 147110 | AM75: 4 | AQ75: Zhou Chuancui（1520041） | AR75: Shao Xiao（11018043） | AS75: Cheng Cheng | AW75: =_xlfn.LET(_xlpm.actual,X75,_xlpm.low,VALUE(_xlfn.TEXTBEFORE(Y75,"-")),_xlpm.high,VALUE(_xlfn.TEXTAFTER(Y75,"-")),IF(AND(_xlpm.actual=0,OR(_xlpm.low<>0,_xlpm.high<>0)),"0 increase",IF(_xlpm.actual>_xlpm.high*1.2,">20",IF(_xlpm.actual<_xlpm.low*0.8,"<20","OK")))) -> OK | AX75: 11-15 | AY75: 50-70
A76: CN15 | B76: 15003608 | C76: Indirect Active | D76: OP | E76: SC | F76: SNa-SC4MX | G76: 390501 | H76: 40276 | I76: Planner | J76: Material Planner | K76: BAND A4 | L76: 2 | M76: 3 | N76: 9055 | O76: 0.025 | P76: 226 | Q76: 0 | R76: 0 | S76: 0.024958586 | T76: 226 | U76: 9281 | V76: 9281 | W76: 226 | X76: 0.025 | Y76: 2.00%-3.00% | AD76: 0 | AE76: 9281 | AF76: 226 | AG76: 0.024958586 | AH76: 14 | AI76: 450 | AK76: 688 | AL76: 136022 | AM76: 3 | AQ76: Zhou Chuancui（1520041） | AR76: Shao Xiao（11018043） | AS76: Cheng Cheng | AW76: =_xlfn.LET(_xlpm.actual,X76,_xlpm.low,VALUE(_xlfn.TEXTBEFORE(Y76,"-")),_xlpm.high,VALUE(_xlfn.TEXTAFTER(Y76,"-")),IF(AND(_xlpm.actual=0,OR(_xlpm.low<>0,_xlpm.high<>0)),"0 increase",IF(_xlpm.actual>_xlpm.high*1.2,">20",IF(_xlpm.actual<_xlpm.low*0.8,"<20","OK")))) -> OK | AX76: 16-20 | AY76: 70-90
A77: CN15 | B77: 15016766 | C77: Indirect Active | D77: OP | E77: SC | F77: SNa-SC4MM | G77: 390501 | H77: 42816 | I77: Senior Planner | J77: Senior Material Planner | K77: BAND A5 | L77: 2 | M77: 4 | N77: 10250 | O77: 0.0375 | P77: 384 | Q77: 0.0155 | R77: 159 | S77: 0.05297561 | T77: 543 | U77: 10793 | V77: 11000 | W77: 750 | X77: 0.0732 | Y77: 4.24%-6.36% | AD77: 0 | AE77: 11000 | AF77: 750 | AG77: 0.073170732 | AH77: 14 | AI77: 450 | AK77: 688 | AL77: 160088 | AM77: 3 | AO77: 1. Excellent in managing e-mechanics suppliers, with significant contributions following the MP group consolidation. 2. Leading SAP solutions in MP – Key deliverables:  Resolved inaccuracies in FCGNa chemical parts BOM. Collaborated with IT to adjust MRP (excluding stock of 100) to ensure smooth production. This solution is expected to be rolled out to other factories.  Set up automated email reminders for planners to change MRP controllers from "Series One" to "Phase-out" or "CS" MRP controllers. 3. Backup speaker role in FEDNa:  Served as SC MP lead for all new product projects in FEDNa, responsible for parts ordering and risk control.  Acted as backup for Weiwei, handling all MP-related issues in FEDNa. | AP77: Good performance/talent | AQ77: Zhou Chuancui（1520041） | AR77: Shao Xiao（11018043） | AS77: Cheng Cheng | AW77: =_xlfn.LET(_xlpm.actual,X77,_xlpm.low,VALUE(_xlfn.TEXTBEFORE(Y77,"-")),_xlpm.high,VALUE(_xlfn.TEXTAFTER(Y77,"-")),IF(AND(_xlpm.actual=0,OR(_xlpm.low<>0,_xlpm.high<>0)),"0 increase",IF(_xlpm.actual>_xlpm.high*1.2,">20",IF(_xlpm.actual<_xlpm.low*0.8,"<20","OK")))) -> OK | AX77: 6-10 | AY77: 70-90
A78: CN15 | B78: 15000227 | C78: Indirect Active | D78: OP | E78: SC | F78: SNa-SC4MX | G78: 390501 | H78: 38614 | I78: Senior Planner | J78: Senior Material Planner | K78: BAND A5 | L78: 2 | M78: 3 | N78: 13114 | O78: 0.025 | P78: 328 | Q78: 0 | R78: 0 | S78: 0.025011438 | T78: 328 | U78: 13442 | V78: 13393 | W78: 279 | X78: 0.0213 | Y78: 2.00%-3.00% | AD78: 0 | AE78: 13393 | AF78: 279 | AG78: 0.021274973 | AH78: 14 | AI78: 450 | AK78: 688 | AL78: 193590 | AM78: 2 | AQ78: Zhou Chuancui（1520041） | AR78: Shao Xiao（11018043） | AS78: Cheng Cheng | AW78: =_xlfn.LET(_xlpm.actual,X78,_xlpm.low,VALUE(_xlfn.TEXTBEFORE(Y78,"-")),_xlpm.high,VALUE(_xlfn.TEXTAFTER(Y78,"-")),IF(AND(_xlpm.actual=0,OR(_xlpm.low<>0,_xlpm.high<>0)),"0 increase",IF(_xlpm.actual>_xlpm.high*1.2,">20",IF(_xlpm.actual<_xlpm.low*0.8,"<20","OK")))) -> OK | AX78: 16-20 | AY78: 70-90
A79: CN15 | B79: 1120274 | C79: Indirect Active | D79: OP | E79: SC | F79: SNa-SC4MM | G79: 390501 | H79: 44130 | I79: Specialist | J79: Material Planning Specialist | K79: BAND A4 | L79: 2 | M79: 3 | N79: 8155 | O79: 0.025 | P79: 204 | Q79: 0 | R79: 0 | S79: 0.025015328 | T79: 204 | U79: 8359 | V79: 8359 | W79: 204 | X79: 0.025 | Y79: 2.00%-3.00% | AD79: 0 | AE79: 8359 | AF79: 204 | AG79: 0.025015328 | AH79: 14 | AI79: 450 | AK79: 688 | AL79: 123114 | AM79: 3 | AQ79: Zhou Chuancui（1520041） | AR79: Shao Xiao（11018043） | AS79: Cheng Cheng | AW79: =_xlfn.LET(_xlpm.actual,X79,_xlpm.low,VALUE(_xlfn.TEXTBEFORE(Y79,"-")),_xlpm.high,VALUE(_xlfn.TEXTAFTER(Y79,"-")),IF(AND(_xlpm.actual=0,OR(_xlpm.low<>0,_xlpm.high<>0)),"0 increase",IF(_xlpm.actual>_xlpm.high*1.2,">20",IF(_xlpm.actual<_xlpm.low*0.8,"<20","OK")))) -> OK | AX79: 0-5 | AY79: 70-90
A80: CN15 | B80: 15002550 | C80: Indirect Active | D80: OP | E80: SC | F80: SNa-SC4MM | G80: 390501 | H80: 39995 | I80: Supervisor | J80: Head of SNa-SC4MM | K80: BAND A6 | L80: 2 | M80: 5 | N80: 18800 | O80: 0.04 | P80: 752 | Q80: 0 | R80: 0 | S80: 0.04 | T80: 752 | U80: 19552 | V80: 19425 | W80: 625 | X80: 0.0332 | Y80: 3.20%-4.80% | AD80: 0 | AE80: 19425 | AF80: 625 | AG80: 0.033244681 | AH80: 14 | AI80: 510 | AK80: 688 | AL80: 278758 | AM80: 5 | AQ80: Zhou Chuancui（1520041） | AR80: Shao Xiao（11018043） | AS80: Cheng Cheng | AW80: =_xlfn.LET(_xlpm.actual,X80,_xlpm.low,VALUE(_xlfn.TEXTBEFORE(Y80,"-")),_xlpm.high,VALUE(_xlfn.TEXTAFTER(Y80,"-")),IF(AND(_xlpm.actual=0,OR(_xlpm.low<>0,_xlpm.high<>0)),"0 increase",IF(_xlpm.actual>_xlpm.high*1.2,">20",IF(_xlpm.actual<_xlpm.low*0.8,"<20","OK")))) -> OK | AX80: 16-20 | AY80: 90-110
A81: CN15 | B81: 15001696 | C81: Indirect Active | D81: OP | E81: SC | F81: SNa-SC4 | G81: 390500 | H81: 39616 | I81: Supervisor | J81: Project Management | K81: BAND A6 | L81: 2 | M81: 4 | N81: 14903 | O81: 0.045 | P81: 671 | Q81: 0.0421 | R81: 627 | S81: 0.087096558 | T81: 1298 | U81: 16201 | V81: 16000 | W81: 1097 | X81: 0.0736 | Y81: 6.97%-10.45% | AD81: 0 | AE81: 16000 | AF81: 1097 | AG81: 0.07360934 | AH81: 14 | AI81: 450 | AK81: 688 | AL81: 230088 | AM81: 3 | AQ81: Cao Xuelian（15020877） | AR81: Shao Xiao（11018043） | AS81: Cheng Cheng | AW81: =_xlfn.LET(_xlpm.actual,X81,_xlpm.low,VALUE(_xlfn.TEXTBEFORE(Y81,"-")),_xlpm.high,VALUE(_xlfn.TEXTAFTER(Y81,"-")),IF(AND(_xlpm.actual=0,OR(_xlpm.low<>0,_xlpm.high<>0)),"0 increase",IF(_xlpm.actual>_xlpm.high*1.2,">20",IF(_xlpm.actual<_xlpm.low*0.8,"<20","OK")))) -> OK | AX81: 16-20 | AY81: 50-70
A82: CN15 | B82: 15020877 | C82: Indirect Active | D82: OP | E82: SC | F82: SNa-SC4 | G82: 390500 | H82: 43346 | I82: Senior Project Manager | J82: Senior Project Manager | K82: BAND B | L82: 2 | M82: 5 | N82: 24381 | O82: 0.05 | P82: 1219 | Q82: 0.027 | R82: 658 | S82: 0.076986178 | T82: 1877 | U82: 26258 | V82: 26000 | W82: 1619 | X82: 0.0664 | Y82: 6.16%-9.24% | AD82: 0 | AE82: 26000 | AF82: 1619 | AG82: 0.066404167 | AH82: 14 | AI82: 450 | AK82: 688 | AL82: 370088 | AM82: 5 | AQ82: Pastirmaci Ali Kaan（1600047） | AR82: Shao Xiao（11018043） | AS82: Cheng Cheng | AW82: =_xlfn.LET(_xlpm.actual,X82,_xlpm.low,VALUE(_xlfn.TEXTBEFORE(Y82,"-")),_xlpm.high,VALUE(_xlfn.TEXTAFTER(Y82,"-")),IF(AND(_xlpm.actual=0,OR(_xlpm.low<>0,_xlpm.high<>0)),"0 increase",IF(_xlpm.actual>_xlpm.high*1.2,">20",IF(_xlpm.actual<_xlpm.low*0.8,"<20","OK")))) -> OK | AX82: 6-10 | AY82: 70-90
A83: CN15 | B83: 15022628 | C83: Indirect Active | D83: OP | E83: SC | F83: SNa-SC4L | G83: 390503 | H83: 45839 | I83: Director | J83: Head of SNa-SC4L | K83: BAND C | L83: 2 | M83: 2 | N83: 25500 | O83: 0 | P83: 0 | Q83: 0 | R83: 0 | S83: 0 | T83: 0 | U83: 25500 | V83: 25750 | W83: 250 | X83: 0.0098 | Y83: 0.00%-0.00% | AD83: 0 | AE83: 25750 | AF83: 250 | AG83: 0.0098039216 | AH83: 14 | AI83: 450 | AJ83: 1000 | AK83: 688 | AL83: 378588 | AM83: #N/A | AP83: Internal balance | AQ83: Pastirmaci Ali Kaan（1600047） | AR83: Shao Xiao（11018043） | AS83: Cheng Cheng | AW83: =_xlfn.LET(_xlpm.actual,X83,_xlpm.low,VALUE(_xlfn.TEXTBEFORE(Y83,"-")),_xlpm.high,VALUE(_xlfn.TEXTAFTER(Y83,"-")),IF(AND(_xlpm.actual=0,OR(_xlpm.low<>0,_xlpm.high<>0)),"0 increase",IF(_xlpm.actual>_xlpm.high*1.2,">20",IF(_xlpm.actual<_xlpm.low*0.8,"<20","OK")))) -> >20 | AX83: 6-10 | AY83: 0
A84: CN15 | B84: 51202404 | C84: Indirect Active | D84: OP | E84: SC | F84: SNa-SC4P | G84: 390502 | H84: 40763 | I84: Manager | J84: Head of Supply Fulfillment | K84: BAND B | L84: 2 | M84: 3 | N84: 29250 | O84: 0 | P84: 0 | Q84: 0 | R84: 0 | S84: 0 | T84: 0 | U84: 29250 | V84: 29250 | W84: 0 | X84: 0 | Y84: 0.00%-0.00% | AD84: 0 | AE84: 29250 | AF84: 0 | AG84: 0 | AH84: 14 | AI84: 1450 | AK84: 688 | AL84: 427588 | AM84: 3 | AQ84: Pastirmaci Ali Kaan（1600047） | AR84: Shao Xiao（11018043） | AS84: Cheng Cheng | AW84: =_xlfn.LET(_xlpm.actual,X84,_xlpm.low,VALUE(_xlfn.TEXTBEFORE(Y84,"-")),_xlpm.high,VALUE(_xlfn.TEXTAFTER(Y84,"-")),IF(AND(_xlpm.actual=0,OR(_xlpm.low<>0,_xlpm.high<>0)),"0 increase",IF(_xlpm.actual>_xlpm.high*1.2,">20",IF(_xlpm.actual<_xlpm.low*0.8,"<20","OK")))) -> OK | AX84: 11-15 | AY84: >90
A85: CN15 | B85: 15000475 | C85: Indirect Active | D85: OP | E85: SC | F85: SNa-SC4L2 | G85: 390503 | H85: 38808 | I85: Supervisor | J85: Head of Log. Value Stream FCGNa | K85: BAND A6 | L85: 2 | M85: 4 | N85: 14690 | O85: 0.03 | P85: 441 | Q85: 0 | R85: 0 | S85: 0.030020422 | T85: 441 | U85: 15131 | V85: 15500 | W85: 810 | X85: 0.0551 | Y85: 2.40%-3.60% | AD85: 0 | AE85: 15500 | AF85: 810 | AG85: 0.055139551 | AH85: 14 | AI85: 450 | AK85: 688 | AL85: 223088 | AM85: 4 | AO85: Good performance and high competence | AP85: Good performance and high potential | AQ85: Jiang Rebecca（15022628） | AR85: Shao Xiao（11018043） | AS85: Zhao Chujun | AW85: =_xlfn.LET(_xlpm.actual,X85,_xlpm.low,VALUE(_xlfn.TEXTBEFORE(Y85,"-")),_xlpm.high,VALUE(_xlfn.TEXTAFTER(Y85,"-")),IF(AND(_xlpm.actual=0,OR(_xlpm.low<>0,_xlpm.high<>0)),"0 increase",IF(_xlpm.actual>_xlpm.high*1.2,">20",IF(_xlpm.actual<_xlpm.low*0.8,"<20","OK")))) -> >20 | AX85: 16-20 | AY85: 90-110
A86: CN15 | B86: 15001515 | C86: Indirect Active | D86: OP | E86: SC | F86: SNa-SC4LS | G86: 390505 | H86: 39553 | I86: Team Leader | J86: Scrapping Management | K86: BAND A3 | L86: 2 | M86: 2 | N86: 9185 | O86: 0 | P86: 0 | Q86: 0 | R86: 0 | S86: 0 | T86: 0 | U86: 9185 | V86: 9185 | W86: 0 | X86: 0 | Y86: 0.00%-0.00% | AD86: 0 | AE86: 9185 | AF86: 0 | AG86: 0 | AH86: 14 | AI86: 550 | AK86: 688 | AL86: 135878 | AM86: 3 | AQ86: Jiang Rebecca（15022628） | AR86: Shao Xiao（11018043） | AS86: Zhao Chujun | AW86: =_xlfn.LET(_xlpm.actual,X86,_xlpm.low,VALUE(_xlfn.TEXTBEFORE(Y86,"-")),_xlpm.high,VALUE(_xlfn.TEXTAFTER(Y86,"-")),IF(AND(_xlpm.actual=0,OR(_xlpm.low<>0,_xlpm.high<>0)),"0 increase",IF(_xlpm.actual>_xlpm.high*1.2,">20",IF(_xlpm.actual<_xlpm.low*0.8,"<20","OK")))) -> OK | AX86: 16-20 | AY86: 0
A87: CN15 | B87: 15003602 | C87: Indirect Active | D87: OP | E87: SC | F87: SNa-SC4L | G87: 390503 | H87: 40276 | I87: Supervisor | J87: Supervisor | K87: BAND A6 | L87: 2 | M87: 3 | N87: 17784 | O87: 0 | P87: 0 | Q87: 0 | R87: 0 | S87: 0 | T87: 0 | U87: 17784 | V87: 17784 | W87: 0 | X87: 0 | Y87: 0.00%-0.00% | AD87: 0 | AE87: 17784 | AF87: 0 | AG87: 0 | AH87: 14 | AI87: 450 | AK87: 688 | AL87: 255064 | AM87: 3 | AO87: Significantly enlarged responsibilities with proven performance | AQ87: Jiang Rebecca（15022628） | AR87: Shao Xiao（11018043） | AS87: Zhao Chujun | AW87: =_xlfn.LET(_xlpm.actual,X87,_xlpm.low,VALUE(_xlfn.TEXTBEFORE(Y87,"-")),_xlpm.high,VALUE(_xlfn.TEXTAFTER(Y87,"-")),IF(AND(_xlpm.actual=0,OR(_xlpm.low<>0,_xlpm.high<>0)),"0 increase",IF(_xlpm.actual>_xlpm.high*1.2,">20",IF(_xlpm.actual<_xlpm.low*0.8,"<20","OK")))) -> OK | AX87: 16-20 | AY87: >90
A88: CN15 | B88: 15002964 | C88: Indirect Active | D88: OP | E88: SC | F88: SNa-SC4LS | G88: 390505 | H88: 40094 | I88: Supervisor | J88: Supervisor | K88: BAND A6 | L88: 2 | M88: 3 | N88: 13620 | O88: 0.025 | P88: 341 | Q88: 0 | R88: 0 | S88: 0.025036711 | T88: 341 | U88: 13961 | V88: 13620 | W88: 0 | X88: 0 | Y88: 2.00%-3.00% | AD88: 0 | AE88: 13620 | AF88: 0 | AG88: 0 | AH88: 14 | AI88: 450 | AK88: 688 | AL88: 196768 | AM88: 3 | AO88: Discipline issue | AP88: Discipline issue | AQ88: Jiang Rebecca（15022628） | AR88: Shao Xiao（11018043） | AS88: Zhao Chujun | AW88: =_xlfn.LET(_xlpm.actual,X88,_xlpm.low,VALUE(_xlfn.TEXTBEFORE(Y88,"-")),_xlpm.high,VALUE(_xlfn.TEXTAFTER(Y88,"-")),IF(AND(_xlpm.actual=0,OR(_xlpm.low<>0,_xlpm.high<>0)),"0 increase",IF(_xlpm.actual>_xlpm.high*1.2,">20",IF(_xlpm.actual<_xlpm.low*0.8,"<20","OK")))) -> 0 increase | AX88: 16-20 | AY88: 70-90
A89: CN15 | B89: 15014268 | C89: Indirect Active | D89: OP | E89: SC | F89: SNa-SC4L1 | G89: 390503 | H89: 42186 | I89: Manager | J89: Head of SNa-SC4L1 | K89: BAND B | L89: 2 | M89: 2 | N89: 14047 | O89: 0 | P89: 0 | Q89: 0 | R89: 0 | S89: 0 | T89: 0 | U89: 14047 | V89: 14047 | W89: 0 | X89: 0 | Y89: 0.00%-0.00% | AD89: 0 | AE89: 14047 | AF89: 0 | AG89: 0 | AH89: 14 | AI89: 450 | AK89: 688 | AL89: 202746 | AM89: 5 | AQ89: Jiang Rebecca（15022628） | AR89: Shao Xiao（11018043） | AS89: Zhao Chujun | AW89: =_xlfn.LET(_xlpm.actual,X89,_xlpm.low,VALUE(_xlfn.TEXTBEFORE(Y89,"-")),_xlpm.high,VALUE(_xlfn.TEXTAFTER(Y89,"-")),IF(AND(_xlpm.actual=0,OR(_xlpm.low<>0,_xlpm.high<>0)),"0 increase",IF(_xlpm.actual>_xlpm.high*1.2,">20",IF(_xlpm.actual<_xlpm.low*0.8,"<20","OK")))) -> OK | AX89: 6-10 | AY89: 0
A90: CN15 | B90: 15021808 | C90: Indirect Active | D90: OP | E90: SC | F90: SNa-SC4P | G90: 390502 | H90: 44480 | I90: Senior Planner | J90: Senior Planner | K90: BAND A5 | L90: 2 | M90: 4 | N90: 11375 | O90: 0.03 | P90: 341 | Q90: 0 | R90: 0 | S90: 0.029978022 | T90: 341 | U90: 11716 | V90: 11700 | W90: 325 | X90: 0.0286 | Y90: 2.40%-3.60% | Z90: Promotion | AA90: Functional Specialist | AB90: A6 | AC90: 0.05 | AD90: 569 | AE90: 12269 | AF90: 894 | AG90: 0.078593407 | AH90: 14 | AI90: 900 | AK90: 688 | AL90: 183254 | AM90: 4 | AQ90: Zhou Zongshang（51202404） | AR90: Shao Xiao（11018043） | AS90: Zhao Chujun | AW90: =_xlfn.LET(_xlpm.actual,X90,_xlpm.low,VALUE(_xlfn.TEXTBEFORE(Y90,"-")),_xlpm.high,VALUE(_xlfn.TEXTAFTER(Y90,"-")),IF(AND(_xlpm.actual=0,OR(_xlpm.low<>0,_xlpm.high<>0)),"0 increase",IF(_xlpm.actual>_xlpm.high*1.2,">20",IF(_xlpm.actual<_xlpm.low*0.8,"<20","OK")))) -> OK | AX90: 0-5 | AY90: 90-110
A91: CN15 | B91: 15000708 | C91: Indirect Active | D91: OP | E91: SC | F91: SNa-SC4P | G91: 390502 | H91: 39008 | I91: Planner | J91: Planner | K91: BAND A4 | L91: 2 | M91: 3 | N91: 8900 | O91: 0.025 | P91: 223 | Q91: 0 | R91: 0 | S91: 0.02505618 | T91: 223 | U91: 9123 | V91: 9103 | W91: 203 | X91: 0.0228 | Y91: 2.00%-3.01% | AD91: 0 | AE91: 9103 | AF91: 203 | AG91: 0.022808989 | AH91: 14 | AI91: 450 | AK91: 688 | AL91: 133530 | AM91: 3 | AQ91: Zhou Zongshang（51202404） | AR91: Shao Xiao（11018043） | AS91: Zhao Chujun | AW91: =_xlfn.LET(_xlpm.actual,X91,_xlpm.low,VALUE(_xlfn.TEXTBEFORE(Y91,"-")),_xlpm.high,VALUE(_xlfn.TEXTAFTER(Y91,"-")),IF(AND(_xlpm.actual=0,OR(_xlpm.low<>0,_xlpm.high<>0)),"0 increase",IF(_xlpm.actual>_xlpm.high*1.2,">20",IF(_xlpm.actual<_xlpm.low*0.8,"<20","OK")))) -> OK | AX91: 16-20 | AY91: 70-90
A92: CN15 | B92: 11011058 | C92: Indirect Active | D92: OP | E92: SC | F92: SNa-SC4P | G92: 390502 | H92: 41813 | I92: Planner | J92: Planner | K92: BAND A4 | L92: 2 | M92: 3 | N92: 8702 | O92: 0.025 | P92: 218 | Q92: 0 | R92: 0 | S92: 0.025051712 | T92: 218 | U92: 8920 | V92: 8910 | W92: 208 | X92: 0.0239 | Y92: 2.00%-3.01% | AD92: 0 | AE92: 8910 | AF92: 208 | AG92: 0.023902551 | AH92: 14 | AI92: 510 | AK92: 688 | AL92: 131548 | AM92: 3 | AQ92: Zhou Zongshang（51202404） | AR92: Shao Xiao（11018043） | AS92: Zhao Chujun | AW92: =_xlfn.LET(_xlpm.actual,X92,_xlpm.low,VALUE(_xlfn.TEXTBEFORE(Y92,"-")),_xlpm.high,VALUE(_xlfn.TEXTAFTER(Y92,"-")),IF(AND(_xlpm.actual=0,OR(_xlpm.low<>0,_xlpm.high<>0)),"0 increase",IF(_xlpm.actual>_xlpm.high*1.2,">20",IF(_xlpm.actual<_xlpm.low*0.8,"<20","OK")))) -> OK | AX92: 11-15 | AY92: 70-90
A93: CN15 | B93: 15000449 | C93: Indirect Active | D93: OP | E93: SC | F93: SNa-SC4P | G93: 390502 | H93: 38808 | I93: Planner | J93: Planner | K93: BAND A4 | L93: 2 | M93: 3 | N93: 7926 | O93: 0.025 | P93: 198 | Q93: 0 | R93: 0 | S93: 0.024981075 | T93: 198 | U93: 8124 | V93: 8154 | W93: 228 | X93: 0.0288 | Y93: 2.00%-3.00% | AD93: 0 | AE93: 8154 | AF93: 228 | AG93: 0.028766086 | AH93: 14 | AI93: 510 | AK93: 688 | AL93: 120964 | AM93: 2 | AQ93: Zhou Zongshang（51202404） | AR93: Shao Xiao（11018043） | AS93: Zhao Chujun | AW93: =_xlfn.LET(_xlpm.actual,X93,_xlpm.low,VALUE(_xlfn.TEXTBEFORE(Y93,"-")),_xlpm.high,VALUE(_xlfn.TEXTAFTER(Y93,"-")),IF(AND(_xlpm.actual=0,OR(_xlpm.low<>0,_xlpm.high<>0)),"0 increase",IF(_xlpm.actual>_xlpm.high*1.2,">20",IF(_xlpm.actual<_xlpm.low*0.8,"<20","OK")))) -> OK | AX93: 16-20 | AY93: 70-90
A94: CN15 | B94: 15005122 | C94: Indirect Active | D94: OP | E94: SC | F94: SNa-SC4P | G94: 390502 | H94: 40898 | I94: Planner | J94: Production Planner | K94: BAND A4 | L94: 2 | M94: 4 | N94: 7500 | O94: 0.045 | P94: 338 | Q94: 0.0421 | R94: 316 | S94: 0.0872 | T94: 654 | U94: 8154 | V94: 8154 | W94: 654 | X94: 0.0872 | Y94: 6.98%-10.46% | AD94: 0 | AE94: 8154 | AF94: 654 | AG94: 0.0872 | AH94: 14 | AI94: 450 | AK94: 688 | AL94: 120244 | AM94: 3 | AQ94: Zhou Zongshang（51202404） | AR94: Shao Xiao（11018043） | AS94: Zhao Chujun | AW94: =_xlfn.LET(_xlpm.actual,X94,_xlpm.low,VALUE(_xlfn.TEXTBEFORE(Y94,"-")),_xlpm.high,VALUE(_xlfn.TEXTAFTER(Y94,"-")),IF(AND(_xlpm.actual=0,OR(_xlpm.low<>0,_xlpm.high<>0)),"0 increase",IF(_xlpm.actual>_xlpm.high*1.2,">20",IF(_xlpm.actual<_xlpm.low*0.8,"<20","OK")))) -> OK | AX94: 11-15 | AY94: 50-70
A95: CN15 | B95: 15001412 | C95: Indirect Active | D95: OP | E95: SC | F95: SNa-SC4S | G95: 390504 | H95: 39511 | I95: Expert (CN) | J95: Expert (CN) | K95: BAND B | L95: 2 | M95: 3 | N95: 19240 | O95: 0.03 | P95: 577 | Q95: 0 | R95: 0 | S95: 0.029989605 | T95: 577 | U95: 19817 | V95: 19817 | W95: 577 | X95: 0.03 | Y95: 2.40%-3.60% | AD95: 0 | AE95: 19817 | AF95: 577 | AG95: 0.029989605 | AH95: 14 | AI95: 450 | AK95: 688 | AL95: 283526 | AM95: 4 | AQ95: Ma Ruiming（11007900） | AR95: Shao Xiao（11018043） | AS95: Wu Ellen | AW95: =_xlfn.LET(_xlpm.actual,X95,_xlpm.low,VALUE(_xlfn.TEXTBEFORE(Y95,"-")),_xlpm.high,VALUE(_xlfn.TEXTAFTER(Y95,"-")),IF(AND(_xlpm.actual=0,OR(_xlpm.low<>0,_xlpm.high<>0)),"0 increase",IF(_xlpm.actual>_xlpm.high*1.2,">20",IF(_xlpm.actual<_xlpm.low*0.8,"<20","OK")))) -> OK | AX95: 16-20 | AY95: 50-70
A96: CN15 | B96: 11009910 | C96: Indirect Active | D96: OP | E96: SC | F96: SNa-SC4S | G96: 390504 | H96: 41491 | I96: Engineer | J96: Engineer | K96: BAND A4 | L96: 2 | M96: 3 | N96: 8533 | O96: 0.03 | P96: 256 | Q96: 0 | R96: 0 | S96: 0.030001172 | T96: 256 | U96: 8789 | V96: 9000 | W96: 467 | X96: 0.0547 | Y96: 2.40%-3.60% | AD96: 0 | AE96: 9000 | AF96: 467 | AG96: 0.0547287 | AH96: 14 | AI96: 450 | AK96: 688 | AL96: 132088 | AM96: 3 | AO96: Internal balance | AP96: Internal balance | AQ96: Ma Ruiming（11007900） | AR96: Shao Xiao（11018043） | AS96: Wu Ellen | AW96: =_xlfn.LET(_xlpm.actual,X96,_xlpm.low,VALUE(_xlfn.TEXTBEFORE(Y96,"-")),_xlpm.high,VALUE(_xlfn.TEXTAFTER(Y96,"-")),IF(AND(_xlpm.actual=0,OR(_xlpm.low<>0,_xlpm.high<>0)),"0 increase",IF(_xlpm.actual>_xlpm.high*1.2,">20",IF(_xlpm.actual<_xlpm.low*0.8,"<20","OK")))) -> >20 | AX96: 11-15 | AY96: 50-70
A97: CN15 | B97: 15002411 | C97: Indirect Active | D97: OP | E97: SC | F97: SNa-SC4S | G97: 390504 | H97: 39968 | I97: Associate Expert (CN) | J97: Associate Expert (C) | K97: BAND A6 | L97: 2 | M97: 4 | N97: 12700 | O97: 0.045 | P97: 572 | Q97: 0.0421 | R97: 535 | S97: 0.087165354 | T97: 1107 | U97: 13807 | V97: 13700 | W97: 1000 | X97: 0.0787 | Y97: 6.97%-10.46% | AD97: 0 | AE97: 13700 | AF97: 1000 | AG97: 0.078740157 | AH97: 14 | AI97: 450 | AK97: 688 | AL97: 197888 | AM97: 3 | AQ97: Ma Ruiming（11007900） | AR97: Shao Xiao（11018043） | AS97: Wu Ellen | AW97: =_xlfn.LET(_xlpm.actual,X97,_xlpm.low,VALUE(_xlfn.TEXTBEFORE(Y97,"-")),_xlpm.high,VALUE(_xlfn.TEXTAFTER(Y97,"-")),IF(AND(_xlpm.actual=0,OR(_xlpm.low<>0,_xlpm.high<>0)),"0 increase",IF(_xlpm.actual>_xlpm.high*1.2,">20",IF(_xlpm.actual<_xlpm.low*0.8,"<20","OK")))) -> OK | AX97: 16-20 | AY97: 50-70
A98: CN15 | B98: 15016940 | C98: Indirect Active | D98: OP | E98: SC | F98: SNa-SC4S | G98: 390504 | H98: 42830 | I98: Senior Engineer | J98: Senior Engineer | K98: BAND A5 | L98: 2 | M98: 3 | N98: 11042 | O98: 0.03 | P98: 331 | Q98: 0 | R98: 0 | S98: 0.029976454 | T98: 331 | U98: 11373 | V98: 11350 | W98: 308 | X98: 0.0279 | Y98: 2.40%-3.60% | AD98: 0 | AE98: 11350 | AF98: 308 | AG98: 0.027893498 | AH98: 14 | AI98: 450 | AK98: 688 | AL98: 164988 | AM98: 3 | AQ98: Ma Ruiming（11007900） | AR98: Shao Xiao（11018043） | AS98: Wu Ellen | AV98: >20 | AW98: =_xlfn.LET(_xlpm.actual,X98,_xlpm.low,VALUE(_xlfn.TEXTBEFORE(Y98,"-")),_xlpm.high,VALUE(_xlfn.TEXTAFTER(Y98,"-")),IF(AND(_xlpm.actual=0,OR(_xlpm.low<>0,_xlpm.high<>0)),"0 increase",IF(_xlpm.actual>_xlpm.high*1.2,">20",IF(_xlpm.actual<_xlpm.low*0.8,"<20","OK")))) -> OK | AX98: 6-10 | AY98: 50-70
A99: CN15 | B99: 15014058 | C99: Indirect Active | D99: OP | E99: SNa | F99: SNa-PS | G99: 42095 | H99: Expert (CN) | I99: Expert (CN) | J99: Expert (CN) | K99: BAND B | L99: 2 | M99: 3 | N99: 21411 | O99: 0.025 | P99: 535 | Q99: 0 | R99: 0 | S99: 0.024987156 | T99: 535 | U99: 21946 | V99: 21946 | W99: 535 | X99: 0.025 | Y99: 2.00%-3.00% | AD99: 0 | AE99: 21946 | AF99: 535 | AG99: 0.024987156 | AH99: 14 | AI99: 450 | AK99: 688 | AL99: 313332 | AM99: 4 | AQ99: Wang Ning（15001553） | AR99: Li Mingzhe（15018080） | AW99: =_xlfn.LET(_xlpm.actual,X99,_xlpm.low,VALUE(_xlfn.TEXTBEFORE(Y99,"-")),_xlpm.high,VALUE(_xlfn.TEXTAFTER(Y99,"-")),IF(AND(_xlpm.actual=0,OR(_xlpm.low<>0,_xlpm.high<>0)),"0 increase",IF(_xlpm.actual>_xlpm.high*1.2,">20",IF(_xlpm.actual<_xlpm.low*0.8,"<20","OK")))) -> OK | AX99: 11-15 | AY99: 70-90
A100: CN15 | B100: 15021285 | C100: Indirect Active | D100: OP | E100: SNa | F100: SNa-PS | G100: 41793 | H100: Functional Specialist | I100: Functional Specialist | J100: Functional Specialist | K100: BAND A6 | L100: 2 | M100: 3 | N100: 16150 | O100: 0.025 | P100: 404 | Q100: 0 | R100: 0 | S100: 0.02501548 | T100: 404 | U100: 16554 | V100: 16554 | W100: 404 | X100: 0.025 | Y100: 2.00%-3.00% | AD100: 0 | AE100: 16554 | AF100: 404 | AG100: 0.02501548 | AH100: 14 | AI100: 550 | AK100: 688 | AL100: 239044 | AM100: 3 | AQ100: Wang Ning（15001553） | AR100: Li Mingzhe（15018080） | AW100: =_xlfn.LET(_xlpm.actual,X100,_xlpm.low,VALUE(_xlfn.TEXTBEFORE(Y100,"-")),_xlpm.high,VALUE(_xlfn.TEXTAFTER(Y100,"-")),IF(AND(_xlpm.actual=0,OR(_xlpm.low<>0,_xlpm.high<>0)),"0 increase",IF(_xlpm.actual>_xlpm.high*1.2,">20",IF(_xlpm.actual<_xlpm.low*0.8,"<20","OK")))) -> OK | AX100: 11-15 | AY100: 70-90
...

Sheet 升职
A1: Promotion
A2: Company code | B2: Pers.no. | C2: Subgroup | D2: Area | E2: Subarea | F2: Dept. | G2: Cost ctr | H2: Join date | I2: Job | J2: Position | K2: Band Level | L2: Workplan type | M2: 2025 Performance Level | N2: Basic salary | O2: ① Merit increase % | P2: Merit Increase amount | Q2: ② Equity Increase% | R2: Equity Increase amount | S2: Total recommended Increase % (①+②) | T2: Total Recommended Increase amount | U2: Recommended new basic salary | V2: Adjutsed basic salary (input by DH) | W2: Adjutsed increased/decreased basic salary by DH | X2: Adjusted basic increase/decreased % by DH | Y2: Adjustment range reference | Z2: Promotion or demotion | AA2: New position title | AB2: New band | AC2: ③ Promotion increase/Demotion decrease % (±5%-±20%) | AD2: Promotion increase/Demotion decrease amount | AE2: Final new basic salary | AF2: Final increase/decrease amount | AG2: Final increase/decrease rate | AH2: Pay months | AI2: Monthly allowance/bonus | AJ2: Monthly Car Allowance | AK2: Other income(e.g.:festival bonus) | AL2: Annual target cash | AM2: 2024 Performance Level | AN2: Disciplinary Records | AO2: Justifications by DH | AP2: HR Remark | AQ2: Responsible ASR Manager | AR2: Responsible ASR HRBP | AS2: PY | AT2: Editable column 1 | AU2: Editable column 2 | AV2: -
A3: CN15 | B3: 15021373 | C3: Indirect Active | D3: OP | E3: GQM | F3: GQM-EDCD | G3: 170600 | H3: 44349 | I3: Senior Engineer | J3: Senior Quality Engineer | K3: BAND A5 | L3: 2 | M3: 5 | N3: 15564 | O3: 0.04 | P3: 623 | Q3: 0 | R3: 0 | S3: 0.04002827 | T3: 623 | U3: 16187 | V3: 15564 | W3: 0 | X3: 0 | Y3: 3.20%-4.80% | Z3: Promotion | AA3: Functional Specialist | AB3: A6 | AC3: 0.07 | AD3: 1089 | AE3: 16653 | AF3: 1089 | AG3: 0.06996916 | AH3: 14 | AI3: 450 | AK3: 688 | AL3: 239230 | AM3: 3 | AO3: Take dual role of QMD and QML with high efficiency, actively contribute in strategic project. | AP3: Combined with promotion | AQ3: Li Chen（15022148） | AR3: Mo Xiaohong（11005372） | AS3: Zhao Chujun | AU3: Special | AV3: 0 increase
A4: CN15 | B4: 15020450 | C4: Indirect Blue_NP | D4: OP | E4: GQM | F4: GQM-LCCT | G4: 140600 | H4: 44378 | I4: Technician | J4: Technician | K4: BAND A | L4: 2 | M4: 3 | N4: 5100 | O4: 0 | P4: 0 | Q4: 0 | R4: 0 | S4: 0 | T4: 0 | U4: 5100 | V4: 5100 | W4: 0 | X4: 0 | Y4: 0.00%-0.00% | Z4: Promotion | AA4: Junior Test Engineer | AB4: A3 | AC4: 0.1356 | AD4: 692 | AE4: 5792 | AF4: 692 | AG4: 0.13568627 | AH4: 14 | AI4: 500 | AK4: 688 | AL4: 87776 | AM4: 4 | AO4: 1. High perfomer, overqualify current position 2. Top young talent in Technicians, successor of Mr. Lan Guojin to take over TD validation engineer works 3. T-shape with multiple skill in Lifetime test management, Lean-Lab managment,CMM measurement, Lab digital transition and Training vedio filming&producing 4. Fullfil capability required for Junior Test Enginner and show high potential to be further developed to Test enginner in coming 1-3 years. | AP4: Good performance and high potential | AQ4: Zhu Chen (15010791) | AR4: Mo Xiaohong（11005372） | AS4: Zhao Chujun | AU4: Special | AV4: OK
A5: CN15 | B5: 1120211 | C5: Indirect Active | D5: OP | E5: GQM | F5: GQM-CGCD | G5: 130600 | H5: 43200 | I5: Senior Engineer | J5: Senior Measurement Engineer | K5: BAND A5 | L5: 2 | M5: 5 | N5: 10987 | O5: 0.05 | P5: 549 | Q5: 0.027 | R5: 297 | S5: 0.077000091 | T5: 846 | U5: 11833 | V5: 11500 | W5: 513 | X5: 0.0467 | Y5: 6.16%-9.24% | Z5: Promotion | AA5: Functional specialist | AB5: A6 | AC5: 0.1218 | AD5: 1338 | AE5: 12838 | AF5: 1851 | AG5: 0.16847183 | AH5: 14 | AI5: 450 | AK5: 688 | AL5: 185820 | AM5: 3 | AO5: -EDSP BOX2 and EDD as driver; Workplan 5; - Work as metrology LPO and very active in CG global specialist cycle, also in local cross-categrory quality measurement club. - With profound knowledge about GD&T and measurement, he proactively collabrates with DE to optimize drawing, coach and align with supplier on meansurement approach. - He is very dedicated to work and managed all measurement demands without any delay, rated as 2025 star employee in CG RCT | AP5: Combined with promotion | AQ5: Liu Baocui （15002216） | AR5: Mo Xiaohong（11005372） | AS5: Zhao Chujun | AU5: Special | AV5: <20
A6: CN15 | B6: 1132124 | C6: Indirect Active | D6: OP | E6: SCh | F6: FCLCh-VFM | G6: 310203 | H6: 37823 | I6: Senior Engineer | J6: Senior Engineer | K6: BAND A5 | L6: 2 | M6: 4 | N6: 12754 | O6: 0.0375 | P6: 478 | Q6: 0.0155 | R6: 198 | S6: 0.053002979 | T6: 676 | U6: 13430 | V6: 13430 | W6: 676 | X6: 0.053 | Y6: 4.24%-6.36% | Z6: Promotion | AA6: Funcation specialist | AC6: 0.1 | AD6: 1275 | AE6: 14705 | AF6: 1951 | AG6: 0.15297162 | AH6: 14 | AI6: 450 | AK6: 688 | AL6: 211958 | AM6: 3 | AQ6: Zhao Biao（1150001） | AR6: Cao Wei（1114141） | AS6: Cheng Cheng | AU6: Special | AV6: OK
A7: CN15 | B7: 11018246 | C7: Indirect Active | D7: OP | E7: GPL-CN | F7: GPL-LO8 | G7: 120010 | H7: 44298 | I7: Specialist | J7: Specialist | K7: BAND A4 | L7: 2 | M7: 5 | N7: 11300 | O7: 0.03 | P7: 339 | Q7: 0 | R7: 0 | S7: 0.03 | T7: 339 | U7: 11639 | V7: 11300 | W7: 0 | X7: 0 | Y7: 2.40%-3.60% | Z7: Promotion | AB7: BAND A5 | AC7: 0.155 | AD7: 1752 | AE7: 13052 | AF7: 1752 | AG7: 0.15504425 | AH7: 14 | AI7: 550 | AK7: 688 | AL7: 190016 | AM7: 3 | AO7: Roll out BPS concept in GPL area, contributed in TPM_Lean SC pillar RGC strategical project | AQ7: Li Xiaochun（11008077） | AR7: Xu Lan（11013544） | AU7: Pending | AV7: 0 increase
A8: CN15 | B8: 11017101 | C8: Indirect Active | D8: OP | E8: GOM-DCC | F8: GOM-DCC | G8: 224011 | H8: 43864 | I8: Senior Specialist | J8: Senior Product Specialist | K8: BAND A5 | L8: 2 | M8: 4 | N8: 15188 | O8: 0.0375 | P8: 570 | Q8: 0.0155 | R8: 235 | S8: 0.05300237 | T8: 805 | U8: 15993 | V8: 15990 | W8: 802 | X8: 0.0528 | Y8: 4.24%-6.36% | Z8: Promotion | AA8: Product Manager | AB8: A6 | AC8: 0.0665 | AD8: 1010 | AE8: 17000 | AF8: 1812 | AG8: 0.11930471 | AH8: 14 | AI8: 450 | AK8: 688 | AL8: 244088 | AM8: 3 | AO8: Good performance and high competence | AP8: Good performance and high competence | AQ8: Pan Jian（15013507） | AR8: Zhu Qianqian（11016705） | AU8: Pending | AV8: OK
A9: CN15 | B9: 15012982 | C9: Indirect Active | D9: OP | E9: GOM-CGC | F9: GOM-CGCO | G9: 221012 | H9: 41821 | I9: Senior Specialist | J9: Product Specialist | K9: BAND A5 | L9: 2 | M9: 4 | N9: 16004 | O9: 0.0375 | P9: 600 | Q9: 0.0155 | R9: 248 | S9: 0.052986753 | T9: 848 | U9: 16852 | V9: 16852 | W9: 848 | X9: 0.053 | Y9: 4.24%-6.36% | Z9: Promotion | AA9: Product Manager | AB9: A6 | AC9: 0.122 | AD9: 1952 | AE9: 18804 | AF9: 2800 | AG9: 0.17495626 | AH9: 14 | AI9: 450 | AK9: 688 | AL9: 269344 | AM9: 3 | AO9: good performance and competence enhanced in last 2 years | AP9: Good performance and high competence | AQ9: Tao Song（15000036） | AR9: Zhu Qianqian（11016705） | AU9: Pending | AV9: OK
A10: CN15 | B10: 11016645 | C10: Indirect Active | D10: OP | E10: GOM-LCC | F10: GOM-LCCL | G10: 223010 | H10: 43332 | I10: Professional | J10: Product Manager | K10: BAND A6 | L10: 2 | M10: 4 | N10: 21710 | O10: 0.0375 | P10: 814 | Q10: 0.0155 | R10: 337 | S10: 0.053017043 | T10: 1151 | U10: 22861 | V10: 22650 | W10: 940 | X10: 0.0433 | Y10: 4.24%-6.36% | Z10: Promotion | AA10: Senior Product Manager | AB10: B | AC10: 0.08 | AD10: 1737 | AE10: 24387 | AF10: 2677 | AG10: 0.12330723 | AH10: 14 | AI10: 450 | AK10: 688 | AL10: 347506 | AM10: 3 | AO10: Under the G2M target, she has leveraged the collaboration with DE and redefined the lifecycle process, enabling the fulfillment for high complexity requirements in short time—such as new CMF and new BT in the lifecycle loop. Meanwhile, she taken on the role of MPO for the Monaco project, driving the product realization for slim depth dryer on T27L.IPE result:BandB | AP10: Good performance and high competence | AQ10: Zhou Yan（15001209） | AR10: Zhu Qianqian（11016705） | AU10: Pending | AV10: OK
A11: CN15 | B11: 15020888 | C11: Indirect Active | D11: OP | E11: GOM-LCC | F11: GOM-LCCI | G11: 223010 | H11: 44202 | I11: Senior Specialist | J11: Senior Innovation Specialist | K11: BAND A5 | L11: 2 | M11: 4 | N11: 18376 | O11: 0.0375 | P11: 689 | Q11: 0.0155 | R11: 285 | S11: 0.053003918 | T11: 974 | U11: 19350 | V11: 19160 | W11: 784 | X11: 0.0427 | Y11: 4.24%-6.36% | Z11: Promotion | AA11: Product Manager | AB11: A6 | AC11: 0.07 | AD11: 1286 | AE11: 20446 | AF11: 2070 | AG11: 0.11264693 | AH11: 14 | AI11: 450 | AK11: 688 | AL11: 292332 | AM11: 3 | AO11: Working competence and performance fully fulfill current job requirement, driving RGC innovation push forward and global innovation strategy landing with high quality.IPE result:BandA6 | AP11: Good performance and high competence | AQ11: Zhou Yan（15001209） | AR11: Zhu Qianqian（11016705） | AU11: Pending | AV11: OK
A12: CN15 | B12: 15002828 | C12: Indirect Active | D12: OP | E12: PCP | F12: PCP-OPGEE | G12: 270006 | H12: 40269 | I12: Technician | J12: Technician | K12: BAND A | L12: 2 | M12: 4 | N12: 5342 | O12: 0.03 | P12: 160 | Q12: 0 | R12: 0 | S12: 0.029951329 | T12: 160 | U12: 5502 | V12: 6103 | W12: 761 | X12: 0.1425 | Y12: 2.40%-3.59% | Z12: Promotion | AA12: Junior Engineer | AB12: A3 | AC12: 0.141 | AD12: 753 | AE12: 6856 | AF12: 1514 | AG12: 0.28341445 | AH12: 14 | AI12: 550 | AK12: 688 | AL12: 103272 | AM12: 3 | AO12: - Switched from Test Technician to Packaging Engineer; fast role adaptation & on-time project delivery - Proactive optimization initiatives achieved cost savings RMB 200k+ - Salary below new role band level | AP12: Good performance and high competence | AQ12: Li Huihua（15000253） | AR12: Zhu Qianqian（11016705） | AU12: Pending | AV12: >20
A13: CN15 | B13: 15009624 | C13: Indirect Active | D13: OP | E13: PCP | F13: PCP-BAUQGO | G13: 270005 | H13: 41347 | I13: Technician | J13: Technician | K13: BAND A3 | L13: 2 | M13: 4 | N13: 8111 | O13: 0.045 | P13: 365 | Q13: 0.0155 | R13: 126 | S13: 0.060535076 | T13: 491 | U13: 8602 | V13: 8510 | W13: 399 | X13: 0.0492 | Y13: 4.84%-7.26% | Z13: Promotion | AA13: Senior Technician | AB13: A3 | AC13: 0.101 | AD13: 819 | AE13: 9329 | AF13: 1218 | AG13: 0.15016644 | AH13: 14 | AI13: 450 | AK13: 688 | AL13: 136694 | AM13: 4 | AO13: Good performance and high competence | AP13: Good performance and high competence | AQ13: Li Huihua（15000253） | AR13: Zhu Qianqian（11016705） | AU13: Pending | AV13: OK
A14: CN15 | B14: 1213118 | C14: Indirect Active | D14: OP | E14: SCh | F14: FCLCh-VB2 | G14: 310400 | H14: 38924 | I14: Supervisor | J14: Head of FCLCh-VB2 | K14: BAND A6 | L14: 2 | M14: 5 | N14: 17489 | O14: 0.04 | P14: 700 | Q14: 0 | R14: 0 | S14: 0.040025159 | T14: 700 | U14: 18189 | V14: 18059 | W14: 570 | X14: 0.0326 | Y14: 3.20%-4.80% | Z14: Promotion | AA14: FCLCh-VB2 | AC14: 0.1 | AD14: 1749 | AE14: 19808 | AF14: 2319 | AG14: 0.13259763 | AH14: 14 | AI14: 450 | AK14: 688 | AL14: 283400 | AM14: 4 | AO14: High performer and responsible for a big production line with more than 200 direct employees, promote to Band B | AQ14: Zhao Biao（1150001） | AR14: Cao Wei（1114141） | AS14: Cheng Cheng | AU14: Pending | AV14: OK
A15: CN15 | B15: 1214051 | C15: Indirect Active | D15: OP | E15: SCh | F15: FCLCh-MEW | G15: 290301 | H15: 39638 | I15: Supervisor | J15: Head of FCLCh-MEW | K15: BAND A6 | L15: 2 | M15: 5 | N15: 18500 | O15: 0.05 | P15: 925 | Q15: 0.027 | R15: 500 | S15: 0.077027027 | T15: 1425 | U15: 19925 | V15: 20325 | W15: 1825 | X15: 0.0986 | Y15: 6.16%-9.24% | Z15: Promotion | AA15: Manager | AB15: B | AC15: 0.05 | AD15: 925 | AE15: 21250 | AF15: 2750 | AG15: 0.14864865 | AH15: 14 | AI15: 900 | AK15: 688 | AL15: 308988 | AM15: 5 | AO15: High performer, global project, promotion and new step | AQ15: Zhao Biao（1150001） | AR15: Cao Wei（1114141） | AS15: Cheng Cheng | AU15: Pending | AV15: OK
A16: CN15 | B16: 1421203 | C16: Indirect Active | D16: OP | E16: SC | F16: SCh-SC2MP | G16: 290153 | H16: 41939 | I16: Supervisor | J16: Head of SCh-SC2MP | K16: BAND A6 | L16: 2 | M16: 5 | N16: 16206 | O16: 0.05 | P16: 810 | Q16: 0 | R16: 0 | S16: 0.049981488 | T16: 810 | U16: 17016 | V16: 17016 | W16: 810 | X16: 0.05 | Y16: 4.00%-6.00% | Z16: Promotion | AA16: Manager | AB16: B | AC16: 0.05 | AD16: 810 | AE16: 17826 | AF16: 1620 | AG16: 0.099962977 | AH16: 14 | AI16: 900 | AK16: 688 | AL16: 261052 | AM16: 5 | AO16: Performance is average but potential is low,internal balance needed too. | AP16: Internal balance | AQ16: Zhou Chuancui（1520041） | AR16: Shao Xiao（11018043） | AS16: Cheng Cheng | AT16: Need to Apply IPE | AU16: Pending | AV16: OK
A17: CN15 | B17: 1707038 | C17: Indirect Active | D17: OP | E17: SC | F17: SCh-SC2LSW | G17: 290152 | H17: 40392 | I17: Supervisor | J17: Head of SCh-SC2LSW | K17: BAND A6 | L17: 2 | M17: 4 | N17: 9294 | O17: 0.045 | P17: 418 | Q17: 0.0421 | R17: 391 | S17: 0.087045406 | T17: 809 | U17: 10103 | V17: 10000 | W17: 706 | X17: 0.076 | Y17: 6.96%-10.45% | Z17: Promotion | AA17: SC2LS head | AB17: B | AC17: 0.1 | AD17: 929 | AE17: 10929 | AF17: 1635 | AG17: 0.17591995 | AH17: 14 | AI17: 450 | AK17: 688 | AL17: 159094 | AM17: 4 | AQ17: Wang Xiaoqing（1120031） | AR17: Shao Xiao（11018043） | AS17: Cheng Cheng | AT17: Can give more budget considering B balance,Proposed 15%-20% | AU17: Pending | AV17: OK
A18: CN15 | B18: 15014810 | C18: Indirect Active | D18: OP | E18: SNa | F18: FCGNa-VVE | G18: 330404 | H18: 42248 | I18: Senior Specialist | J18: Senior IE Specialist | K18: BAND A5 | L18: 2 | M18: 4 | N18: 11666 | O18: 0.0375 | P18: 437 | Q18: 0.0155 | R18: 181 | S18: 0.052974456 | T18: 618 | U18: 12284 | V18: 12312 | W18: 646 | X18: 0.0554 | Y18: 4.24%-6.36% | Z18: Promotion | AA18: Function specialist | AB18: A6 | AC18: 0.0646 | AD18: 754 | AE18: 13066 | AF18: 1400 | AG18: 0.12000686 | AH18: 14 | AI18: 550 | AK18: 688 | AL18: 190212 | AM18: 4 | AO18: Good performance and high competence | AP18: Good performance and high competence | AQ18: Miao Siyuan（15005811） | AR18: Zhu Qianqian（11016705） | AS18: Zhao Chujun | AU18: OK | AV18: OK
A19: CN15 | B19: 15013255 | C19: Indirect Active | D19: OP | E19: SNa | F19: FCGNa-VC | G19: 330405 | H19: 41801 | I19: Manager | J19: Head of Value Stream Cooktop | K19: BAND B | L19: 2 | M19: 4 | N19: 23800 | O19: 0.03 | P19: 714 | Q19: 0 | R19: 0 | S19: 0.03 | T19: 714 | U19: 24514 | V19: 24514 | W19: 714 | X19: 0.03 | Y19: 2.40%-3.60% | Z19: Promotion | AA19: Head of Value Stream Cooktop | AB19: C | AC19: 0.09 | AD19: 2142 | AE19: 26656 | AF19: 2856 | AG19: 0.12 | AH19: 14 | AI19: 450 | AK19: 688 | AL19: 391272 | AM19: 5 | AO19: Good performance and high competence | AP19: Good performance and high competence | AQ19: Chen Chao（15005032） | AR19: Zhu Qianqian（11016705） | AS19: Zhao Chujun | AU19: OK | AV19: OK
A20: CN15 | B20: 15005811 | C20: Indirect Active | D20: OP | E20: SNa | F20: FCGNa-VV | G20: 330404 | H20: 40646 | I20: Manager | J20: Head of Value Stream Ventilation | K20: BAND B | L20: 2 | M20: 5 | N20: 24500 | O20: 0.04 | P20: 980 | Q20: 0 | R20: 0 | S20: 0.04 | T20: 980 | U20: 25480 | V20: 25480 | W20: 980 | X20: 0.04 | Y20: 3.20%-4.80% | Z20: Promotion | AA20: Head of Value Stream Ventilation | AB20: C | AC20: 0.08 | AD20: 1960 | AE20: 27440 | AF20: 2940 | AG20: 0.12 | AH20: 14 | AI20: 450 | AK20: 688 | AL20: 402248 | AM20: 3 | AO20: Good performance and high competence | AP20: Good performance and high competence | AQ20: Chen Chao（15005032） | AR20: Zhu Qianqian（11016705） | AS20: Zhao Chujun | AU20: OK | AV20: OK
A21: CN15 | B21: 15021547 | C21: Indirect Active | D21: OP | E21: SNa | F21: FEDNa-MEP | G21: 370200 | H21: 44391 | I21: Engineer | J21: Electrical Engineer | K21: BAND A4 | L21: 2 | M21: 4 | N21: 10500 | O21: 0.0375 | P21: 394 | Q21: 0 | R21: 0 | S21: 0.03752381 | T21: 394 | U21: 10894 | V21: 10827 | W21: 327 | X21: 0.0311 | Y21: 3.00%-4.50% | Z21: Promotion | AA21: senior engineer | AB21: A5 | AC21: 0.1117 | AD21: 1173 | AE21: 12000 | AF21: 1500 | AG21: 0.14285714 | AH21: 14 | AI21: 500 | AK21: 688 | AL21: 174688 | AM21: 3 | AP21: Good performance and high competence | AQ21: Ding Xudong（15000307） | AR21: Xu Lan（11013544） | AS21: Zhao Chujun | AU21: OK | AV21: OK
A22: CN15 | B22: 15022075 | C22: Indirect Active | D22: OP | E22: SNa | F22: FLCNa-MEA | G22: 340200 | H22: 44524 | I22: Engineer | J22: Assembly Process Engineer | K22: BAND A4 | L22: 2 | M22: 4 | N22: 12645 | O22: 0.03 | P22: 379 | Q22: 0 | R22: 0 | S22: 0.029972321 | T22: 379 | U22: 13024 | V22: 12645 | W22: 0 | X22: 0 | Y22: 2.40%-3.60% | Z22: Promotion | AA22: Senior Assembly Process Engineer | AB22: A5 | AC22: 0.1 | AD22: 1265 | AE22: 13910 | AF22: 1265 | AG22: 0.10003954 | AH22: 14 | AI22: 450 | AK22: 688 | AL22: 200828 | AM22: 4 | AO22: Very positive feedback from VS and high potential in assembly team，combined with promotion | AP22: Combined with promotion | AQ22: Hu Jun（51202067） | AR22: Mo Xiaohong（11005372） | AS22: Zhao Chujun | AT22: recommend increasing but propose zero increase | AU22: OK | AV22: 0 increase
A23: CN15 | B23: 15021416 | C23: Indirect Active | D23: OP | E23: SNa | F23: FLCNa-MEA | G23: 340200 | H23: 44370 | I23: Engineer | J23: Automation Engineer | K23: BAND A4 | L23: 2 | M23: 5 | N23: 12793 | O23: 0.04 | P23: 512 | Q23: 0 | R23: 0 | S23: 0.040021887 | T23: 512 | U23: 13305 | V23: 12793 | W23: 0 | X23: 0 | Y23: 3.20%-4.80% | Z23: Promotion | AA23: Senior Automation Engineer | AB23: A5 | AC23: 0.11 | AD23: 1407 | AE23: 14200 | AF23: 1407 | AG23: 0.10998202 | AH23: 14 | AI23: 450 | AK23: 688 | AL23: 204888 | AM23: 3 | AO23: Testing expert: critical and urgently needed in the factory, combined with promotion. | AP23: Combined with promotion | AQ23: Hu Jun（51202067） | AR23: Mo Xiaohong（11005372） | AS23: Zhao Chujun | AT23: recommend increasing but propose zero increase | AU23: OK | AV23: 0 increase
A24: CN15 | B24: 15021808 | C24: Indirect Active | D24: OP | E24: SC | F24: SNa-SC4P | G24: 390502 | H24: 44480 | I24: Senior Planner | J24: Senior Planner | K24: BAND A5 | L24: 2 | M24: 4 | N24: 11375 | O24: 0.03 | P24: 341 | Q24: 0 | R24: 0 | S24: 0.029978022 | T24: 341 | U24: 11716 | V24: 11700 | W24: 325 | X24: 0.0286 | Y24: 2.40%-3.60% | Z24: Promotion | AA24: Functional Specialist | AB24: A6 | AC24: 0.05 | AD24: 569 | AE24: 12269 | AF24: 894 | AG24: 0.078593407 | AH24: 14 | AI24: 900 | AK24: 688 | AL24: 183254 | AM24: 4 | AQ24: Zhou Zongshang（51202404） | AR24: Shao Xiao（11018043） | AS24: Zhao Chujun | AU24: OK | AV24: OK
A25: CN15 | B25: 1705052 | C25: Indirect Active | D25: OP | E25: GQM | F25: GQM-DSC | G25: 190604 | H25: 39664 | I25: Engineer | J25: Engineer | K25: BAND A4 | L25: 2 | M25: 5 | N25: 9678 | O25: 0.06 | P25: 581 | Q25: 0.0778 | R25: 753 | S25: 0.1378384 | T25: 1334 | U25: 11012 | V25: 11012 | W25: 1334 | X25: 0.1378 | Y25: 11.03%-16.54% | Z25: Promotion | AA25: Senior engineer | AB25: A5 | AC25: 0.05 | AD25: 484 | AE25: 11496 | AF25: 1818 | AG25: 0.18784873 | AH25: 14 | AI25: 450 | AK25: 688 | AL25: 167032 | AM25: 3 | AO25: Has made outstanding contributions to the digital transformation of quality, personal skills and capabilities also got continuously developed and improved. At the same time, actively supported cross-departmental coordination work. | AP25: Good performance and high potential | AQ25: Subasi Gonca（15022750） | AR25: Mo Xiaohong（11005372） | AS25: Zhao Chujun | AU25: OK | AV25: OK
A26: CN15 | B26: 1120271 | C26: Indirect Active | D26: OP | E26: GQM | F26: GQM-PS | G26: 190605 | H26: 44113 | I26: Engineer | J26: Engineer of Product Safety | K26: BAND A4 | L26: 2 | M26: 4 | N26: 9350 | O26: 0.0375 | P26: 351 | Q26: 0.0155 | R26: 145 | S26: 0.053048128 | T26: 496 | U26: 9846 | V26: 9846 | W26: 496 | X26: 0.053 | Y26: 4.24%-6.37% | Z26: Promotion | AA26: Senior engineer | AB26: A5 | AC26: 0.1 | AD26: 935 | AE26: 10781 | AF26: 1431 | AG26: 0.15304813 | AH26: 14 | AI26: 450 | AK26: 688 | AL26: 157022 | AM26: 4 | AO26: Joined BSH more than 6 years and participate GQM-PS from 2023 , professional on CTS investigation, NoTI and Nicrs testing, coordinating with internal and external for high market risk CTS and support the team to handle the case to avoid the potential risk. | AP26: Good performance and high competence | AQ26: Subasi Gonca（15022750） | AR26: Mo Xiaohong（11005372） | AS26: Zhao Chujun | AU26: OK | AV26: OK
A27: CN15 | B27: 1211016 | C27: Indirect Active | D27: OP | E27: GQM | F27: GQM-SRCA | G27: 190601 | H27: 37999 | I27: Engineer | J27: Engineer of Calibration | K27: BAND A4 | L27: 2 | M27: 4 | N27: 8558 | O27: 0.0375 | P27: 321 | Q27: 0.0155 | R27: 133 | S27: 0.053049778 | T27: 454 | U27: 9012 | V27: 9012 | W27: 454 | X27: 0.053 | Y27: 4.24%-6.37% | Z27: Promotion | AA27: Senior engineer | AB27: A5 | AC27: 0.1 | AD27: 856 | AE27: 9868 | AF27: 1310 | AG27: 0.15307315 | AH27: 14 | AI27: 450 | AK27: 688 | AL27: 144240 | AM27: 4 | AO27: Worked in BSH more than 20 years and professional in internal & external calibration, total cost saving more than 2M RMB for BSH. She is supporting Qingbo for calibration strategy project from 2026, total saving arrived 330K RMB. | AP27: Good performance and high competence | AQ27: Subasi Gonca（15022750） | AR27: Mo Xiaohong（11005372） | AS27: Zhao Chujun | AU27: OK | AV27: OK
A28: CN15 | B28: 15021228 | C28: Indirect Active | D28: OP | E28: GQM | F28: GQM-DCC | G28: 120600 | H28: 44300 | I28: Engineer | J28: Project Quality Engineer | K28: BAND A4 | L28: 2 | M28: 4 | N28: 8306 | O28: 0.0375 | P28: 311 | Q28: 0.0155 | R28: 129 | S28: 0.052973754 | T28: 440 | U28: 8746 | V28: 8350 | W28: 44 | X28: 0.0053 | Y28: 4.24%-6.36% | Z28: Promotion | AA28: Senior engineer | AB28: A5 | AC28: 0.0726 | AD28: 603 | AE28: 8953 | AF28: 647 | AG28: 0.077895497 | AH28: 14 | AI28: 450 | AK28: 688 | AL28: 131430 | AM28: 3 | AO28: Promote from engineer to senior engineer. 1. Act as Q lead of GV650AX.3CN & GV650AX.6CN projects to achieve very good quality KPI and launch performance. 2. Act as Q lead of dishwasher Taiwan project, first export product, 5 months ealier than normal VAVO project. | AP28: Combined with promotion | AQ28: Guo Yuwei （15014438） | AR28: Mo Xiaohong（11005372） | AS28: Cheng Cheng | AU28: OK | AV28: <20
A29: CN15 | B29: 1213149 | C29: Indirect Active | D29: OP | E29: GQM | F29: GQM-CLCD | G29: 110600 | H29: 40725 | I29: Engineer | J29: Quality Planning Engineer | K29: BAND A4 | L29: 2 | M29: 4 | N29: 10342 | O29: 0.03 | P29: 310 | Q29: 0 | R29: 0 | S29: 0.02997486 | T29: 310 | U29: 10652 | V29: 10342 | W29: 0 | X29: 0 | Y29: 2.40%-3.60% | Z29: Promotion | AA29: Senior engineer | AB29: A5 | AC29: 0.168 | AD29: 1737 | AE29: 12079 | AF29: 1737 | AG29: 0.16795591 | AH29: 14 | AI29: 450 | AK29: 688 | AL29: 175194 | AM29: 3 | AO29: 1. As Q-lead in MD85 0 gap project, earlier detection, good cooperation and collaboration to contribute project launch; 2. As project lead, successful handled appliance release in TCNG, good driver in QM and DE between local and global. 3. As CBA Architecture local Q-lead (Additionally tasks), well handled the lessons learn, engineering release for each SWG.4. As MCC local QM driver (Additionally tasks), good arrangement within QM each functions to ensure MCC project quality under high pressure and limited cap. | AP29: Combined with promotion | AQ29: Li Chaozi （1211022） | AR29: Mo Xiaohong（11005372） | AS29: Zhao Chujun | AU29: OK | AV29: 0 increase
A30: CN15 | B30: 15021707 | C30: Indirect Active | D30: OP | E30: GQM | F30: GQM-EDCL | G30: 170600 | H30: 44440 | I30: Engineer | J30: Quality Engineer | K30: BAND A4 | L30: 2 | M30: 4 | N30: 13000 | O30: 0.03 | P30: 390 | Q30: 0 | R30: 0 | S30: 0.03 | T30: 390 | U30: 13390 | V30: 13000 | W30: 0 | X30: 0 | Y30: 2.40%-3.60% | Z30: Promotion | AA30: Senior Quality Engineer | AB30: A5 | AC30: 0.077 | AD30: 1001 | AE30: 14001 | AF30: 1001 | AG30: 0.077 | AH30: 14 | AI30: 450 | AK30: 688 | AL30: 202102 | AM30: 3 | AO30: Use promotion budget | AP30: Combined with promotion | AQ30: Li Chen（15022148） | AR30: Mo Xiaohong（11005372） | AS30: Zhao Chujun | AU30: OK | AV30: 0 increase
A31: CN15 | B31: 15002626 | C31: Indirect Active | D31: OP | E31: GQM | F31: FLCNa-QM | G31: 340600 | H31: 40360 | I31: Engineer | J31: Quality Engineer | K31: BAND A4 | L31: 2 | M31: 5 | N31: 9860 | O31: 0.03 | P31: 296 | Q31: 0 | R31: 0 | S31: 0.030020284 | T31: 296 | U31: 10156 | V31: 10200 | W31: 340 | X31: 0.0345 | Y31: 2.40%-3.60% | Z31: Promotion | AA31: Senior Quality Engineer | AB31: A5 | AC31: 0.05 | AD31: 493 | AE31: 10693 | AF31: 833 | AG31: 0.084482759 | AH31: 14 | AI31: 450 | AK31: 688 | AL31: 155790 | AM31: 3 | AO31: 1. High perfomer, overqualify current position, ranking5 2. Young talent in FLCNa factory QM team, EDSP box3 3. T-shape with multiple skill in Problem solving, Manufacturing engineering, Training vedio filming&producing 4. Fullfil capability required for Senior QMP Enginner and show high potential to be further developed to QMP functional specialist in coming 1-3 years. | AP31: Good performance and high potential | AQ31: Zhu Chen (15010791) | AR31: Mo Xiaohong（11005372） | AS31: Zhao Chujun | AU31: OK | AV31: OK
A32: CN15 | B32: 15020110 | C32: Indirect Active | D32: OP | E32: GQM | F32: FLCNa-QMS | G32: 340601 | H32: 44013 | I32: Engineer | J32: Incoming Quality Engineer | K32: BAND A4 | L32: 2 | M32: 4 | N32: 8720 | O32: 0.03 | P32: 262 | Q32: 0 | R32: 0 | S32: 0.030045872 | T32: 262 | U32: 8982 | V32: 9020 | W32: 300 | X32: 0.0344 | Y32: 2.40%-3.61% | Z32: Promotion | AA32: Senior Quality Engineer | AB32: A5 | AC32: 0.05 | AD32: 436 | AE32: 9456 | AF32: 736 | AG32: 0.08440367 | AH32: 14 | AI32: 450 | AK32: 688 | AL32: 138472 | AM32: 3 | AO32: 1. High perfomer, overqualify current position, ranking4 3. T-shape with multiple skill in Problem solving, Supplier quality management and Digital inspection technology. 4. Fullfil capability required for Senior QMS Enginner and show high potential to be further developed to QMS functional specialist in coming 3-5 years. | AP32: Good performance and high potential | AQ32: Zhu Chen (15010791) | AR32: Mo Xiaohong（11005372） | AS32: Zhao Chujun | AU32: OK | AV32: OK
A33: CN15 | B33: 1708021 | C33: Indirect Active | D33: OP | E33: GQM | F33: FLCCh-QMS | G33: 340601 | H33: 40764 | I33: Engineer | J33: Engineer | K33: BAND A4 | L33: 2 | M33: 5 | N33: 7903 | O33: 0.06 | P33: 474 | Q33: 0.0778 | R33: 615 | S33: 0.13779577 | T33: 1089 | U33: 8992 | V33: 8800 | W33: 897 | X33: 0.1135 | Y33: 11.02%-16.54% | Z33: Promotion | AA33: Senior Quality Engineer | AB33: A5 | AC33: 0.05 | AD33: 395 | AE33: 9195 | AF33: 1292 | AG33: 0.16348222 | AH33: 14 | AI33: 450 | AK33: 688 | AL33: 134818 | AM33: 4 | AO33: 1. High perfomer, overqualify current position, ranking5, EDSP box2 3. T-shape with multiple skill in Problem solving, Supplier quality management, Digital inspection technology and Labor Union activities management 4. Fullfil capability required for Senior QMS Enginner and show high potential to be further developed to QMS functional specialist in coming 1-3 years | AP33: Good performance and high potential | AQ33: Zhu Chen (15010791) | AR33: Mo Xiaohong（11005372） | AS33: Zhao Chujun | AU33: OK | AV33: OK
A34: CN15 | B34: 15020957 | C34: Indirect Active | D34: OP | E34: GQM | F34: GQM-LCCT | G34: 140600 | H34: 44265 | I34: Engineer | J34: Quality Test Engineer | K34: BAND A4 | L34: 2 | M34: 4 | N34: 12634 | O34: 0.0375 | P34: 474 | Q34: 0.0155 | R34: 196 | S34: 0.053031502 | T34: 670 | U34: 13304 | V34: 13304 | W34: 670 | X34: 0.053 | Y34: 4.24%-6.36% | Z34: Promotion | AA34: Senior Test Engineer | AB34: A5 | AC34: 0.05 | AD34: 632 | AE34: 13936 | AF34: 1302 | AG34: 0.10305525 | AH34: 14 | AI34: 450 | AK34: 688 | AL34: 201192 | AM34: 4 | AO34: 1. High perfomer, overqualify current position, ranking4 2. Virtual leader of WM/WD validation working team, key contrbutor for Modena/Napoli/Slim product time to market 3. T-shape with multiple skill in Validation design, Risk assessment, Problem solving and Product connectivity&analytics 4. Fullfil capability required for Senior Test Enginner and show high potential to be further developed to Test functional specialist in coming 1-3 years | AP34: Good performance and high potential | AQ34: Zhu Chen (15010791) | AR34: Mo Xiaohong（11005372） | AS34: Zhao Chujun | AU34: OK | AV34: OK
A35: CN15 | B35: 11010005 | C35: Indirect Active | D35: OP | E35: GPL-CN | F35: GPL-LO8G | G35: 120010 | H35: 41526 | I35: Specialist | J35: Specialist | K35: BAND A4 | L35: 2 | M35: 4 | N35: 9200 | O35: 0.03 | P35: 276 | Q35: 0 | R35: 0 | S35: 0.03 | T35: 276 | U35: 9476 | V35: 9200 | W35: 0 | X35: 0 | Y35: 2.40%-3.60% | Z35: Promotion | AB35: A5 | AC35: 0.1408 | AD35: 1295 | AE35: 10495 | AF35: 1295 | AG35: 0.14076087 | AH35: 14 | AI35: 450 | AK35: 688 | AL35: 153018 | AM35: 3 | AQ35: Li Xiaochun（11008077） | AR35: Xu Lan（11013544） | AU35: OK | AV35: 0 increase
A36: CN15 | B36: 11002805 | C36: Indirect Active | D36: OP | E36: GPL-CN | F36: GPL-SC8XA | G36: 232230 | H36: 38504 | I36: RDC Operations & Delivery Execution | J36: RDC Operations & Delivery Execution | K36: BAND A | L36: 2 | M36: 5 | N36: 8717 | O36: 0.03 | P36: 262 | Q36: 0 | R36: 0 | S36: 0.030056212 | T36: 262 | U36: 8979 | V36: 8717 | W36: 0 | X36: 0 | Y36: 2.40%-3.61% | Z36: Promotion | AA36: Senior Specialist | AB36: A5 | AC36: 0.113 | AD36: 985 | AE36: 9702 | AF36: 985 | AG36: 0.11299759 | AH36: 14 | AI36: 1050 | AK36: 688 | AL36: 149116 | AM36: 4 | AQ36: Chen Meng（11007521） | AR36: Xu Lan（11013544） | AU36: OK | AV36: 0 increase
A37: CN15 | B37: 11011160 | C37: Indirect Active | D37: OP | E37: GPL-CN | F37: GPL-SC8XX | G37: 234630 | H37: 41827 | I37: RDC Operations | J37: RDC Operations | K37: BAND A | L37: 2 | M37: 4 | N37: 8300 | O37: 0.0225 | P37: 187 | Q37: 0 | R37: 0 | S37: 0.02253012 | T37: 187 | U37: 8487 | V37: 8300 | W37: 0 | X37: 0 | Y37: 1.80%-2.70% | Z37: Promotion | AA37: Senior Specialist | AB37: A5 | AC37: 0.16 | AD37: 1328 | AE37: 9628 | AF37: 1328 | AG37: 0.16 | AH37: 14 | AI37: 1650 | AK37: 688 | AL37: 155280 | AM37: 3 | AQ37: Chen Meng（11007521） | AR37: Xu Lan（11013544） | AU37: OK | AV37: 0 increase
A38: CN15 | B38: 11013956 | C38: Indirect Active | D38: OP | E38: GPL-CN | F38: GPL-SC8XH | G38: 231230 | H38: 42562 | I38: RDC Operations | J38: RDC Operations | K38: BAND A | L38: 2 | M38: 5 | N38: 9217 | O38: 0.02 | P38: 184 | Q38: 0 | R38: 0 | S38: 0.019963112 | T38: 184 | U38: 9401 | V38: 9217 | W38: 0 | X38: 0 | Y38: 1.60%-2.40% | Z38: Promotion | AA38: Senior Specialist | AB38: A5 | AC38: 0.1101 | AD38: 1015 | AE38: 10232 | AF38: 1015 | AG38: 0.1101226 | AH38: 14 | AI38: 2150 | AK38: 688 | AL38: 169736 | AM38: 5 | AQ38: Chen Meng（11007521） | AR38: Xu Lan（11013544） | AU38: OK | AV38: 0 increase
A39: CN15 | B39: 11015490 | C39: Indirect Active | D39: OP | E39: GPL-CN | F39: GPL-SC8XEO | G39: 234330 | H39: 43017 | I39: Delivery Execution | J39: Delivery Execution | K39: BAND A | L39: 2 | M39: 5 | N39: 9723 | O39: 0.04 | P39: 389 | Q39: 0 | R39: 0 | S39: 0.040008228 | T39: 389 | U39: 10112 | V39: 9723 | W39: 0 | X39: 0 | Y39: 3.20%-4.80% | Z39: Promotion | AA39: Senior Specialist | AB39: A5 | AC39: 0.1 | AD39: 972 | AE39: 10695 | AF39: 972 | AG39: 0.099969145 | AH39: 14 | AI39: 450 | AK39: 688 | AL39: 155818 | AM39: 3 | AQ39: Chen Meng（11007521） | AR39: Xu Lan（11013544） | AU39: OK | AV39: 0 increase
A40: CN15 | B40: 11017418 | C40: Indirect Active | D40: OP | E40: GPL-CN | F40: GPL-SC8XS | G40: 233330 | H40: 44053 | I40: RDC Operations | J40: RDC Operations | K40: BAND A | L40: 2 | M40: 5 | N40: 8922 | O40: 0.03 | P40: 268 | Q40: 0 | R40: 0 | S40: 0.030038108 | T40: 268 | U40: 9190 | V40: 8922 | W40: 0 | X40: 0 | Y40: 2.40%-3.60% | Z40: Promotion | AA40: Senior Specialist | AB40: A5 | AC40: 0.129 | AD40: 1151 | AE40: 10073 | AF40: 1151 | AG40: 0.12900695 | AH40: 14 | AI40: 2650 | AK40: 688 | AL40: 173510 | AM40: 4 | AQ40: Chen Meng（11007521） | AR40: Xu Lan（11013544） | AU40: OK | AV40: 0 increase
A41: CN15 | B41: 11017501 | C41: Indirect Active | D41: OP | E41: GPL-CN | F41: GPL-SC8XW | G41: 233630 | H41: 44075 | I41: Channel FCST & Fulfillment | J41: Channel FCST & Fulfillment | K41: BAND A | L41: 2 | M41: 5 | N41: 9755 | O41: 0.04 | P41: 390 | Q41: 0 | R41: 0 | S41: 0.039979498 | T41: 390 | U41: 10145 | V41: 9755 | W41: 0 | X41: 0 | Y41: 3.20%-4.80% | Z41: Promotion | AA41: Senior Specialist | AB41: A5 | AC41: 0.1 | AD41: 976 | AE41: 10731 | AF41: 976 | AG41: 0.10005126 | AH41: 14 | AI41: 450 | AK41: 688 | AL41: 156322 | AM41: 4 | AQ41: Chen Meng（11007521） | AR41: Xu Lan（11013544） | AU41: OK | AV41: 0 increase
A42: CN15 | B42: 15014796 | C42: Indirect Active | D42: OP | E42: PCP | F42: PCP-OPGEE | G42: 150800 | H42: 42256 | I42: Engineer | J42: Approbation Engineer | K42: BAND A4 | L42: 2 | M42: 4 | N42: 12030 | O42: 0.03 | P42: 361 | Q42: 0 | R42: 0 | S42: 0.030008313 | T42: 361 | U42: 12391 | V42: 12320 | W42: 290 | X42: 0.0241 | Y42: 2.40%-3.60% | Z42: Promotion | AA42: Senior Engineer | AB42: A5 | AC42: 0.055 | AD42: 662 | AE42: 12982 | AF42: 952 | AG42: 0.079135495 | AH42: 14 | AI42: 450 | AK42: 688 | AL42: 187836 | AM42: 4 | AO42: Good performance and high competence | AP42: Good performance and high competence | AQ42: Li Huihua（15000253） | AR42: Zhu Qianqian（11016705） | AU42: OK | AV42: OK
A43: CN15 | B43: 15003876 | C43: Indirect Active | D43: OP | E43: PCP | F43: PCP-OPGEV | G43: 150800 | H43: 40322 | I43: Junior Engineer | J43: Junior Engineer | K43: BAND A3 | L43: 2 | M43: 5 | N43: 7746 | O43: 0.05 | P43: 387 | Q43: 0.027 | R43: 209 | S43: 0.076942938 | T43: 596 | U43: 8342 | V43: 8230 | W43: 484 | X43: 0.0625 | Y43: 6.16%-9.23% | Z43: Promotion | AA43: Test Engineer | AB43: A4 | AC43: 0.065 | AD43: 503 | AE43: 8733 | AF43: 987 | AG43: 0.1274206 | AH43: 14 | AI43: 450 | AK43: 688 | AL43: 128350 | AM43: 3 | AO43: Good performance and high competence | AP43: Good performance and high competence | AQ43: Li Huihua（15000253） | AR43: Zhu Qianqian（11016705） | AU43: OK | AV43: OK
A44: CN15 | B44: 15013982 | C44: Indirect Active | D44: OP | E44: PCP | F44: PCP-OPGEX | G44: 150800 | H44: 42032 | I44: Engineer | J44: Product Engineer | K44: BAND A4 | L44: 2 | M44: 4 | N44: 16369 | O44: 0.03 | P44: 491 | Q44: 0 | R44: 0 | S44: 0.029995724 | T44: 491 | U44: 16860 | V44: 16770 | W44: 401 | X44: 0.0245 | Y44: 2.40%-3.60% | Z44: Promotion | AA44: Senior Engineer | AB44: A5 | AC44: 0.05 | AD44: 818 | AE44: 17588 | AF44: 1219 | AG44: 0.074470035 | AH44: 14 | AI44: 450 | AK44: 688 | AL44: 252320 | AM44: 3 | AO44: Good performance and high competence | AP44: Good performance and high competence | AQ44: Li Huihua（15000253） | AR44: Zhu Qianqian（11016705） | AU44: OK | AV44: OK
A45: CN15 | B45: 15020884 | C45: Indirect Active | D45: OP | E45: PCP | F45: PCP-FDTG | G45: 150700 | H45: 44230 | I45: Engineer | J45: Nutrition Engineer | K45: BAND A4 | L45: 2 | M45: 4 | N45: 13215 | O45: 0.0375 | P45: 496 | Q45: 0 | R45: 0 | S45: 0.037533106 | T45: 496 | U45: 13711 | V45: 13777 | W45: 562 | X45: 0.0425 | Y45: 3.00%-4.50% | Z45: Promotion | AA45: senior engineer | AB45: A5 | AC45: 0.1 | AD45: 1322 | AE45: 15099 | AF45: 1884 | AG45: 0.14256527 | AH45: 14 | AI45: 550 | AK45: 688 | AL45: 218674 | AM45: 4 | AO45: Good performance and high competence | AP45: Good performance and high competence | AQ45: Li Huihua（15000253） | AR45: Zhu Qianqian（11016705） | AU45: OK | AV45: OK
A46: CN15 | B46: 11017114 | C46: Indirect Active | D46: OP | E46: PCP | F46: PCP-BAUQGP | G46: 935119 | H46: 43928 | I46: Senior Engineer | J46: Senior Engineer | K46: BAND A5 | L46: 2 | M46: 4 | N46: 17016 | O46: 0.0225 | P46: 383 | Q46: 0 | R46: 0 | S46: 0.022508228 | T46: 383 | U46: 17399 | V46: 17399 | W46: 383 | X46: 0.0225 | Y46: 1.80%-2.70% | Z46: Promotion | AA46: Functional Specialist | AB46: A6 | AC46: 0.13 | AD46: 2212 | AE46: 19611 | AF46: 2595 | AG46: 0.15250353 | AH46: 14 | AI46: 450 | AK46: 688 | AL46: 280642 | AM46: 5 | AO46: Good performance and high competence | AP46: Good performance and high competence | AQ46: Li Huihua（15000253） | AR46: Zhu Qianqian（11016705） | AU46: OK | AV46: OK
A47: CN15 | B47: 11014818 | C47: Indirect Active | D47: OP | E47: OP-TE | F47: CN/OP-TEI | G47: 131050 | H47: 42891 | I47: Senior Engineer | J47: Senior Engineer | K47: BAND A5 | L47: 2 | M47: 4 | N47: 20519 | O47: 0.03 | P47: 616 | Q47: 0 | R47: 0 | S47: 0.030020956 | T47: 616 | U47: 21135 | V47: 21135 | W47: 616 | X47: 0.03 | Y47: 2.40%-3.60% | Z47: Promotion | AB47: A6 | AC47: 0.07 | AD47: 1436 | AE47: 22571 | AF47: 2052 | AG47: 0.10000487 | AH47: 14 | AI47: 450 | AK47: 688 | AL47: 322082 | AM47: 4 | AQ47: Zhang Rui（11000448） | AR47: Xu Lan（11013544） | AS47: Wu Ellen | AU47: OK | AV47: OK
A48: CN15 | B48: 11016622 | C48: Indirect Active | D48: OP | E48: CN/OP-RM | F48: CN/OP-RMH | G48: 121054 | H48: 44013 | I48: Specialist | J48: Specialist | K48: BAND A4 | L48: 2 | M48: 5 | N48: 7962 | O48: 0.04 | P48: 318 | Q48: 0 | R48: 0 | S48: 0.039939714 | T48: 318 | U48: 8280 | V48: 8300 | W48: 338 | X48: 0.0425 | Y48: 3.20%-4.79% | Z48: Promotion | AA48: Senior specialist | AB48: A5 | AC48: 0.11 | AD48: 876 | AE48: 9176 | AF48: 1214 | AG48: 0.15247425 | AH48: 14 | AI48: 450 | AK48: 688 | AL48: 134552 | AM48: 5 | AO48: Since May 2025, Zheng Han has served as RM TA alongside her core role, supporting the RM Head and team in delivering multiple workshops, events, and meetings — all on target. She demonstrates strong learning agility, proactive ownership, and creative thinking, with exceptional potential. | AP48: Good performance and high potential | AQ48: Shen Fendi-Siyuan（11021165） | AR48: Mo Xiaohong（11005372） | AS48: Wu Ellen | AU48: OK | AV48: OK
A49: CN15 | B49: 1120346 | C49: Indirect Active | D49: OP | E49: CN/OP-RM | F49: CN/OP-RMCF | G49: 290300 | H49: 44440 | I49: Engineer | J49: Engineer of Electrical | K49: BAND A4 | L49: 2 | M49: 4 | N49: 9580 | O49: 0.0375 | P49: 359 | Q49: 0.0155 | R49: 148 | S49: 0.052922756 | T49: 507 | U49: 10087 | V49: 10000 | W49: 420 | X49: 0.0438 | Y49: 4.23%-6.35% | Z49: Promotion | AA49: Senior Engineer | AB49: A5 | AC49: 0.093 | AD49: 891 | AE49: 10891 | AF49: 1311 | AG49: 0.1368476 | AH49: 14 | AI49: 450 | AK49: 688 | AL49: 158562 | AM49: 3 | AO49: 1. From 2025.09.01, took energy management platform tasks in EA and HA. 2. Lead energy efficiency project in EA and HA 3. As RM energy officer in RGC | AP49: Good performance and high potential | AQ49: Fu Gang（1320032） | AR49: Mo Xiaohong（11005372） | AS49: Wu Ellen | AU49: OK | AV49: OK
A50: CN15 | B50: 15013014 | C50: Indirect Active | D50: OP | E50: CN/OP-RM | F50: CN/OP-RMNF | G50: 290300 | H50: 41766 | I50: Senior Engineer | J50: Senior Facility Engineer | K50: BAND A5 | L50: 2 | M50: 5 | N50: 12600 | O50: 0.05 | P50: 630 | Q50: 0.027 | R50: 340 | S50: 0.076984127 | T50: 970 | U50: 13570 | V50: 13400 | W50: 800 | X50: 0.0635 | Y50: 6.16%-9.24% | Z50: Promotion | AA50: Functional specialist | AB50: A6 | AC50: 0.084 | AD50: 1058 | AE50: 14458 | AF50: 1858 | AG50: 0.14746032 | AH50: 14 | AI50: 450 | AK50: 688 | AL50: 208500 | AM50: 4 | AO50: 1. Take additional task as Sna Location Electrical Safety officer 2. From 2025.09.01, he took fire fighting system, air condition system in SCh ,and deliver good performance. | AP50: Good performance and high potential | AQ50: Chen Lianrong（15022534） | AR50: Mo Xiaohong（11005372） | AS50: Wu Ellen | AU50: OK | AV50: OK
A51: CN15 | B51: 1116073 | C51: Indirect Active | D51: OP | E51: SCh | F51: FCLCh-MET | G51: 310204 | H51: 38566 | I51: Engineer | J51: Thermoforming Engineer | K51: BAND A4 | L51: 2 | M51: 5 | N51: 8880 | O51: 0.05 | P51: 444 | Q51: 0.027 | R51: 240 | S51: 0.077027027 | T51: 684 | U51: 9564 | V51: 10200 | W51: 1320 | X51: 0.1486 | Y51: 6.16%-9.24% | Z51: Promotion | AA51: senior engineer | AB51: A5 | AC51: 0.0897 | AD51: 797 | AE51: 10997 | AF51: 2117 | AG51: 0.2384009 | AH51: 14 | AI51: 450 | AK51: 688 | AL51: 160046 | AM51: 4 | AO51: High performer, recognized in CL | AQ51: Zhao Biao（1150001） | AR51: Cao Wei（1114141） | AS51: Cheng Cheng | AU51: OK | AV51: >20
A52: CN15 | B52: 1705021 | C52: Indirect Active | D52: OP | E52: SCh | F52: FCLCh-MET | G52: 310204 | H52: 39664 | I52: Senior Engineer | J52: Senior Door Gasket Extrusion Engineer | K52: BAND A5 | L52: 2 | M52: 4 | N52: 11633 | O52: 0.0375 | P52: 436 | Q52: 0.0155 | R52: 180 | S52: 0.052952807 | T52: 616 | U52: 12249 | V52: 12800 | W52: 1167 | X52: 0.1003 | Y52: 4.24%-6.35% | Z52: Promotion | AA52: functional specialist | AB52: A6 | AC52: 0.05 | AD52: 582 | AE52: 13382 | AF52: 1749 | AG52: 0.15034815 | AH52: 14 | AI52: 450 | AK52: 688 | AL52: 193436 | AM52: 4 | AO52: Recognition in CL, act as informal GPO | AQ52: Zhao Biao（1150001） | AR52: Cao Wei（1114141） | AS52: Cheng Cheng | AU52: OK | AV52: >20
A53: CN15 | B53: 1120158 | C53: Indirect Active | D53: OP | E53: SCh | F53: FDCCh-MEA | G53: 320200 | H53: 44179 | I53: Senior Engineer | J53: Senior Process Engineer | K53: BAND A5 | L53: 2 | M53: 5 | N53: 16000 | O53: 0.04 | P53: 640 | Q53: 0 | R53: 0 | S53: 0.04 | T53: 640 | U53: 16640 | V53: 16200 | W53: 200 | X53: 0.0125 | Y53: 3.20%-4.80% | Z53: Promotion | AA53: Head of MEA | AB53: A6 | AC53: 0.093 | AD53: 1488 | AE53: 17688 | AF53: 1688 | AG53: 0.1055 | AH53: 14 | AI53: 450 | AK53: 688 | AL53: 253720 | AM53: 4 | AO53: Blance with promotion budget | AQ53: Lin Xianzhong（1132204） | AR53: Li Mingzhe（15018080） | AS53: Cheng Cheng | AU53: OK | AV53: <20
A54: CN15 | B54: 1120255 | C54: Indirect Active | D54: OP | E54: SCh | F54: FLCCh-ME | G54: 340200 | H54: 44010 | I54: Engineer | J54: Engineer of Testing | K54: BAND A4 | L54: 2 | M54: 4 | N54: 9207 | O54: 0.0375 | P54: 345 | Q54: 0.0155 | R54: 143 | S54: 0.05300315 | T54: 488 | U54: 9695 | V54: 9559 | W54: 352 | X54: 0.0382 | Y54: 4.24%-6.36% | Z54: Promotion | AA54: Senior Engineer | AB54: A5 | AC54: 0.075 | AD54: 691 | AE54: 10250 | AF54: 1043 | AG54: 0.11328337 | AH54: 14 | AI54: 450 | AK54: 688 | AL54: 149588 | AM54: 3 | AP54: Good performance and high competence | AQ54: Gu Yinhua（51200135） | AR54: Fan Ivy-Linlin（11022356） | AS54: Cheng Cheng | AU54: OK | AV54: OK
A55: CN15 | B55: 1120264 | C55: Indirect Active | D55: OP | E55: SCh | F55: FLCCh-ME | G55: 340200 | H55: 44075 | I55: Senior Engineer | J55: Senior Engineer of Testing | K55: BAND A5 | L55: 2 | M55: 4 | N55: 11125 | O55: 0.045 | P55: 501 | Q55: 0.0155 | R55: 172 | S55: 0.060494382 | T55: 673 | U55: 11798 | V55: 11666 | W55: 541 | X55: 0.0486 | Y55: 4.84%-7.26% | Z55: Promotion | AA55: Functional specialist | AB55: A6 | AC55: 0.075 | AD55: 834 | AE55: 12500 | AF55: 1375 | AG55: 0.12359551 | AH55: 14 | AI55: 450 | AK55: 688 | AL55: 181088 | AM55: 5 | AP55: Good performance and high competence | AQ55: Gu Yinhua（51200135） | AR55: Fan Ivy-Linlin（11022356） | AS55: Cheng Cheng | AU55: OK | AV55: OK
A56: CN15 | B56: 1230108 | C56: Indirect Active | D56: OP | E56: SC | F56: SCh-SC2ME | G56: 290153 | H56: 42877 | I56: Senior Planner | J56: Senior Material Planner | K56: BAND A5 | L56: 2 | M56: 4 | N56: 9451 | O56: 0.045 | P56: 425 | Q56: 0.0421 | R56: 398 | S56: 0.087080732 | T56: 823 | U56: 10274 | V56: 10110 | W56: 659 | X56: 0.0697 | Y56: 6.97%-10.45% | Z56: Promotion | AA56: funcational specialist | AB56: A6 | AC56: 0.05 | AD56: 473 | AE56: 10583 | AF56: 1132 | AG56: 0.11977569 | AH56: 14 | AI56: 450 | AK56: 688 | AL56: 154250 | AM56: 4 | AO56: She is the candidate in future MM OPEX study1 and She can be also candidate for expert role after Step-2 either in MM or GPL-SCS MM LPO. 1.Excellent in managing electronic suppliers, with significant contributions following the MP group consolidation. 2. Drove the following key and complex projects from the supply chain side:  Resolution of TFT bottleneck and contribution to ratio (through local source introduction).  Key leading role in supply and demand management during the Delta factory relocation (over 10 months), ensuring demand supply with no OB risk. 3. MP digitalization pioneer; subject matter expert in Power BI and Quick BI. Key deliverables include inventory and OB stock Quick BI reports in MP. | AQ56: Zhou Chuancui（1520041） | AR56: Shao Xiao（11018043） | AS56: Cheng Cheng | AU56: OK | AV56: OK
A57: CN15 | B57: 11008282 | C57: Indirect Active | D57: OP | E57: SC | F57: SCh-SC2P | G57: 290154 | H57: 40843 | I57: Senior Planner | J57: Senior Production Planner | K57: BAND A5 | L57: 2 | M57: 4 | N57: 10500 | O57: 0.0375 | P57: 394 | Q57: 0.0155 | R57: 163 | S57: 0.053047619 | T57: 557 | U57: 11057 | V57: 10950 | W57: 450 | X57: 0.0429 | Y57: 4.24%-6.37% | Z57: Promotion | AA57: Functional Specialist | AB57: A6 | AC57: 0.05 | AD57: 525 | AE57: 11475 | AF57: 975 | AG57: 0.092857143 | AH57: 14 | AI57: 450 | AK57: 688 | AL57: 166738 | AM57: 4 | AO57: 1.Proficient in SAP systems 2.Be proficient in lean manufacturing and continuous improvement methodologies, and fully utilize digital, AI - related statistical and analytical capabilities. 3. She is leading the LC Inhouse Production Planning and coverage optimization project. After the completion of this project, standardization will be achieved and introduced to other EA and HA factories. | AQ57: Yang Fangfang（1421065） | AR57: Shao Xiao（11018043） | AS57: Cheng Cheng | AT57: budget need to be discussed, need consider internal balance with Dawei | AU57: OK | AV57: OK
A58: CN15 | B58: 1120312 | C58: Indirect Active | D58: OP | E58: SC | F58: SCh-SC2S | G58: 290151 | H58: 44314 | I58: Engineer | J58: Engineer of Logistics | K58: BAND A4 | L58: 2 | M58: 5 | N58: 10600 | O58: 0.03 | P58: 318 | Q58: 0 | R58: 0 | S58: 0.03 | T58: 318 | U58: 10918 | V58: 10750 | W58: 150 | X58: 0.0142 | Y58: 2.40%-3.60% | Z58: Promotion | AA58: Senior Engineer | AB58: A5 | AC58: 0.07 | AD58: 742 | AE58: 11492 | AF58: 892 | AG58: 0.084150943 | AH58: 14 | AI58: 850 | AK58: 688 | AL58: 171776 | AM58: 3 | AO58: Combined with promotion | AP58: Combined with promotion | AQ58: Ma Ruiming（11007900） | AR58: Shao Xiao（11018043） | AS58: Wu Ellen | AT58: No use of salary increase budget, only use promotion budget.Not reasonable,proposed rate VS benchmark:10% | AU58: OK | AV58: <20
A59: CN15 | B59: 1132015 | C59: Indirect Active | D59: OP | E59: SCh | F59: FCLCh-MEW | G59: 290301 | H59: 34182 | I59: Engineer | J59: Engineer of Foaming | K59: BAND A4 | L59: 2 | M59: 1 | N59: 8937 | O59: 0 | P59: 0 | Q59: 0 | R59: 0 | S59: 0 | T59: 0 | U59: 8937 | V59: 8740 | W59: -197 | X59: -0.022 | Y59: 0.00%-0.00% | Z59: Demotion | AA59: Mould make technician | AB59: Rank 44 | AD59: 0 | AE59: 8740 | AF59: -197 | AG59: -0.022043191 | AH59: 14 | AI59: 450 | AK59: 688 | AL59: 128448 | AM59: 1 | AO59: Demotion | AP59: Salary adjustment letter already signed | AQ59: Zhao Biao（1150001） | AR59: Cao Wei（1114141） | AS59: Cheng Cheng | AU59: Demotion | AV59: <20

Sheet 特殊
A1: Special Type | B1: Company code | C1: Pers.no. | D1: Subgroup | E1: Area | F1: Subarea | G1: Dept. | H1: Cost ctr | I1: Join date | J1: Job | K1: Position | L1: Band Level | M1: Workplan type | N1: 2025 Performance Level | O1: Basic salary | P1: ① Merit increase % | Q1: Merit Increase amount | R1: ② Equity Increase% | S1: Equity Increase amount | T1: Total recommended Increase % (①+②) | U1: Total Recommended Increase amount | V1: Recommended new basic salary | W1: Adjutsed basic salary (input by DH) | X1: Adjutsed increased/decreased basic salary by DH | Y1: Adjusted basic increase/decreased % by DH | Z1: Adjustment range reference | AA1: Promotion or demotion | AB1: New position title | AC1: New band | AD1: ③ Promotion increase/Demotion decrease % (±5%-±20%) | AE1: Promotion increase/Demotion decrease amount | AF1: Final new basic salary | AG1: Final increase/decrease amount | AH1: Final increase/decrease rate | AI1: Pay months | AJ1: Monthly allowance/bonus | AK1: Monthly Car Allowance | AL1: Other income(e.g.:festival bonus) | AM1: Annual target cash | AN1: 2024 Performance Level | AO1: Disciplinary Records | AP1: Justifications by DH | AQ1: HR Remark | AR1: Responsible ASR Manager | AS1: Responsible ASR HRBP | AT1: PY | AU1: Editable column 1 | AV1: Editable column 2 | AW1: - | AX1: Attention
A2: 20% higher than suggested range | B2: CN15 | C2: 15022538 | D2: Indirect Active | E2: OP | F2: GQM | G2: GQM-LCCT | H2: 140600 | I2: 45748 | J2: Engineer | K2: Quality Engineer | L2: BAND A4 | M2: 2 | N2: 5 | O2: 11700 | P2: 0.05 | Q2: 585 | R2: 0.027 | S2: 316 | T2: 0.077008547 | U2: 901 | V2: 12601 | W2: 16700 | X2: 5000 | Y2: 0.4274 | Z2: 6.16%-9.24% | AE2: 0 | AF2: 16700 | AG2: 5000 | AH2: 0.42735043 | AI2: 14 | AJ2: 450 | AL2: 688 | AM2: 239888 | AN2: #N/A | AP2: Special budget already approved by Oliver in Feb. 2026 | AQ2: Top critical position/player | AR2: Zhu Chen (15010791) | AS2: Mo Xiaohong（11005372） | AT2: Zhao Chujun | AW2: >20 | AX2: Attention
B3: CN15 | C3: 1706037 | D3: Indirect Active | E3: OP | F3: GQM | G3: FCLCh-QMP | H3: 310604 | I3: 40023 | J3: Engineer | K3: Engineer of Quality | L3: BAND A4 | M3: 2 | N3: 5 | O3: 6492 | P3: 0.05 | Q3: 325 | R3: 0.027 | S3: 175 | T3: 0.077017868 | U3: 500 | V3: 6992 | W3: 7790 | X3: 1298 | Y3: 0.1999 | Z3: 6.16%-9.24% | AE3: 0 | AF3: 7790 | AG3: 1298 | AH3: 0.19993839 | AI3: 14 | AJ3: 450 | AL3: 688 | AM3: 115148 | AN3: 4 | AP3: Low basic salary and in 2025 take big additional task of SKD project with very good performance | AQ3: Good performers with extremely lower salary | AR3: Li Chaozi （1211022） | AS3: Mo Xiaohong（11005372） | AT3: Zhao Chujun | AW3: >20
B4: CN15 | C4: 1706029 | D4: Indirect Active | E4: OP | F4: SCh | G4: FCLCh-MEA | H4: 310201 | I4: 40023 | J4: Engineer | K4: Engineer | L4: BAND A4 | M4: 2 | N4: 5 | O4: 8050 | P4: 0.06 | Q4: 483 | R4: 0.027 | S4: 217 | T4: 0.086956522 | U4: 700 | V4: 8750 | W4: 9600 | X4: 1550 | Y4: 0.1925 | Z4: 6.96%-10.43% | AE4: 0 | AF4: 9600 | AG4: 1550 | AH4: 0.19254658 | AI4: 14 | AJ4: 450 | AL4: 688 | AM4: 140488 | AN4: 3 | AP4: High performance | AQ4: Good performance/talent | AR4: Zhao Biao（1150001） | AS4: Cao Wei（1114141） | AT4: Cheng Cheng | AW4: >20
B5: CN15 | C5: 15010296 | D5: Indirect Active | E5: OP | F5: SCh | G5: SCh | H5: 390100 | I5: 41408 | J5: Senior Project Manager | K5: Senior Project Manager | L5: BAND B | M5: 2 | N5: 5 | O5: 21200 | P5: 0.06 | Q5: 1272 | R5: 0.027 | S5: 572 | T5: 0.086981132 | U5: 1844 | V5: 23044 | W5: 25000 | X5: 3800 | Y5: 0.1792 | Z5: 6.96%-10.44% | AE5: 0 | AF5: 25000 | AG5: 3800 | AH5: 0.17924528 | AI5: 14 | AJ5: 450 | AL5: 688 | AM5: 356088 | AN5: 4 | AQ5: Significantly enlarged responsibilities with proven performance | AR5: Tan Tyler（11015792） | AS5: Wan Changju（15007713） | AT5: Zhao Chujun | AW5: >20
B6: CN15 | C6: 1132162 | D6: Indirect Active | E6: OP | F6: CN/OP-RM | G6: CN/OP-RMCF | H6: 290300 | I6: 40735 | J6: Senior Engineer | K6: Senior Engineer of Electrical | L6: BAND A5 | M6: 2 | N6: 4 | O6: 8140 | P6: 0.0525 | Q6: 427 | R6: 0.0421 | S6: 343 | T6: 0.094594595 | U6: 770 | V6: 8910 | W6: 9500 | X6: 1360 | Y6: 0.1671 | Z6: 7.57%-11.35% | AE6: 0 | AF6: 9500 | AG6: 1360 | AH6: 0.16707617 | AI6: 14 | AJ6: 450 | AL6: 688 | AM6: 139088 | AN6: 3 | AP6: 1.持续学习和成长，被评为问题解决specialist，成为部门内的问题解决专家。 2.勇于担当，主动承担电气安全管理工作，主动寻找解决方案，减少工厂隐患；在光伏项目及特种设备管理工作中也发挥了关键作用 | AQ6: Good performance and high potential | AR6: Fu Gang（1320032） | AS6: Mo Xiaohong（11005372） | AT6: Wu Ellen | AW6: >20
B7: CN15 | C7: 1116073 | D7: Indirect Active | E7: OP | F7: SCh | G7: FCLCh-MET | H7: 310204 | I7: 38566 | J7: Engineer | K7: Thermoforming Engineer | L7: BAND A4 | M7: 2 | N7: 5 | O7: 8880 | P7: 0.05 | Q7: 444 | R7: 0.027 | S7: 240 | T7: 0.077027027 | U7: 684 | V7: 9564 | W7: 10200 | X7: 1320 | Y7: 0.1486 | Z7: 6.16%-9.24% | AA7: Promotion | AB7: senior engineer | AC7: A5 | AD7: 0.0897 | AE7: 797 | AF7: 10997 | AG7: 2117 | AH7: 0.2384009 | AI7: 14 | AJ7: 450 | AL7: 688 | AM7: 160046 | AN7: 4 | AP7: High performer, recognized in CL | AQ7: Combined with promotion | AR7: Zhao Biao（1150001） | AS7: Cao Wei（1114141） | AT7: Cheng Cheng | AW7: >20
B8: CN15 | C8: 15002828 | D8: Indirect Active | E8: OP | F8: PCP | G8: PCP-OPGEE | H8: 270006 | I8: 40269 | J8: Technician | K8: Technician | L8: BAND A | M8: 2 | N8: 4 | O8: 5342 | P8: 0.03 | Q8: 160 | R8: 0 | S8: 0 | T8: 0.029951329 | U8: 160 | V8: 5502 | W8: 6103 | X8: 761 | Y8: 0.1425 | Z8: 2.40%-3.59% | AA8: Promotion | AB8: Junior Engineer | AC8: A3 | AD8: 0.141 | AE8: 753 | AF8: 6856 | AG8: 1514 | AH8: 0.28341445 | AI8: 14 | AJ8: 550 | AL8: 688 | AM8: 103272 | AN8: 3 | AP8: - Switched from Test Technician to Packaging Engineer; fast role adaptation & on-time project delivery - Proactive optimization initiatives achieved cost savings RMB 200k+ - Salary below new role band level | AQ8: Combined with promotion | AR8: Li Huihua（15000253） | AS8: Zhu Qianqian（11016705） | AW8: >20
B9: CN15 | C9: 1120273 | D9: Indirect Active | E9: OP | F9: SCh | G9: SCh-ES | H9: 290135 | I9: 44124 | J9: Functional Specialist | K9: Functional Specialist | L9: BAND A6 | M9: 2 | N9: 3 | O9: 12302 | P9: 0.03 | Q9: 369 | R9: 0 | S9: 0 | T9: 0.029995123 | U9: 369 | V9: 12671 | W9: 13808 | X9: 1506 | Y9: 0.1224 | Z9: 2.40%-3.60% | AE9: 0 | AF9: 13808 | AG9: 1506 | AH9: 0.12241912 | AI9: 14 | AJ9: 450 | AL9: 688 | AM9: 199400 | AN9: 4 | AQ9: Good performers with relatively lower salary | AR9: Tan Tyler（11015792） | AS9: Wan Changju（15007713） | AT9: Zhao Chujun | AW9: >20
B10: CN15 | C10: 15021739 | D10: Indirect Active | E10: OP | F10: PCP | G10: PCP-HCTG | H10: 150700 | I10: 44454 | J10: Senior Engineer | K10: Senior Engineer | L10: BAND A5 | M10: 2 | N10: 5 | O10: 11507 | P10: 0.05 | Q10: 575 | R10: 0.027 | S10: 311 | T10: 0.076996611 | U10: 886 | V10: 12393 | W10: 12807 | X10: 1300 | Y10: 0.113 | Z10: 6.16%-9.24% | AE10: 0 | AF10: 12807 | AG10: 1300 | AH10: 0.11297471 | AI10: 14 | AJ10: 550 | AL10: 688 | AM10: 186586 | AN10: 2 | AP10: Key position and high performance but with low basic salary, need to catch up | AQ10: Good performance and high competence | AR10: Li Huihua（15000253） | AS10: Zhu Qianqian（11016705） | AW10: >20
B11: CN15 | C11: 1707015 | D11: Indirect Active | E11: OP | F11: SCh | G11: FCLCh-MEA | H11: 310201 | I11: 40391 | J11: Engineer | K11: Engineer | L11: BAND A4 | M11: 2 | N11: 4 | O11: 7774 | P11: 0.0375 | Q11: 292 | R11: 0.0155 | S11: 120 | T11: 0.05299717 | U11: 412 | V11: 8186 | W11: 8600 | X11: 826 | Y11: 0.1063 | Z11: 4.24%-6.36% | AE11: 0 | AF11: 8600 | AG11: 826 | AH11: 0.10625161 | AI11: 14 | AJ11: 450 | AL11: 688 | AM11: 126488 | AN11: 3 | AP11: Low basic salary and high performance in new role | AQ11: Good performers and talent with relative low salary | AR11: Zhao Biao（1150001） | AS11: Cao Wei（1114141） | AT11: Cheng Cheng | AW11: >20
B12: CN15 | C12: 1711024 | D12: Indirect Active | E12: OP | F12: GQM | G12: FDCCh-QMP | H12: 320600 | I12: 41814 | J12: Junior Engineer | K12: Junior Engineer | L12: BAND A3 | M12: 2 | N12: NA | O12: 5720 | P12: 0.025 | Q12: 143 | R12: 0 | S12: 0 | T12: 0.025 | U12: 143 | V12: 5863 | W12: 6297 | X12: 577 | Y12: 0.1009 | Z12: 2.00%-3.00% | AE12: 0 | AF12: 6297 | AG12: 577 | AH12: 0.10087413 | AI12: 14 | AJ12: 450 | AL12: 688 | AM12: 94246 | AN12: NA | AP12: Transfer from shift leader to junior engineer in 2025. Performance in 22025: 1. lead pss problem solving for outer door scratch with maturity 21. 2. build up standard for AEA testing auto judgement. 3.lead 2 times inhouse process release with KPI (Q,C,D) achievement. | AQ12: Good performers with relatively lower salary | AR12: Guo Yuwei （15014438） | AS12: Mo Xiaohong（11005372） | AT12: Cheng Cheng | AW12: >20
B13: CN15 | C13: 15006800 | D13: Indirect Active | E13: OP | F13: SNa | G13: FLCNa-V1 | H13: 340100 | I13: 40744 | J13: Manager | K13: Head of FLCNa-V1 | L13: BAND B | M13: 2 | N13: 3 | O13: 15455 | P13: 0.03 | Q13: 464 | R13: 0 | S13: 0 | T13: 0.030022646 | U13: 464 | V13: 15919 | W13: 17010 | X13: 1555 | Y13: 0.1006 | Z13: 2.40%-3.60% | AE13: 0 | AF13: 17010 | AG13: 1555 | AH13: 0.10061469 | AI13: 14 | AJ13: 450 | AL13: 688 | AM13: 244228 | AN13: 5 | AP13: took VS head with excellent performance. Lower salary. | AQ13: Enlarged responsibilities with proven performance | AR13: Jiang Xiujuan（11012739） | AS13: Mo Xiaohong（11005372） | AT13: Zhao Chujun | AU13: exceed +/-20% adjustment | AV13: >20 | AW13: >20
B14: CN15 | C14: 1705021 | D14: Indirect Active | E14: OP | F14: SCh | G14: FCLCh-MET | H14: 310204 | I14: 39664 | J14: Senior Engineer | K14: Senior Door Gasket Extrusion Engineer | L14: BAND A5 | M14: 2 | N14: 4 | O14: 11633 | P14: 0.0375 | Q14: 436 | R14: 0.0155 | S14: 180 | T14: 0.052952807 | U14: 616 | V14: 12249 | W14: 12800 | X14: 1167 | Y14: 0.1003 | Z14: 4.24%-6.35% | AA14: Promotion | AB14: functional specialist | AC14: A6 | AD14: 0.05 | AE14: 582 | AF14: 13382 | AG14: 1749 | AH14: 0.15034815 | AI14: 14 | AJ14: 450 | AL14: 688 | AM14: 193436 | AN14: 4 | AP14: Recognition in CL, act as informal GPO | AQ14: Combined with promotion | AR14: Zhao Biao（1150001） | AS14: Cao Wei（1114141） | AT14: Cheng Cheng | AW14: >20
B15: CN15 | C15: 1120196 | D15: Indirect Active | E15: OP | F15: SCh | G15: FCLCh-MET | H15: 310204 | I15: 43094 | J15: Expert (CN) | K15: Expert (CN) | L15: BAND B | M15: 2 | N15: 3 | O15: 17480 | P15: 0.03 | Q15: 524 | R15: 0 | S15: 0 | T15: 0.029977117 | U15: 524 | V15: 18004 | W15: 19228 | X15: 1748 | Y15: 0.1 | Z15: 2.40%-3.60% | AE15: 0 | AF15: 19228 | AG15: 1748 | AH15: 0.1 | AI15: 14 | AJ15: 450 | AL15: 688 | AM15: 275280 | AN15: 4 | AP15: Critical expert for CL | AQ15: Good performance and high potential | AR15: Zhao Biao（1150001） | AS15: Cao Wei（1114141） | AT15: Cheng Cheng | AW15: >20
B16: CN15 | C16: 1118259 | D16: Indirect Active | E16: OP | F16: SCh | G16: FCLCh-VB3 | H16: 310400 | I16: 37715 | J16: Supervisor | K16: Head of FCLCh-VB3 | L16: BAND A6 | M16: 2 | N16: 4 | O16: 14894 | P16: 0.0375 | Q16: 559 | R16: 0.0155 | S16: 231 | T16: 0.053041493 | U16: 790 | V16: 15684 | W16: 16380 | X16: 1486 | Y16: 0.0998 | Z16: 4.24%-6.36% | AE16: 0 | AF16: 16380 | AG16: 1486 | AH16: 0.09977172 | AI16: 14 | AJ16: 450 | AL16: 688 | AM16: 235408 | AN16: 5 | AP16: High performer and responsible for a big production line with more than 350 direct employees, even can be promote to Band B | AQ16: Enlarged responsibilities with proven performance | AR16: Zhao Biao（1150001） | AS16: Cao Wei（1114141） | AT16: Cheng Cheng | AW16: >20
B17: CN15 | C17: 1120353 | D17: Indirect Active | E17: OP | F17: SCh | G17: FCLCh-MEA | H17: 310201 | I17: 44452 | J17: Senior Engineer | K17: Senior Engineer | L17: BAND A5 | M17: 2 | N17: 3 | O17: 9274 | P17: 0.03 | Q17: 278 | R17: 0 | S17: 0 | T17: 0.029976278 | U17: 278 | V17: 9552 | W17: 10200 | X17: 926 | Y17: 0.0998 | Z17: 2.40%-3.60% | AE17: 0 | AF17: 10200 | AG17: 926 | AH17: 0.09984904 | AI17: 14 | AJ17: 450 | AL17: 688 | AM17: 148888 | AN17: 4 | AP17: Future potential functional specialist | AQ17: Good performance and high potential | AR17: Zhao Biao（1150001） | AS17: Cao Wei（1114141） | AT17: Cheng Cheng | AW17: >20
B18: CN15 | C18: 1707005 | D18: Indirect Active | E18: OP | F18: GQM | G18: FDCCh-QMS | H18: 320601 | I18: 40391 | J18: Senior Engineer | K18: Senior Engineer | L18: BAND A5 | M18: 2 | N18: 3 | O18: 7103 | P18: 0.035 | Q18: 249 | R18: 0 | S18: 0 | T18: 0.03505561 | U18: 249 | V18: 7352 | W18: 7800 | X18: 697 | Y18: 0.0981 | Z18: 2.80%-4.21% | AE18: 0 | AF18: 7800 | AG18: 697 | AH18: 0.098127552 | AI18: 14 | AJ18: 450 | AL18: 688 | AM18: 115288 | AN18: 3 | AP18: Good performance but with lower salary. 2025Q3 Excellent Employee. Lead 8D problem solving for Zeolite fog issue with maturity 22. | AQ18: Good performers with relatively lower salary | AR18: Guo Yuwei （15014438） | AS18: Mo Xiaohong（11005372） | AT18: Cheng Cheng | AW18: >20
B19: CN15 | C19: 1213096 | D19: Indirect Active | E19: OP | F19: GQM | G19: GQM-CLCD | H19: 110600 | I19: 37088 | J19: Manager | K19: Head of Project Quality | L19: BAND B | M19: 2 | N19: 4 | O19: 23768 | P19: 0.0375 | Q19: 891 | R19: 0.0155 | S19: 368 | T19: 0.05297038 | U19: 1259 | V19: 25027 | W19: 26000 | X19: 2232 | Y19: 0.0939 | Z19: 4.24%-6.36% | AE19: 0 | AF19: 26000 | AG19: 2232 | AH19: 0.093907775 | AI19: 14 | AJ19: 450 | AL19: 688 | AM19: 370088 | AN19: 4 | AP19: Both workload (Addtionally workload responsible for MCC & CBA) and performance alsp very good level of 2025. | AQ19: Enlarged responsibilities with proven performance | AR19: Li Chaozi （1211022） | AS19: Mo Xiaohong（11005372） | AT19: Zhao Chujun | AW19: >20
B20: CN15 | C20: 11016123 | D20: Indirect Active | E20: OP | F20: GPL-CN | G20: GPL-SC8PS | H20: 210150 | I20: 43234 | J20: Supervisor | K20: Supervisor | L20: BAND A6 | M20: 2 | N20: 4 | O20: 14800 | P20: 0.0375 | Q20: 555 | R20: 0.0155 | S20: 229 | T20: 0.052972973 | U20: 784 | V20: 15584 | W20: 16184 | X20: 1384 | Y20: 0.0935 | Z20: 4.24%-6.36% | AE20: 0 | AF20: 16184 | AG20: 1384 | AH20: 0.093513514 | AI20: 14 | AJ20: 450 | AL20: 688 | AM20: 232664 | AN20: 3 | AQ20: Enlarged responsibilities with proven performance | AR20: Chen Meng（11007521） | AS20: Xu Lan（11013544） | AW20: >20
B21: CN15 | C21: 15007522 | D21: Indirect Active | E21: OP | F21: SNa | G21: FCGNa-VCE | H21: 330405 | I21: 41091 | J21: Supervisor | K21: Head of FCGNa-VCE | L21: BAND A6 | M21: 2 | N21: 3 | O21: 13100 | P21: 0.03 | Q21: 393 | R21: 0 | S21: 0 | T21: 0.03 | U21: 393 | V21: 13493 | W21: 14312 | X21: 1212 | Y21: 0.0925 | Z21: 2.40%-3.60% | AE21: 0 | AF21: 14312 | AG21: 1212 | AH21: 0.092519084 | AI21: 14 | AJ21: 450 | AL21: 688 | AM21: 206456 | AN21: 2 | AP21: 1. In 2025, he achieved an 11% reduction in cooker SPC and cut silicone usage by 50%. 2. As a supervisor, his salary is the lowest in the team, so I need to catch up appropriately. | AQ21: Good performers with relatively lower salary | AR21: Liu Haigang（15013255） | AS21: Zhu Qianqian（11016705） | AT21: Zhao Chujun | AU21: exceed +/-20% adjustment | AV21: >20 | AW21: >20 | AX21: Attention
B22: CN15 | C22: 11011629 | D22: Indirect Active | E22: OP | F22: GPL-CN | G22: GPL-SC8X1 | H22: 210152 | I22: 41920 | J22: Specialist | K22: Specialist | L22: BAND A4 | M22: 2 | N22: 3 | O22: 8185 | P22: 0.025 | Q22: 205 | R22: 0 | S22: 0 | T22: 0.025045816 | U22: 205 | V22: 8390 | W22: 8890 | X22: 705 | Y22: 0.0861 | Z22: 2.00%-3.01% | AE22: 0 | AF22: 8890 | AG22: 705 | AH22: 0.08613317 | AI22: 14 | AJ22: 450 | AL22: 688 | AM22: 130548 | AN22: 3 | AQ22: Internal balance | AR22: Chen Meng（11007521） | AS22: Xu Lan（11013544） | AW22: >20
B23: CN15 | C23: 11007521 | D23: Indirect Active | E23: OP | F23: GPL-CN | G23: GPL-SC8 | H23: 210150 | I23: 40653 | J23: Senior Director | K23: Head of Demand Fulfillment | L23: BAND D | M23: 1 | N23: 3 | O23: 48000 | P23: 0.045025672 | Q23: 2161 | R23: 0 | S23: 0 | T23: 0.045020833 | U23: 2161 | V23: 50161 | W23: 52053 | X23: 4053 | Y23: 0.0844 | Z23: 3.60%-5.40% | AE23: 0 | AF23: 52053 | AG23: 4053 | AH23: 0.0844375 | AI23: 16 | AJ23: 450 | AK23: 5000 | AL23: 0 | AM23: 898248 | AN23: 3 | AP23: Great Gap | AQ23: Good performers with extremely lower salary | AR23: Kalak Ahmet（11018931） | AS23: Xu Lan（11013544） | AW23: >20
B24: CN15 | C24: 15003288 | D24: Indirect Active | E24: OP | F24: GPL-CN | G24: GPL-LO8G | H24: 120010 | I24: 40360 | J24: Specialist | K24: Specialist | L24: BAND A4 | M24: 2 | N24: 4 | O24: 8300 | P24: 0.03 | Q24: 249 | R24: 0 | S24: 0 | T24: 0.03 | U24: 249 | V24: 8549 | W24: 9000 | X24: 700 | Y24: 0.0843 | Z24: 2.40%-3.60% | AE24: 0 | AF24: 9000 | AG24: 700 | AH24: 0.084337349 | AI24: 14 | AJ24: 450 | AL24: 688 | AM24: 132088 | AN24: 3 | AQ24: Good performance and high competence | AR24: Li Xiaochun（11008077） | AS24: Xu Lan（11013544） | AW24: >20
B25: CN15 | C25: 1705001 | D25: Indirect Active | E25: OP | F25: GQM | G25: GQM-CLCD | H25: 110600 | I25: 39664 | J25: Senior Engineer | K25: Senior Engineer | L25: BAND A5 | M25: 2 | N25: 3 | O25: 8315 | P25: 0.03 | Q25: 249 | R25: 0 | S25: 0 | T25: 0.029945881 | U25: 249 | V25: 8564 | W25: 9000 | X25: 685 | Y25: 0.0824 | Z25: 2.40%-3.59% | AE25: 0 | AF25: 9000 | AG25: 685 | AH25: 0.082381239 | AI25: 14 | AJ25: 450 | AL25: 688 | AM25: 132088 | AN25: 5 | AP25: 1.5 times overload for project quality management tasks and with very good delivery like EP85 project | AQ25: Enlarged responsibilities with proven performance | AR25: Li Chaozi （1211022） | AS25: Mo Xiaohong（11005372） | AT25: Zhao Chujun | AW25: >20
B26: CN15 | C26: 1709022 | D26: Indirect Active | E26: OP | F26: SC | G26: SCh-SC2LS | H26: 290152 | I26: 41115 | J26: Functional Specialist | K26: Safety Functional Specialist | L26: BAND A6 | M26: 2 | N26: 3 | O26: 8880 | P26: 0.03 | Q26: 266 | R26: 0 | S26: 0 | T26: 0.029954955 | U26: 266 | V26: 9146 | W26: 9600 | X26: 720 | Y26: 0.0811 | Z26: 2.40%-3.59% | AE26: 0 | AF26: 9600 | AG26: 720 | AH26: 0.081081081 | AI26: 14 | AJ26: 450 | AL26: 688 | AM26: 140488 | AN26: 3 | AP26: Internal balance | AQ26: Good performers with relatively lower salary | AR26: Wang Xiaoqing（1120031） | AS26: Shao Xiao（11018043） | AT26: Cheng Cheng | AW26: >20
B27: CN15 | C27: 15001698 | D27: Indirect Active | E27: OP | F27: SNa | G27: FLCNa-MEF | H27: 340200 | I27: 39616 | J27: Senior Engineer | K27: Senior Manufacturing Engineer | L27: BAND A5 | M27: 2 | N27: 4 | O27: 11737 | P27: 0.0375 | Q27: 440 | R27: 0.0155 | S27: 182 | T27: 0.052994803 | U27: 622 | V27: 12359 | W27: 12659 | X27: 922 | Y27: 0.0786 | Z27: 4.24%-6.36% | AE27: 0 | AF27: 12659 | AG27: 922 | AH27: 0.078554997 | AI27: 14 | AJ27: 450 | AL27: 688 | AM27: 183314 | AN27: 3 | AP27: Excellent performance in laser welding relocation。同时兼任FLCNa,FLCCh 两家工厂的内筒激光焊接 | AQ27: Significantly enlarged responsibilities with proven performance | AR27: Hu Jun（51202067） | AS27: Mo Xiaohong（11005372） | AT27: Zhao Chujun | AU27: exceed +/-20% adjustment | AV27: >20 | AW27: >20
B28: CN15 | C28: 1120352 | D28: Indirect Active | E28: OP | F28: SCh | G28: FDCCh-MEA | H28: 320200 | I28: 44445 | J28: Functional Specialist | K28: Functional Specialist | L28: BAND A6 | M28: 2 | N28: 3 | O28: 12522 | P28: 0.03 | Q28: 376 | R28: 0 | S28: 0 | T28: 0.030027152 | U28: 376 | V28: 12898 | W28: 13500 | X28: 978 | Y28: 0.0781 | Z28: 2.40%-3.60% | AE28: 0 | AF28: 13500 | AG28: 978 | AH28: 0.07810254 | AI28: 14 | AJ28: 450 | AL28: 688 | AM28: 195088 | AN28: 5 | AP28: Workplan 2025 Preliminary PL4 | AQ28: Good performers and talent with relative low salary | AR28: Lin Xianzhong（1132204） | AS28: Li Mingzhe（15018080） | AT28: Cheng Cheng | AW28: >20
B29: CN15 | C29: 15018456 | D29: Indirect Active | E29: OP | F29: CN/OP-RM | G29: CN/OP-RMNG | H29: 290104 | I29: 43042 | J29: Specialist | K29: Specialist | L29: BAND A4 | M29: 2 | N29: 4 | O29: 6679 | P29: 0.0375 | Q29: 250 | R29: 0 | S29: 0 | T29: 0.037430753 | U29: 250 | V29: 6929 | W29: 7185 | X29: 506 | Y29: 0.0758 | Z29: 2.99%-4.49% | AE29: 0 | AF29: 7185 | AG29: 506 | AH29: 0.075759844 | AI29: 14 | AJ29: 450 | AL29: 688 | AM29: 106678 | AN29: 3 | AP29: 1.Optimized RMN internal purchasing process 2.Frame contract utility rate is top 3 3.SC order follow up professionally. | AQ29: Enlarged responsibilities with proven performance | AR29: Chen Lianrong（15022534） | AS29: Mo Xiaohong（11005372） | AT29: Wu Ellen | AW29: >20
B30: CN15 | C30: 15015270 | D30: Indirect Active | E30: OP | F30: GQM | G30: GQM-SRC | H30: 190601 | I30: 42552 | J30: Director | K30: Head of Shared Services | L30: BAND C | M30: 2 | N30: 3 | O30: 21000 | P30: 0.035 | Q30: 735 | R30: 0 | S30: 0 | T30: 0.035 | U30: 735 | V30: 21735 | W30: 22500 | X30: 1500 | Y30: 0.0714 | Z30: 2.80%-4.20% | AE30: 0 | AF30: 22500 | AG30: 1500 | AH30: 0.071428571 | AI30: 14 | AJ30: 450 | AK30: 1000 | AL30: 688 | AM30: 333088 | AN30: 5 | AP30: DPRC relations and CoNC ownership | AQ30: Good performers with relatively lower salary | AR30: Subasi Gonca（15022750） | AS30: Mo Xiaohong（11005372） | AT30: Zhao Chujun | AW30: >20
B31: CN15 | C31: 15004177 | D31: Indirect Active | E31: OP | F31: CN/OP-RM | G31: CN/OP-RMNF | H31: 290300 | I31: 40373 | J31: Junior Engineer | K31: Junior Engineer | L31: BAND A3 | M31: 2 | N31: 3 | O31: 6725 | P31: 0.03 | Q31: 202 | R31: 0 | S31: 0 | T31: 0.030037175 | U31: 202 | V31: 6927 | W31: 7200 | X31: 475 | Y31: 0.0706 | Z31: 2.40%-3.60% | AE31: 0 | AF31: 7200 | AG31: 475 | AH31: 0.07063197 | AI31: 14 | AJ31: 450 | AL31: 688 | AM31: 106888 | AN31: 2 | AP31: 1.Took over additional management work for special equipment, with excellent on-site management and implementation. | AQ31: Enlarged responsibilities with proven performance | AR31: Chen Lianrong（15022534） | AS31: Mo Xiaohong（11005372） | AT31: Wu Ellen | AW31: >20 | AX31: Attention
B32: CN15 | C32: 15022342 | D32: Indirect Active | E32: OP | F32: SNa | G32: FLCNa-MEA | H32: 340200 | I32: 45035 | J32: Senior Engineer | K32: Senior Assembly Engineer | L32: BAND A5 | M32: 2 | N32: 3 | O32: 11020 | P32: 0.03 | Q32: 331 | R32: 0 | S32: 0 | T32: 0.030036298 | U32: 331 | V32: 11351 | W32: 11751 | X32: 731 | Y32: 0.0663 | Z32: 2.40%-3.60% | AE32: 0 | AF32: 11751 | AG32: 731 | AH32: 0.066333938 | AI32: 14 | AJ32: 550 | AL32: 688 | AM32: 171802 | AN32: 5 | AP32: Excellent performance in India SKD project and new line rampup | AQ32: Good performers with relatively lower salary | AR32: Hu Jun（51202067） | AS32: Mo Xiaohong（11005372） | AT32: Zhao Chujun | AU32: exceed +/-20% adjustment | AV32: >20 | AW32: >20
B33: CN15 | C33: 1007579 | D33: Indirect Active | E33: OP | F33: SC | G33: SCh-SC2P | H33: 290154 | I33: 40994 | J33: Functional Specialist | K33: Functional Specialist | L33: BAND A6 | M33: 2 | N33: 3 | O33: 9848 | P33: 0.03 | Q33: 295 | R33: 0 | S33: 0 | T33: 0.029955321 | U33: 295 | V33: 10143 | W33: 10500 | X33: 652 | Y33: 0.0662 | Z33: 2.40%-3.59% | AE33: 0 | AF33: 10500 | AG33: 652 | AH33: 0.066206336 | AI33: 14 | AJ33: 450 | AL33: 688 | AM33: 153088 | AN33: 4 | AP33: Internal balance | AQ33: Good performers with relatively lower salary | AR33: Yang Fangfang（1421065） | AS33: Shao Xiao（11018043） | AT33: Cheng Cheng | AW33: >20
B34: CN15 | C34: 11018858 | D34: Indirect Active | E34: OP | F34: GPL-CN | G34: GPL-SCS8 | H34: 210151 | I34: 44480 | J34: Functional Specialist | K34: Functional Specialist | L34: BAND A6 | M34: 2 | N34: 3 | O34: 16818 | P34: 0.035 | Q34: 589 | R34: 0 | S34: 0 | T34: 0.035022 | U34: 589 | V34: 17407 | W34: 17900 | X34: 1082 | Y34: 0.0643 | Z34: 2.80%-4.20% | AE34: 0 | AF34: 17900 | AG34: 1082 | AH34: 0.064335831 | AI34: 14 | AJ34: 450 | AL34: 688 | AM34: 256688 | AN34: 3 | AQ34: Good performers with extremely lower salary | AR34: Ma Ruiming（11007900） | AS34: Xu Lan（11013544） | AW34: >20
